Workbook

Sheet Mapa Oficinas
A1: Mapeo Oficinas CB → Zona → Localidad
A4: Referencia del PDF oficial Oficinas-CB-ARG-UY-PY.pdf
A6: Oficina | B6: Zona CB | C6: Localidad CB | D6: Operaciones en dataset
A7: Seniority | B7: CABA | C7: Barrio Parque
A8: Ser | B8: CABA | C8: Belgrano
A9: Space BA | B9: CABA | C9: Belgrano
A10: Desiderio | B10: CABA | C10: Caballito
A11: Goyena | B11: CABA | C11: Caballito
A12: Database | B12: CABA | C12: Núñez
A13: Haka | B13: CABA | C13: Núñez
A14: Horizon Group | B14: CABA | C14: Núñez
A15: Wings | B15: CABA | C15: Núñez
A16: Livello | B16: CABA | C16: Palermo
A17: Niceto | B17: CABA | C17: Palermo
A18: Notable | B18: CABA | C18: Palermo
... A46: Golden Team | B46: Zona Sur (GBA) | C46: La Plata

Sheet Operaciones Venta
A1: Fecha | B1: Ref # | C1: Unificador | D1: Publicación | E1: Estado | F1: Portal | G1: Precio Publicación | H1: Precio Cierre Total | I1: Moneda Cierre | J1: Moneda Publicación | K1: Dirección | L1: Ubicación | M1: Tipo Propiedad | N1: Lados | O1: Oficina | P1: Tipo Operación | Q1: Operación | R1: Zona CB | S1: Localidad CB
A2: 45658 | B2: CLA6158186 | C2: 1 | D2: ¡Terreno para desarrollar en pleno Florida! ¡701 mts construíbles! | E2: Realizado | F2: AR MercadoLibre | G2: 320000 | H2: 282000 | I2: Dólares | J2: Dólares | K2: Laprida al 2000 | L2: Argentina | G.B.A. Zona Norte | Vicente López | Florida | M2: Terreno | N2: 2 | O2: Concept | P2: Propia (Único Asesor) | Q2: Venta | R2: =VLOOKUP($O2,'Mapa Oficinas'!$A$7:$C$46,2,FALSE) -> Zona Norte (GBA) | S2: =VLOOKUP($O2,'Mapa Oficinas'!$A$7:$C$46,3,FALSE) -> Tigre
A3: 45658 | B3: ZP-ZP-M-43773962 | C3: 1 | D3: Hermosa casa con piscina en Barrio privado San Francisco - Tigre | E3: Realizado | F3: AR MercadoLibre | G3: 315000 | H3: 308000 | I3: Dólares | J3: Dólares | K3: Aristóbulo del Valle al 5100 | L3: Argentina | G.B.A. Zona Norte | Tigre | Countries/B.Cerrado (Tigre) | Villanueva | San Francisco | M3: Casa | N3: 2 | O3: Concept | P3: Propia (Único Asesor) | Q3: Venta | R3: =VLOOKUP($O3,'Mapa Oficinas'!$A$7:$C$46,2,FALSE) -> Zona Norte (GBA) | S3: =VLOOKUP($O3,'Mapa Oficinas'!$A$7:$C$46,3,FALSE) -> Tigre
A4: 45659 | B4: CHO5264010 | C4: 1 | D4: CASA EN VENTA, 3 AMBIENTES, SAN SEBASTIAN, AREA 12 | E4: Realizado | F4: AR ZonaProp | G4: 125000 | H4: 115000 | I4: Dólares | J4: Dólares | K4: Hermosa Casa en San Sebastián, área 12 | L4: Argentina | G.B.A. Zona Norte | Pilar | Countries/B.Cerrado (Pilar) | San Sebastian | M4: Casa | N4: 2 | O4: Haka | P4: Propia (Único Asesor) | Q4: Venta | R4: =VLOOKUP($O4,'Mapa Oficinas'!$A$7:$C$46,2,FALSE) -> CABA | S4: =VLOOKUP($O4,'Mapa Oficinas'!$A$7:$C$46,3,FALSE) -> Núñez
A5: 45659 | B5: CAP6363861 | D5: Venta Departamento 3 Ambientes en Complejo Al Río c/ cochera - baulera - balcón | E5: Realizado | F5: AR ZonaProp | G5: 420000 | H5: 405000 | I5: Dólares | J5: Dólares | K5: Juan Carlos Cruz 100 | L5: Argentina | G.B.A. Zona Norte | Vicente López | Libertador al Río | M5: Departamento | N5: 1 | O5: Seniority Plus | P5: Compartida Fuera de la Red Búsqueda | Q5: Venta | R5: =VLOOKUP($O5,'Mapa Oficinas'!$A$7:$C$46,2,FALSE) -> CABA | S5: =VLOOKUP($O5,'Mapa Oficinas'!$A$7:$C$46,3,FALSE) -> Palermo
A6: 45659 | B6: OP 85 | D6: Gelly y Obes 2243 5 | E6: Realizado | F6: AR ZonaProp | G6: 900000 | H6: 900000 | I6: Dólares | J6: Dólares | K6: Gelly y Obes 2243 5 | L6: Argentina | Capital Federal | Recoleta | M6: Departamento | N6: 1 | O6: Seniority Plus | P6: Compartida Fuera de la Red Búsqueda | Q6: Venta | R6: =VLOOKUP($O6,'Mapa Oficinas'!$A$7:$C$46,2,FALSE) -> CABA | S6: =VLOOKUP($O6,'Mapa Oficinas'!$A$7:$C$46,3,FALSE) -> Palermo
A7: 45660 | B7: JLO5618192 | C7: 1 | D7: VENTA LOCAL LOMAS DE ZAMORA | E7: Realizado | F7: AR ZonaProp | G7: 49900 | H7: 42000 | I7: Dólares | J7: Dólares | K7: General Carlos María de Alvear al 600 | L7: Argentina | G.B.A. Zona Sur | Lomas De Zamora (Partido) | Lomas De Zamora | M7: Local Comercial | N7: 2 | O7: Lion Team Norte | P7: Propia (Único Asesor) | Q7: Venta | R7: =VLOOKUP($O7,'Mapa Oficinas'!$A$7:$C$46,2,FALSE) -> Zona Norte (GBA) | S7: =VLOOKUP($O7,'Mapa Oficinas'!$A$7:$C$46,3,FALSE) -> Vicente López
A8: 45660 | B8: CPH5611863 | C8: 1 | D8: PH reciclado Parque Chacabuco | E8: Realizado | F8: AR ZonaProp | G8: 120000 | H8: 110000 | I8: Dólares | J8: Dólares | K8: Av Cobo al 700 | L8: Argentina | Capital Federal | Parque Chacabuco | M8: PH | N8: 2 | O8: Lion Team | P8: Propia (Único Asesor) | Q8: Venta | R8: =VLOOKUP($O8,'Mapa Oficinas'!$A$7:$C$46,2,FALSE) -> CABA | S8: =VLOOKUP($O8,'Mapa Oficinas'!$A$7:$C$46,3,FALSE) -> Villa Urquiza
A9: 45660 | B9: CAP6333484 | C9: 1 | D9: VENTA DEPARTAMENTO 3 AMBIENTES con gran patio EN PALERMO | E9: Realizado | F9: AR ZonaProp | G9: 139000 | H9: 115000 | I9: Dólares | J9: Dólares | K9: ARAOZ 2400 | L9: Argentina | Capital Federal | Palermo | M9: Departamento | N9: 2 | O9: Seniority | P9: Propia (Único Asesor) | Q9: Venta | R9: =VLOOKUP($O9,'Mapa Oficinas'!$A$7:$C$46,2,FALSE) -> CABA | S9: =VLOOKUP($O9,'Mapa Oficinas'!$A$7:$C$46,3,FALSE) -> Barrio Parque
A10: 45663 | B10: CAP6452531 | C10: 1 | D10: Departamento en Junin 530 | E10: Realizado | F10: Facebook | G10: 58000 | H10: 63000 | I10: Dólares | J10: Dólares | K10: Junin 530 | L10: Argentina | Salta | Capital | Salta | Zona Centro | M10: Departamento | N10: 2 | O10: Realty Group | P10: Propia (Único Asesor) | Q10: Venta | R10: =VLOOKUP($O10,'Mapa Oficinas'!$A$7:$C$46,2,FALSE) -> Interior - Salta | S10: =VLOOKUP($O10,'Mapa Oficinas'!$A$7:$C$46,3,FALSE) -> San Lorenzo Chico
A11: 45663 | B11: CCM54953 LO5934597 | D11: Local en Porto San Lorenzo chico | E11: Realizado | F11: Referido | G11: 167000 | H11: 68000 | I11: Dólares | J11: Dólares | K11: san Lorenzo chico | L11: Argentina | Salta | Capital | M11: Local Comercial | N11: 2 | O11: Realty Group | P11: Compartida en Oficina (Dos Asesores) | Q11: Venta | R11: =VLOOKUP($O11,'Mapa Oficinas'!$A$7:$C$46,2,FALSE) -> Interior - Salta | S11: =VLOOKUP($O11,'Mapa Oficinas'!$A$7:$C$46,3,FALSE) -> San Lorenzo Chico
A12: 45663 | C12: 1 | D12: VENTA Monoambiente 39,94m2 - UF 50, pozo, Paseo Retamas, Villa la Angostura, Villa la Angostura | E12: Realizado | F12: Conocido | G12: 71793 | H12: 71793 | I12: Dólares | J12: Dólares | K12: Retamas 200 | L12: Argentina | Neuquen | Villa La Angostura | Centro | M12: Departamento | N12: 2 | O12: Patagonia Lakes VLA | P12: Propia (Único Asesor) | Q12: Venta | R12: =VLOOKUP($O12,'Mapa Oficinas'!$A$7:$C$46,2,FALSE) -> Interior - Neuquén | S12: =VLOOKUP($O12,'Mapa Oficinas'!$A$7:$C$46,3,FALSE) -> Villa La Angostura
A13: 45663 | B13: CBU59337 AP6535062 | C13: 1 | D13: VENTA Monoambiente 43,72m2 - UF 51, pozo, Paseo Retamas, Villa la Angostura, Villa la Angostura | E13: Realizado | F13: Conocido | G13: 74784 | H13: 74184 | I13: Dólares | J13: Dólares | K13: Retamas al 300 | L13: Argentina | Neuquen | Villa La Angostura | Centro | M13: Departamento | N13: 2 | O13: Patagonia Lakes VLA | P13: Propia (Único Asesor) | Q13: Venta | R13: =VLOOKUP($O13,'Mapa Oficinas'!$A$7:$C$46,2,FALSE) -> Interior - Neuquén | S13: =VLOOKUP($O13,'Mapa Oficinas'!$A$7:$C$46,3,FALSE) -> Villa La Angostura
A14: 45663 | B14: CAP6454429 | C14: 1 | D14: VENTA Departamento 2 ambientes A estrenar Balcón al Frente Villa Urquiza | E14: Realizado | F14: AR ArgenProp | G14: 102000 | H14: 100250 | I14: Dólares | J14: Dólares | K14: Bauness al 1100 | L14: Argentina | Capital Federal | Villa Urquiza | M14: Departamento | N14: 2 | O14: Lion Team | P14: Propia (Único Asesor) | Q14: Venta | R14: =VLOOKUP($O14,'Mapa Oficinas'!$A$7:$C$46,2,FALSE) -> CABA | S14: =VLOOKUP($O14,'Mapa Oficinas'!$A$7:$C$46,3,FALSE) -> Villa Urquiza
A15: 45663 | B15: CBU49671 AP6414032 | C15: 1 | D15: Departamento Monoambiente divisible A Estrenar con Balcon Piso 1 - Villa Urquiza VENTA | E15: Realizado | F15: AR ArgenProp | G15: 90000 | H15: 100250 | I15: Dólares | J15: Dólares | K15: Bauness al 1100 | L15: Argentina | Capital Federal | Villa Urquiza | M15: Departamento | N15: 2 | O15: Lion Team | P15: Propia (Único Asesor) | Q15: Venta | R15: =VLOOKUP($O15,'Mapa Oficinas'!$A$7:$C$46,2,FALSE) -> CABA | S15: =VLOOKUP($O15,'Mapa Oficinas'!$A$7:$C$46,3,FALSE) -> Villa Urquiza
A16: 45663 | B16: CBU59337 AP6535088 | D16: VENTA Departamento céntrico 2 amb 59,64m2 UF 73 - en pozo, Paseo Retamas, El Cruce, Las Retamas 300, Villa la Angostura | E16: Realizado | F16: Repetido | G16: 104158 | H16: 104000 | I16: Dólares | J16: Dólares | K16: Retamas al 300 | L16: Argentina | Neuquen | Villa La Angostura | Centro | M16: Departamento | N16: 2 | O16: Patagonia Lakes VLA | P16: Compartida en Oficina (Dos Asesores) | Q16: Venta | R16: =VLOOKUP($O16,'Mapa Oficinas'!$A$7:$C$46,2,FALSE) -> Interior - Neuquén | S16: =VLOOKUP($O16,'Mapa Oficinas'!$A$7:$C$46,3,FALSE) -> Villa La Angostura
A17: 45663 | B17: CPH6635419 | D17: PH duplex | E17: Realizado | F17: Teléfono | G17: 114000 | H17: 114000 | I17: Dólares | J17: Dólares | K17: ph duplex 139 50 y139 50 y 52 52 | L17: Argentina | G.B.A. Zona Sur | La Plata | La Plata | M17: PH | N17: 1 | O17: Golden Team | P17: Compartida Fuera de la Red Búsqueda | Q17: Venta | R17: =VLOOKUP($O17,'Mapa Oficinas'!$A$7:$C$46,2,FALSE) -> Zona Sur (GBA) | S17: =VLOOKUP($O17,'Mapa Oficinas'!$A$7:$C$46,3,FALSE) -> La Plata
A18: 45663 | B18: 10257 | D18: Ecuador 1182 5A | E18: Realizado | F18: AR ZonaProp | G18: 0 | H18: 163000 | I18: Dólares | J18: Dólares | L18: Argentina | Capital Federal | Almagro | M18: Departamento | N18: 1 | O18: Seniority | P18: Compartida Fuera de la Red Búsqueda | Q18: Venta | R18: =VLOOKUP($O18,'Mapa Oficinas'!$A$7:$C$46,2,FALSE) -> CABA | S18: =VLOOKUP($O18,'Mapa Oficinas'!$A$7:$C$46,3,FALSE) -> Barrio Parque
A19: 45664 | B19: VCO60746 AP6653300 | C19: 1 | D19: Departamento 2 ambientes a estrenar con amenities | E19: Realizado | F19: AR ZonaProp | G19: 99900 | H19: 85000 | I19: Dólares | J19: Dólares | K19: Guiraldes 400 | L19: Argentina | G.B.A. Zona Norte | Tigre | Don Torcuato | Ibanez | M19: Departamento | N19: 2 | O19: Puerto Norte | P19: Propia (Único Asesor) | Q19: Venta | R19: =VLOOKUP($O19,'Mapa Oficinas'!$A$7:$C$46,2,FALSE) -> Zona Norte (GBA) | S19: =VLOOKUP($O19,'Mapa Oficinas'!$A$7:$C$46,3,FALSE) -> Nordelta
A20: 45664 | B20: GRANADEROS CABA | C20: 1 | D20: DPTO GRANADEROS | E20: Realizado | F20: AR ZonaProp | G20: 95000 | H20: 95000 | I20: Dólares | J20: Dólares | K20: GRANADERO 467 | L20: Argentina | Capital Federal | Flores | M20: Departamento | N20: 2 | O20: Puerto Norte | P20: Propia (Único Asesor) | Q20: Venta | R20: =VLOOKUP($O20,'Mapa Oficinas'!$A$7:$C$46,2,FALSE) -> Zona Norte (GBA) | S20: =VLOOKUP($O20,'Mapa Oficinas'!$A$7:$C$46,3,FALSE) -> Nordelta
A21: 45664 | B21: Bartolomé Hidalgo 3056 | C21: 1 | D21: Bartolomé Hidalgo 3056 | E21: Realizado | F21: AR MercadoLibre | G21: 218000 | H21: 218000 | I21: Dólares | J21: Dólares | K21: Bartolomé Hidalgo 3056 | L21: Argentina | Capital Federal | Capital Federal | M21: Casa | N21: 2 | O21: Lion Team | P21: Propia (Único Asesor) | Q21: Venta | R21: =VLOOKUP($O21,'Mapa Oficinas'!$A$7:$C$46,2,FALSE) -> CABA | S21: =VLOOKUP($O21,'Mapa Oficinas'!$A$7:$C$46,3,FALSE) -> Villa Urquiza
A22: 45665 | B22: TerrenoLomasdelCauquen | D22: Terreno Monte Moro N°541 | E22: Realizado | F22: Salón | G22: 0 | H22: 52500 | I22: Dólares | J22: Dólares | L22: Argentina | Rio Negro | Bariloche | San Carlos De Bariloche | M22: Terreno | N22: 1 | O22: Patagonia Lakes BRC | P22: (Interior) Compartida Fuera de la Red Búsqueda | Q22: Venta | R22: =VLOOKUP($O22,'Mapa Oficinas'!$A$7:$C$46,2,FALSE) -> Interior - Río Negro | S22: =VLOOKUP($O22,'Mapa Oficinas'!$A$7:$C$46,3,FALSE) -> Bariloche
A23: 45665 | B23: CAP6492529 | D23: venta - Departamento dos ambientes - villa urquiza - balcon - amenities | E23: Realizado | F23: AR ZonaProp | G23: 125000 | H23: 120000 | I23: Dólares | J23: Dólares | K23: Pedro Ignacio Rivera al 4700 | L23: Argentina | Capital Federal | Villa Urquiza | M23: Departamento | N23: 2 | O23: Lion Team | P23: Compartida en Oficina (Dos Asesores) | Q23: Venta | R23: =VLOOKUP($O23,'Mapa Oficinas'!$A$7:$C$46,2,FALSE) -> CABA | S23: =VLOOKUP($O23,'Mapa Oficinas'!$A$7:$C$46,3,FALSE) -> Villa Urquiza
A24: 45666 | B24: CHO6440273 | C24: 1 | D24: VENTA Casa 2 ambientes 60m² dos plantas Terreno 200m² B° Los Manzanos, San Martín de los Andes | E24: Realizado | F24: Teléfono | G24: 42000 | H24: 42000 | I24: Dólares | J24: Dólares | K24: Lote 3, mza E | L24: Argentina | Neuquen | Lacar | San Martin De Los Andes | Chacra 28 | M24: Casa | N24: 2 | O24: Patagonia Lakes SMA | P24: Propia (Único Asesor) | Q24: Venta | R24: =VLOOKUP($O24,'Mapa Oficinas'!$A$7:$C$46,2,FALSE) -> Interior - Neuquén | S24: =VLOOKUP($O24,'Mapa Oficinas'!$A$7:$C$46,3,FALSE) -> San Martín de los Andes
A25: 45666 | B25: CGL6038938 | C25: 1 | D25: Galpón en Sarandi | E25: Realizado | F25: AR ZonaProp | G25: 75000 | H25: 45000 | I25: Dólares | J25: Dólares | K25: Helguera al 2500 | L25: Argentina | G.B.A. Zona Sur | Avellaneda | Sarandi | N25: 2 | O25: Destino | P25: Propia (Único Asesor) | Q25: Venta | R25: =VLOOKUP($O25,'Mapa Oficinas'!$A$7:$C$46,2,FALSE) -> CABA | S25: =VLOOKUP($O25,'Mapa Oficinas'!$A$7:$C$46,3,FALSE) -> Recoleta
A26: 45666 | B26: CBU49671 AP6414022 | C26: 1 | D26: Departamento Monoambiente dividido A Estrenar Balcon frente Villa Urquiza VENTA | E26: Realizado | F26: AR MercadoLibre | G26: 79000 | H26: 80000 | I26: Dólares | J26: Dólares | K26: Bauness al 1100 | L26: Argentina | Capital Federal | Villa Urquiza | M26: Departamento | N26: 2 | O26: Lion Team | P26: Propia (Único Asesor) | Q26: Venta | R26: =VLOOKUP($O26,'Mapa Oficinas'!$A$7:$C$46,2,FALSE) -> CABA | S26: =VLOOKUP($O26,'Mapa Oficinas'!$A$7:$C$46,3,FALSE) -> Villa Urquiza
A27: 45666 | B27: CAP6674303 | D27: pujol 1095 7A | E27: Realizado | F27: AR ZonaProp | G27: 110000 | H27: 110000 | I27: Dólares | J27: Dólares | K27: Pujol 1095 7A | L27: Argentina | Capital Federal | Caballito | M27: Departamento | N27: 1 | O27: Notable | P27: Compartida Fuera de la Red Búsqueda | Q27: Venta | R27: =VLOOKUP($O27,'Mapa Oficinas'!$A$7:$C$46,2,FALSE) -> CABA | S27: =VLOOKUP($O27,'Mapa Oficinas'!$A$7:$C$46,3,FALSE) -> Palermo
A28: 45666 | D28: Departamento 2 ambientes de 58,97 m2? - UF 58, parte del Edificio Nº 2 más su unidad complementaria (cochera) N° 2, conforme croquis adjunto en el ANEXO III, ubicado en calle Las Retamas y Las Mutisias, que será parte del Fideicomiso Retamas, emprendimie | E28: Realizado | F28: Teléfono | G28: 118402 | H28: 118402 | I28: Dólares | J28: Dólares | K28: Retamas 200 | L28: Argentina | Neuquen | Villa La Angostura | Centro | M28: Departamento | N28: 2 | O28: Patagonia Lakes VLA | P28: Compartida en Oficina (Dos Asesores) | Q28: Venta | R28: =VLOOKUP($O28,'Mapa Oficinas'!$A$7:$C$46,2,FALSE) -> Interior - Neuquén | S28: =VLOOKUP($O28,'Mapa Oficinas'!$A$7:$C$46,3,FALSE) -> Villa La Angostura
A29: 45667 | B29: CAP6403040 | D29: DEPARTAMENTO en 1 y 57 LA PLATA | E29: Realizado | F29: Referido | G29: 45000 | H29: 40000 | I29: Dólares | J29: Dólares | K29: DEPARTAMENTO 1 dormitorio en 1 y 57 | L29: Argentina | G.B.A. Zona Sur | La Plata | La Plata | M29: Departamento | N29: 2 | O29: Golden Team | P29: Propia (Único Asesor) | Q29: Venta | R29: =VLOOKUP($O29,'Mapa Oficinas'!$A$7:$C$46,2,FALSE) -> Zona Sur (GBA) | S29: =VLOOKUP($O29,'Mapa Oficinas'!$A$7:$C$46,3,FALSE) -> La Plata
A30: 45667 | B30: CBU60695 AP6633713 | D30: Departamento en Venta en Lujan de Cuyo - Mendoza | E30: Realizado | F30: Conocido | G30: 45000 | H30: 45000 | I30: Dólares | J30: Dólares | K30: Azcuenaga s/n | L30: Argentina | Mendoza | Lujan De Cuyo | M30: Departamento | N30: 1 | O30: Cuyo Real | P30: (Interior) Compartida Fuera de la Red Captación Propia | Q30: Venta | R30: =VLOOKUP($O30,'Mapa Oficinas'!$A$7:$C$46,2,FALSE) -> Interior - Mendoza | S30: =VLOOKUP($O30,'Mapa Oficinas'!$A$7:$C$46,3,FALSE) -> Capital Mendoza
A31: 45667 | B31: CLA5824535 | D31: Oportunidad de inversión! Terreno en Tres Cerritos con hermosas vistas de la ciudad. | E31: Realizado | F31: Facebook | G31: 45000 | H31: 45000 | I31: Dólares | J31: Dólares | K31: Los Parrales al 800 | L31: Argentina | Salta | Capital | Salta | Bo.Tres Cerritos | M31: Terreno | N31: 2 | O31: Realty Group | P31: Propia (Único Asesor) | Q31: Venta | R31: =VLOOKUP($O31,'Mapa Oficinas'!$A$7:$C$46,2,FALSE) -> Interior - Salta | S31: =VLOOKUP($O31,'Mapa Oficinas'!$A$7:$C$46,3,FALSE) -> San Lorenzo Chico
A32: 45667 | B32: CHO6149910 | D32: Casa en Venta para reciclar - Tupungato - Mendoza | E32: Realizado | F32: AR ZonaProp | G32: 70000 | H32: 55000 | I32: Dólares | J32: Dólares | K32: Calle Irigoyen al 200 | L32: Argentina | Mendoza | Tupungato | San Jose De Tupungato | M32: Casa | N32: 2 | O32: Cuyo Real | P32: Propia (Único Asesor) | Q32: Venta | R32: =VLOOKUP($O32,'Mapa Oficinas'!$A$7:$C$46,2,FALSE) -> Interior - Mendoza | S32: =VLOOKUP($O32,'Mapa Oficinas'!$A$7:$C$46,3,FALSE) -> Capital Mendoza
A33: 45667 | D33: PARANA 3296 | E33: Realizado | F33: AR ZonaProp | G33: 88000 | H33: 88000 | I33: Dólares | J33: Dólares | K33: PARANA 3296 | L33: Argentina | G.B.A. Zona Norte | Vicente López | Olivos | M33: Casa | N33: 2 | O33: Lion Team Norte | P33: Propia (Único Asesor) | Q33: Venta | R33: =VLOOKUP($O33,'Mapa Oficinas'!$A$7:$C$46,2,FALSE) -> Zona Norte (GBA) | S33: =VLOOKUP($O33,'Mapa Oficinas'!$A$7:$C$46,3,FALSE) -> Vicente López
A34: 45667 | B34: CHO6571935 | D34: Casa en barrio Sto. Cabral- Santa Fe | E34: Realizado | F34: AR ZonaProp | G34: 115000 | H34: 105000 | I34: Dólares | J34: Dólares | K34: Pje Madeo al 4400 | L34: Argentina | Santa Fe | La Capital | Santa Fe | Sargento Cabral | M34: Casa | N34: 1 | O34: De la Veracruz | P34: (Interior) Compartida Fuera de la Red Captación Propia | Q34: Venta | R34: =VLOOKUP($O34,'Mapa Oficinas'!$A$7:$C$46,2,FALSE) -> Interior - Santa Fe | S34: =VLOOKUP($O34,'Mapa Oficinas'!$A$7:$C$46,3,FALSE) -> Capital Santa Fe
A35: 45667 | B35: Búsqueda | D35: Búsqueda | E35: Realizado | F35: AR ZonaProp | G35: 163000 | H35: 163000 | I35: Dólares | J35: Dólares | K35: Tinogasta 3128 5° "A" CABA | M35: Departamento | N35: 1 | O35: Ser | P35: Compartida Fuera de la Red Búsqueda | Q35: Venta | R35: =VLOOKUP($O35,'Mapa Oficinas'!$A$7:$C$46,2,FALSE) -> CABA | S35: =VLOOKUP($O35,'Mapa Oficinas'!$A$7:$C$46,3,FALSE) -> Belgrano
A36: 45667 | B36: CPH6286814 | D36: PH EN MARTINEZ CON COCHERA CUBIERTA JARDIN INTRADA INDIVIDUAL TIPO CHALET | E36: Realizado | F36: AR ZonaProp | G36: 175000 | H36: 165000 | I36: Dólares | J36: Dólares | K36: VELEZ SARSFIELD 800 | L36: Argentina | G.B.A. Zona Norte | San Isidro | Martinez | M36: PH | N36: 2 | O36: Lion Team Norte | P36: Propia (Único Asesor) | Q36: Venta | R36: =VLOOKUP($O36,'Mapa Oficinas'!$A$7:$C$46,2,FALSE) -> Zona Norte (GBA) | S36: =VLOOKUP($O36,'Mapa Oficinas'!$A$7:$C$46,3,FALSE) -> Vicente López
A37: 45667 | B37: CAP6092043 | D37: Departamento en Villa Santa Rita | E37: Realizado | F37: AR ZonaProp | G37: 179000 | H37: 170000 | I37: Dólares | J37: Dólares | K37: Camarones al 3100 | L37: Argentina | Capital Federal | Villa del Parque | M37: Departamento | N37: 2 | O37: Ser | P37: Propia (Único Asesor) | Q37: Venta | R37: =VLOOKUP($O37,'Mapa Oficinas'!$A$7:$C$46,2,FALSE) -> CABA | S37: =VLOOKUP($O37,'Mapa Oficinas'!$A$7:$C$46,3,FALSE) -> Belgrano
A38: 45667 | B38: CPH6260765 | D38: Duplex a Estrenar de 3 Dormitorios en Venta en Confluencia | E38: Realizado | F38: AR ZonaProp | G38: 170000 | H38: 170000 | I38: Dólares | J38: Dólares | K38: granaderos al 500 | L38: Argentina | Neuquen | Capital | Confluencia Urbana | M38: PH | N38: 2 | O38: Sensus | P38: Propia (Único Asesor) | Q38: Venta | R38: =VLOOKUP($O38,'Mapa Oficinas'!$A$7:$C$46,2,FALSE) -> Interior - Neuquén | S38: =VLOOKUP($O38,'Mapa Oficinas'!$A$7:$C$46,3,FALSE) -> Capital Neuquén
A39: 45667 | B39: CAP6280063 | D39: Venta 3 ambientes con patio propio reciclado mas cochera! | E39: Realizado | F39: AR ZonaProp | G39: 215000 | H39: 200000 | I39: Dólares | J39: Dólares | K39: Avenida Pueyrredon al 2100 | L39: Argentina | Capital Federal | Recoleta | M39: Departamento | N39: 2 | O39: Destino | P39: Propia (Único Asesor) | Q39: Venta | R39: =VLOOKUP($O39,'Mapa Oficinas'!$A$7:$C$46,2,FALSE) -> CABA | S39: =VLOOKUP($O39,'Mapa Oficinas'!$A$7:$C$46,3,FALSE) -> Recoleta
A40: 45669 | B40: VAP6500846 | D40: Departamento en venta !! OPORTUNIDAD | E40: Realizado | F40: AR ZonaProp | G40: 105000 | H40: 105000 | I40: Dólares | J40: Dólares | K40: Cramer 1660 al 1600 | L40: Argentina | Capital Federal | Belgrano | M40: Departamento | N40: 2 | O40: Puerto Norte | P40: Compartida en Oficina (Dos Asesores) | Q40: Venta | R40: =VLOOKUP($O40,'Mapa Oficinas'!$A$7:$C$46,2,FALSE) -> Zona Norte (GBA) | S40: =VLOOKUP($O40,'Mapa Oficinas'!$A$7:$C$46,3,FALSE) -> Nordelta
A41: 45669 | B41: VHO5927190 | D41: Casa de Santa Ana Joven - 3 AMB - OPORTUNIDAD- Villanueva | E41: Realizado | F41: AR ZonaProp | G41: 150000 | H41: 155000 | I41: Dólares | J41: Dólares | K41: Casa de Santa Ana Joven - 3 AMB - OPORTUNIDAD- Villanueva | L41: Argentina | G.B.A. Zona Norte | Tigre | Benavidez | Santa Ana Joven | M41: Casa | N41: 1 | O41: Puerto Norte | P41: (Interior) Compartida Fuera de la Red Captación Propia | Q41: Venta | R41: =VLOOKUP($O41,'Mapa Oficinas'!$A$7:$C$46,2,FALSE) -> Zona Norte (GBA) | S41: =VLOOKUP($O41,'Mapa Oficinas'!$A$7:$C$46,3,FALSE) -> Nordelta
A42: 45669 | B42: VHO6454255 | D42: Casa en Venta - 4 AMB a Estrenar en Santa Isabel II | E42: Realizado | F42: AR ZonaProp | G42: 175000 | H42: 175000 | I42: Dólares | J42: Dólares | K42: Casa en Venta - 4 AMB a Estrenar en Santa Isabel II | L42: Argentina | G.B.A. Zona Norte | Escobar | Ingeniero Maschwitz | M42: Casa | N42: 2 | O42: Puerto Norte | P42: Propia (Único Asesor) | Q42: Venta | R42: =VLOOKUP($O42,'Mapa Oficinas'!$A$7:$C$46,2,FALSE) -> Zona Norte (GBA) | S42: =VLOOKUP($O42,'Mapa Oficinas'!$A$7:$C$46,3,FALSE) -> Nordelta
A43: 45669 | B43: TORRES ZAFIRO | D43: TORRES ZAFIRO | E43: Realizado | F43: AR ZonaProp | G43: 307200 | H43: 206700 | I43: Dólares | J43: Dólares | K43: Ruta 27, Torres Zafiro | L43: Argentina | G.B.A. Zona Norte | Tigre | Countries/B.Cerrado (Tigre) | Nordelta | M43: Departamento | N43: 2 | O43: Puerto Norte | P43: Compartida Fuera de la Red Captación Propia | Q43: Venta | R43: =VLOOKUP($O43,'Mapa Oficinas'!$A$7:$C$46,2,FALSE) -> Zona Norte (GBA) | S43: =VLOOKUP($O43,'Mapa Oficinas'!$A$7:$C$46,3,FALSE) -> Nordelta
A44: 45670 | B44: CBA47695 LA6368113 | D44: VENTA terreno de 315,33 m2 en LOTEO "ANTIGUO CAMINO" Bariloche | E44: Realizado | F44: Teléfono | G44: 44150 | H44: 44146 | I44: Dólares | J44: Dólares | K44: Antiguo Camino, San Carlos de Bariloche | L44: Argentina | Rio Negro | Bariloche | San Carlos De Bariloche | Lago Moreno | M44: Terreno | N44: 2 | O44: Patagonia Lakes BRC | P44: Propia (Único Asesor) | Q44: Venta | R44: =VLOOKUP($O44,'Mapa Oficinas'!$A$7:$C$46,2,FALSE) -> Interior - Río Negro | S44: =VLOOKUP($O44,'Mapa Oficinas'!$A$7:$C$46,3,FALSE) -> Bariloche
A45: 45670 | B45: Salcedo 2913 | D45: Salcedo 2913 | E45: Realizado | F45: AR MercadoLibre | G45: 55000 | H45: 55000 | I45: Dólares | J45: Dólares | K45: Salcedo 2913 | L45: Argentina | Capital Federal | Capital Federal | M45: Departamento | N45: 2 | O45: Lion Team | P45: Propia (Único Asesor) | Q45: Venta | R45: =VLOOKUP($O45,'Mapa Oficinas'!$A$7:$C$46,2,FALSE) -> CABA | S45: =VLOOKUP($O45,'Mapa Oficinas'!$A$7:$C$46,3,FALSE) -> Villa Urquiza
A46: 45670 | B46: CAP6681895 | D46: Venta Departamento en Pozo, 39m2, Barrio Belgrano | E46: Realizado | F46: Teléfono | G46: 90000 | H46: 90000 | I46: Dólares | J46: Dólares | K46: salta al 300 | L46: Argentina | Rio Negro | Bariloche | San Carlos De Bariloche | Centro | M46: Departamento | N46: 2 | O46: Patagonia Lakes BRC | P46: Propia (Único Asesor) | Q46: Venta | R46: =VLOOKUP($O46,'Mapa Oficinas'!$A$7:$C$46,2,FALSE) -> Interior - Río Negro | S46: =VLOOKUP($O46,'Mapa Oficinas'!$A$7:$C$46,3,FALSE) -> Bariloche
A47: 45671 | B47: CAP6662178 | D47: Departamento Monoambiente en Venta de pozo en 50 entre 26 y 27 | E47: Realizado | F47: Referido | G47: 50500 | H47: 73400 | I47: Dólares | J47: Dólares | K47: Departamento Monoambiente en Venta de pozo en 50 entre 26 y 27 | L47: Argentina | G.B.A. Zona Sur | La Plata | La Plata | M47: Departamento | N47: 2 | O47: Golden Team | P47: Propia (Único Asesor) | Q47: Venta | R47: =VLOOKUP($O47,'Mapa Oficinas'!$A$7:$C$46,2,FALSE) -> Zona Sur (GBA) | S47: =VLOOKUP($O47,'Mapa Oficinas'!$A$7:$C$46,3,FALSE) -> La Plata
A48: 45671 | B48: CAP6517340 | D48: VENTA DEPARTAMENTO 3 AMBIENTES EN FLORIDA | E48: Realizado | F48: AR ZonaProp | G48: 145000 | H48: 137000 | I48: Dólares | J48: Dólares | K48: Vergara al 2300 | L48: Argentina | G.B.A. Zona Norte | Vicente López | Florida | M48: Departamento | N48: 2 | O48: Seniority | P48: Propia (Único Asesor) | Q48: Venta | R48: =VLOOKUP($O48,'Mapa Oficinas'!$A$7:$C$46,2,FALSE) -> CABA | S48: =VLOOKUP($O48,'Mapa Oficinas'!$A$7:$C$46,3,FALSE) -> Barrio Parque
A49: 45671 | B49: 10262 | D49: Malaver 2725 | E49: Realizado | F49: AR ZonaProp | G49: 0 | H49: 140000 | I49: Dólares | J49: Dólares | K49: malaver | L49: Argentina | G.B.A. Zona Norte | Vicente López | Florida | Florida Mitre/Este | M49: Departamento | N49: 1 | O49: Seniority | P49: Compartida Fuera de la Red Búsqueda | Q49: Venta | R49: =VLOOKUP($O49,'Mapa Oficinas'!$A$7:$C$46,2,FALSE) -> CABA | S49: =VLOOKUP($O49,'Mapa Oficinas'!$A$7:$C$46,3,FALSE) -> Barrio Parque
A50: 45671 | B50: Emi63 | D50: Casa en Guadalupe | E50: Realizado | F50: Cartel | G50: 150000 | H50: 145000 | I50: Dólares | J50: Dólares | K50: Cardenal Fasolino 466 | L50: Argentina | Santa Fe | La Capital | Santa Fe | M50: Casa | N50: 1 | O50: De la Veracruz | P50: (Interior) Compartida Fuera de la Red Búsqueda | Q50: Venta | R50: =VLOOKUP($O50,'Mapa Oficinas'!$A$7:$C$46,2,FALSE) -> Interior - Santa Fe | S50: =VLOOKUP($O50,'Mapa Oficinas'!$A$7:$C$46,3,FALSE) -> Capital Santa Fe
A51: 45671 | B51: VHO6370655 | D51: Casa en Country Club Privado Loma Verde | E51: Realizado | F51: AR ZonaProp | G51: 150000 | H51: 161000 | I51: Dólares | J51: Dólares | K51: Casa en Club Privado Loma Verde | L51: Argentina | G.B.A. Zona Norte | Escobar | Loma Verde | Country Club Privado Loma Verde | M51: Casa | N51: 2 | O51: Puerto Norte | P51: Compartida en Oficina (Dos Asesores) | Q51: Venta | R51: =VLOOKUP($O51,'Mapa Oficinas'!$A$7:$C$46,2,FALSE) -> Zona Norte (GBA) | S51: =VLOOKUP($O51,'Mapa Oficinas'!$A$7:$C$46,3,FALSE) -> Nordelta
A52: 45671 | B52: 10225 | D52: Cramer 2547 9B | E52: Realizado | F52: AR ZonaProp | G52: 0 | H52: 300000 | I52: Dólares | J52: Dólares | L52: Argentina | Capital Federal | Belgrano | M52: Departamento | N52: 2 | O52: Seniority | P52: Propia (Único Asesor) | Q52: Venta | R52: =VLOOKUP($O52,'Mapa Oficinas'!$A$7:$C$46,2,FALSE) -> CABA | S52: =VLOOKUP($O52,'Mapa Oficinas'!$A$7:$C$46,3,FALSE) -> Barrio Parque
A53: 45672 | B53: 10159 | D53: la perdiz | E53: Realizado | F53: Web Coldwell-Banker | G53: 0 | H53: 77500 | I53: Dólares | J53: Dólares | L53: Argentina | G.B.A. Zona Norte | Pilar | M53: Casa | N53: 2 | O53: Seniority | P53: Compartida en Red (50%) | Q53: Venta | R53: =VLOOKUP($O53,'Mapa Oficinas'!$A$7:$C$46,2,FALSE) -> CABA | S53: =VLOOKUP($O53,'Mapa Oficinas'!$A$7:$C$46,3,FALSE) -> Barrio Parque
A54: 45672 | B54: CBU39556 AP3990515 | D54: VENTA Departamento 2 Ambientes - Monserrat | E54: Realizado | F54: AR ZonaProp | G54: 96000 | H54: 95000 | I54: Dólares | J54: Dólares | K54: Sáenz Peña al 1000 | L54: Argentina | Capital Federal | Monserrat | M54: Departamento | N54: 2 | O54: Seniority | P54: Propia (Único Asesor) | Q54: Venta | R54: =VLOOKUP($O54,'Mapa Oficinas'!$A$7:$C$46,2,FALSE) -> CABA | S54: =VLOOKUP($O54,'Mapa Oficinas'!$A$7:$C$46,3,FALSE) -> Barrio Parque
A55: 45672 | B55: 10271 | D55: B cerrado valle claro | E55: Realizado | F55: AR ZonaProp | G55: 0 | H55: 134000 | I55: Dólares | J55: Dólares | L55: Argentina | G.B.A. Zona Norte | Tigre | Benavidez | M55: Departamento | N55: 1 | O55: Seniority | P55: Compartida Fuera de la Red Búsqueda | Q55: Venta | R55: =VLOOKUP($O55,'Mapa Oficinas'!$A$7:$C$46,2,FALSE) -> CABA | S55: =VLOOKUP($O55,'Mapa Oficinas'!$A$7:$C$46,3,FALSE) -> Barrio Parque
A56: 45672 | C56: 1 | D56: Departamento en construcción MBV Manzano Bay View UF XXVI y UC (a designar) de baulera de total de 72,5 m2 (cubierta 58 m2 + Terraza 12 + 2,5 baulera m2) | E56: Realizado | F56: Conocido | G56: 213000 | H56: 213000 | I56: Dólares | J56: Dólares | L56: Argentina | Neuquen | Villa La Angostura | Puerto Manzano | M56: Departamento | N56: 2 | O56: Patagonia Lakes VLA | P56: Master | Q56: Venta | R56: =VLOOKUP($O56,'Mapa Oficinas'!$A$7:$C$46,2,FALSE) -> Interior - Neuquén | S56: =VLOOKUP($O56,'Mapa Oficinas'!$A$7:$C$46,3,FALSE) -> Villa La Angostura
A57: 45672 | C57: 0 | D57: Departamento en construcción MBV Manzano Bay View UF XXVI y UC (a designar) de baulera de total de 72,5 m2 (cubierta 58 m2 + Terraza 12 + 2,5 baulera m2) | E57: Realizado | F57: AR ZonaProp | G57: 213000 | H57: 213000 | I57: Dólares | J57: Dólares | L57: Argentina | Neuquen | Villa La Angostura | Puerto Manzano | M57: Departamento | N57: 2 | O57: Patagonia Lakes SMA | P57: Master | Q57: Venta | R57: =VLOOKUP($O57,'Mapa Oficinas'!$A$7:$C$46,2,FALSE) -> Interior - Neuquén | S57: =VLOOKUP($O57,'Mapa Oficinas'!$A$7:$C$46,3,FALSE) -> San Martín de los Andes
A58: 45673 | B58: CAP6003828 | D58: Departamento en Venta Complejo Jardines de Esmeralda | E58: Realizado | F58: AR ZonaProp | G58: 59000 | H58: 59000 | I58: Dólares | J58: Dólares | K58: Miguel Muñoz al 1000 | L58: Argentina | Rio Negro | Cipolletti | M58: Departamento | N58: 2 | O58: Sensus | P58: Compartida Fuera de la Red Captación Propia | Q58: Venta | R58: =VLOOKUP($O58,'Mapa Oficinas'!$A$7:$C$46,2,FALSE) -> Interior - Neuquén | S58: =VLOOKUP($O58,'Mapa Oficinas'!$A$7:$C$46,3,FALSE) -> Capital Neuquén
A59: 45673 | B59: CAP6118322 | D59: Venta Departamento 2 Ambientes a Estrenar en Caseros | E59: Realizado | F59: AR ZonaProp | G59: 65500 | H59: 65000 | I59: Dólares | J59: Dólares | K59: David Magdalena al 2700 | L59: Argentina | G.B.A. Zona Oeste | Tres De Febrero | Caseros | M59: Departamento | N59: 2 | O59: Seniority Plus | P59: Compartida Fuera de la Red Captación Propia | Q59: Venta | R59: =VLOOKUP($O59,'Mapa Oficinas'!$A$7:$C$46,2,FALSE) -> CABA | S59: =VLOOKUP($O59,'Mapa Oficinas'!$A$7:$C$46,3,FALSE) -> Palermo
A60: 45673 | B60: CAP6454429 | D60: VENTA Departamento 2 ambientes A estrenar Balcón al Frente Villa Urquiza | E60: Realizado | F60: AR MercadoLibre | G60: 102000 | H60: 75500 | I60: Dólares | J60: Dólares | K60: Bauness al 1100 | L60: Argentina | Capital Federal | Villa Urquiza | M60: Departamento | N60: 2 | O60: Lion Team | P60: Propia (Único Asesor) | Q60: Venta | R60: =VLOOKUP($O60,'Mapa Oficinas'!$A$7:$C$46,2,FALSE) -> CABA | S60: =VLOOKUP($O60,'Mapa Oficinas'!$A$7:$C$46,3,FALSE) -> Villa Urquiza
A61: 45673 | B61: CAP6625851 | D61: Venta Departamento 2 ambientes en Belgrano muy luminoso y silencioso excelente ubicación. | E61: Realizado | F61: AR ZonaProp | G61: 85000 | H61: 82000 | I61: Dólares | J61: Dólares | K61: OLAZÁBAL al 2000 | L61: Argentina | Capital Federal | Belgrano | Belgrano Barrancas | M61: Departamento | N61: 2 | O61: Seniority | P61: Propia (Único Asesor) | Q61: Venta | R61: =VLOOKUP($O61,'Mapa Oficinas'!$A$7:$C$46,2,FALSE) -> CABA | S61: =VLOOKUP($O61,'Mapa Oficinas'!$A$7:$C$46,3,FALSE) -> Barrio Parque
A62: 45673 | B62: CAP6566341 | D62: Depto 2 amb con Jardin Venta- Lagoon Pilar | E62: Realizado | F62: Referido | G62: 750 | H62: 100000 | I62: Dólares | J62: Dólares | K62: Depto 2 amb con Jardin Venta- Lagoon Pilar | L62: Argentina | G.B.A. Zona Norte | Pilar | Countries/B.Cerrado (Pilar) | Lagoon Pilar | M62: Departamento | N62: 2 | O62: North Team | P62: Propia (Único Asesor) | Q62: Venta | R62: =VLOOKUP($O62,'Mapa Oficinas'!$A$7:$C$46,2,FALSE) -> Zona Norte (GBA) | S62: =VLOOKUP($O62,'Mapa Oficinas'!$A$7:$C$46,3,FALSE) -> Pilar
A63: 45673 | B63: CAP6440015 | D63: VENTA DEPARTAMENTO 3 AMBIENTES BALCON CORRIDO COGHLAN | E63: Realizado | F63: AR ArgenProp | G63: 114999 | H63: 105000 | I63: Dólares | J63: Dólares | K63: Manuela Pedraza al 3600 | L63: Argentina | Capital Federal | Coghlan | M63: Departamento | N63: 2 | O63: Lion Team | P63: Propia (Único Asesor) | Q63: Venta | R63: =VLOOKUP($O63,'Mapa Oficinas'!$A$7:$C$46,2,FALSE) -> CABA | S63: =VLOOKUP($O63,'Mapa Oficinas'!$A$7:$C$46,3,FALSE) -> Villa Urquiza
A64: 45673 | B64: CAP6420218 | D64: Venta Departamento Monoambiente con Balcón y Cochera en Las Cañitas | E64: Realizado | F64: AR ZonaProp | G64: 115000 | H64: 115000 | I64: Dólares | J64: Dólares | K64: Eslovenia 1900 | L64: Argentina | Capital Federal | Palermo | Las Cañitas | M64: Departamento | N64: 2 | O64: Seniority Plus | P64: Compartida en Oficina (Dos Asesores) | Q64: Venta | R64: =VLOOKUP($O64,'Mapa Oficinas'!$A$7:$C$46,2,FALSE) -> CABA | S64: =VLOOKUP($O64,'Mapa Oficinas'!$A$7:$C$46,3,FALSE) -> Palermo
A65: 45673 | B65: CPN55403 AP6593779 | D65: Venta OPORTUNIDAD Departamento 3 ambientes a estrenar - Lagoon Pilar | E65: Realizado | F65: Referido | G65: 850 | H65: 125000 | I65: Dólares | J65: Dólares | K65: Venta OPORTUNIDAD Departamento 3 ambientes a estrenar - Lagoon Pilar | L65: Argentina | G.B.A. Zona Norte | Pilar | Countries/B.Cerrado (Pilar) | Lagoon Pilar | M65: Departamento | N65: 2 | O65: North Team | P65: Compartida en Oficina (Dos Asesores) | Q65: Venta | R65: =VLOOKUP($O65,'Mapa Oficinas'!$A$7:$C$46,2,FALSE) -> Zona Norte (GBA) | S65: =VLOOKUP($O65,'Mapa Oficinas'!$A$7:$C$46,3,FALSE) -> Pilar
A66: 45673 | B66: CHO5699741 | D66: VENTA CASA LOTE PROPIO 6 AMBIENTES DOS COCHERAS PISCINA TERRAZA JARDIN TERRAZA | E66: Realizado | F66: AR ZonaProp | G66: 169900 | H66: 163000 | I66: Dólares | J66: Dólares | K66: Sargento Cabral al 3200 | L66: Argentina | G.B.A. Zona Norte | Vicente López | Munro | Munro-Este | M66: Casa | N66: 2 | O66: Lion Team | P66: Propia (Único Asesor) | Q66: Venta | R66: =VLOOKUP($O66,'Mapa Oficinas'!$A$7:$C$46,2,FALSE) -> CABA | S66: =VLOOKUP($O66,'Mapa Oficinas'!$A$7:$C$46,3,FALSE) -> Villa Urquiza
A67: 45674 | B67: Pola 2800 | D67: POLA 2855 DPTO 3 | E67: Realizado | F67: AR ZonaProp | G67: 36500 | H67: 36500 | I67: Dólares | J67: Dólares | K67: POLA 2855 DPTO 3 | L67: Argentina | Capital Federal | Villa Lugano | M67: PH | N67: 2 | O67: Lion Team Norte | P67: Propia (Único Asesor) | Q67: Venta | R67: =VLOOKUP($O67,'Mapa Oficinas'!$A$7:$C$46,2,FALSE) -> Zona Norte (GBA) | S67: =VLOOKUP($O67,'Mapa Oficinas'!$A$7:$C$46,3,FALSE) -> Vicente López
A68: 45674 | B68: CLA6695688 | D68: VENTA Lote/Terreno 1.651,30m2 Las Marías del Valle, Club de campo, San Martín de los Andes | E68: Realizado | F68: Teléfono | G68: 50000 | H68: 40000 | I68: Dólares | J68: Dólares | K68: RN 40 al 2200 | L68: Argentina | Neuquen | Lacar | San Martin De Los Andes | Las Marias Del Valle | M68: Terreno | N68: 2 | O68: Patagonia Lakes SMA | P68: Propia (Único Asesor) | Q68: Venta | R68: =VLOOKUP($O68,'Mapa Oficinas'!$A$7:$C$46,2,FALSE) -> Interior - Neuquén | S68: =VLOOKUP($O68,'Mapa Oficinas'!$A$7:$C$46,3,FALSE) -> San Martín de los Andes
A69: 45674 | B69: CAP6700432 | D69: Departamento en venta Barrio Parque Belgrano - Zona Norte - Salta Capital | E69: Realizado | F69: Facebook | G69: 47000 | H69: 47000 | I69: Dólares | J69: Dólares | K69: Barrio Parque Belgrano Block 17 | L69: Argentina | Salta | Capital | Salta | Zona Norte | M69: Departamento | N69: 1 | O69: Realty Group | P69: (Interior) Compartida Fuera de la Red Búsqueda | Q69: Venta | R69: =VLOOKUP($O69,'Mapa Oficinas'!$A$7:$C$46,2,FALSE) -> Interior - Salta | S69: =VLOOKUP($O69,'Mapa Oficinas'!$A$7:$C$46,3,FALSE) -> San Lorenzo Chico
... A79: 45678 | B79: CHO6750139 | D79: Old man 704, lote 480 | E79: Realizado | F79: AR ZonaProp | G79: 220000 | H79: 185000 | I79: Dólares | J79: Dólares | K79: Old man 704, lote 480 | L79: Argentina | G.B.A. Zona Norte | Escobar | Countries/B.Cerrado (Escobar) | Haras Santa Maria | M79: Casa | N79: 1 | O79: Notable | P79: Compartida Fuera de la Red Búsqueda | Q79: Venta | R79: =VLOOKUP($O79,'Mapa Oficinas'!$A$7:$C$46,2,FALSE) -> CABA | S79: =VLOOKUP($O79,'Mapa Oficinas'!$A$7:$C$46,3,FALSE) -> Palermo
A80: 45678 | B80: Casa venta Santa Ines | D80: Casa venta Santa Ines | E80: Realizado | F80: AR ZonaProp | G80: 220000 | H80: 220000 | I80: Dólares | J80: Dólares | L80: Argentina | G.B.A. Zona Sur | Ezeiza | M80: Casa | N80: 2 | O80: Livello | P80: Propia (Único Asesor) | Q80: Venta | R80: =VLOOKUP($O80,'Mapa Oficinas'!$A$7:$C$46,2,FALSE) -> CABA | S80: =VLOOKUP($O80,'Mapa Oficinas'!$A$7:$C$46,3,FALSE) -> Palermo
A81: 45679 | B81: CLA6660815 | D81: VENTA Lote 805m2 10 Manzana A POSTAL PATAGONIA San Martin de los Andes | E81: Realizado | F81: Conocido | G81: 68000 | H81: 68000 | I81: Dólares | J81: Dólares | K81: Ruta 40 | L81: Argentina | Neuquen | Lacar | San Martin De Los Andes | Centro | M81: Terreno | N81: 2 | O81: Patagonia Lakes SMA | P81: Propia (Único Asesor) | Q81: Venta | R81: =VLOOKUP($O81,'Mapa Oficinas'!$A$7:$C$46,2,FALSE) -> Interior - Neuquén | S81: =VLOOKUP($O81,'Mapa Oficinas'!$A$7:$C$46,3,FALSE) -> San Martín de los Andes
A82: 45679 | B82: CAP6382284 | D82: MONOAMBIENTE PREMIUM | E82: Realizado | F82: AR ZonaProp | G82: 82000 | H82: 80000 | I82: Dólares | J82: Dólares | K82: San Martin al 425 | L82: Argentina | Neuquen | Confluencia | Neuquen | M82: Departamento | N82: 2 | O82: Sensus | P82: Propia (Único Asesor) | Q82: Venta | R82: =VLOOKUP($O82,'Mapa Oficinas'!$A$7:$C$46,2,FALSE) -> Interior - Neuquén | S82: =VLOOKUP($O82,'Mapa Oficinas'!$A$7:$C$46,3,FALSE) -> Capital Neuquén
A83: 45680 | B83: CAP5978284 | D83: Venta - Departamento - 4 Ambientes - Luminoso - Parque Avellaneda | E83: Realizado | F83: AR ArgenProp | G83: 98000 | H83: 92000 | I83: Dólares | J83: Dólares | K83: Directorio al 4000 | L83: Argentina | Capital Federal | Parque Avellaneda | M83: Departamento | N83: 2 | O83: Lion Team | P83: Propia (Único Asesor) | Q83: Venta | R83: =VLOOKUP($O83,'Mapa Oficinas'!$A$7:$C$46,2,FALSE) -> CABA | S83: =VLOOKUP($O83,'Mapa Oficinas'!$A$7:$C$46,3,FALSE) -> Villa Urquiza
A84: 45680 | B84: Lautaro 46 | D84: Lautaro 46 | E84: Realizado | F84: AR MercadoLibre | G84: 92000 | H84: 92000 | I84: Dólares | J84: Dólares | K84: Lautaro 46 | L84: Argentina | Capital Federal | Capital Federal | M84: Departamento | N84: 2 | O84: Lion Team | P84: Propia (Único Asesor) | Q84: Venta | R84: =VLOOKUP($O84,'Mapa Oficinas'!$A$7:$C$46,2,FALSE) -> CABA | S84: =VLOOKUP($O84,'Mapa Oficinas'!$A$7:$C$46,3,FALSE) -> Villa Urquiza
A85: 45681 | B85: CHO4635234 | D85: Casa - Villa Santos Tesei | E85: Realizado | F85: AR ZonaProp | G85: 79900 | H85: 70000 | I85: Dólares | J85: Dólares | K85: Santa Monica al 4100 | L85: Argentina | G.B.A. Zona Oeste | Hurlingham | Villa Santos Tesei | M85: Casa | N85: 2 | O85: Lion Team | P85: Compartida en Red (50%) | Q85: Venta | R85: =VLOOKUP($O85,'Mapa Oficinas'!$A$7:$C$46,2,FALSE) -> CABA | S85: =VLOOKUP($O85,'Mapa Oficinas'!$A$7:$C$46,3,FALSE) -> Villa Urquiza
A86: 45681 | B86: CHO5741428 | D86: Casa en Barrio Sargento Cabral | E86: Realizado | F86: Conocido | G86: 99000 | H86: 90000 | I86: Dólares | J86: Dólares | K86: Sarmiento al 5300 | L86: Argentina | Santa Fe | La Capital | Santa Fe | Sargento Cabral | M86: Casa | N86: 2 | O86: De la Veracruz | P86: Compartida en Oficina (Dos Asesores) | Q86: Venta | R86: =VLOOKUP($O86,'Mapa Oficinas'!$A$7:$C$46,2,FALSE) -> Interior - Santa Fe | S86: =VLOOKUP($O86,'Mapa Oficinas'!$A$7:$C$46,3,FALSE) -> Capital Santa Fe
A87: 45681 | B87: CAP6516212 | D87: Departamento 3 ambientes - A Estrenar con Cochera - Beccar | E87: Realizado | F87: Referido | G87: 162000 | H87: 140000 | I87: Dólares | J87: Dólares | K87: Departamento 3 ambientes a estrenar en Beccar | L87: Argentina | G.B.A. Zona Norte | San Isidro | Beccar | M87: Departamento | N87: 2 | O87: North Team | P87: Master | Q87: Venta | R87: =VLOOKUP($O87,'Mapa Oficinas'!$A$7:$C$46,2,FALSE) -> Zona Norte (GBA) | S87: =VLOOKUP($O87,'Mapa Oficinas'!$A$7:$C$46,3,FALSE) -> Pilar
A88: 45682 | B88: CHO6603149 | D88: CASA A LA VENTA EN BERISSO | E88: Realizado | F88: Referido | G88: 51000 | H88: 47000 | I88: Dólares | J88: Dólares | K88: CASA A LA VENTA EN BERISSO | L88: Argentina | G.B.A. Zona Sur | Berisso | Berisso | M88: Casa | N88: 2 | O88: Golden Team | P88: Propia (Único Asesor) | Q88: Venta | R88: =VLOOKUP($O88,'Mapa Oficinas'!$A$7:$C$46,2,FALSE) -> Zona Sur (GBA) | S88: =VLOOKUP($O88,'Mapa Oficinas'!$A$7:$C$46,3,FALSE) -> La Plata
A89: 45682 | B89: CPH5961166 | D89: Espectacular PH 5 Ambientes Con Patio/Gran Terraza | E89: Realizado | F89: AR ZonaProp | G89: 328000 | H89: 289000 | I89: Dólares | J89: Dólares | K89: Honduras 4000 | L89: Argentina | Capital Federal | Palermo | M89: PH | N89: 2 | O89: Destino | P89: Propia (Único Asesor) | Q89: Venta | R89: =VLOOKUP($O89,'Mapa Oficinas'!$A$7:$C$46,2,FALSE) -> CABA | S89: =VLOOKUP($O89,'Mapa Oficinas'!$A$7:$C$46,3,FALSE) -> Recoleta
A90: 45683 | B90: VPN7622 LA4688472 | D90: VENTA LOTE INTERNO - Bahía VILLANUEVA | E90: Realizado | F90: AR ZonaProp | G90: 135268 | H90: 163500 | I90: Dólares | J90: Dólares | K90: BAHIA VILLANUEVA | L90: Argentina | G.B.A. Zona Norte | Tigre | Countries/B.Cerrado (Tigre) | Villanueva | Bahia | M90: Terreno | N90: 2 | O90: Puerto Norte | P90: Compartida Fuera de la Red Captación Propia | Q90: Venta | R90: =VLOOKUP($O90,'Mapa Oficinas'!$A$7:$C$46,2,FALSE) -> Zona Norte (GBA) | S90: =VLOOKUP($O90,'Mapa Oficinas'!$A$7:$C$46,3,FALSE) -> Nordelta
A91: 45683 | B91: VHO6475900 | D91: Casa en Venta - Haras Santa María, El Molino Sur - 5 Ambientes | E91: Realizado | F91: AR ZonaProp | G91: 279000 | H91: 260000 | I91: Dólares | J91: Dólares | K91: Haras Santa Maria, El Molino Sur | L91: Argentina | G.B.A. Zona Norte | Escobar | Countries/B.Cerrado (Escobar) | Haras Santa Maria | El Molino Sur | M91: Casa | N91: 2 | O91: Puerto Norte | P91: Compartida en Oficina (Dos Asesores) | Q91: Venta | R91: =VLOOKUP($O91,'Mapa Oficinas'!$A$7:$C$46,2,FALSE) -> Zona Norte (GBA) | S91: =VLOOKUP($O91,'Mapa Oficinas'!$A$7:$C$46,3,FALSE) -> Nordelta
A92: 45684 | B92: VPN55315 LA5976242 | D92: Lote Interno en Venta, La Serena, General Rodriguez | E92: Realizado | F92: Instagram | G92: 44880 | H92: 43320 | I92: Dólares | J92: Dólares | K92: Venta lote La Serena Barrio Cerrado Gral Rodriguez, Ruta 28 | L92: Argentina | G.B.A. Zona Oeste | General Rodriguez | Countries/B.Cerrado (G. Rodriguez) | M92: Terreno | N92: 2 | O92: Puerto Norte | P92: Compartida en Oficina (Dos Asesores) | Q92: Venta | R92: =VLOOKUP($O92,'Mapa Oficinas'!$A$7:$C$46,2,FALSE) -> Zona Norte (GBA) | S92: =VLOOKUP($O92,'Mapa Oficinas'!$A$7:$C$46,3,FALSE) -> Nordelta
... A97: 45684 | B97: CLA6239420 | D97: Venta terreno/lote en Mataderos | E97: Realizado | F97: AR ZonaProp | G97: 180000 | H97: 145000 | I97: Dólares | J97: Dólares | K97: Basualdo al 900 | L97: Argentina | Capital Federal | Mataderos | M97: Terreno | N97: 2 | O97: Destino | P97: Propia (Único Asesor) | Q97: Venta | R97: =VLOOKUP($O97,'Mapa Oficinas'!$A$7:$C$46,2,FALSE) -> CABA | S97: =VLOOKUP($O97,'Mapa Oficinas'!$A$7:$C$46,3,FALSE) -> Recoleta
A98: 45684 | B98: VLA5679693 | C98: 1 | D98: Terreno en Pilar Barrio Privado Verona | E98: Realizado | F98: Instagram | G98: 156200 | H98: 147630 | I98: Dólares | J98: Dólares | K98: Venta Lote interno Verona - Pilar | L98: Argentina | G.B.A. Zona Norte | Pilar | Countries/B.Cerrado (Pilar) | Verona Pilar | M98: Terreno | N98: 2 | O98: Puerto Norte | P98: Compartida en Oficina (Dos Asesores) | Q98: Venta | R98: =VLOOKUP($O98,'Mapa Oficinas'!$A$7:$C$46,2,FALSE) -> Zona Norte (GBA) | S98: =VLOOKUP($O98,'Mapa Oficinas'!$A$7:$C$46,3,FALSE) -> Nordelta
A99: 45684 | B99: VLA5679693 | C99: 0 | D99: Terreno en Pilar Barrio Privado Verona | E99: Realizado | F99: AR ZonaProp | G99: 156200 | H99: 158235 | I99: Dólares | J99: Dólares | K99: Venta Lote interno Verona - Pilar | L99: Argentina | G.B.A. Zona Norte | Pilar | Countries/B.Cerrado (Pilar) | Verona Pilar | M99: Terreno | N99: 2 | O99: Puerto Norte | P99: Compartida en Oficina (Dos Asesores) | Q99: Venta | R99: =VLOOKUP($O99,'Mapa Oficinas'!$A$7:$C$46,2,FALSE) -> Zona Norte (GBA) | S99: =VLOOKUP($O99,'Mapa Oficinas'!$A$7:$C$46,3,FALSE) -> Nordelta
A100: 45684 | B100: APH5198583 | D100: PH 5 ambientes con quincho y terraza | E100: Realizado | F100: AR ZonaProp | G100: 199000 | H100: 191000 | I100: Dólares | J100: Dólares | K100: Chivilcoy 4800 | L100: Argentina | Capital Federal | Villa Devoto | M100: PH | N100: 2 | O100: Desiderio | P100: Compartida Fuera de la Red Captación Propia | Q100: Venta | R100: =VLOOKUP($O100,'Mapa Oficinas'!$A$7:$C$46,2,FALSE) -> CABA | S100: =VLOOKUP($O100,'Mapa Oficinas'!$A$7:$C$46,3,FALSE) -> Caballito
A101: 45684 | B101: CBU60233 AP6592888 | D101: Venta Departamento Tres Ambientes vista al lago a 5 minutos del centro | E101: Realizado | F101: Teléfono | G101: 238023 | H101: 254805 | I101: Dólares | J101: Dólares | K101: Avenida Pioneros Km 2, San Carlos de Bariloche | L101: Argentina | Rio Negro | Bariloche | San Carlos De Bariloche | Centro | M101: Departamento | N101: 2 | O101: Patagonia Lakes BRC | P101: Compartida en Oficina (Dos Asesores) | Q101: Venta | R101: =VLOOKUP($O101,'Mapa Oficinas'!$A$7:$C$46,2,FALSE) -> Interior - Río Negro | S101: =VLOOKUP($O101,'Mapa Oficinas'!$A$7:$C$46,3,FALSE) -> Bariloche
A102: 45685 | B102: Valentin Vergara 1471 | D102: Valentin Vergara 1471 | E102: Realizado | F102: AR ZonaProp | G102: 65000 | H102: 65000 | I102: Dólares | J102: Dólares | K102: Valentin Vergara 1471 | L102: Argentina | G.B.A. Zona Sur | Lomas De Zamora (Partido) | Banfield | M102: Departamento | N102: 2 | O102: Lion Team | P102: Propia (Único Asesor) | Q102: Venta | R102: =VLOOKUP($O102,'Mapa Oficinas'!$A$7:$C$46,2,FALSE) -> CABA | S102: =VLOOKUP($O102,'Mapa Oficinas'!$A$7:$C$46,3,FALSE) -> Villa Urquiza
A103: 45685 | B103: CAP6563369 | D103: Venta Departamento 3 ambientes con dependencia y balcon Piso alto en Recoleta - Barrio Norte | E103: Realizado | F103: AR ZonaProp | G103: 109990 | H103: 102000 | I103: Dólares | J103: Dólares | K103: Junin al 400 | L103: Argentina | Capital Federal | Recoleta | M103: Departamento | N103: 2 | O103: Lion Team | P103: Compartida en Oficina (Dos Asesores) | Q103: Venta | R103: =VLOOKUP($O103,'Mapa Oficinas'!$A$7:$C$46,2,FALSE) -> CABA | S103: =VLOOKUP($O103,'Mapa Oficinas'!$A$7:$C$46,3,FALSE) -> Villa Urquiza
A104: 45685 | B104: calle 14 del Luján 306 | D104: calle 14 del Luján 306 | E104: Realizado | F104: AR ZonaProp | G104: 200000 | H104: 200000 | I104: Dólares | J104: Dólares | K104: ESCOBAR | L104: Argentina | G.B.A. Zona Norte | Escobar | M104: Casa | N104: 2 | O104: Lion Team Norte | P104: Propia (Único Asesor) | Q104: Venta | R104: =VLOOKUP($O104,'Mapa Oficinas'!$A$7:$C$46,2,FALSE) -> Zona Norte (GBA) | S104: =VLOOKUP($O104,'Mapa Oficinas'!$A$7:$C$46,3,FALSE) -> Vicente López
A105: 45685 | B105: 10284 | D105: Referido - Bariloche | E105: Realizado | F105: Referido | G105: 0 | H105: 203000 | I105: Dólares | J105: Dólares | L105: Argentina | Rio Negro | Bariloche | M105: Casa | N105: 2 | O105: Seniority | P105: Profesional Referenciador (30%) | Q105: Venta | R105: =VLOOKUP($O105,'Mapa Oficinas'!$A$7:$C$46,2,FALSE) -> CABA | S105: =VLOOKUP($O105,'Mapa Oficinas'!$A$7:$C$46,3,FALSE) -> Barrio Parque
A106: 45686 | B106: CAP5970035 | D106: Departamento 4 ambientes Nuñez TODO A NUEVO Luminoso VENTA Seguridad | E106: Realizado | F106: AR MercadoLibre | G106: 130000 | H106: 130000 | I106: Dólares | J106: Dólares | K106: Manzanares al 1800 | L106: Argentina | Capital Federal | Nuñez | M106: Departamento | N106: 2 | O106: Lion Team | P106: Propia (Único Asesor) | Q106: Venta | R106: =VLOOKUP($O106,'Mapa Oficinas'!$A$7:$C$46,2,FALSE) -> CABA | S106: =VLOOKUP($O106,'Mapa Oficinas'!$A$7:$C$46,3,FALSE) -> Villa Urquiza
A107: 45686 | B107: italia 4545 | D107: italia 4545 | E107: Realizado | F107: AR ZonaProp | G107: 128000 | H107: 147000 | I107: Dólares | J107: Dólares | K107: italia 4545 | L107: Argentina | Capital Federal | Capital Federal | M107: Terreno | N107: 2 | O107: Lion Team | P107: Propia (Único Asesor) | Q107: Venta | R107: =VLOOKUP($O107,'Mapa Oficinas'!$A$7:$C$46,2,FALSE) -> CABA | S107: =VLOOKUP($O107,'Mapa Oficinas'!$A$7:$C$46,3,FALSE) -> Villa Urquiza
A108: 45686 | B108: CAP6556808 | D108: Departamento 3 ambientes en ALQUILER en Arboris Las Lomas - San Isidro | E108: Realizado | F108: Referido | G108: 360000 | H108: 335000 | I108: Dólares | J108: Dólares | K108: don bosco al 1500 ARBORIS LAS LOMAS | L108: Argentina | G.B.A. Zona Norte | San Isidro | Arboris Las Lomas | M108: Departamento | N108: 2 | O108: Concept | P108: Compartida Fuera de la Red Captación Propia | Q108: Venta | R108: =VLOOKUP($O108,'Mapa Oficinas'!$A$7:$C$46,2,FALSE) -> Zona Norte (GBA) | S108: =VLOOKUP($O108,'Mapa Oficinas'!$A$7:$C$46,3,FALSE) -> Tigre
A109: 45687 | B109: CHO6606168 | D109: Casa QUINCHO EN VILLA EL CHOCON | E109: Realizado | F109: AR ZonaProp | G109: 44000 | H109: 44000 | I109: Dólares | J109: Dólares | K109: S.N | L109: Argentina | Neuquen | Confluencia | Villa El Chocon | M109: Casa | N109: 2 | O109: Sensus | P109: Propia (Único Asesor) | Q109: Venta | R109: =VLOOKUP($O109,'Mapa Oficinas'!$A$7:$C$46,2,FALSE) -> Interior - Neuquén | S109: =VLOOKUP($O109,'Mapa Oficinas'!$A$7:$C$46,3,FALSE) -> Capital Neuquén
A110: 45687 | B110: CPH6643473 | D110: Venta PH 3 ambientes Patio Wilde | E110: Realizado | F110: AR ZonaProp | G110: 49000 | H110: 46000 | I110: Dólares | J110: Dólares | K110: Lartigau 555 | L110: Argentina | G.B.A. Zona Sur | Avellaneda | Wilde | M110: PH | N110: 2 | O110: Destino | P110: Compartida Fuera de la Red Captación Propia | Q110: Venta | R110: =VLOOKUP($O110,'Mapa Oficinas'!$A$7:$C$46,2,FALSE) -> CABA | S110: =VLOOKUP($O110,'Mapa Oficinas'!$A$7:$C$46,3,FALSE) -> Recoleta
A111: 45687 | B111: CLA6713319 | D111: Terreno en Confluencia | E111: Realizado | F111: AR ZonaProp | G111: 49000 | H111: 49000 | I111: Dólares | J111: Dólares | K111: Belisle | L111: Argentina | Neuquen | Capital | Confluencia Rural | M111: Terreno | N111: 2 | O111: Sensus | P111: Propia (Único Asesor) | Q111: Venta | R111: =VLOOKUP($O111,'Mapa Oficinas'!$A$7:$C$46,2,FALSE) -> Interior - Neuquén | S111: =VLOOKUP($O111,'Mapa Oficinas'!$A$7:$C$46,3,FALSE) -> Capital Neuquén
A112: 45687 | B112: CAP6435586 | D112: Venta Departamento Monoambiente en Devoto. | E112: Realizado | F112: AR ZonaProp | G112: 55000 | H112: 50000 | I112: Dólares | J112: Dólares | K112: Bahía Blanca al 3300 | L112: Argentina | Capital Federal | Villa Devoto | M112: Departamento | N112: 2 | O112: Audacity | P112: Propia (Único Asesor) | Q112: Venta | R112: =VLOOKUP($O112,'Mapa Oficinas'!$A$7:$C$46,2,FALSE) -> Zona Oeste (GBA) | S112: =VLOOKUP($O112,'Mapa Oficinas'!$A$7:$C$46,3,FALSE) -> Parque Leloir
A113: 45687 | B113: CAP6492091 | D113: Departamento en Cipolletti | E113: Realizado | F113: AR ZonaProp | G113: 63000 | H113: 63000 | I113: Dólares | J113: Dólares | K113: San Martin al 700 | L113: Argentina | Rio Negro | Cipolletti | M113: Departamento | N113: 2 | O113: Sensus | P113: Compartida en Oficina (Dos Asesores) | Q113: Venta | R113: =VLOOKUP($O113,'Mapa Oficinas'!$A$7:$C$46,2,FALSE) -> Interior - Neuquén | S113: =VLOOKUP($O113,'Mapa Oficinas'!$A$7:$C$46,3,FALSE) -> Capital Neuquén
...

Sheet DESCARTADO
A2: 45943 | B2: 9102025 | D2: Reserva Venta Flor Lote Dos Valles A25 | E2: Realizado | F2: Teléfono | G2: 43000 | H2: 750 | I2: Dólares | J2: Dólares | L2: Argentina | Rio Negro | Bariloche | San Carlos De Bariloche | M2: Terreno | N2: 1 | O2: Patagonia Lakes BRC | P2: Master | Q2: Venta
A3: 45798 | B3: VCO59064 AP6619653 | D3: Departamento en Altos de Maschwitz - 2 AMB con Jardín | E3: Realizado | F3: AR ZonaProp | G3: 102194 | H3: 1000 | I3: Dólares | J3: Dólares | K3: Departamento en Altos de Maschwitz - 2 AMB con Jardín | L3: Argentina | G.B.A. Zona Norte | Escobar | Ingeniero Maschwitz | Altos de Maschwitz | M3: Departamento | N3: 2 | O3: Puerto Norte | P3: Compartida en Oficina (Dos Asesores) | Q3: Venta
A4: 45992 | B4: CAP7356426 | D4: Departamento en Las Heras | E4: Realizado | F4: AR ZonaProp | G4: 31900 | H4: 2000 | I4: Dólares | J4: Local | K4: Adolfo Calle y Bombal | L4: Argentina | Mendoza | Las Heras | M4: Departamento | N4: 2 | O4: Cuyo Real | P4: Propia (Único Asesor) | Q4: Venta
A5: 45706 | B5: VAP6607532 | D5: Departamento 3 AMB en Alquiler en Infinity Nordelta | E5: Realizado | F5: AR ZonaProp | G5: 800 | H5: 3000 | I5: Dólares | J5: Dólares | K5: Departamento 3 AMB en Alquiler en Infinity Nordelta | L5: Argentina | G.B.A. Zona Norte | Tigre | Countries/B.Cerrado (Tigre) | Nordelta | El Palmar | Infinity Residences | M5: Departamento | N5: 2 | O5: Puerto Norte | P5: Propia (Único Asesor) | Q5: Venta
A6: 45758 | B6: CLA6354054 | D6: LOTES en Barrio Estancia Kingsbroock - 122 y 612 | E6: Realizado | F6: AR ZonaProp | G6: 5200 | H6: 4500 | I6: Dólares | J6: Dólares | K6: LOTES en Barrio Estancia Kingsbroock - 122 y 612 | L6: Argentina | G.B.A. Zona Sur | La Plata | Villa Elvira | M6: Terreno | N6: 2 | O6: Golden Team | P6: Propia (Único Asesor) | Q6: Venta
A7: 45721 | B7: CLA6354054 | D7: LOTES en Barrio Estancia Kingsbroock - 122 y 612 | E7: Realizado | F7: Referido | G7: 5300 | H7: 4774 | I7: Dólares | J7: Dólares | K7: LOTES en Barrio Estancia Kingsbroock - 122 y 612 | L7: Argentina | G.B.A. Zona Sur | La Plata | Villa Elvira | M7: Terreno | N7: 2 | O7: Golden Team | P7: Propia (Único Asesor) | Q7: Venta
A8: 45992 | B8: CHO7100411 | D8: Casa en Las Heras | E8: Realizado | F8: AR ZonaProp | G8: 48000 | H8: 4840 | I8: Dólares | J8: Dólares | K8: 3 de febrero al 500 | L8: Argentina | Mendoza | Las Heras | M8: Casa | N8: 2 | O8: Cuyo Real | P8: Propia (Único Asesor) | Q8: Venta
A9: 45952 | B9: CGA7289163 | D9: Cochera en Mendoza | E9: Realizado | F9: Facebook | G9: 4900 | H9: 4900 | I9: Dólares | J9: Dólares | K9: Garibaldi al 100 | L9: Argentina | Mendoza | Capital | Mendoza | M9: Garage | N9: 2 | O9: Cuyo Real | P9: Propia (Único Asesor) | Q9: Venta
A10: 45992 | B10: CHO6734839 | D10: CASA EN VENTA VISTALBA LOTEO DON CARLOS | E10: Realizado | F10: AR ZonaProp | G10: 140000 | H10: 5000 | I10: Dólares | J10: Dólares | K10: LOTEO DON CARLOS LOS TILOS LOTE K | L10: Argentina | Mendoza | Lujan De Cuyo | Vistalba | M10: Casa | N10: 1 | O10: Cuyo Real | P10: (Interior) Compartida Fuera de la Red Búsqueda | Q10: Venta
A11: 45777 | B11: CGA6673233 | D11: Venta Cochera en Almagro | E11: Realizado | F11: AR ZonaProp | G11: 7000 | H11: 5000 | I11: Dólares | J11: Dólares | K11: Corrientes al 3800 | L11: Argentina | Capital Federal | Almagro | M11: Garage | N11: 2 | O11: Seniority | P11: Propia (Único Asesor) | Q11: Venta
A12: 45951 | B12: CAP7331334 | D12: Departamento 2 AMB en Alquiler - Marinas del Portezuelo | E12: Realizado | F12: AR MercadoLibre | G12: 650 | H12: 5200 | I12: Dólares | J12: Dólares | K12: Departamento 2 AMB en Alquiler - Marinas del Portezuelo | L12: Argentina | G.B.A. Zona Norte | Tigre | Countries/B.Cerrado (Tigre) | Nordelta | Portezuelo | Marinas del Portezuelo | M12: Departamento | N12: 2 | O12: Puerto Norte | P12: Propia (Único Asesor) | Q12: Venta
A13: 45842 | B13: CLA6354054 | D13: LOTES en Barrio Estancia Kingsbroock - 122 y 612 | E13: Realizado | F13: AR ZonaProp | G13: 5200 | H13: 5200 | I13: Dólares | J13: Dólares | K13: LOTES en Barrio Estancia Kingsbroock - 122 y 612 | L13: Argentina | G.B.A. Zona Sur | La Plata | Villa Elvira | M13: Terreno | N13: 2 | O13: Golden Team | P13: Propia (Único Asesor) | Q13: Venta
A14: 45954 | B14: CHO7300194 | D14: Casa en alquiler permanente en Bariloche | E14: Realizado | F14: Teléfono | G14: 2800 | H14: 5600 | I14: Dólares | J14: Dólares | K14: Centro, San Carlos de Bariloche | L14: Argentina | Rio Negro | Bariloche | M14: Casa | N14: 2 | O14: Patagonia Lakes BRC | P14: Master | Q14: Venta
... A27: 45929 | B27: CHO5031458 | D27: ALQUILER TURÍSTICO - Casa categoria impresionante vista al lago en barrio cerrado Villa la Angostura | E27: Realizado | F27: Referido | G27: 700 | H27: 8400 | I27: Dólares | J27: Dólares | K27: Barrio cerrado Dos Lagos, Villa La Angostura | L27: Argentina | Neuquen | Villa La Angostura | Countries/ B. Cerrado (V. La Angostura) | M27: Casa | N27: 2 | O27: Patagonia Lakes VLA | P27: Propia (Único Asesor) | Q27: Venta
A28: 45992 | B28: Casa C/ Remax Follow | D28: Casa c/ remax follow | E28: Realizado | F28: AR ZonaProp | G28: 34000 | H28: 8450 | I28: Dólares | J28: Dólares | L28: Argentina | Mendoza | Guaymallen | M28: Casa | N28: 1 | O28: Cuyo Real | P28: (Interior) Compartida Fuera de la Red Búsqueda | Q28: Venta
A29: 46077 | B29: CLA7827009 | D29: Terreno en Lujan | E29: Realizado | F29: Repetido | G29: 8500 | H29: 8500 | I29: Dólares | J29: Dólares | K29: BARRIO SANTA IRENE RUTA 6 KM 155.5 LUJAN 30 | L29: Argentina | G.B.A. Zona Oeste | Lujan | M29: Terreno | N29: 2 | O29: Audacity | P29: Propia (Único Asesor) | Q29: Venta
A30: 46066 | B30: CLA6250455 | D30: Terreno en Venta, Santo Tome, Santa Fe | E30: Realizado | F30: Conocido | G30: 10000 | H30: 8500 | I30: Dólares | J30: Dólares | K30: Terreno en Venta, Santo Tome, Santa Fe | L30: Argentina | Santa Fe | La Capital | Santo Tome | M30: Terreno | N30: 2 | O30: De la Veracruz | P30: Compartida en Oficina (Dos Asesores) | Q30: Venta
A31: 46066 | B31: CLA6250311 | D31: Terreno en Venta, Santo Tome, Santa Fe | E31: Realizado | F31: Conocido | G31: 10000 | H31: 8500 | I31: Dólares | J31: Dólares | K31: Terreno en Venta, Santo Tome, Santa Fe | L31: Argentina | Santa Fe | La Capital | Santo Tome | M31: Terreno | N31: 2 | O31: De la Veracruz | P31: Compartida en Oficina (Dos Asesores) | Q31: Venta
A32: 46066 | B32: CLA6250352 | D32: Terreno en Venta, Santo Tome, Santa Fe | E32: Realizado | F32: Conocido | G32: 10000 | H32: 8500 | I32: Dólares | J32: Dólares | K32: Terreno en Venta, Santo Tome, Santa Fe | L32: Argentina | Santa Fe | La Capital | Santo Tome | M32: Terreno | N32: 2 | O32: De la Veracruz | P32: Compartida en Oficina (Dos Asesores) | Q32: Venta
A33: 46059 | B33: CLA6250391 | D33: Terreno en Venta, Santo Tome, Santa Fe | E33: Realizado | F33: Conocido | G33: 10000 | H33: 8500 | I33: Dólares | J33: Dólares | K33: Terreno en Venta, Santo Tome, Santa Fe | L33: Argentina | Santa Fe | La Capital | Santo Tome | M33: Terreno | N33: 2 | O33: De la Veracruz | P33: Compartida en Oficina (Dos Asesores) | Q33: Venta
A34: 46059 | B34: CLA6250401 | D34: Terreno en Venta, Santo Tome, Santa Fe | E34: Realizado | F34: Conocido | G34: 10000 | H34: 8500 | I34: Dólares | J34: Dólares | K34: Terreno en Venta, Santo Tome, Santa Fe | L34: Argentina | Santa Fe | La Capital | Santo Tome | M34: Terreno | N34: 2 | O34: De la Veracruz | P34: Compartida en Oficina (Dos Asesores) | Q34: Venta
A35: 45816 | B35: CLA6687636 | D35: Terreno en venta Pucara | E35: Realizado | F35: Facebook | G35: 8600 | H35: 8600 | I35: Dólares | J35: Dólares | K35: PUCARA | L35: Argentina | Salta | Capital | Salta | Zona Oeste | M35: Terreno | N35: 2 | O35: Realty Group | P35: Compartida en Oficina (Dos Asesores) | Q35: Venta
A36: 45973 | B36: CLA6250455 | D36: Terreno en Venta, Santo Tome, Santa Fe | E36: Realizado | F36: Facebook | G36: 10000 | H36: 9000 | I36: Dólares | J36: Dólares | K36: Terreno en Venta, Santo Tome, Santa Fe | L36: Argentina | Santa Fe | La Capital | Santo Tome | M36: Terreno | N36: 2 | O36: De la Veracruz | P36: Compartida en Oficina (Dos Asesores) | Q36: Venta
A37: 45926 | B37: CAP7128288 | D37: Departamento en alquiler 2amb con balcón | E37: Realizado | F37: AR MercadoLibre | G37: 450000 | H37: 9000 | I37: Dólares | J37: Local | K37: Bonifacini al 3800 | L37: Argentina | G.B.A. Zona Oeste | Tres De Febrero | Santos Lugares | M37: Departamento | N37: 2 | O37: Lion Team | P37: Propia (Único Asesor) | Q37: Venta
A38: 45897 | B38: CLA7070818 | D38: Terreno en Jardines del valle (Cerrillos) | E38: Realizado | F38: Facebook | G38: 11000 | H38: 9000 | I38: Dólares | J38: Dólares | K38: RUTA 68 cerrillos | L38: Argentina | Salta | Cerrillos | M38: Terreno | N38: 2 | O38: Realty Group | P38: Propia (Único Asesor) | Q38: Venta
A39: 45780 | B39: CPN57379 LA6447276 | D39: Terreno - Los Hornos | E39: Realizado | F39: Teléfono | G39: 9000 | H39: 9000 | I39: Dólares | J39: Dólares | K39: Terreno en VENTA, Barrio PRIVADO, Solares, Calle 83 y 139 | L39: Argentina | G.B.A. Zona Sur | La Plata | Los Hornos | M39: Terreno | N39: 2 | O39: Golden Team | P39: Propia (Único Asesor) | Q39: Venta
A40: 45780 | B40: CPN57379 LA6447276 | D40: Terreno - Los Hornos | E40: Realizado | F40: Conocido | G40: 9000 | H40: 9000 | I40: Dólares | J40: Dólares | K40: Terreno en VENTA, Barrio PRIVADO, Solares, Calle 83 y 139 | L40: Argentina | G.B.A. Zona Sur | La Plata | Los Hornos | M40: Terreno | N40: 2 | O40: Golden Team | P40: Propia (Único Asesor) | Q40: Venta
A41: 46094 | B41: Corralitos terreno | D41: Terreno en venta en corralitos | E41: Realizado | F41: AR ZonaProp | G41: 0 | H41: 9500 | I41: Dólares | J41: Dólares | L41: Argentina | Mendoza | Guaymallen | Los Corralitos | M41: Terreno | N41: 1 | O41: Cuyo Real | P41: (Interior) Compartida Fuera de la Red Búsqueda | Q41: Venta
A42: 45841 | B42: CGA6814291 | D42: Venta Cochera céntrica Bariloche OPORTUNIDAD Permuta | E42: Realizado | F42: Teléfono | G42: 10000 | H42: 9500 | I42: Dólares | J42: Dólares | K42: Centro, San Carlos de Bariloche | L42: Argentina | Rio Negro | Bariloche | San Carlos De Bariloche | Centro | M42: Garage | N42: 2 | O42: Patagonia Lakes BRC | P42: Propia (Único Asesor) | Q42: Venta
A43: 45761 | B43: CLA6730114 | D43: Terreno en venta nuevo alisos | E43: Realizado | F43: Conocido | G43: 10500 | H43: 9551 | I43: Dólares | J43: Dólares | K43: nuevo alisos manzana 8 lote 1 | L43: Argentina | Jujuy | San Antonio | Los Alisos | M43: Terreno | N43: 2 | O43: Plaza | P43: Compartida en Oficina (Dos Asesores) | Q43: Venta
A44: 45854 | B44: CLA6758657 | D44: Terreno en venta en Valle Alegre | E44: Realizado | F44: Referido | G44: 9600 | H44: 9600 | I44: Dólares | J44: Dólares | K44: VALLE ALEGRE | L44: Argentina | Salta | La Caldera | M44: Terreno | N44: 2 | O44: Realty Group | P44: Compartida en Oficina (Dos Asesores) | Q44: Venta
A45: 46065 | B45: CLA7690260 | D45: Terreno en venta Loteo Pucara | E45: Realizado | F45: Facebook | G45: 10500 | H45: 9965 | I45: Dólares | J45: Dólares | K45: LOTEO PUCARA | L45: Argentina | Salta | Capital | Salta | Zona Oeste | M45: Terreno | N45: 2 | O45: Realty Group | P45: Propia (Único Asesor) | Q45: Venta
A46: 46063 | B46: CLA7484087 | D46: Terreno en venta ubicado en Potreros de Quijano - Salta | E46: Realizado | F46: AR ZonaProp | G46: 10000 | H46: 10000 | I46: Dólares | J46: Dólares | K46: Potreros de Quijano | L46: Argentina | Salta | Rosario De Lerma | Campo Quijano | M46: Terreno | N46: 2 | O46: Realty Group | P46: Propia (Único Asesor) | Q46: Venta
A47: 46056 | B47: CLA7320742 | D47: Terreno en venta ubicado en Loteo Pucara - Salta | E47: Realizado | F47: Facebook | G47: 10500 | H47: 10000 | I47: Dólares | J47: Dólares | K47: Loteo Pucara | L47: Argentina | Salta | Capital | Salta | Zona Sur | M47: Terreno | N47: 2 | O47: Realty Group | P47: Propia (Único Asesor) | Q47: Venta
A48: 46036 | B48: CPN57379 LA6447276 | D48: Terreno - Los Hornos | E48: Realizado | F48: AR ZonaProp | G48: 10000 | H48: 10000 | I48: Dólares | J48: Dólares | K48: Terreno en VENTA, Barrio PRIVADO, Solares, Calle 83 y 139 | L48: Argentina | G.B.A. Zona Sur | La Plata | Los Hornos | M48: Terreno | N48: 2 | O48: Golden Team | P48: Propia (Único Asesor) | Q48: Venta
A49: 46028 | B49: CLA6752890 | D49: Terreno en Barrio Santa Rita | E49: Realizado | F49: Facebook | G49: 12000 | H49: 10000 | I49: Dólares | J49: Dólares | K49: TERRENO BARRIO SANTA RITA | L49: Argentina | Santa Fe | La Capital | Santa Fe | M49: Terreno | N49: 2 | O49: De la Veracruz | P49: Propia (Único Asesor) | Q49: Venta
A50: 45992 | B50: CHO6728128 | D50: Venta casa 3 habitaciones barrio privado maipu | E50: Realizado | F50: AR ZonaProp | G50: 115000 | H50: 10000 | I50: Dólares | J50: Dólares | K50: Videla Castillo | L50: Argentina | Mendoza | Maipu | M50: Casa | N50: 1 | O50: Cuyo Real | P50: (Interior) Compartida Fuera de la Red Búsqueda | Q50: Venta
A51: 45981 | B51: CLA6948853 | D51: VENTA TERRENO DE 1132 M2 EN AREA 60, LA VICTORIA POLO COUNTRY ¡OFERTA INCREIBLE! | E51: Realizado | F51: AR ZonaProp | G51: 13000 | H51: 10000 | I51: Dólares | J51: Dólares | K51: Club de campo La Victoria, Area 60, Lote 160 | L51: Argentina | Interior Buenos Aires | Coronel Brandsen | Area 60 | M51: Terreno | N51: 2 | O51: Destino II | P51: Propia (Único Asesor) | Q51: Venta
A52: 45965 | B52: CLA7384505 | D52: CB VENDE - TERRENO - BOSQUE DEL CEIBAL I | E52: Realizado | F52: Conocido | G52: 10500 | H52: 10000 | I52: Dólares | J52: Dólares | K52: Calle Lapacho al 800 | L52: Argentina | Jujuy | San Antonio | M52: Terreno | N52: 2 | O52: Plaza | P52: Propia (Único Asesor) | Q52: Venta
A53: 45938 | B53: CLA7263283 | D53: Terreno en los Domingos sauce viejo | E53: Realizado | F53: Conocido | G53: 13000 | H53: 10000 | I53: Dólares | J53: Dólares | K53: Lote en los Domingos, sauce Viejo | L53: Argentina | Santa Fe | La Capital | Sauce Viejo | M53: Terreno | N53: 2 | O53: De la Veracruz | P53: Propia (Único Asesor) | Q53: Venta
... A59: 45775 | B59: CLA6949078 | D59: Terrenos en Rio Blanco | E59: Realizado | F59: Referido | G59: 10000 | H59: 10000 | I59: Dólares | J59: Dólares | K59: LOTEO PAYPAYA | L59: Argentina | Jujuy | Dr Manuel Belgrano | Rio Blanco | M59: Terreno | N59: 2 | O59: Plaza | P59: Compartida en Oficina (Dos Asesores) | Q59: Venta
A60: 45760 | D60: Op. con inmo colega LOTE PH UF 4 VALLE CHAPELCO 312,05m2 NC 152106681480004 | E60: Realizado | F60: Repetido | G60: 10000 | H60: 10000 | I60: Dólares | J60: Dólares | L60: Argentina | Neuquen | Lacar | San Martin De Los Andes | Valle Chapelco | M60: Terreno | N60: 1 | O60: Patagonia Lakes SMA | P60: (Interior) Compartida Fuera de la Red Búsqueda | Q60: Venta
A61: 45713 | D61: Op. con inmo colega LOTE PH UF 3 VALLE CHAPELCO 312,05m2 NC 152106681480003 | E61: Realizado | F61: Conocido | G61: 10000 | H61: 10000 | I61: Dólares | J61: Dólares | L61: Argentina | Neuquen | Lacar | San Martin De Los Andes | Valle Chapelco | M61: Terreno | N61: 1 | O61: Patagonia Lakes SMA | P61: (Interior) Compartida Fuera de la Red Búsqueda | Q61: Venta
A62: 45700 | B62: CGA6497473 | D62: Cochera en venta calle 45 e/ 5 y 6 | E62: Realizado | F62: AR ArgenProp | G62: 10500 | H62: 10000 | I62: Dólares | J62: Dólares | K62: Cochera en venta calle 45 e/ 5 y 6 | L62: Argentina | G.B.A. Zona Sur | La Plata | La Plata | Microcentro | M62: Garage | N62: 2 | O62: Golden Team | P62: Propia (Único Asesor) | Q62: Venta
A63: 46108 | B63: CGA7476226 | D63: Venta Cochera Av. Cabildo 100 Palermo Caba | E63: Realizado | F63: AR ZonaProp | G63: 15000 | H63: 10500 | I63: Dólares | J63: Dólares | K63: Av. Cabildo al 100 Palermo Caba | L63: Argentina | Capital Federal | Palermo | M63: Garage | N63: 2 | O63: Lion Team | P63: Propia (Único Asesor) | Q63: Venta
A64: 46087 | B64: CLA7568177 | D64: Terreno Pucara | E64: Realizado | F64: Facebook | G64: 10500 | H64: 10500 | I64: Dólares | J64: Dólares | K64: LOTEO PUCARA | L64: Argentina | Salta | Capital | Salta | Zona Oeste | M64: Terreno | N64: 2 | O64: Realty Group | P64: Propia (Único Asesor) | Q64: Venta
A65: 45912 | B65: CLA6972931 | D65: Terreno en La Viña | E65: Realizado | F65: Facebook | G65: 12000 | H65: 10500 | I65: Dólares | J65: Dólares | K65: Coronel Moldes | L65: Argentina | Salta | La Viña | M65: Terreno | N65: 2 | O65: Realty Group | P65: Propia (Único Asesor) | Q65: Venta
A66: 45777 | B66: CLA6673168 | D66: Terreno en Venta La Celestina Mza I | E66: Realizado | F66: Facebook | G66: 10000 | H66: 10500 | I66: Dólares | J66: Dólares | K66: Terreno La Celestina Mza I | L66: Argentina | Salta | Cerrillos | Cerrillos | M66: Terreno | N66: 2 | O66: Realty Group | P66: Propia (Único Asesor) | Q66: Venta
A67: 45687 | B67: CLA6236629 | D67: Terreno en venta en barrio abierto SENDAS UR | E67: Realizado | F67: Facebook | G67: 10500 | H67: 10500 | I67: Dólares | J67: Dólares | K67: SENDAS UR | L67: Argentina | Salta | Capital | Salta | Zona Oeste | M67: Terreno | N67: 2 | O67: Realty Group | P67: Propia (Único Asesor) | Q67: Venta
A68: 46111 | B68: CGA7342048 | D68: Cochera en Colegiales | E68: Realizado | F68: AR ZonaProp | G68: 12000 | H68: 10600 | I68: Dólares | J68: Dólares | K68: Aguilar al 2500 | L68: Argentina | Capital Federal | Colegiales | M68: Garage | N68: 2 | O68: Niceto | P68: Propia (Único Asesor) | Q68: Venta
A69: 46049 | B69: CLA7387500 | D69: Terreno en venta ubicado en Cielos del Valle - Ruta 68 - Salta | E69: Realizado | F69: Facebook | G69: 12500 | H69: 11000 | I69: Dólares | J69: Dólares | K69: Cielos del Valle | L69: Argentina | Salta | Capital | Salta | Zona Sur | M69: Terreno | N69: 2 | O69: Realty Group | P69: Propia (Único Asesor) | Q69: Venta
A70: 45658 | B70: CGA6322619 | D70: Cochera fija en venta! Ubicación estratégica! | E70: Realizado | F70: AR ZonaProp | G70: 13000 | H70: 11000 | I70: Dólares | J70: Dólares | K70: Marcelo t de Alvear al 1300 | L70: Argentina | Capital Federal | Recoleta | M70: Garage | N70: 2 | O70: Destino | P70: Propia (Único Asesor) | Q70: Venta
A71: 45973 | B71: CGA7248532 | D71: COCHERA CUBIERTA EN RECOLETA | E71: Realizado | F71: AR ZonaProp | G71: 13000 | H71: 11500 | I71: Dólares | J71: Dólares | K71: Billinghurst al 2000 | L71: Argentina | Capital Federal | Recoleta | M71: Garage | N71: 2 | O71: Destino II | P71: Compartida en Oficina (Dos Asesores) | Q71: Venta
A72: 45946 | B72: CLA7341975 | D72: Terreno en venta en La Celestina, Cerrillos | E72: Realizado | F72: Facebook | G72: 12000 | H72: 11500 | I72: Dólares | J72: Dólares | K72: La Celestina | L72: Argentina | Salta | Cerrillos | Cerrillos | M72: Terreno | N72: 2 | O72: Realty Group | P72: Compartida en Oficina (Dos Asesores) | Q72: Venta
A73: 45827 | B73: CLA6925280 | D73: Terreno en Santa María de los Cerrillos | E73: Realizado | F73: Facebook | G73: 12000 | H73: 11500 | I73: Dólares | J73: Dólares | K73: Terreno Santa María de los Cerrillos | L73: Argentina | Salta | Cerrillos | Cerrillos | M73: Terreno | N73: 2 | O73: Realty Group | P73: Propia (Único Asesor) | Q73: Venta
... A100: 46108 | B100: CAP7734188 | D100: depto en alquiler en temperley, 3 ambientes en alquiler, a estrenar, amenities, zona sur | E100: Realizado | F100: AR MercadoLibre | G100: 750000 | H100: 15000 | I100: Dólares | J100: Local | K100: CANGALLO al 400 | L100: Argentina | G.B.A. Zona Sur | Lomas De Zamora (Partido) | Temperley | Temperley Este | M100: Departamento | N100: 2 | O100: Lion Team | P100: Propia (Único Asesor) | Q100: Venta
A101: 46105 | B101: COCHERA EL FARO | D101: COCHERA EN VENTA EN EL EDIFICIO EL FARO | E101: Realizado | F101: AR ZonaProp | G101: 15000 | H101: 15000 | I101: Dólares | J101: Dólares | L101: Argentina | G.B.A. Zona Norte | Tigre | Countries/B.Cerrado (Tigre) | Nordelta | Portezuelo | El Faro | M101: Garage | N101: 2 | O101: Puerto Norte | P101: Propia (Único Asesor) | Q101: Venta
A102: 46101 | B102: CLA7261069 | D102: VENTA Lote/Terreno 800m² Kaleuche Alto San Martín de los Andes | E102: Realizado | F102: AR ZonaProp | G102: 16000 | H102: 15000 | I102: Dólares | J102: Dólares | K102: B° Kaleuche Alto | L102: Argentina | Neuquen | Lacar | San Martin De Los Andes | M102: Terreno | N102: 2 | O102: Patagonia Lakes SMA | P102: Propia (Único Asesor) | Q102: Venta
A103: 46058 | B103: CLA7240665 | D103: Terreno en Arroyo Leyes | E103: Realizado | F103: Referido | G103: 16000 | H103: 15000 | I103: Dólares | J103: Dólares | K103: Terreno con financiación en Arroyo Leyes | L103: Argentina | Santa Fe | La Capital | Arroyo Leyes | M103: Terreno | N103: 2 | O103: De la Veracruz | P103: Propia (Único Asesor) | Q103: Venta
A104: 46048 | B104: CLA4698257 | D104: Lote en venta zona norte Santa Fe | E104: Realizado | F104: Facebook | G104: 15000 | H104: 15000 | I104: Dólares | J104: Dólares | K104: Lote en venta zona Norte Santa Fe | L104: Argentina | Santa Fe | La Capital | Santa Fe | M104: Terreno | N104: 2 | O104: De la Veracruz | P104: Propia (Único Asesor) | Q104: Venta
A105: 45959 | B105: Nuñez 2120 | D105: Nuñez 2120 | E105: Realizado | F105: AR MercadoLibre | G105: 15000 | H105: 15000 | I105: Dólares | J105: Dólares | K105: Nuñez 2120 | L105: Argentina | Capital Federal | Capital Federal | M105: Departamento | N105: 2 | O105: Lion Team | P105: Compartida en Oficina (Dos Asesores) | Q105: Venta
A106: 45958 | B106: CLA4698181 | D106: Terreno - Santa Fe | E106: Realizado | F106: Conocido | G106: 15000 | H106: 15000 | I106: Dólares | J106: Dólares | K106: Diagonal aguado 8800 | L106: Argentina | Santa Fe | La Capital | Santa Fe | M106: Terreno | N106: 2 | O106: De la Veracruz | P106: Propia (Único Asesor) | Q106: Venta
A107: 45906 | B107: CLA7056731 | D107: VENTA DE LOTE BARRIO FRONTERAS SAN VICENTE | E107: Realizado | F107: AR ZonaProp | G107: 15000 | H107: 15000 | I107: Dólares | J107: Dólares | K107: CALLE IBAÑEZ | L107: Argentina | G.B.A. Zona Sur | San Vicente | M107: Terreno | N107: 2 | O107: Boutique | P107: Propia (Único Asesor) | Q107: Venta
A108: 45836 | B108: CLA5742225 | D108: Terreno en General Fernandez Oro | E108: Realizado | F108: AR ZonaProp | G108: 14000 | H108: 15000 | I108: Dólares | J108: Dólares | K108: loteo el sol | L108: Argentina | Rio Negro | General Fernandez Oro | M108: Terreno | N108: 2 | O108: Sensus | P108: Compartida Fuera de la Red Captación Propia | Q108: Venta
A109: 45821 | B109: OP 143 | D109: Libertador 1080 cochera | E109: Realizado | F109: AR ZonaProp | G109: 15000 | H109: 15000 | I109: Dólares | J109: Dólares | K109: Libertador 1080 | L109: Argentina | Capital Federal | Recoleta | M109: Garage | N109: 2 | O109: Seniority Plus | P109: Propia (Único Asesor) | Q109: Venta
A110: 45803 | B110: Cinco Saltos | D110: Terreno Cinco Saltos | E110: Realizado | F110: AR ZonaProp | G110: 15000 | H110: 15000 | I110: Dólares | J110: Dólares | L110: Argentina | Rio Negro | General Roca | Cinco Saltos | M110: Terreno | N110: 2 | O110: Sensus | P110: Propia (Único Asesor) | Q110: Venta
A111: 45685 | B111: CLA6564185 | D111: Terreno en venta villa Casa del Sol San luis | E111: Realizado | F111: Facebook | G111: 15000 | H111: 15000 | I111: Dólares | J111: Dólares | K111: casa del sol | L111: Argentina | Salta | Capital | Salta | Zona Sur | M111: Terreno | N111: 2 | O111: Realty Group | P111: Propia (Único Asesor) | Q111: Venta
A112: 45665 | B112: CLO6520624 | D112: Venta de Local en Manzanares Paseo Dino | E112: Realizado | F112: Cartel | G112: 15000 | H112: 15000 | I112: Dólares | J112: Dólares | K112: Paseo Dino, Manzanares | L112: Argentina | G.B.A. Zona Norte | Pilar | Manzanares | M112: Local Comercial | N112: 2 | O112: Acqua | P112: Propia (Único Asesor) | Q112: Venta
A113: 46083 | B113: CLA7469441 | D113: VENTA Lote | Terreno 308 m2, Valle Chapelco, San Martín de los Andes | E113: Realizado | F113: Conocido | G113: 17900 | H113: 15500 | I113: Dólares | J113: Dólares | K113: PH UF N1 Lote PH | L113: Argentina | Neuquen | Lacar | San Martin De Los Andes | Valle Chapelco | M113: Terreno | N113: 2 | O113: Patagonia Lakes SMA | P113: Propia (Único Asesor) | Q113: Venta
A114: 45877 | B114: CAP6660554 | D114: ALQUILER depto 3 amb REMODELADO A NUEVO balcón hermosa vista Recoleta | E114: Realizado | F114: AR ZonaProp | G114: 1300 | H114: 15600 | I114: Dólares | J114: Dólares | K114: Quintana al 500 | L114: Argentina | Capital Federal | Recoleta | M114: Departamento | N114: 2 | O114: Seniority | P114: Propia (Único Asesor) | Q114: Venta
A115: 45974 | B115: CST7123830 | D115: Depósito en Esandi Bariloche a la VENTA | E115: Realizado | F115: Salón | G115: 17500 | H115: 16000 | I115: Dólares | J115: Dólares | K115: Esandi | L115: Argentina | Rio Negro | Bariloche | San Carlos De Bariloche | Ñireco | M115: Storage | N115: 2 | O115: Patagonia Lakes BRC | P115: Compartida en Oficina (Dos Asesores) | Q115: Venta
A116: 45797 | D116: Op. con inmo colega María Belén Nuñez Gerstmayer UF 1 Valle Chapelco | E116: Realizado | F116: Conocido | G116: 16000 | H116: 16000 | I116: Dólares | J116: Dólares | L116: Argentina | Neuquen | Lacar | San Martin De Los Andes | Valle Chapelco | M116: Terreno | N116: 1 | O116: Patagonia Lakes SMA | P116: (Interior) Compartida Fuera de la Red Búsqueda | Q116: Venta
A117: 45995 | B117: Manuel Artigas 5106 | D117: Manuel Artigas 5106 | E117: Realizado | F117: AR ZonaProp | G117: 65000 | H117: 16250 | I117: Dólares | J117: Dólares | K117: Manuel Artigas 5106 | L117: Argentina | Capital Federal | Capital Federal | M117: Departamento | N117: 2 | O117: Lion Team | P117: Propia (Único Asesor) | Q117: Venta
A118: 45680 | B118: CLA6353157 | D118: LOTES en Barrio DON CARMELO - 22 y 652 | E118: Realizado | F118: Teléfono | G118: 16284 | H118: 16274 | I118: Dólares | J118: Dólares | K118: LOTES en Barrio DON CARMELO - 22 y 652 | L118: Argentina | G.B.A. Zona Sur | La Plata | Villa Parque Sicardi | M118: Terreno | N118: 2 | O118: Golden Team | P118: Propia (Único Asesor) | Q118: Venta
A119: 45831 | B119: CBA47695 LA6263100 | D119: VENTA terreno de 146,30 m2 en LOTEO "ANTIGUO CAMINO" Bariloche | E119: Realizado | F119: Teléfono | G119: 17600 | H119: 16417 | I119: Dólares | J119: Dólares | K119: Antiguo Camino, San Carlos de Bariloche | L119: Argentina | Rio Negro | Bariloche | San Carlos De Bariloche | Lago Moreno | M119: Terreno | N119: 2 | O119: Patagonia Lakes BRC | P119: Compartida en Oficina (Dos Asesores) | Q119: Venta
A120: 45861 | B120: 76edu | D120: Oficina Hermes | E120: Realizado | F120: AR ZonaProp | G120: 18000 | H120: 16500 | I120: Dólares | J120: Dólares | K120: Primera Junta 2507 | L120: Argentina | Santa Fe | La Capital | Santa Fe | M120: Oficina | N120: 1 | O120: De la Veracruz | P120: (Interior) Compartida Fuera de la Red Búsqueda | Q120: Venta
A121: 45874 | B121: CLA6942928 | D121: TERRENO EN LA MESETA CENTENARIO | E121: Realizado | F121: AR ZonaProp | G121: 10000 | H121: 16660 | I121: Dólares | J121: Dólares | K121: ALBERDI Y SANTA FE-LA MESETA CENTENARIO | L121: Argentina | Neuquen | Confluencia | Centenario | M121: Terreno | N121: 2 | O121: Sensus | P121: Propia (Único Asesor) | Q121: Venta
A122: 45749 | B122: CLA6606201 | D122: Terreno en BARRIO LA MESETA 2 CENTENARIO | E122: Realizado | F122: AR ZonaProp | G122: 10000 | H122: 16660 | I122: Dólares | J122: Dólares | K122: S,N | L122: Argentina | Neuquen | Confluencia | Centenario | Sarmiento II | M122: Terreno | N122: 2 | O122: Sensus | P122: Propia (Único Asesor) | Q122: Venta
A123: 45747 | B123: CLA6374066 | D123: Terreno en Lote 5 Mz 773 SEJUN Centenario | E123: Realizado | F123: AR ZonaProp | G123: 4500 | H123: 16660 | I123: Dólares | J123: Dólares | K123: VENTA LOTE 300 M2 SEJUN CENTENARIO | L123: Argentina | Neuquen | Confluencia | Centenario | M123: Terreno | N123: 2 | O123: Sensus | P123: Compartida en Oficina (Dos Asesores) | Q123: Venta
A124: 46031 | B124: CLA6969938 | D124: Terreno en La Meseta Centenario | E124: Realizado | F124: Cartel | G124: 11000000 | H124: 17000 | I124: Dólares | J124: Local | K124: Calle S/N | L124: Argentina | Neuquen | Confluencia | Centenario | M124: Terreno | N124: 2 | O124: Sensus | P124: Compartida en Oficina (Dos Asesores) | Q124: Venta
A125: 46008 | B125: COF7502573 | D125: Venta Oficina en Microcentro a metros del Obelico / No apta vivienda | E125: Realizado | F125: AR MercadoLibre | G125: 19000 | H125: 17000 | I125: Dólares | J125: Dólares | K125: Cerrito esquina Avenida Presidente Roque Sáenz Peña | L125: Argentina | Capital Federal | Centro (Capital Federal) | Microcentro | M125: Oficina | N125: 2 | O125: Concept | P125: Propia (Único Asesor) | Q125: Venta
A126: 45972 | B126: CAP7419403 | D126: Departamento en alquiler dos ambientes con balcon y amenities. | E126: Realizado | F126: AR MercadoLibre | G126: 900000 | H126: 17000 | I126: Dólares | J126: Local | K126: Rio de Janeiro al 200 | L126: Argentina | Capital Federal | Caballito | M126: Departamento | N126: 2 | O126: Lion Team | P126: Propia (Único Asesor) | Q126: Venta
A127: 45857 | B127: CLA6939233 | D127: Lotes en Venta - Jardines de La Falda | E127: Realizado | F127: AR ZonaProp | G127: 18200 | H127: 17000 | I127: Dólares | J127: Dólares | K127: Venezuela y Quilmebai | L127: Argentina | Rio Negro | General Roca | Cipolletti | Distrito Noreste | M127: Terreno | N127: 2 | O127: Sensus | P127: Compartida Fuera de la Red Captación Propia | Q127: Venta
A128: 45968 | B128: CLA4698164 | D128: Lote en venta zona norte Santa Fe | E128: Realizado | F128: Referido | G128: 15000 | H128: 17100 | I128: Dólares | J128: Dólares | K128: Lote en venta zona norte Santa Fe | L128: Argentina | Santa Fe | La Capital | Santa Fe | M128: Terreno | N128: 2 | O128: De la Veracruz | P128: Propia (Único Asesor) | Q128: Venta
... A133: 46097 | B133: CLA7689447 | D133: Terreno en venta ubicado en el Mollar II - Cerrillos - Salta | E133: Realizado | F133: Facebook | G133: 18000 | H133: 18000 | I133: Dólares | J133: Dólares | K133: El Mollar II | L133: Argentina | Salta | Capital | Salta | Zona Sur | M133: Terreno | N133: 2 | O133: Realty Group | P133: Compartida en Oficina (Dos Asesores) | Q133: Venta
A134: 46078 | B134: Santa Clara 855 | D134: Santa Clara al sur 855 | E134: Realizado | F134: AR MercadoLibre | G134: 18000 | H134: 18000 | I134: Dólares | J134: Dólares | L134: Argentina | G.B.A. Zona Sur | San Vicente | M134: Terreno | N134: 2 | O134: Livello | P134: Propia (Único Asesor) | Q134: Venta
A135: 46065 | B135: CLA6980928 | D135: Terreno en venta en barrio Los Sauces | E135: Realizado | F135: AR MercadoLibre | G135: 20000 | H135: 18000 | I135: Dólares | J135: Dólares | K135: Ruta 52 | L135: Argentina | G.B.A. Zona Sur | Ezeiza | Canning (Ezeiza) | M135: Terreno | N135: 2 | O135: Boutique | P135: Propia (Único Asesor) | Q135: Venta
A136: 46044 | B136: CHO7678463 | D136: Casa en San Rafael | E136: Realizado | F136: Facebook | G136: 18000 | H136: 18000 | I136: Dólares | J136: Dólares | K136: comodoro Pí al 200 | L136: Argentina | Mendoza | San Rafael | San Rafael | M136: Casa | N136: 2 | O136: Andes | P136: Propia (Único Asesor) | Q136: Venta
A137: 46029 | B137: CGA7659656 | D137: COCHERA EN VENTA VILLA URQUIZA | E137: Realizado | F137: AR ZonaProp | G137: 18000 | H137: 18000 | I137: Dólares | J137: Dólares | K137: Av. Congreso al 4300 | L137: Argentina | Capital Federal | Villa Urquiza | M137: Garage | N137: 2 | O137: Destino II | P137: Propia (Único Asesor) | Q137: Venta
A138: 46027 | B138: CLA7467331 | D138: TERRENO EN VENTA MAIPU CON TOUR VIRTUAL | E138: Realizado | F138: AR ZonaProp | G138: 19000 | H138: 18000 | I138: Dólares | J138: Dólares | K138: La Florida Lunlunta | L138: Argentina | Mendoza | Maipu | M138: Terreno | N138: 2 | O138: Impacto Pro | P138: Propia (Único Asesor) | Q138: Venta
A139: 46022 | D139: UC 8 | E139: Realizado | F139: Repetido | G139: 20000 | H139: 18000 | I139: Dólares | J139: Dólares | K139: Retamas 200 | L139: Argentina | Neuquen | Villa La Angostura | Centro | M139: Garage | N139: 2 | O139: Patagonia Lakes VLA | P139: Compartida en Oficina (Dos Asesores) | Q139: Venta
A140: 46022 | D140: UC 7 | E140: Realizado | F140: Repetido | G140: 20000 | H140: 18000 | I140: Dólares | J140: Dólares | K140: Retamas 200 | L140: Argentina | Neuquen | Villa La Angostura | Centro | M140: Garage | N140: 2 | O140: Patagonia Lakes VLA | P140: Compartida en Oficina (Dos Asesores) | Q140: Venta
A141: 46008 | B141: CGA7621543 | D141: COCHERA EN VENTA VILLA URQUIZA | E141: Realizado | F141: AR ZonaProp | G141: 18000 | H141: 18000 | I141: Dólares | J141: Dólares | K141: Av. Congreso al 4300 | L141: Argentina | Capital Federal | Villa Urquiza | M141: Garage | N141: 2 | O141: Destino II | P141: Propia (Único Asesor) | Q141: Venta
A142: 45876 | B142: CLA6950692 | D142: Terreno en Barrio Norte | E142: Realizado | F142: Cartel | G142: 20000 | H142: 18000 | I142: Dólares | J142: Dólares | K142: BARRIO NORTE | L142: Argentina | Jujuy | Dr Manuel Belgrano | San Salvador De Jujuy | M142: Terreno | N142: 2 | O142: Plaza | P142: Propia (Único Asesor) | Q142: Venta
A143: 45875 | B143: CCH7037710 | D143: Chacra en Cinco Saltos | E143: Realizado | F143: AR ZonaProp | G143: 35000 | H143: 18000 | I143: Dólares | J143: Dólares | K143: Calle S/N | L143: Argentina | Rio Negro | General Roca | Cinco Saltos | M143: Rancho | N143: 2 | O143: Sensus | P143: Propia (Único Asesor) | Q143: Venta
A144: 45737 | B144: La Elina | D144: Lote en Venta Barrio Cerrado La Elina, Comarcas de Lujan | E144: Realizado | F144: Conocido | G144: 18000 | H144: 18000 | I144: Dólares | J144: Dólares | L144: Argentina | G.B.A. Zona Oeste | Lujan | M144: Terreno | N144: 1 | O144: Audacity | P144: (Interior) Compartida Fuera de la Red Búsqueda | Q144: Venta
A145: 45694 | B145: CLA6618292 | D145: Terreno en VENTA VALLE AZUL Bariloche | E145: Realizado | F145: Teléfono | G145: 18000 | H145: 18000 | I145: Dólares | J145: Dólares | K145: VALLE AZUL -CASCADA CHACHIN | L145: Argentina | Rio Negro | Bariloche | San Carlos De Bariloche | Valle Azul | M145: Terreno | N145: 2 | O145: Patagonia Lakes BRC | P145: Propia (Único Asesor) | Q145: Venta
A146: 45659 | B146: CLA5798692 | D146: Terreno en Venta Sauce Viejo Santa Fe | E146: Realizado | F146: AR ZonaProp | G146: 21000 | H146: 18000 | I146: Dólares | J146: Dólares | K146: Terreno en Venta, Guatemala entre Antartida Argentina y Malvinas, Sauce Viejo | L146: Argentina | Santa Fe | La Capital | Sauce Viejo | M146: Terreno | N146: 2 | O146: De la Veracruz | P146: Propia (Único Asesor) | Q146: Venta
A147: 45735 | B147: CLA4152962 | D147: Terreno Estacion Alvarado Zona Sur Salta - Capital | E147: Realizado | F147: Referido | G147: 18500 | H147: 18500 | I147: Dólares | J147: Dólares | K147: estacion alvarado | L147: Argentina | Salta | Capital | Salta | Zona Sur | M147: Terreno | N147: 2 | O147: Realty Group | P147: Compartida en Oficina (Dos Asesores) | Q147: Venta
A148: 45930 | B148: CLA6367472 | D148: VENTA LOTE en PH de 98 mts, Las Victorias San Carlos de Bariloche | E148: Realizado | F148: Teléfono | G148: 21000 | H148: 18600 | I148: Dólares | J148: Dólares | K148: Las Victorias, San Carlos de Bariloche | L148: Argentina | Rio Negro | Bariloche | San Carlos De Bariloche | Las Victorias | M148: Terreno | N148: 1 | O148: Patagonia Lakes BRC | P148: (Interior) Compartida Fuera de la Red Búsqueda | Q148: Venta
...
