Workbook

Sheet Hoja2
B4: Todas las ventas | D4: Ene25 - Mar26 | G4: PROM MES
B5: TOTAL | C5: USD | D5: 399136299 | E5: =D5/D$5 -> 1 | G5: =D5/15 -> 26609087
B6: TOTAL | C6: TRX | D6: 2695 | E6: =D6/D$6 -> 1 | G6: =D6/15 -> 179.66667
B7: TOTAL | C7: TICK PROM | D7: =D5/D6 -> 148102.52 | E7: =D7/D$7 -> 1 | G7: =G5/G6 -> 148102.52
B8: Exluye ventas compartidas con otra RED
B9: CB | C9: USD | D9: 261332623 | E9: =D9/D$5 -> 0.65474532 | G9: =D9/15 -> 17422175
B10: CB | C10: TRX | D10: 1852 | E10: =D10/D$6 -> 0.68719852 | G10: =D10/15 -> 123.46667
B11: CB | C11: TICK PROM | D11: =D9/D10 -> 141108.33 | E11: =D11/D$7 -> 0.95277464 | G11: =G9/G10 -> 141108.33
B14: CABA + GBA | C14: USD | D14: 201806790 | E14: =D14/D$5 -> 0.50560871 | G14: =D14/15 -> 13453786
B15: CABA + GBA | C15: TRX | D15: 1357 | E15: =D15/D$6 -> 0.50352505 | G15: =D15/15 -> 90.466667
B16: CABA + GBA | C16: TICK PROM | D16: =D14/D15 -> 148715.39 | E16: =D16/D$7 -> 1.0041382 | G16: =G14/G15 -> 148715.39
B18: Sólo Casa, Departamento, Oficina y PH - Excl: Terreno, Storage, Hotel, Garage
B19: CABA + GBA | C19: USD | D19: 185256641 | E19: =D19/D$5 -> 0.46414381 | G19: =D19/15 -> 12350443
B20: CABA + GBA | C20: TRX | D20: 1255 | E20: =D20/D$6 -> 0.46567718 | G20: =D20/15 -> 83.666667
B21: CABA + GBA | C21: TICK PROM | D21: =D19/D20 -> 147614.85 | E21: =D21/D$7 -> 0.99670722 | G21: =G19/G20 -> 147614.85
B23: =CONCATENATE("Con Rango de Precio > ",'Mapa Oficinas'!I21," y < ",'Mapa Oficinas'!I20) -> Con Rango de Precio > 69999 y < 1000000
B24: CABA + GBA | C24: USD | D24: =DINAMICA!BL50 -> 170271805 | E24: =D24/D$5 -> 0.42660065 | G24: =D24/15 -> 11351454
B25: CABA + GBA | C25: TRX | D25: =DINAMICA!BL58 -> 1016 | E25: =D25/D$6 -> 0.37699443 | G25: =D25/15 -> 67.733333
B26: CABA + GBA | C26: TICK PROM | D26: =D24/D25 -> 167590.36 | E26: =D26/D$7 -> 1.1315834 | G26: =G24/G25 -> 167590.36
B28: Sólo CABA
B29: CABA | C29: USD | D29: =DINAMICA!BL69 -> 109991127 | E29: =D29/D$5 -> 0.27557285 | G29: =D29/15 -> 7332741.8
B30: CABA | C30: TRX | D30: =DINAMICA!BL70 -> 677 | E30: =D30/D$6 -> 0.25120594 | G30: =D30/15 -> 45.133333
B31: CABA | C31: TICK PROM | D31: =D29/D30 -> 162468.43 | E31: =D31/D$7 -> 1.0969997 | G31: =G29/G30 -> 162468.43
B35: Captación Inicial | D35: 3000000
B36: Costo captación | C36: 0.0175 | D36: =(1-C36)*D35 -> 2947500
B37: Neto a colocar | C37: 0.95 | D37: =D36*C37 -> 2800125 | E37: =D37/D24 -> 0.01644503
B38: Cantidad Operaciones | C38: 40000 | D38: =ROUND(D37/C38,0) -> 70 | E38: =D38/D25 -> 0.068897638
B40: Penetración | C40: % | D40: Ventas X Mes | G40: Meses hasta completar
B41: =B24 -> CABA + GBA | C41: 0.1 | D41: =ROUND(C41*G$25,0) -> 7 | G41: =$D$38/D41 -> 10
B42: =B25 -> CABA + GBA | C42: 0.15 | D42: =ROUND(C42*G$25,0) -> 10 | G42: =$D$38/D42 -> 7
B43: =B26 -> CABA + GBA | C43: 0.25 | D43: =ROUND(C43*G$25,0) -> 17 | G43: =$D$38/D43 -> 4.1176471
B45: =B29 -> CABA | C45: 0.1 | D45: =ROUND(C45*G$30,0) -> 5 | G45: =$D$38/D45 -> 14
B46: =B29 -> CABA | C46: 0.15 | D46: =ROUND(C46*G$30,0) -> 7 | G46: =$D$38/D46 -> 10
B47: =B30 -> CABA | C47: 0.25 | D47: =ROUND(C47*G$30,0) -> 11 | G47: =$D$38/D47 -> 6.3636364

Sheet DINAMICA
B1: Unificador | C1: (Varios elementos) | X1: Unificador | Y1: (Varios elementos) | AS1: Unificador | AT1: (Varios elementos)
B2: RANGO_TCMC | C2: (Todas) | X2: Precio Cierre Total | Y2: (Todas) | AS2: RANGO_TCMC | AT2: 1
X3: TIPO_OPERACION2 | Y3: CB | AS3: TIPO_OPERACION2 | AT3: CB
B4: Suma de Precio Cierre Total | D4: AÑO | E4: MES | Z4: 3 | AA4: 4 | AB4: 5 | AC4: 6 | AD4: 7 | AE4: 8 | AF4: 9 | AG4: 10 | AH4: 11 | AI4: 12 | AJ4: 13 | AK4: 14 | AL4: 15 | AM4: 16 | AN4: 17 | AO4: 18 | AP4: 19 | AQ4: 20 | AU4: 3 | AV4: 4 | AW4: 5 | AX4: 6 | AY4: 7 | AZ4: 8 | BA4: 9 | BB4: 10 | BC4: 11 | BD4: 12 | BE4: 13 | BF4: 14 | BG4: 15 | BH4: 16 | BI4: 17 | BJ4: 18 | BK4: 19 | BL4: 20
D5: 2025 | E5: 2025 | F5: 2025 | G5: 2025 | H5: 2025 | I5: 2025 | J5: 2025 | K5: 2025 | L5: 2025 | M5: 2025 | N5: 2025 | O5: 2025 | P5: Total 2025 | Q5: 2026 | R5: 2026 | S5: 2026 | T5: Total 2026 | U5: Total general | X5: Suma de Precio Cierre Total | Z5: AÑO | AA5: MES | AS5: Suma de Precio Cierre Total | AU5: AÑO | AV5: MES
B6: TIPO_OPERACION2 | C6: Zona CB | D6: 1 | E6: 2 | F6: 3 | G6: 4 | H6: 5 | I6: 6 | J6: 7 | K6: 8 | L6: 9 | M6: 10 | N6: 11 | O6: 12 | Q6: 1 | R6: 2 | S6: 3 | Z6: 2025 | AA6: 2025 | AB6: 2025 | AC6: 2025 | AD6: 2025 | AE6: 2025 | AF6: 2025 | AG6: 2025 | AH6: 2025 | AI6: 2025 | AJ6: 2025 | AK6: 2025 | AL6: Total 2025 | AM6: 2026 | AN6: 2026 | AO6: 2026 | AP6: Total 2026 | AQ6: Total general | AU6: 2025 | AV6: 2025 | AW6: 2025 | AX6: 2025 | AY6: 2025 | AZ6: 2025 | BA6: 2025 | BB6: 2025 | BC6: 2025 | BD6: 2025 | BE6: 2025 | BF6: 2025 | BG6: Total 2025 | BH6: 2026 | BI6: 2026 | BJ6: 2026 | BK6: Total 2026 | BL6: Total general
B7: CB | C7: CABA | D7: 5716689 | E7: 5667000 | F7: 7765900 | G7: 10044500 | H7: 9498070 | I7: 9536000 | J7: 9727250 | K7: 10229000 | L7: 8158380 | M7: 10522326 | N7: 6506466 | O7: 8897282 | P7: 102268863 | Q7: 7653250 | R7: 7308500 | S7: 11938406 | T7: 26900156 | U7: 129169019 | X7: Tipo Propiedad | Y7: Zona CB | Z7: 1 | AA7: 2 | AB7: 3 | AC7: 4 | AD7: 5 | AE7: 6 | AF7: 7 | AG7: 8 | AH7: 9 | AI7: 10 | AJ7: 11 | AK7: 12 | AM7: 1 | AN7: 2 | AO7: 3 | AS7: Tipo Propiedad | AT7: Zona CB | AU7: 1 | AV7: 2 | AW7: 3 | AX7: 4 | AY7: 5 | AZ7: 6 | BA7: 7 | BB7: 8 | BC7: 9 | BD7: 10 | BE7: 11 | BF7: 12 | BH7: 1 | BI7: 2 | BJ7: 3
B8: CB | C8: Interior - Jujuy | E8: 144000 | G8: 498900 | H8: 70000 | I8: 186000 | J8: 493350 | K8: 38000 | L8: 62000 | O8: 242500 | P8: 1734750 | Q8: 120000 | R8: 232000 | S8: 590000 | T8: 942000 | U8: 2676750 | X8: Casa | Y8: CABA | Z8: 1900000 | AA8: 523000 | AB8: 1744000 | AC8: 1803000 | AD8: 1002000 | AE8: 3093000 | AF8: 2269000 | AG8: 2111500 | AH8: 1259880 | AI8: 1682000 | AJ8: 801730 | AK8: 929000 | AL8: 19118110 | AM8: 1287000 | AN8: 970000 | AO8: 1403500 | AP8: 3660500 | AQ8: 22778610 | AS8: Casa | AT8: CABA | AU8: 1900000 | AV8: 458000 | AW8: 1744000 | AX8: 1803000 | AY8: 1002000 | AZ8: 1875000 | BA8: 2269000 | BB8: 2111500 | BC8: 1153880 | BD8: 1682000 | BE8: 746730 | BF8: 879000 | BG8: 17624110 | BH8: 1287000 | BI8: 905000 | BJ8: 1179500 | BK8: 3371500 | BL8: 20995610
B9: CB | C9: Interior - Mendoza | D9: 55000 | E9: 156000 | F9: 67800 | G9: 331900 | H9: 251000 | I9: 786500 | J9: 668000 | K9: 375000 | L9: 238000 | M9: 734000 | N9: 290000 | O9: 2525800 | P9: 6479000 | Q9: 771500 | R9: 551000 | S9: 1158000 | T9: 2480500 | U9: 8959500 | X9: Casa | Y9: Zona Norte (GBA) | Z9: 1192000 | AA9: 842000 | AB9: 1284100 | AC9: 1898400 | AD9: 1562000 | AE9: 3185000 | AF9: 3090000 | AG9: 1817000 | AH9: 1386000 | AI9: 1001000 | AJ9: 1401000 | AK9: 1078000 | AL9: 19736500 | AM9: 2254000 | AN9: 2080850 | AO9: 1632000 | AP9: 5966850 | AQ9: 25703350 | AS9: Casa | AT9: Zona Norte (GBA) | AU9: 1192000 | AV9: 842000 | AW9: 1284100 | AX9: 1898400 | AY9: 1562000 | AZ9: 3185000 | BA9: 3090000 | BB9: 1817000 | BC9: 1336000 | BD9: 1001000 | BE9: 1401000 | BF9: 1078000 | BG9: 19686500 | BH9: 2254000 | BI9: 2080850 | BJ9: 1632000 | BK9: 5966850 | BL9: 25653350
B10: CB | C10: Interior - Neuquén | D10: 1469379 | E10: 1120650 | F10: 1397800 | G10: 1514000 | H10: 4732813 | I10: 2050714 | J10: 659500 | K10: 2377000 | L10: 3757000 | M10: 1950900 | N10: 288000 | O10: 1177000 | P10: 22494756 | Q10: 1438000 | R10: 1149200 | S10: 2157583 | T10: 4744783 | U10: 27239539 | X10: Casa | Y10: Zona Oeste (GBA) | AB10: 137000 | AC10: 50000 | AD10: 256000 | AE10: 57000 | AH10: 170000 | AJ10: 42000 | AL10: 712000 | AM10: 72500 | AN10: 89000 | AO10: 195000 | AP10: 356500 | AQ10: 1068500 | AS10: Casa | AT10: Zona Oeste (GBA) | AW10: 72000 | AY10: 210000 | BC10: 115000 | BG10: 397000 | BH10: 72500 | BI10: 89000 | BJ10: 195000 | BK10: 356500 | BL10: 753500
B11: CB | C11: Interior - Río Negro | D11: 705343 | E11: 1424694 | F11: 656210 | G11: 1060959 | H11: 1688689 | I11: 455753 | J11: 1128750 | K11: 425080 | L11: 435000 | M11: 693000 | N11: 558000 | O11: 958985 | P11: 10190463 | Q11: 753125 | R11: 525700 | S11: 1342756 | T11: 2621581 | U11: 12812044 | X11: Casa | Y11: Zona Sur (GBA) | Z11: 47000 | AA11: 228000 | AC11: 158000 | AD11: 317000 | AE11: 185000 | AG11: 47000 | AI11: 160000 | AJ11: 36000 | AK11: 146500 | AL11: 1324500 | AN11: 175000 | AO11: 175000 | AP11: 350000 | AQ11: 1674500 | AS11: Casa | AT11: Zona Sur (GBA) | AV11: 112000 | AX11: 158000 | AY11: 317000 | AZ11: 185000 | BD11: 160000 | BF11: 95000 | BG11: 1027000 | BI11: 175000 | BJ11: 175000 | BK11: 350000 | BL11: 1377000
B12: CB | C12: Interior - Salta | D12: 176000 | E12: 330000 | F12: 258500 | G12: 401000 | H12: 201500 | I12: 149000 | J12: 781000 | K12: 385000 | L12: 90000 | M12: 527500 | N12: 104000 | O12: 204000 | P12: 3607500 | Q12: 47000 | R12: 120000 | S12: 343000 | T12: 510000 | U12: 4117500 | X12: Total Casa | Z12: 3139000 | AA12: 1593000 | AB12: 3165100 | AC12: 3909400 | AD12: 3137000 | AE12: 6520000 | AF12: 5359000 | AG12: 3975500 | AH12: 2815880 | AI12: 2843000 | AJ12: 2280730 | AK12: 2153500 | AL12: 40891110 | AM12: 3613500 | AN12: 3314850 | AO12: 3405500 | AP12: 10333850 | AQ12: 51224960 | AS12: Total Casa | AU12: 3092000 | AV12: 1412000 | AW12: 3100100 | AX12: 3859400 | AY12: 3091000 | AZ12: 5245000 | BA12: 5359000 | BB12: 3928500 | BC12: 2604880 | BD12: 2843000 | BE12: 2147730 | BF12: 2052000 | BG12: 38734610 | BH12: 3613500 | BI12: 3249850 | BJ12: 3181500 | BK12: 10044850 | BL12: 48779460
B13: CB | C13: Interior - San Luis | O13: 65000 | P13: 65000 | U13: 65000 | X13: Departamento | Y13: CABA | Z13: 2917689 | AA13: 4177500 | AB13: 4855900 | AC13: 6831000 | AD13: 7618570 | AE13: 4528000 | AF13: 6082000 | AG13: 6968700 | AH13: 5348000 | AI13: 7249456 | AJ13: 4316736 | AK13: 6243882 | AL13: 67137433 | AM13: 5304150 | AN13: 5660500 | AO13: 6735500 | AP13: 17700150 | AQ13: 84837583 | AS13: Departamento | AT13: CABA | AU13: 2797689 | AV13: 3892500 | AW13: 4667900 | AX13: 6315000 | AY13: 7182070 | AZ13: 4275000 | BA13: 5273000 | BB13: 6664200 | BC13: 4956500 | BD13: 6457456 | BE13: 3761500 | BF13: 4460682 | BG13: 60703497 | BH13: 4848250 | BI13: 5134500 | BJ13: 6326000 | BK13: 16308750 | BL13: 77012247
B14: CB | C14: Interior - Santa Fe | D14: 90000 | F14: 42000 | G14: 81500 | I14: 130000 | J14: 80000 | K14: 1400000 | L14: 337000 | M14: 265000 | N14: 58000 | P14: 2483500 | Q14: 252000 | R14: 380000 | S14: 540000 | T14: 1172000 | U14: 3655500 | X14: Departamento | Y14: Zona Norte (GBA) | Z14: 1127000 | AA14: 1435484 | AB14: 2765089 | AC14: 2538500 | AD14: 2096000 | AE14: 3029750 | AF14: 2778128 | AG14: 1881000 | AH14: 1376000 | AI14: 1879500 | AJ14: 1085300 | AK14: 2255000 | AL14: 24246751 | AM14: 1862500 | AN14: 1423447 | AO14: 3200000 | AP14: 6485947 | AQ14: 30732698 | AS14: Departamento | AT14: Zona Norte (GBA) | AU14: 1127000 | AV14: 1435484 | AW14: 2527589 | AX14: 2395000 | AY14: 2051000 | AZ14: 2968750 | BA14: 2362128 | BB14: 1881000 | BC14: 1312000 | BD14: 1829500 | BE14: 878300 | BF14: 2211000 | BG14: 22978751 | BH14: 1798500 | BI14: 1247447 | BJ14: 3076000 | BK14: 6121947 | BL14: 29100698
B15: CB | C15: Zona Norte (GBA) | D15: 3135830 | E15: 3151484 | F15: 4635189 | G15: 5728900 | H15: 4074540 | I15: 6926750 | J15: 6062128 | K15: 4503330 | L15: 4823650 | M15: 3014850 | N15: 3457323 | O15: 3747000 | P15: 53260974 | Q15: 4689000 | R15: 3827297 | S15: 5286000 | T15: 13802297 | U15: 67063271 | X15: Departamento | Y15: Zona Oeste (GBA) | Z15: 50000 | AB15: 69000 | AF15: 291000 | AG15: 168000 | AH15: 118500 | AI15: 48000 | AJ15: 41200 | AK15: 275500 | AL15: 1061200 | AN15: 71500 | AO15: 102000 | AP15: 173500 | AQ15: 1234700 | AS15: Departamento | AT15: Zona Oeste (GBA) | BA15: 180000 | BC15: 118500 | BF15: 275500 | BG15: 574000 | BI15: 71500 | BJ15: 102000 | BK15: 173500 | BL15: 747500
B16: CB | C16: Zona Oeste (GBA) | D16: 50000 | F16: 206000 | G16: 50000 | H16: 406000 | I16: 57000 | J16: 339500 | K16: 280000 | L16: 288500 | M16: 48000 | N16: 83200 | O16: 275500 | P16: 2083700 | Q16: 112500 | R16: 160500 | S16: 297000 | T16: 570000 | U16: 2653700 | X16: Departamento | Y16: Zona Sur (GBA) | Z16: 113400 | AD16: 62000 | AE16: 82000 | AF16: 82000 | AG16: 223400 | AH16: 235000 | AI16: 204000 | AK16: 74000 | AL16: 1075800 | AM16: 45000 | AN16: 67500 | AP16: 112500 | AQ16: 1188300 | AS16: Departamento | AT16: Zona Sur (GBA) | AU16: 73400 | BA16: 82000 | BB16: 151400 | BC16: 87500 | BD16: 140000 | BF16: 74000 | BG16: 608300 | BL16: 608300
B17: CB | C17: Zona Sur (GBA) | D17: 160400 | E17: 228000 | G17: 158000 | H17: 379000 | I17: 325000 | J17: 82000 | K17: 270400 | L17: 235000 | M17: 364000 | N17: 36000 | O17: 220500 | P17: 2458300 | Q17: 45000 | R17: 242500 | S17: 175000 | T17: 462500 | U17: 2920800 | X17: Total Departamento | Z17: 4208089 | AA17: 5612984 | AB17: 7689989 | AC17: 9369500 | AD17: 9776570 | AE17: 7639750 | AF17: 9233128 | AG17: 9241100 | AH17: 7077500 | AI17: 9380956 | AJ17: 5443236 | AK17: 8848382 | AL17: 93521184 | AM17: 7211650 | AN17: 7222947 | AO17: 10037500 | AP17: 24472097 | AQ17: 117993281 | AS17: Total Departamento | AU17: 3998089 | AV17: 5327984 | AW17: 7195489 | AX17: 8710000 | AY17: 9233070 | AZ17: 7243750 | BA17: 7897128 | BB17: 8696600 | BC17: 6474500 | BD17: 8426956 | BE17: 4639800 | BF17: 7021182 | BG17: 84864548 | BH17: 6646750 | BI17: 6453447 | BJ17: 9504000 | BK17: 22604197 | BL17: 107468745
B18: Total CB | D18: 11558641 | E18: 12221828 | F18: 15029399 | G18: 19869659 | H18: 21301612 | I18: 20602717 | J18: 20021478 | K18: 20282810 | L18: 18424530 | M18: 18119576 | N18: 11380989 | O18: 18313567 | P18: 207126806 | Q18: 15881375 | R18: 14496697 | S18: 23827745 | T18: 54205817 | U18: 261332623 | X18: Garage | Y18: CABA | AC18: 90000 | AJ18: 50000 | AL18: 140000 | AQ18: 140000 | AS18: Garage | AT18: CABA | AX18: 90000 | BG18: 90000 | BL18: 90000
B19: Otra Red Búsqueda | C19: CABA | D19: 2585000 | E19: 970000 | F19: 1084000 | G19: 1714000 | H19: 1793500 | I19: 1801000 | J19: 2084500 | K19: 3130000 | L19: 1866000 | M19: 5472400 | N19: 3576000 | O19: 4195000 | P19: 30271400 | Q19: 1666500 | R19: 2374000 | S19: 3873250 | T19: 7913750 | U19: 38185150 | X19: Total Garage | AC19: 90000 | AJ19: 50000 | AL19: 140000 | AQ19: 140000 | AS19: Total Garage | AX19: 90000 | BG19: 90000 | BL19: 90000
B20: Otra Red Búsqueda | C20: Interior - Mendoza | F20: 36500 | G20: 169000 | I20: 276000 | J20: 65000 | L20: 280000 | M20: 55000 | O20: 966500 | P20: 1848000 | R20: 73000 | S20: 752000 | T20: 825000 | U20: 2673000 | X20: Hotel | Y20: CABA | AO20: 70000 | AP20: 70000 | AQ20: 70000 | AS20: Hotel | AT20: CABA | BJ20: 70000 | BK20: 70000 | BL20: 70000
B21: Otra Red Búsqueda | C21: Interior - Neuquén | E21: 507300 | F21: 334000 | G21: 169000 | H21: 144000 | I21: 179500 | J21: 182000 | K21: 93000 | L21: 448000 | M21: 668000 | O21: 100000 | P21: 2824800 | Q21: 325000 | R21: 379000 | S21: 129200 | T21: 833200 | U21: 3658000 | X21: Total Hotel | AO21: 70000 | AP21: 70000 | AQ21: 70000 | AS21: Total Hotel | BJ21: 70000 | BK21: 70000 | BL21: 70000
B22: Otra Red Búsqueda | C22: Interior - Río Negro | D22: 52500 | E22: 122000 | F22: 129000 | G22: 255000 | H22: 218000 | I22: 518000 | J22: 796260 | K22: 784000 | L22: 220000 | N22: 746000 | O22: 565000 | P22: 4405760 | R22: 185000 | S22: 493000 | T22: 678000 | U22: 5083760 | X22: Local Comercial | Y22: CABA | Z22: 83000 | AA22: 295000 | AE22: 240000 | AF22: 125000 | AH22: 45000 | AI22: 118000 | AJ22: 180000 | AL22: 1086000 | AQ22: 1086000 | AS22: Local Comercial | AT22: CABA | AU22: 83000 | AV22: 295000 | AZ22: 240000 | BA22: 125000 | BD22: 118000 | BE22: 180000 | BG22: 1041000 | BL22: 1041000
B23: Otra Red Búsqueda | C23: Interior - Salta | D23: 47000 | F23: 66000 | H23: 440000 | J23: 190000 | O23: 134000 | P23: 877000 | U23: 877000 | X23: Local Comercial | Y23: Zona Norte (GBA) | Z23: 42000 | AC23: 37500 | AG23: 95000 | AH23: 111000 | AK23: 144000 | AL23: 429500 | AQ23: 429500 | AS23: Local Comercial | AT23: Zona Norte (GBA) | BF23: 92000 | BG23: 92000 | BL23: 92000
B24: Otra Red Búsqueda | C24: Interior - Santa Fe | D24: 145000 | F24: 49500 | G24: 100000 | I24: 98500 | J24: 285600 | K24: 353000 | L24: 259000 | M24: 373000 | N24: 591500 | O24: 263000 | P24: 2518100 | R24: 262000 | S24: 177500 | T24: 439500 | U24: 2957600 | X24: Local Comercial | Y24: Zona Oeste (GBA) | AD24: 150000 | AL24: 150000 | AQ24: 150000 | AS24: Local Comercial | AT24: Zona Oeste (GBA) | AY24: 150000 | BG24: 150000 | BL24: 150000
B25: Otra Red Búsqueda | C25: Zona Norte (GBA) | G25: 575000 | H25: 58000 | J25: 636650 | K25: 1407500 | L25: 1985000 | M25: 4158050 | N25: 1646230 | O25: 2041500 | P25: 12507930 | Q25: 728000 | R25: 1175000 | S25: 3474500 | T25: 5377500 | U25: 17885430 | X25: Total Local Comercial | Z25: 125000 | AA25: 295000 | AC25: 37500 | AD25: 150000 | AE25: 240000 | AF25: 125000 | AG25: 95000 | AH25: 156000 | AI25: 118000 | AJ25: 180000 | AK25: 144000 | AL25: 1665500 | AQ25: 1665500 | AS25: Total Local Comercial | AU25: 83000 | AV25: 295000 | AY25: 150000 | AZ25: 240000 | BA25: 125000 | BD25: 118000 | BE25: 180000 | BF25: 92000 | BG25: 1283000 | BL25: 1283000
B26: Otra Red Búsqueda | C26: Zona Oeste (GBA) | F26: 216000 | J26: 176000 | K26: 65000 | M26: 132000 | P26: 589000 | S26: 63000 | T26: 63000 | U26: 652000 | X26: Oficina | Y26: CABA | AA26: 132500 | AD26: 85000 | AF26: 105000 | AK26: 42000 | AL26: 364500 | AM26: 55500 | AO26: 320000 | AP26: 375500 | AQ26: 740000 | AS26: Oficina | AT26: CABA | AV26: 132500 | AY26: 85000 | BA26: 105000 | BG26: 322500 | BJ26: 320000 | BK26: 320000 | BL26: 642500
B27: Otra Red Búsqueda | C27: Zona Sur (GBA) | D27: 114000 | E27: 160000 | G27: 195000 | H27: 378500 | I27: 107000 | J27: 493000 | K27: 634000 | L27: 145266 | M27: 45000 | O27: 104500 | P27: 2376266 | U27: 2376266 | X27: Oficina | Y27: Zona Norte (GBA) | AG27: 88830 | AJ27: 152000 | AL27: 240830 | AM27: 89000 | AO27: 81000 | AP27: 170000 | AQ27: 410830 | AS27: Oficina | AT27: Zona Norte (GBA) | BB27: 88830 | BE27: 152000 | BG27: 240830 | BH27: 89000 | BJ27: 81000 | BK27: 170000 | BL27: 410830
B28: Total Otra Red Búsqueda | D28: 2943500 | E28: 1759300 | F28: 1915000 | G28: 3177000 | H28: 3032000 | I28: 2980000 | J28: 4909010 | K28: 6466500 | L28: 5203266 | M28: 10903450 | N28: 6559730 | O28: 8369500 | P28: 58218256 | Q28: 2719500 | R28: 4448000 | S28: 8962450 | T28: 16129950 | U28: 74348206 | X28: Total Oficina | AA28: 132500 | AD28: 85000 | AF28: 105000 | AG28: 88830 | AJ28: 152000 | AK28: 42000 | AL28: 605330 | AM28: 144500 | AO28: 401000 | AP28: 545500 | AQ28: 1150830 | AS28: Total Oficina | AV28: 132500 | AY28: 85000 | BA28: 105000 | BB28: 88830 | BE28: 152000 | BG28: 563330 | BH28: 89000 | BJ28: 401000 | BK28: 490000 | BL28: 1053330
B29: Otra Red Captación | C29: CABA | D29: 619000 | E29: 2282000 | F29: 1476500 | G29: 1630500 | H29: 2193000 | I29: 2326500 | J29: 3359500 | K29: 3443000 | L29: 4349815 | M29: 3235000 | N29: 2545000 | O29: 4134200 | P29: 31594015 | Q29: 1450500 | R29: 1745000 | S29: 2451000 | T29: 5646500 | U29: 37240515 | X29: PH | Y29: CABA | Z29: 399000 | AA29: 148000 | AB29: 446000 | AC29: 658000 | AD29: 581000 | AE29: 925000 | AF29: 529500 | AG29: 798800 | AH29: 1385000 | AI29: 1248870 | AJ29: 608000 | AK29: 1361400 | AL29: 9088570 | AM29: 331000 | AN29: 593000 | AO29: 1459500 | AP29: 2383500 | AQ29: 11472070 | AS29: PH | AT29: CABA | AU29: 399000 | AV29: 148000 | AW29: 245000 | AX29: 611000 | AY29: 581000 | AZ29: 879000 | BA29: 423000 | BB29: 573000 | BC29: 1254000 | BD29: 1119870 | BE29: 608000 | BF29: 1296400 | BG29: 8137270 | BH29: 217000 | BI29: 593000 | BJ29: 1352500 | BK29: 2162500 | BL29: 10299770
B30: Otra Red Captación | C30: Interior - Mendoza | D30: 45000 | E30: 45000 | G30: 175000 | I30: 66600 | J30: 220000 | N30: 53000 | O30: 966700 | P30: 1571300 | Q30: 67000 | R30: 278000 | S30: 155000 | T30: 500000 | U30: 2071300 | X30: PH | Y30: Zona Norte (GBA) | Z30: 201500 | AA30: 209000 | AB30: 49000 | AC30: 250000 | AD30: 195000 | AE30: 443000 | AF30: 152000 | AG30: 404500 | AH30: 356000 | AI30: 52000 | AJ30: 252000 | AK30: 270000 | AL30: 2834000 | AM30: 55000 | AN30: 118000 | AO30: 150000 | AP30: 323000 | AQ30: 3157000 | AS30: PH | AT30: Zona Norte (GBA) | AU30: 165000 | AV30: 145000 | AX30: 250000 | AY30: 130000 | AZ30: 443000 | BA30: 84000 | BB30: 354500 | BC30: 356000 | BE30: 252000 | BF30: 270000 | BG30: 2449500 | BI30: 118000 | BJ30: 103000 | BK30: 221000 | BL30: 2670500
B31: Otra Red Captación | C31: Interior - Neuquén | D31: 224000 | E31: 185000 | F31: 380000 | G31: 333000 | H31: 90000 | I31: 376000 | J31: 63000 | K31: 220000 | L31: 1104000 | O31: 162000 | P31: 3137000 | R31: 706000 | S31: 165000 | T31: 871000 | U31: 4008000 | X31: PH | Y31: Zona Oeste (GBA) | AF31: 48500 | AG31: 112000 | AL31: 160500 | AM31: 40000 | AP31: 40000 | AQ31: 200500 | AS31: Total PH | AU31: 564000 | AV31: 293000 | AW31: 245000 | AX31: 861000 | AY31: 711000 | AZ31: 1322000 | BA31: 507000 | BB31: 927500 | BC31: 1610000 | BD31: 1119870 | BE31: 860000 | BF31: 1566400 | BG31: 10586770 | BH31: 217000 | BI31: 711000 | BJ31: 1455500 | BK31: 2383500 | BL31: 12970270
B32: Otra Red Captación | C32: Interior - Río Negro | G32: 615000 | H32: 133000 | I32: 45000 | J32: 98000 | K32: 55000 | L32: 318000 | N32: 170000 | O32: 361000 | P32: 1795000 | Q32: 181000 | S32: 93000 | T32: 274000 | U32: 2069000 | X32: PH | Y32: Zona Sur (GBA) | AE32: 58000 | AL32: 58000 | AQ32: 58000 | AS32: Storage | AT32: CABA | AX32: 229000 | BA32: 190000 | BF32: 135000 | BG32: 554000 | BL32: 554000
B33: Otra Red Captación | C33: Interior - Salta | E33: 157500 | H33: 72000 | I33: 241000 | K33: 620000 | L33: 66000 | M33: 40000 | N33: 115000 | O33: 187000 | P33: 1498500 | Q33: 100000 | S33: 89000 | T33: 189000 | U33: 1687500 | X33: Total PH | Z33: 600500 | AA33: 357000 | AB33: 495000 | AC33: 908000 | AD33: 776000 | AE33: 1426000 | AF33: 730000 | AG33: 1315300 | AH33: 1741000 | AI33: 1300870 | AJ33: 860000 | AK33: 1631400 | AL33: 12141070 | AM33: 426000 | AN33: 711000 | AO33: 1609500 | AP33: 2746500 | AQ33: 14887570 | AS33: Storage | AT33: Zona Norte (GBA) | AZ33: 99000 | BG33: 99000 | BL33: 99000
B34: Otra Red Captación | C34: Interior - Santa Fe | D34: 152000 | E34: 180000 | G34: 53000 | I34: 90000 | J34: 40000 | K34: 204000 | L34: 60000 | O34: 135200 | P34: 914200 | Q34: 266000 | R34: 93000 | S34: 124500 | T34: 483500 | U34: 1397700 | X34: Storage | Y34: CABA | Z34: 45000 | AC34: 229000 | AF34: 190000 | AK34: 135000 | AL34: 599000 | AO34: 58000 | AP34: 58000 | AQ34: 657000 | AS34: Total Storage | AX34: 229000 | AZ34: 99000 | BA34: 190000 | BF34: 135000 | BG34: 653000 | BL34: 653000
B35: Otra Red Captación | C35: Zona Norte (GBA) | D35: 860200 | E35: 562000 | F35: 1622000 | G35: 2362500 | H35: 1550622 | I35: 994500 | J35: 1010733 | K35: 525500 | L35: 963000 | M35: 771000 | N35: 431000 | O35: 50000 | P35: 11703055 | Q35: 290000 | R35: 238000 | S35: 97000 | T35: 625000 | U35: 12328055 | X35: Storage | Y35: Zona Norte (GBA) | AE35: 99000 | AL35: 99000 | AQ35: 99000 | AS35: Terreno | AT35: CABA | AU35: 372000 | AV35: 327000 | AW35: 669000 | AX35: 385000 | AY35: 148000 | AZ35: 750000 | BA35: 371800 | BB35: 350000 | BC35: 71500 | BD35: 167000 | BE35: 550000 | BF35: 150000 | BG35: 4311300 | BH35: 675600 | BI35: 85000 | BJ35: 426000 | BK35: 1186600 | BL35: 5497900
B36: Otra Red Captación | C36: Zona Oeste (GBA) | F36: 150000 | K36: 172000 | N36: 335000 | O36: 131000 | P36: 788000 | S36: 69000 | T36: 69000 | U36: 857000 | X36: Total Storage | Z36: 45000 | AC36: 229000 | AE36: 99000 | AF36: 190000 | AK36: 135000 | AL36: 698000 | AO36: 58000 | AP36: 58000 | AQ36: 756000 | AS36: Terreno | AT36: Zona Norte (GBA) | AU36: 530010 | AV36: 665000 | AW36: 500000 | AX36: 915000 | AY36: 134540 | AZ36: 170000 | BB36: 160000 | BC36: 1547100 | BD36: 82350 | BE36: 508578 | BG36: 5212578 | BH36: 428500 | BI36: 205000 | BJ36: 125000 | BK36: 758500 | BL36: 5971078
B37: Otra Red Captación | C37: Zona Sur (GBA) | F37: 221000 | G37: 46500 | H37: 355000 | I37: 240500 | M37: 462500 | O37: 179000 | P37: 1504500 | R37: 36000 | S37: 255900 | T37: 291900 | U37: 1796400 | X37: Terreno | Y37: CABA | Z37: 372000 | AA37: 391000 | AB37: 720000 | AC37: 433500 | AD37: 211500 | AE37: 750000 | AF37: 426750 | AG37: 350000 | AH37: 120500 | AI37: 224000 | AJ37: 550000 | AK37: 186000 | AL37: 4735250 | AM37: 675600 | AN37: 85000 | AO37: 1891906 | AP37: 2652506 | AQ37: 7387756 | AS37: Total Terreno | AU37: 902010 | AV37: 992000 | AW37: 1169000 | AX37: 1300000 | AY37: 282540 | AZ37: 920000 | BA37: 371800 | BB37: 510000 | BC37: 1618600 | BD37: 249350 | BE37: 1058578 | BF37: 150000 | BG37: 9523878 | BH37: 1104100 | BI37: 290000 | BJ37: 551000 | BK37: 1945100 | BL37: 11468978
B38: Total Otra Red Captación | D38: 1900200 | E38: 3411500 | F38: 3849500 | G38: 5215500 | H38: 4393622 | I38: 4380100 | J38: 4791233 | K38: 5239500 | L38: 6860815 | M38: 4508500 | N38: 3649000 | O38: 6306100 | P38: 54505570 | Q38: 2354500 | R38: 3096000 | S38: 3499400 | T38: 8949900 | U38: 63455470 | X38: Terreno | Y38: Zona Norte (GBA) | Z38: 573330 | AA38: 665000 | AB38: 537000 | AC38: 1004500 | AD38: 221540 | AE38: 170000 | AF38: 42000 | AG38: 217000 | AH38: 1594650 | AI38: 82350 | AJ38: 567023 | AL38: 5674393 | AM38: 428500 | AN38: 205000 | AO38: 223000 | AP38: 856500 | AQ38: 6530893 | AS38: Total general | AU38: 8639099 | AV38: 8452484 | AW38: 11709589 | AX38: 15049400 | AY38: 13552610 | AZ38: 15069750 | BA38: 14554928 | BB38: 14151430 | BC38: 12307980 | BD38: 12757176 | BE38: 9038108 | BF38: 11016582 | BG38: 146299136 | BH38: 11670350 | BI38: 10704297 | BJ38: 15163000 | BK38: 37537647 | BL38: 183836783
B39: Total general | D39: 16402341 | E39: 17392628 | F39: 20793899 | G39: 28262159 | H39: 28727234 | I39: 27962817 | J39: 29721721 | K39: 31988810 | L39: 30488611 | M39: 33531526 | N39: 21589719 | O39: 32989167 | P39: 319850632 | Q39: 20955375 | R39: 22040697 | S39: 36289595 | T39: 79285667 | U39: 399136299 | X39: Total Terreno | Z39: 945330 | AA39: 1056000 | AB39: 1257000 | AC39: 1438000 | AD39: 433040 | AE39: 920000 | AF39: 468750 | AG39: 567000 | AH39: 1715150 | AI39: 306350 | AJ39: 1117023 | AK39: 186000 | AL39: 10409643 | AM39: 1104100 | AN39: 290000 | AO39: 2114906 | AP39: 3509006 | AQ39: 13918649
X40: Total general | Z40: 9062919 | AA40: 9046484 | AB40: 12607089 | AC40: 15981400 | AD40: 14357610 | AE40: 16844750 | AF40: 16210878 | AG40: 15282730 | AH40: 13505530 | AI40: 13949176 | AJ40: 10082989 | AK40: 13140282 | AL40: 160071837 | AM40: 12499750 | AN40: 11538797 | AO40: 17696406 | AP40: 41734953 | AQ40: 201806790
B42: Unificador | C42: (Varios elementos)
B43: RANGO_TCMC | C43: (Todas)
Z44: =Z6 -> 2025 | AA44: =AA6 -> 2025 | AB44: =AB6 -> 2025 | AC44: =AC6 -> 2025 | AD44: =AD6 -> 2025 | AE44: =AE6 -> 2025 | AF44: =AF6 -> 2025 | AG44: =AG6 -> 2025 | ... AQ44: =AQ6 -> Total general | AU44: =AU6 -> 2025 | AV44: =AV6 -> 2025 | AW44: =AW6 -> 2025 | AX44: =AX6 -> 2025 | AY44: =AY6 -> 2025 | AZ44: =AZ6 -> 2025 | BA44: =BA6 -> 2025 | BB44: =BB6 -> 2025 | ... BL44: =BL6 -> Total general
B45: Cuenta de Precio Cierre Total | D45: AÑO | E45: MES | X45: VOLUMEN | Z45: =Z7 -> 1 | AA45: =AA7 -> 2 | AB45: =AB7 -> 3 | AC45: =AC7 -> 4 | AD45: =AD7 -> 5 | AE45: =AE7 -> 6 | AF45: =AF7 -> 7 | AG45: =AG7 -> 8 | ... AQ45: =AQ7 -> 0 | AS45: VOLUMEN | AU45: =AU7 -> 1 | AV45: =AV7 -> 2 | AW45: =AW7 -> 3 | AX45: =AX7 -> 4 | AY45: =AY7 -> 5 | AZ45: =AZ7 -> 6 | BA45: =BA7 -> 7 | BB45: =BB7 -> 8 | ... BL45: =BL7 -> 0
D46: 2025 | E46: 2025 | F46: 2025 | G46: 2025 | H46: 2025 | I46: 2025 | J46: 2025 | K46: 2025 | L46: 2025 | M46: 2025 | N46: 2025 | O46: 2025 | P46: Total 2025 | Q46: 2026 | R46: 2026 | S46: 2026 | T46: Total 2026 | U46: Total general | X46: Total Casa | Z46: =VLOOKUP($X46,$X$8:$AQ$39,Z$4,FALSE) -> 3139000 | AA46: =VLOOKUP($X46,$X$8:$AQ$39,AA$4,FALSE) -> 1593000 | AB46: =VLOOKUP($X46,$X$8:$AQ$39,AB$4,FALSE) -> 3165100 | AC46: =VLOOKUP($X46,$X$8:$AQ$39,AC$4,FALSE) -> 3909400 | AD46: =VLOOKUP($X46,$X$8:$AQ$39,AD$4,FALSE) -> 3137000 | AE46: =VLOOKUP($X46,$X$8:$AQ$39,AE$4,FALSE) -> 6520000 | AF46: =VLOOKUP($X46,$X$8:$AQ$39,AF$4,FALSE) -> 5359000 | AG46: =VLOOKUP($X46,$X$8:$AQ$39,AG$4,FALSE) -> 3975500 | ... AQ46: =VLOOKUP($X46,$X$8:$AQ$39,AQ$4,FALSE) -> 51224960 | AS46: Total Casa | AU46: =VLOOKUP($X46,$AS$8:$BL$39,AU$4,FALSE) -> 3092000 | AV46: =VLOOKUP($X46,$AS$8:$BL$39,AV$4,FALSE) -> 1412000 | AW46: =VLOOKUP($X46,$AS$8:$BL$39,AW$4,FALSE) -> 3100100 | AX46: =VLOOKUP($X46,$AS$8:$BL$39,AX$4,FALSE) -> 3859400 | AY46: =VLOOKUP($X46,$AS$8:$BL$39,AY$4,FALSE) -> 3091000 | AZ46: =VLOOKUP($X46,$AS$8:$BL$39,AZ$4,FALSE) -> 5245000 | BA46: =VLOOKUP($X46,$AS$8:$BL$39,BA$4,FALSE) -> 5359000 | BB46: =VLOOKUP($X46,$AS$8:$BL$39,BB$4,FALSE) -> 3928500 | ... BL46: =VLOOKUP($X46,$AS$8:$BL$39,BL$4,FALSE) -> 48779460
B47: TIPO_OPERACION2 | C47: Zona CB | D47: 1 | E47: 2 | F47: 3 | G47: 4 | H47: 5 | I47: 6 | J47: 7 | K47: 8 | L47: 9 | M47: 10 | N47: 11 | O47: 12 | Q47: 1 | R47: 2 | S47: 3 | X47: Total Departamento | Z47: =VLOOKUP($X47,$X$8:$AQ$39,Z$4,FALSE) -> 4208089 | AA47: =VLOOKUP($X47,$X$8:$AQ$39,AA$4,FALSE) -> 5612984 | AB47: =VLOOKUP($X47,$X$8:$AQ$39,AB$4,FALSE) -> 7689989 | AC47: =VLOOKUP($X47,$X$8:$AQ$39,AC$4,FALSE) -> 9369500 | AD47: =VLOOKUP($X47,$X$8:$AQ$39,AD$4,FALSE) -> 9776570 | AE47: =VLOOKUP($X47,$X$8:$AQ$39,AE$4,FALSE) -> 7639750 | AF47: =VLOOKUP($X47,$X$8:$AQ$39,AF$4,FALSE) -> 9233128 | AG47: =VLOOKUP($X47,$X$8:$AQ$39,AG$4,FALSE) -> 9241100 | ... AQ47: =VLOOKUP($X47,$X$8:$AQ$39,AQ$4,FALSE) -> 117993281 | AS47: Total Departamento | AU47: =VLOOKUP($X47,$AS$8:$BL$39,AU$4,FALSE) -> 3998089 | AV47: =VLOOKUP($X47,$AS$8:$BL$39,AV$4,FALSE) -> 5327984 | AW47: =VLOOKUP($X47,$AS$8:$BL$39,AW$4,FALSE) -> 7195489 | AX47: =VLOOKUP($X47,$AS$8:$BL$39,AX$4,FALSE) -> 8710000 | AY47: =VLOOKUP($X47,$AS$8:$BL$39,AY$4,FALSE) -> 9233070 | AZ47: =VLOOKUP($X47,$AS$8:$BL$39,AZ$4,FALSE) -> 7243750 | BA47: =VLOOKUP($X47,$AS$8:$BL$39,BA$4,FALSE) -> 7897128 | BB47: =VLOOKUP($X47,$AS$8:$BL$39,BB$4,FALSE) -> 8696600 | ... BL47: =VLOOKUP($X47,$AS$8:$BL$39,BL$4,FALSE) -> 107468745
B48: CB | C48: CABA | D48: 42 | E48: 40 | F48: 45 | G48: 66 | H48: 66 | I48: 51 | J48: 68 | K48: 74 | L48: 62 | M48: 77 | N48: 49 | O48: 60 | P48: 700 | Q48: 50 | R48: 53 | S48: 86 | T48: 189 | U48: 889 | X48: Total Oficina | Z48: =VLOOKUP($X48,$X$8:$AQ$39,Z$4,FALSE) -> 0 | AA48: =VLOOKUP($X48,$X$8:$AQ$39,AA$4,FALSE) -> 132500 | AB48: =VLOOKUP($X48,$X$8:$AQ$39,AB$4,FALSE) -> 0 | AC48: =VLOOKUP($X48,$X$8:$AQ$39,AC$4,FALSE) -> 0 | AD48: =VLOOKUP($X48,$X$8:$AQ$39,AD$4,FALSE) -> 85000 | AE48: =VLOOKUP($X48,$X$8:$AQ$39,AE$4,FALSE) -> 0 | AF48: =VLOOKUP($X48,$X$8:$AQ$39,AF$4,FALSE) -> 105000 | AG48: =VLOOKUP($X48,$X$8:$AQ$39,AG$4,FALSE) -> 88830 | ... AQ48: =VLOOKUP($X48,$X$8:$AQ$39,AQ$4,FALSE) -> 1150830 | AS48: Total Oficina | AU48: =VLOOKUP($X48,$AS$8:$BL$39,AU$4,FALSE) -> 0 | AV48: =VLOOKUP($X48,$AS$8:$BL$39,AV$4,FALSE) -> 132500 | AW48: =VLOOKUP($X48,$AS$8:$BL$39,AW$4,FALSE) -> 0 | AX48: =VLOOKUP($X48,$AS$8:$BL$39,AX$4,FALSE) -> 0 | AY48: =VLOOKUP($X48,$AS$8:$BL$39,AY$4,FALSE) -> 85000 | AZ48: =VLOOKUP($X48,$AS$8:$BL$39,AZ$4,FALSE) -> 0 | BA48: =VLOOKUP($X48,$AS$8:$BL$39,BA$4,FALSE) -> 105000 | BB48: =VLOOKUP($X48,$AS$8:$BL$39,BB$4,FALSE) -> 88830 | ... BL48: =VLOOKUP($X48,$AS$8:$BL$39,BL$4,FALSE) -> 1053330
B49: CB | C49: Interior - Jujuy | E49: 1 | G49: 5 | H49: 1 | I49: 3 | J49: 3 | K49: 1 | L49: 1 | O49: 4 | P49: 19 | Q49: 2 | R49: 2 | S49: 6 | T49: 10 | U49: 29 | X49: Total PH | Z49: =VLOOKUP($X49,$X$8:$AQ$39,Z$4,FALSE) -> 600500 | AA49: =VLOOKUP($X49,$X$8:$AQ$39,AA$4,FALSE) -> 357000 | AB49: =VLOOKUP($X49,$X$8:$AQ$39,AB$4,FALSE) -> 495000 | AC49: =VLOOKUP($X49,$X$8:$AQ$39,AC$4,FALSE) -> 908000 | AD49: =VLOOKUP($X49,$X$8:$AQ$39,AD$4,FALSE) -> 776000 | AE49: =VLOOKUP($X49,$X$8:$AQ$39,AE$4,FALSE) -> 1426000 | AF49: =VLOOKUP($X49,$X$8:$AQ$39,AF$4,FALSE) -> 730000 | AG49: =VLOOKUP($X49,$X$8:$AQ$39,AG$4,FALSE) -> 1315300 | ... AQ49: =VLOOKUP($X49,$X$8:$AQ$39,AQ$4,FALSE) -> 14887570 | AS49: Total PH | AU49: =VLOOKUP($X49,$AS$8:$BL$39,AU$4,FALSE) -> 564000 | AV49: =VLOOKUP($X49,$AS$8:$BL$39,AV$4,FALSE) -> 293000 | AW49: =VLOOKUP($X49,$AS$8:$BL$39,AW$4,FALSE) -> 245000 | AX49: =VLOOKUP($X49,$AS$8:$BL$39,AX$4,FALSE) -> 861000 | AY49: =VLOOKUP($X49,$AS$8:$BL$39,AY$4,FALSE) -> 711000 | AZ49: =VLOOKUP($X49,$AS$8:$BL$39,AZ$4,FALSE) -> 1322000 | BA49: =VLOOKUP($X49,$AS$8:$BL$39,BA$4,FALSE) -> 507000 | BB49: =VLOOKUP($X49,$AS$8:$BL$39,BB$4,FALSE) -> 927500 | ... BL49: =VLOOKUP($X49,$AS$8:$BL$39,BL$4,FALSE) -> 12970270
B50: CB | C50: Interior - Mendoza | D50: 1 | E50: 2 | F50: 1 | G50: 3 | H50: 3 | I50: 7 | J50: 9 | K50: 2 | L50: 3 | M50: 7 | N50: 4 | O50: 29 | P50: 71 | Q50: 7 | R50: 6 | S50: 8 | T50: 21 | U50: 92 | X50: TOTAL | Z50: =SUM(Z46:Z49) -> 7947589 | AA50: =SUM(AA46:AA49) -> 7695484 | AB50: =SUM(AB46:AB49) -> 11350089 | AC50: =SUM(AC46:AC49) -> 14186900 | AD50: =SUM(AD46:AD49) -> 13774570 | AE50: =SUM(AE46:AE49) -> 15585750 | AF50: =SUM(AF46:AF49) -> 15427128 | AG50: =SUM(AG46:AG49) -> 14620730 | ... AQ50: =SUM(AQ46:AQ49) -> 185256641 | AS50: TOTAL | AU50: =SUM(AU46:AU49) -> 7654089 | AV50: =SUM(AV46:AV49) -> 7165484 | AW50: =SUM(AW46:AW49) -> 10540589 | AX50: =SUM(AX46:AX49) -> 13430400 | AY50: =SUM(AY46:AY49) -> 13120070 | AZ50: =SUM(AZ46:AZ49) -> 13810750 | BA50: =SUM(BA46:BA49) -> 13868128 | BB50: =SUM(BB46:BB49) -> 13641430 | ... BL50: =SUM(BL46:BL49) -> 170271805
B51: CB | C51: Interior - Neuquén | D51: 15 | E51: 12 | F51: 14 | G51: 13 | H51: 21 | I51: 19 | J51: 8 | K51: 18 | L51: 12 | M51: 15 | N51: 3 | O51: 8 | P51: 158 | Q51: 15 | R51: 10 | S51: 16 | T51: 41 | U51: 199
B52: CB | C52: Interior - Río Negro | D52: 6 | E52: 8 | F52: 6 | G52: 8 | H52: 9 | I52: 7 | J52: 8 | K52: 4 | L52: 4 | M52: 4 | N52: 2 | O52: 8 | P52: 74 | Q52: 6 | R52: 5 | S52: 9 | T52: 20 | U52: 94 | Z52: =Z44 -> 2025 | AA52: =AA44 -> 2025 | AB52: =AB44 -> 2025 | AC52: =AC44 -> 2025 | AD52: =AD44 -> 2025 | AE52: =AE44 -> 2025 | AF52: =AF44 -> 2025 | AG52: =AG44 -> 2025 | ... AQ52: =AQ44 -> Total general | AU52: =AU44 -> 2025 | AV52: =AV44 -> 2025 | AW52: =AW44 -> 2025 | AX52: =AX44 -> 2025 | AY52: =AY44 -> 2025 | AZ52: =AZ44 -> 2025 | BA52: =BA44 -> 2025 | BB52: =BB44 -> 2025 | ... BL52: =BL44 -> Total general
B53: CB | C53: Interior - Salta | D53: 3 | E53: 3 | F53: 3 | G53: 6 | H53: 2 | I53: 3 | J53: 9 | K53: 5 | L53: 1 | M53: 4 | N53: 2 | O53: 3 | P53: 44 | Q53: 1 | R53: 1 | S53: 3 | T53: 5 | U53: 49 | X53: CANTIDAD | Z53: =Z45 -> 1 | AA53: =AA45 -> 2 | AB53: =AB45 -> 3 | AC53: =AC45 -> 4 | AD53: =AD45 -> 5 | AE53: =AE45 -> 6 | AF53: =AF45 -> 7 | AG53: =AG45 -> 8 | ... AQ53: =AQ45 -> 0 | AS53: CANTIDAD | AU53: =AU45 -> 1 | AV53: =AV45 -> 2 | AW53: =AW45 -> 3 | AX53: =AX45 -> 4 | AY53: =AY45 -> 5 | AZ53: =AZ45 -> 6 | BA53: =BA45 -> 7 | BB53: =BB45 -> 8 | ... BL53: =BL45 -> 0
B54: CB | C54: Interior - San Luis | O54: 1 | P54: 1 | U54: 1 | X54: Total Casa | Z54: =VLOOKUP($X54,$X$91:$AQ$122,Z$4,FALSE) -> 18 | AA54: =VLOOKUP($X54,$X$91:$AQ$122,AA$4,FALSE) -> 10 | AB54: =VLOOKUP($X54,$X$91:$AQ$122,AB$4,FALSE) -> 15 | AC54: =VLOOKUP($X54,$X$91:$AQ$122,AC$4,FALSE) -> 20 | AD54: =VLOOKUP($X54,$X$91:$AQ$122,AD$4,FALSE) -> 18 | AE54: =VLOOKUP($X54,$X$91:$AQ$122,AE$4,FALSE) -> 25 | AF54: =VLOOKUP($X54,$X$91:$AQ$122,AF$4,FALSE) -> 19 | AG54: =VLOOKUP($X54,$X$91:$AQ$122,AG$4,FALSE) -> 20 | ... AQ54: =VLOOKUP($X54,$X$91:$AQ$122,AQ$4,FALSE) -> 258 | AS54: Total Casa | AU54: =VLOOKUP($X54,$AS$91:$BL$122,AU$4,FALSE) -> 17 | AV54: =VLOOKUP($X54,$AS$91:$BL$122,AV$4,FALSE) -> 7 | AW54: =VLOOKUP($X54,$AS$91:$BL$122,AW$4,FALSE) -> 14 | AX54: =VLOOKUP($X54,$AS$91:$BL$122,AX$4,FALSE) -> 19 | AY54: =VLOOKUP($X54,$AS$91:$BL$122,AY$4,FALSE) -> 17 | AZ54: =VLOOKUP($X54,$AS$91:$BL$122,AZ$4,FALSE) -> 22 | BA54: =VLOOKUP($X54,$AS$91:$BL$122,BA$4,FALSE) -> 19 | BB54: =VLOOKUP($X54,$AS$91:$BL$122,BB$4,FALSE) -> 19 | ... BL54: =VLOOKUP($X54,$AS$91:$BL$122,BL$4,FALSE) -> 233
B55: CB | C55: Interior - Santa Fe | D55: 1 | F55: 1 | G55: 2 | I55: 2 | J55: 1 | K55: 3 | L55: 3 | M55: 2 | N55: 1 | P55: 16 | Q55: 4 | R55: 4 | S55: 7 | T55: 15 | U55: 31 | X55: Total Departamento | Z55: =VLOOKUP($X55,$X$91:$AQ$122,Z$4,FALSE) -> 35 | AA55: =VLOOKUP($X55,$X$91:$AQ$122,AA$4,FALSE) -> 39 | AB55: =VLOOKUP($X55,$X$91:$AQ$122,AB$4,FALSE) -> 48 | AC55: =VLOOKUP($X55,$X$91:$AQ$122,AC$4,FALSE) -> 61 | AD55: =VLOOKUP($X55,$X$91:$AQ$122,AD$4,FALSE) -> 65 | AE55: =VLOOKUP($X55,$X$91:$AQ$122,AE$4,FALSE) -> 51 | AF55: =VLOOKUP($X55,$X$91:$AQ$122,AF$4,FALSE) -> 69 | AG55: =VLOOKUP($X55,$X$91:$AQ$122,AG$4,FALSE) -> 71 | ... AQ55: =VLOOKUP($X55,$X$91:$AQ$122,AQ$4,FALSE) -> 859 | AS55: Total Departamento | AU55: =VLOOKUP($X55,$AS$91:$BL$122,AU$4,FALSE) -> 31 | AV55: =VLOOKUP($X55,$AS$91:$BL$122,AV$4,FALSE) -> 34 | AW55: =VLOOKUP($X55,$AS$91:$BL$122,AW$4,FALSE) -> 40 | AX55: =VLOOKUP($X55,$AS$91:$BL$122,AX$4,FALSE) -> 49 | AY55: =VLOOKUP($X55,$AS$91:$BL$122,AY$4,FALSE) -> 55 | AZ55: =VLOOKUP($X55,$AS$91:$BL$122,AZ$4,FALSE) -> 43 | BA55: =VLOOKUP($X55,$AS$91:$BL$122,BA$4,FALSE) -> 44 | BB55: =VLOOKUP($X55,$AS$91:$BL$122,BB$4,FALSE) -> 60 | ... BL55: =VLOOKUP($X55,$AS$91:$BL$122,BL$4,FALSE) -> 684
B56: CB | C56: Zona Norte (GBA) | D56: 21 | E56: 16 | F56: 27 | G56: 32 | H56: 25 | I56: 34 | J56: 31 | K56: 27 | L56: 31 | M56: 22 | N56: 26 | O56: 21 | P56: 313 | Q56: 29 | R56: 22 | S56: 36 | T56: 87 | U56: 400 | X56: Total Oficina | Z56: =VLOOKUP($X56,$X$91:$AQ$122,Z$4,FALSE) -> 0 | AA56: =VLOOKUP($X56,$X$91:$AQ$122,AA$4,FALSE) -> 1 | AB56: =VLOOKUP($X56,$X$91:$AQ$122,AB$4,FALSE) -> 0 | AC56: =VLOOKUP($X56,$X$91:$AQ$122,AC$4,FALSE) -> 0 | AD56: =VLOOKUP($X56,$X$91:$AQ$122,AD$4,FALSE) -> 1 | AE56: =VLOOKUP($X56,$X$91:$AQ$122,AE$4,FALSE) -> 0 | AF56: =VLOOKUP($X56,$X$91:$AQ$122,AF$4,FALSE) -> 1 | AG56: =VLOOKUP($X56,$X$91:$AQ$122,AG$4,FALSE) -> 1 | ... AQ56: =VLOOKUP($X56,$X$91:$AQ$122,AQ$4,FALSE) -> 10 | AS56: Total Oficina | AU56: =VLOOKUP($X56,$AS$91:$BL$122,AU$4,FALSE) -> 0 | AV56: =VLOOKUP($X56,$AS$91:$BL$122,AV$4,FALSE) -> 1 | AW56: =VLOOKUP($X56,$AS$91:$BL$122,AW$4,FALSE) -> 0 | AX56: =VLOOKUP($X56,$AS$91:$BL$122,AX$4,FALSE) -> 0 | AY56: =VLOOKUP($X56,$AS$91:$BL$122,AY$4,FALSE) -> 1 | AZ56: =VLOOKUP($X56,$AS$91:$BL$122,AZ$4,FALSE) -> 0 | BA56: =VLOOKUP($X56,$AS$91:$BL$122,BA$4,FALSE) -> 1 | BB56: =VLOOKUP($X56,$AS$91:$BL$122,BB$4,FALSE) -> 1 | ... BL56: =VLOOKUP($X56,$AS$91:$BL$122,BL$4,FALSE) -> 8
B57: CB | C57: Zona Oeste (GBA) | D57: 1 | F57: 3 | G57: 1 | H57: 3 | I57: 1 | J57: 4 | K57: 5 | L57: 3 | M57: 1 | N57: 2 | O57: 2 | P57: 26 | Q57: 2 | R57: 2 | S57: 2 | T57: 6 | U57: 32 | X57: Total PH | Z57: =VLOOKUP($X57,$X$91:$AQ$122,Z$4,FALSE) -> 4 | AA57: =VLOOKUP($X57,$X$91:$AQ$122,AA$4,FALSE) -> 3 | AB57: =VLOOKUP($X57,$X$91:$AQ$122,AB$4,FALSE) -> 6 | AC57: =VLOOKUP($X57,$X$91:$AQ$122,AC$4,FALSE) -> 8 | AD57: =VLOOKUP($X57,$X$91:$AQ$122,AD$4,FALSE) -> 7 | AE57: =VLOOKUP($X57,$X$91:$AQ$122,AE$4,FALSE) -> 11 | AF57: =VLOOKUP($X57,$X$91:$AQ$122,AF$4,FALSE) -> 8 | AG57: =VLOOKUP($X57,$X$91:$AQ$122,AG$4,FALSE) -> 14 | ... AQ57: =VLOOKUP($X57,$X$91:$AQ$122,AQ$4,FALSE) -> 128 | AS57: Total PH | AU57: =VLOOKUP($X57,$AS$91:$BL$122,AU$4,FALSE) -> 3 | AV57: =VLOOKUP($X57,$AS$91:$BL$122,AV$4,FALSE) -> 2 | AW57: =VLOOKUP($X57,$AS$91:$BL$122,AW$4,FALSE) -> 1 | AX57: =VLOOKUP($X57,$AS$91:$BL$122,AX$4,FALSE) -> 7 | AY57: =VLOOKUP($X57,$AS$91:$BL$122,AY$4,FALSE) -> 6 | AZ57: =VLOOKUP($X57,$AS$91:$BL$122,AZ$4,FALSE) -> 9 | BA57: =VLOOKUP($X57,$AS$91:$BL$122,BA$4,FALSE) -> 4 | BB57: =VLOOKUP($X57,$AS$91:$BL$122,BB$4,FALSE) -> 7 | ... BL57: =VLOOKUP($X57,$AS$91:$BL$122,BL$4,FALSE) -> 91
B58: CB | C58: Zona Sur (GBA) | D58: 3 | E58: 3 | G58: 1 | H58: 3 | I58: 5 | J58: 1 | K58: 5 | L58: 4 | M58: 3 | N58: 1 | O58: 3 | P58: 32 | Q58: 1 | R58: 2 | S58: 1 | T58: 4 | U58: 36 | X58: TOTAL | Z58: =SUM(Z54:Z57) -> 57 | AA58: =SUM(AA54:AA57) -> 53 | AB58: =SUM(AB54:AB57) -> 69 | AC58: =SUM(AC54:AC57) -> 89 | AD58: =SUM(AD54:AD57) -> 91 | AE58: =SUM(AE54:AE57) -> 87 | AF58: =SUM(AF54:AF57) -> 97 | AG58: =SUM(AG54:AG57) -> 106 | ... AQ58: =SUM(AQ54:AQ57) -> 1255 | AS58: TOTAL | AU58: =SUM(AU54:AU57) -> 51 | AV58: =SUM(AV54:AV57) -> 44 | AW58: =SUM(AW54:AW57) -> 55 | AX58: =SUM(AX54:AX57) -> 75 | AY58: =SUM(AY54:AY57) -> 79 | AZ58: =SUM(AZ54:AZ57) -> 74 | BA58: =SUM(BA54:BA57) -> 68 | BB58: =SUM(BB54:BB57) -> 87 | ... BL58: =SUM(BL54:BL57) -> 1016
B59: Total CB | D59: 93 | E59: 85 | F59: 100 | G59: 137 | H59: 133 | I59: 132 | J59: 142 | K59: 144 | L59: 124 | M59: 135 | N59: 90 | O59: 139 | P59: 1454 | Q59: 117 | R59: 107 | S59: 174 | T59: 398 | U59: 1852
B60: Otra Red Búsqueda | C60: CABA | D60: 9 | E60: 4 | F60: 7 | G60: 11 | H60: 11 | I60: 10 | J60: 10 | K60: 17 | L60: 13 | M60: 31 | N60: 25 | O60: 19 | P60: 167 | Q60: 9 | R60: 13 | S60: 21 | T60: 43 | U60: 210
B61: Otra Red Búsqueda | C61: Interior - Mendoza | F61: 1 | G61: 2 | I61: 2 | J61: 1 | L61: 1 | M61: 1 | O61: 8 | P61: 16 | R61: 1 | S61: 3 | T61: 4 | U61: 20 | X61: PROMEDIO | AS61: PROMEDIO
B62: Otra Red Búsqueda | C62: Interior - Neuquén | E62: 5 | F62: 2 | G62: 2 | H62: 2 | I62: 2 | J62: 2 | K62: 1 | L62: 4 | M62: 5 | O62: 1 | P62: 26 | Q62: 2 | R62: 3 | S62: 2 | T62: 7 | U62: 33 | X62: Total Casa | Z62: =IFERROR(Z46/Z54,0) -> 174388.89 | AA62: =IFERROR(AA46/AA54,0) -> 159300 | AB62: =IFERROR(AB46/AB54,0) -> 211006.67 | AC62: =IFERROR(AC46/AC54,0) -> 195470 | AD62: =IFERROR(AD46/AD54,0) -> 174277.78 | AE62: =IFERROR(AE46/AE54,0) -> 260800 | AF62: =IFERROR(AF46/AF54,0) -> 282052.63 | AG62: =IFERROR(AG46/AG54,0) -> 198775 | ... AQ62: =IFERROR(AQ46/AQ54,0) -> 198546.36 | AS62: Total Casa | AU62: =IFERROR(AU46/AU54,0) -> 181882.35 | AV62: =IFERROR(AV46/AV54,0) -> 201714.29 | AW62: =IFERROR(AW46/AW54,0) -> 221435.71 | AX62: =IFERROR(AX46/AX54,0) -> 203126.32 | AY62: =IFERROR(AY46/AY54,0) -> 181823.53 | AZ62: =IFERROR(AZ46/AZ54,0) -> 238409.09 | BA62: =IFERROR(BA46/BA54,0) -> 282052.63 | BB62: =IFERROR(BB46/BB54,0) -> 206763.16 | ... BL62: =IFERROR(BL46/BL54,0) -> 209353.91
B63: Otra Red Búsqueda | C63: Interior - Río Negro | D63: 1 | E63: 1 | F63: 2 | G63: 2 | H63: 2 | I63: 3 | J63: 6 | K63: 4 | L63: 2 | N63: 4 | O63: 4 | P63: 31 | R63: 1 | S63: 2 | T63: 3 | U63: 34 | X63: Total Departamento | Z63: =IFERROR(Z47/Z55,0) -> 120231.11 | AA63: =IFERROR(AA47/AA55,0) -> 143922.67 | AB63: =IFERROR(AB47/AB55,0) -> 160208.1 | AC63: =IFERROR(AC47/AC55,0) -> 153598.36 | AD63: =IFERROR(AD47/AD55,0) -> 150408.77 | AE63: =IFERROR(AE47/AE55,0) -> 149799.02 | AF63: =IFERROR(AF47/AF55,0) -> 133813.45 | AG63: =IFERROR(AG47/AG55,0) -> 130156.34 | ... AQ63: =IFERROR(AQ47/AQ55,0) -> 137361.21 | AS63: Total Departamento | AU63: =IFERROR(AU47/AU55,0) -> 128970.61 | AV63: =IFERROR(AV47/AV55,0) -> 156705.41 | AW63: =IFERROR(AW47/AW55,0) -> 179887.23 | AX63: =IFERROR(AX47/AX55,0) -> 177755.1 | AY63: =IFERROR(AY47/AY55,0) -> 167874 | AZ63: =IFERROR(AZ47/AZ55,0) -> 168459.3 | BA63: =IFERROR(BA47/BA55,0) -> 179480.18 | BB63: =IFERROR(BB47/BB55,0) -> 144943.33 | ... BL63: =IFERROR(BL47/BL55,0) -> 157118.05
B64: Otra Red Búsqueda | C64: Interior - Salta | D64: 1 | F64: 1 | H64: 2 | J64: 1 | O64: 1 | P64: 6 | U64: 6 | X64: Total Oficina | Z64: =IFERROR(Z48/Z56,0) -> 0 | AA64: =IFERROR(AA48/AA56,0) -> 132500 | AB64: =IFERROR(AB48/AB56,0) -> 0 | AC64: =IFERROR(AC48/AC56,0) -> 0 | AD64: =IFERROR(AD48/AD56,0) -> 85000 | AE64: =IFERROR(AE48/AE56,0) -> 0 | AF64: =IFERROR(AF48/AF56,0) -> 105000 | AG64: =IFERROR(AG48/AG56,0) -> 88830 | ... AQ64: =IFERROR(AQ48/AQ56,0) -> 115083 | AS64: Total Oficina | AU64: =IFERROR(AU48/AU56,0) -> 0 | AV64: =IFERROR(AV48/AV56,0) -> 132500 | AW64: =IFERROR(AW48/AW56,0) -> 0 | AX64: =IFERROR(AX48/AX56,0) -> 0 | AY64: =IFERROR(AY48/AY56,0) -> 85000 | AZ64: =IFERROR(AZ48/AZ56,0) -> 0 | BA64: =IFERROR(BA48/BA56,0) -> 105000 | BB64: =IFERROR(BB48/BB56,0) -> 88830 | ... BL64: =IFERROR(BL48/BL56,0) -> 131666.25
B65: Otra Red Búsqueda | C65: Interior - Santa Fe | D65: 1 | F65: 1 | G65: 1 | I65: 2 | J65: 4 | K65: 4 | L65: 2 | M65: 4 | N65: 7 | O65: 3 | P65: 29 | R65: 3 | S65: 2 | T65: 5 | U65: 34 | X65: Total PH | Z65: =IFERROR(Z49/Z57,0) -> 150125 | AA65: =IFERROR(AA49/AA57,0) -> 119000 | AB65: =IFERROR(AB49/AB57,0) -> 82500 | AC65: =IFERROR(AC49/AC57,0) -> 113500 | AD65: =IFERROR(AD49/AD57,0) -> 110857.14 | AE65: =IFERROR(AE49/AE57,0) -> 129636.36 | AF65: =IFERROR(AF49/AF57,0) -> 91250 | AG65: =IFERROR(AG49/AG57,0) -> 93950 | ... AQ65: =IFERROR(AQ49/AQ57,0) -> 116309.14 | AS65: Total PH | AU65: =IFERROR(AU49/AU57,0) -> 188000 | AV65: =IFERROR(AV49/AV57,0) -> 146500 | AW65: =IFERROR(AW49/AW57,0) -> 245000 | AX65: =IFERROR(AX49/AX57,0) -> 123000 | AY65: =IFERROR(AY49/AY57,0) -> 118500 | AZ65: =IFERROR(AZ49/AZ57,0) -> 146888.89 | BA65: =IFERROR(BA49/BA57,0) -> 126750 | BB65: =IFERROR(BB49/BB57,0) -> 132500 | ... BL65: =IFERROR(BL49/BL57,0) -> 142530.44
B66: Otra Red Búsqueda | C66: Zona Norte (GBA) | G66: 1 | H66: 1 | J66: 4 | K66: 6 | L66: 7 | M66: 19 | N66: 9 | O66: 12 | P66: 59 | Q66: 3 | R66: 5 | S66: 14 | T66: 22 | U66: 81 | X66: TOTAL | Z66: =IFERROR(Z50/Z58,0) -> 139431.39 | AA66: =IFERROR(AA50/AA58,0) -> 145197.81 | AB66: =IFERROR(AB50/AB58,0) -> 164494.04 | AC66: =IFERROR(AC50/AC58,0) -> 159403.37 | AD66: =IFERROR(AD50/AD58,0) -> 151368.9 | AE66: =IFERROR(AE50/AE58,0) -> 179146.55 | AF66: =IFERROR(AF50/AF58,0) -> 159042.56 | AG66: =IFERROR(AG50/AG58,0) -> 137931.42 | ... AQ66: =IFERROR(AQ50/AQ58,0) -> 147614.85 | AS66: TOTAL | AU66: =IFERROR(AU50/AU58,0) -> 150080.18 | AV66: =IFERROR(AV50/AV58,0) -> 162851.91 | AW66: =IFERROR(AW50/AW58,0) -> 191647.07 | AX66: =IFERROR(AX50/AX58,0) -> 179072 | AY66: =IFERROR(AY50/AY58,0) -> 166076.84 | AZ66: =IFERROR(AZ50/AZ58,0) -> 186631.76 | BA66: =IFERROR(BA50/BA58,0) -> 203943.06 | BB66: =IFERROR(BB50/BB58,0) -> 156798.05 | ... BL66: =IFERROR(BL50/BL58,0) -> 167590.36
B67: Otra Red Búsqueda | C67: Zona Oeste (GBA) | F67: 1 | J67: 1 | K67: 1 | M67: 1 | P67: 4 | S67: 1 | T67: 1 | U67: 5
B68: Otra Red Búsqueda | C68: Zona Sur (GBA) | D68: 1 | E68: 2 | G68: 1 | H68: 2 | I68: 2 | J68: 4 | K68: 5 | L68: 2 | M68: 1 | O68: 2 | P68: 22 | U68: 22
B69: Total Otra Red Búsqueda | D69: 13 | E69: 12 | F69: 15 | G69: 20 | H69: 20 | I69: 21 | J69: 33 | K69: 38 | L69: 31 | M69: 62 | N69: 45 | O69: 50 | P69: 360 | Q69: 14 | R69: 26 | S69: 45 | T69: 85 | U69: 445 | AS69: CABA | AU69: =AU8+AU13+AU22+AU26+AU29 -> 5179689 | AV69: =AV8+AV13+AV22+AV26+AV29 -> 4926000 | AW69: =AW8+AW13+AW22+AW26+AW29 -> 6656900 | AX69: =AX8+AX13+AX22+AX26+AX29 -> 8729000 | AY69: =AY8+AY13+AY22+AY26+AY29 -> 8850070 | AZ69: =AZ8+AZ13+AZ22+AZ26+AZ29 -> 7269000 | BA69: =BA8+BA13+BA22+BA26+BA29 -> 8195000 | BB69: =BB8+BB13+BB22+BB26+BB29 -> 9348700 | ... BL69: =BL8+BL13+BL22+BL26+BL29 -> 109991127
B70: Otra Red Captación | C70: CABA | D70: 6 | E70: 11 | F70: 9 | G70: 11 | H70: 14 | I70: 13 | J70: 19 | K70: 14 | L70: 21 | M70: 22 | N70: 14 | O70: 23 | P70: 177 | Q70: 8 | R70: 15 | S70: 16 | T70: 39 | U70: 216 | AS70: CABA | AU70: =AU91+AU96+AU105+AU109+AU112 -> 36 | AV70: =AV91+AV96+AV105+AV109+AV112 -> 30 | AW70: =AW91+AW96+AW105+AW109+AW112 -> 34 | AX70: =AX91+AX96+AX105+AX109+AX112 -> 50 | AY70: =AY91+AY96+AY105+AY109+AY112 -> 56 | AZ70: =AZ91+AZ96+AZ105+AZ109+AZ112 -> 42 | BA70: =BA91+BA96+BA105+BA109+BA112 -> 45 | BB70: =BB91+BB96+BB105+BB109+BB112 -> 63 | ... BL70: =BL91+BL96+BL105+BL109+BL112 -> 677
B71: Otra Red Captación | C71: Interior - Mendoza | D71: 1 | E71: 1 | G71: 1 | I71: 1 | J71: 2 | N71: 1 | O71: 11 | P71: 18 | Q71: 1 | R71: 2 | S71: 2 | T71: 5 | U71: 23
B72: Otra Red Captación | C72: Interior - Neuquén | D72: 3 | E72: 1 | F72: 2 | G72: 2 | H72: 1 | I72: 4 | J72: 1 | K72: 2 | L72: 5 | O72: 1 | P72: 22 | R72: 3 | S72: 1 | T72: 4 | U72: 26
B73: Otra Red Captación | C73: Interior - Río Negro | G73: 2 | H73: 1 | I73: 1 | J73: 1 | K73: 1 | L73: 2 | N73: 1 | O73: 3 | P73: 12 | Q73: 1 | S73: 1 | T73: 2 | U73: 14
B74: Otra Red Captación | C74: Interior - Salta | E74: 1 | H74: 1 | I74: 3 | K74: 1 | L74: 1 | M74: 1 | N74: 1 | O74: 2 | P74: 11 | Q74: 1 | S74: 1 | T74: 2 | U74: 13
B75: Otra Red Captación | C75: Interior - Santa Fe | D75: 2 | E75: 1 | G75: 1 | I75: 1 | J75: 1 | K75: 3 | L75: 1 | O75: 3 | P75: 13 | Q75: 3 | R75: 1 | S75: 2 | T75: 6 | U75: 19
B76: Otra Red Captación | C76: Zona Norte (GBA) | D76: 4 | E76: 3 | F76: 10 | G76: 8 | H76: 6 | I76: 6 | J76: 5 | K76: 3 | L76: 5 | M76: 3 | N76: 2 | O76: 1 | P76: 56 | Q76: 2 | R76: 2 | S76: 1 | T76: 5 | U76: 61
B77: Otra Red Captación | C77: Zona Oeste (GBA) | F77: 1 | K77: 1 | N77: 1 | O77: 1 | P77: 4 | S77: 1 | T77: 1 | U77: 5
B78: Otra Red Captación | C78: Zona Sur (GBA) | F78: 2 | G78: 1 | H78: 3 | I78: 3 | M78: 5 | O78: 3 | P78: 17 | R78: 1 | S78: 3 | T78: 4 | U78: 21
B79: Total Otra Red Captación | D79: 16 | E79: 18 | F79: 24 | G79: 26 | H79: 26 | I79: 32 | J79: 29 | K79: 25 | L79: 35 | M79: 31 | N79: 20 | O79: 48 | P79: 330 | Q79: 16 | R79: 24 | S79: 28 | T79: 68 | U79: 398
B80: Total general | D80: 122 | E80: 115 | F80: 139 | G80: 183 | H80: 179 | I80: 185 | J80: 204 | K80: 207 | L80: 190 | M80: 228 | N80: 155 | O80: 237 | P80: 2144 | Q80: 147 | R80: 157 | S80: 247 | T80: 551 | U80: 2695
B84: Unificador | C84: (Varios elementos) | X84: Unificador | Y84: (Varios elementos) | AS84: Unificador | AT84: (Varios elementos)
B85: RANGO_TCMC | C85: (Todas) | X85: Precio Cierre Total | Y85: (Todas) | AS85: TIPO_OPERACION2 | AT85: CB
X86: TIPO_OPERACION2 | Y86: CB | AS86: RANGO_TCMC | AT86: 1
B87: Promedio de Precio Cierre Total | D87: AÑO | E87: MES | Z87: 3 | AA87: 4 | AB87: 5 | AC87: 6 | AD87: 7 | AE87: 8 | AF87: 9 | AG87: 10 | AH87: 11 | AI87: 12 | AJ87: 13 | AK87: 14 | AL87: 15 | AM87: 16 | AN87: 17 | AO87: 18 | AP87: 19 | AQ87: 20 | AU87: 3 | AV87: 4 | AW87: 5 | AX87: 6 | AY87: 7 | AZ87: 8 | BA87: 9 | BB87: 10 | BC87: 11 | BD87: 12 | BE87: 13 | BF87: 14 | BG87: 15 | BH87: 16 | BI87: 17 | BJ87: 18 | BK87: 19 | BL87: 20
D88: 2025 | E88: 2025 | F88: 2025 | G88: 2025 | H88: 2025 | I88: 2025 | J88: 2025 | K88: 2025 | L88: 2025 | M88: 2025 | N88: 2025 | O88: 2025 | P88: Total 2025 | Q88: 2026 | R88: 2026 | S88: 2026 | T88: Total 2026 | U88: Total general | X88: Cuenta de Precio Cierre Total | Z88: AÑO | AA88: MES | AS88: Cuenta de Precio Cierre Total | AU88: AÑO | AV88: MES
B89: TIPO_OPERACION2 | C89: Zona CB | D89: 1 | E89: 2 | F89: 3 | G89: 4 | H89: 5 | I89: 6 | J89: 7 | K89: 8 | L89: 9 | M89: 10 | N89: 11 | O89: 12 | Q89: 1 | R89: 2 | S89: 3 | Z89: 2025 | AA89: 2025 | AB89: 2025 | AC89: 2025 | AD89: 2025 | AE89: 2025 | AF89: 2025 | AG89: 2025 | AH89: 2025 | AI89: 2025 | AJ89: 2025 | AK89: 2025 | AL89: Total 2025 | AM89: 2026 | AN89: 2026 | AO89: 2026 | AP89: Total 2026 | AQ89: Total general | AU89: 2025 | AV89: 2025 | AW89: 2025 | AX89: 2025 | AY89: 2025 | AZ89: 2025 | BA89: 2025 | BB89: 2025 | BC89: 2025 | BD89: 2025 | BE89: 2025 | BF89: 2025 | BG89: Total 2025 | BH89: 2026 | BI89: 2026 | BJ89: 2026 | BK89: Total 2026 | BL89: Total general
B90: CB | C90: CABA | D90: 136111.64 | E90: 141675 | F90: 172575.56 | G90: 152189.39 | H90: 143910.15 | I90: 186980.39 | J90: 143047.79 | K90: 138229.73 | L90: 131586.77 | M90: 136653.58 | N90: 132785.02 | O90: 148288.03 | P90: 146098.38 | Q90: 153065 | R90: 137896.23 | S90: 138818.67 | T90: 142328.87 | U90: 145296.98 | X90: Tipo Propiedad | Y90: Zona CB | Z90: 1 | AA90: 2 | AB90: 3 | AC90: 4 | AD90: 5 | AE90: 6 | AF90: 7 | AG90: 8 | AH90: 9 | AI90: 10 | AJ90: 11 | AK90: 12 | AM90: 1 | AN90: 2 | AO90: 3 | AS90: Tipo Propiedad | AT90: Zona CB | AU90: 1 | AV90: 2 | AW90: 3 | AX90: 4 | AY90: 5 | AZ90: 6 | BA90: 7 | BB90: 8 | BC90: 9 | BD90: 10 | BE90: 11 | BF90: 12 | BH90: 1 | BI90: 2 | BJ90: 3
B91: CB | C91: Interior - Jujuy | E91: 144000 | G91: 99780 | H91: 70000 | I91: 62000 | J91: 164450 | K91: 38000 | L91: 62000 | O91: 60625 | P91: 91302.632 | Q91: 60000 | R91: 116000 | S91: 98333.333 | T91: 94200 | U91: 92301.724 | X91: Casa | Y91: CABA | Z91: 11 | AA91: 4 | AB91: 5 | AC91: 10 | AD91: 5 | AE91: 10 | AF91: 8 | AG91: 13 | AH91: 8 | AI91: 7 | AJ91: 6 | AK91: 5 | AL91: 92 | AM91: 3 | AN91: 6 | AO91: 10 | AP91: 19 | AQ91: 111 | AS91: Casa | AT91: CABA | AU91: 11 | AV91: 3 | AW91: 5 | AX91: 10 | AY91: 5 | AZ91: 8 | BA91: 8 | BB91: 13 | BC91: 6 | BD91: 7 | BE91: 5 | BF91: 4 | BG91: 85 | BH91: 3 | BI91: 5 | BJ91: 6 | BK91: 14 | BL91: 99
B92: CB | C92: Interior - Mendoza | D92: 55000 | E92: 78000 | F92: 67800 | G92: 110633.33 | H92: 83666.667 | I92: 112357.14 | J92: 74222.222 | K92: 187500 | L92: 79333.333 | M92: 104857.14 | N92: 72500 | O92: 87096.552 | P92: 91253.521 | Q92: 110214.29 | R92: 91833.333 | S92: 144750 | T92: 118119.05 | U92: 97385.87 | X92: Casa | Y92: Zona Norte (GBA) | Z92: 6 | AA92: 3 | AB92: 8 | AC92: 8 | AD92: 9 | AE92: 12 | AF92: 11 | AG92: 6 | AH92: 8 | AI92: 5 | AJ92: 8 | AK92: 5 | AL92: 89 | AM92: 12 | AN92: 9 | AO92: 9 | AP92: 30 | AQ92: 119 | AS92: Casa | AT92: Zona Norte (GBA) | AU92: 6 | AV92: 3 | AW92: 8 | AX92: 8 | AY92: 9 | AZ92: 12 | BA92: 11 | BB92: 6 | BC92: 7 | BD92: 5 | BE92: 8 | BF92: 5 | BG92: 88 | BH92: 12 | BI92: 9 | BJ92: 9 | BK92: 30 | BL92: 118
B93: CB | C93: Interior - Neuquén | D93: 97958.6 | E93: 93387.5 | F93: 99842.857 | G93: 116461.54 | H93: 225372.05 | I93: 107932.32 | J93: 82437.5 | K93: 132055.56 | L93: 313083.33 | M93: 130060 | N93: 96000 | O93: 147125 | P93: 142371.87 | Q93: 95866.667 | R93: 114920 | S93: 134848.94 | T93: 115726.41 | U93: 136882.11 | X93: Casa | Y93: Zona Oeste (GBA) | AB93: 2 | AC93: 1 | AD93: 2 | AE93: 1 | AH93: 2 | AJ93: 1 | AL93: 9 | AM93: 1 | AN93: 1 | AO93: 1 | AP93: 3 | AQ93: 12 | AS93: Casa | AT93: Zona Oeste (GBA) | AW93: 1 | AY93: 1 | BC93: 1 | BG93: 3 | BH93: 1 | BI93: 1 | BJ93: 1 | BK93: 3 | BL93: 6
B94: CB | C94: Interior - Río Negro | D94: 117557.17 | E94: 178086.75 | F94: 109368.33 | G94: 132619.88 | H94: 187632.11 | I94: 65107.571 | J94: 141093.75 | K94: 106270 | L94: 108750 | M94: 173250 | N94: 279000 | O94: 119873.12 | P94: 137708.96 | Q94: 125520.83 | R94: 105140 | S94: 149195.11 | T94: 131079.05 | U94: 136298.34 | X94: Casa | Y94: Zona Sur (GBA) | Z94: 1 | AA94: 3 | AC94: 1 | AD94: 2 | AE94: 2 | AG94: 1 | AI94: 1 | AJ94: 1 | AK94: 2 | AL94: 14 | AN94: 1 | AO94: 1 | AP94: 2 | AQ94: 16 | AS94: Casa | AT94: Zona Sur (GBA) | AV94: 1 | AX94: 1 | AY94: 2 | AZ94: 2 | BD94: 1 | BF94: 1 | BG94: 8 | BI94: 1 | BJ94: 1 | BK94: 2 | BL94: 10
B95: CB | C95: Interior - Salta | D95: 58666.667 | E95: 110000 | F95: 86166.667 | G95: 66833.333 | H95: 100750 | I95: 49666.667 | J95: 86777.778 | K95: 77000 | L95: 90000 | M95: 131875 | N95: 52000 | O95: 68000 | P95: 81988.636 | Q95: 47000 | R95: 120000 | S95: 114333.33 | T95: 102000 | U95: 84030.612 | X95: Total Casa | Z95: 18 | AA95: 10 | AB95: 15 | AC95: 20 | AD95: 18 | AE95: 25 | AF95: 19 | AG95: 20 | AH95: 18 | AI95: 13 | AJ95: 16 | AK95: 12 | AL95: 204 | AM95: 16 | AN95: 17 | AO95: 21 | AP95: 54 | AQ95: 258 | AS95: Total Casa | AU95: 17 | AV95: 7 | AW95: 14 | AX95: 19 | AY95: 17 | AZ95: 22 | BA95: 19 | BB95: 19 | BC95: 14 | BD95: 13 | BE95: 13 | BF95: 10 | BG95: 184 | BH95: 16 | BI95: 16 | BJ95: 17 | BK95: 49 | BL95: 233
B96: CB | C96: Interior - San Luis | O96: 65000 | P96: 65000 | U96: 65000 | X96: Departamento | Y96: CABA | Z96: 24 | AA96: 29 | AB96: 31 | AC96: 44 | AD96: 53 | AE96: 32 | AF96: 48 | AG96: 52 | AH96: 41 | AI96: 56 | AJ96: 36 | AK96: 40 | AL96: 486 | AM96: 38 | AN96: 42 | AO96: 56 | AP96: 136 | AQ96: 622 | AS96: Departamento | AT96: CABA | AU96: 22 | AV96: 24 | AW96: 28 | AX96: 35 | AY96: 45 | AZ96: 27 | BA96: 32 | BB96: 46 | BC96: 34 | BD96: 40 | BE96: 27 | BF96: 28 | BG96: 388 | BH96: 29 | BI96: 32 | BJ96: 48 | BK96: 109 | BL96: 497
B97: CB | C97: Interior - Santa Fe | D97: 90000 | F97: 42000 | G97: 40750 | I97: 65000 | J97: 80000 | K97: 466666.67 | L97: 112333.33 | M97: 132500 | N97: 58000 | P97: 155218.75 | Q97: 63000 | R97: 95000 | S97: 77142.857 | T97: 78133.333 | U97: 117919.35 | X97: Departamento | Y97: Zona Norte (GBA) | Z97: 8 | AA97: 10 | AB97: 16 | AC97: 17 | AD97: 11 | AE97: 17 | AF97: 17 | AG97: 12 | AH97: 12 | AI97: 15 | AJ97: 11 | AK97: 13 | AL97: 159 | AM97: 12 | AN97: 11 | AO97: 21 | AP97: 44 | AQ97: 203 | AS97: Departamento | AT97: Zona Norte (GBA) | AU97: 8 | AV97: 10 | AW97: 12 | AX97: 14 | AY97: 10 | AZ97: 16 | BA97: 10 | BB97: 12 | BC97: 11 | BD97: 14 | BE97: 7 | BF97: 12 | BG97: 136 | BH97: 11 | BI97: 8 | BJ97: 19 | BK97: 38 | BL97: 174
B98: CB | C98: Zona Norte (GBA) | D98: 149325.24 | E98: 196967.75 | F98: 171673.67 | G98: 179028.12 | H98: 162981.6 | I98: 203727.94 | J98: 195552.52 | K98: 166790 | L98: 155601.61 | M98: 137038.64 | N98: 132973.96 | O98: 178428.57 | P98: 170162.86 | Q98: 161689.66 | R98: 173968.05 | S98: 146833.33 | T98: 158647.09 | U98: 167658.18 | X98: Departamento | Y98: Zona Oeste (GBA) | Z98: 1 | AB98: 1 | AF98: 3 | AG98: 3 | AH98: 1 | AI98: 1 | AJ98: 1 | AK98: 2 | AL98: 13 | AN98: 1 | AO98: 1 | AP98: 2 | AQ98: 15 | AS98: Departamento | AT98: Zona Oeste (GBA) | BA98: 1 | BC98: 1 | BF98: 2 | BG98: 4 | BI98: 1 | BJ98: 1 | BK98: 2 | BL98: 6
B99: CB | C99: Zona Oeste (GBA) | D99: 50000 | F99: 68666.667 | G99: 50000 | H99: 135333.33 | I99: 57000 | J99: 84875 | K99: 56000 | L99: 96166.667 | M99: 48000 | N99: 41600 | O99: 137750 | P99: 80142.308 | Q99: 56250 | R99: 80250 | S99: 148500 | T99: 95000 | U99: 82928.125 | X99: Departamento | Y99: Zona Sur (GBA) | Z99: 2 | AD99: 1 | AE99: 2 | AF99: 1 | AG99: 4 | AH99: 4 | AI99: 2 | AK99: 1 | AL99: 17 | AM99: 1 | AN99: 1 | AP99: 2 | AQ99: 19 | AS99: Departamento | AT99: Zona Sur (GBA) | AU99: 1 | BA99: 1 | BB99: 2 | BC99: 1 | BD99: 1 | BF99: 1 | BG99: 7 | BL99: 7
B100: CB | C100: Zona Sur (GBA) | D100: 53466.667 | E100: 76000 | G100: 158000 | H100: 126333.33 | I100: 65000 | J100: 82000 | K100: 54080 | L100: 58750 | M100: 121333.33 | N100: 36000 | O100: 73500 | P100: 76821.875 | Q100: 45000 | R100: 121250 | S100: 175000 | T100: 115625 | U100: 81133.333 | X100: Total Departamento | Z100: 35 | AA100: 39 | AB100: 48 | AC100: 61 | AD100: 65 | AE100: 51 | AF100: 69 | AG100: 71 | AH100: 58 | AI100: 74 | AJ100: 48 | AK100: 56 | AL100: 675 | AM100: 51 | AN100: 55 | AO100: 78 | AP100: 184 | AQ100: 859 | AS100: Total Departamento | AU100: 31 | AV100: 34 | AW100: 40 | AX100: 49 | AY100: 55 | AZ100: 43 | BA100: 44 | BB100: 60 | BC100: 47 | BD100: 55 | BE100: 34 | BF100: 43 | BG100: 535 | BH100: 40 | BI100: 41 | BJ100: 68 | BK100: 149 | BL100: 684
B101: Total CB | D101: 124286.46 | E101: 143786.21 | F101: 150293.99 | G101: 145034.01 | H101: 160162.5 | I101: 156081.19 | J101: 140996.32 | K101: 140852.85 | L101: 148584.92 | M101: 134219.08 | N101: 126455.43 | O101: 131752.28 | P101: 142453.1 | Q101: 135738.25 | R101: 135483.15 | S101: 136941.06 | T101: 136195.52 | U101: 141108.33 | X101: Garage | Y101: CABA | AC101: 1 | AJ101: 1 | AL101: 2 | AQ101: 2 | AS101: Garage | AT101: CABA | AX101: 1 | BG101: 1 | BL101: 1
B102: Otra Red Búsqueda | C102: CABA | D102: 287222.22 | E102: 242500 | F102: 154857.14 | G102: 155818.18 | H102: 163045.45 | I102: 180100 | J102: 208450 | K102: 184117.65 | L102: 143538.46 | M102: 176529.03 | N102: 143040 | O102: 220789.47 | P102: 181265.87 | Q102: 185166.67 | R102: 182615.38 | S102: 184440.48 | T102: 184040.7 | U102: 181834.05 | X102: Total Garage | AC102: 1 | AJ102: 1 | AL102: 2 | AQ102: 2 | AS102: Total Garage | AX102: 1 | BG102: 1 | BL102: 1
B103: Otra Red Búsqueda | C103: Interior - Mendoza | F103: 36500 | G103: 84500 | I103: 138000 | J103: 65000 | L103: 280000 | M103: 55000 | O103: 120812.5 | P103: 115500 | R103: 73000 | S103: 250666.67 | T103: 206250 | U103: 133650 | X103: Hotel | Y103: CABA | AO103: 1 | AP103: 1 | AQ103: 1 | AS103: Hotel | AT103: CABA | BJ103: 1 | BK103: 1 | BL103: 1
B104: Otra Red Búsqueda | C104: Interior - Neuquén | E104: 101460 | F104: 167000 | G104: 84500 | H104: 72000 | I104: 89750 | J104: 91000 | K104: 93000 | L104: 112000 | M104: 133600 | O104: 100000 | P104: 108646.15 | Q104: 162500 | R104: 126333.33 | S104: 64600 | T104: 119028.57 | U104: 110848.48 | X104: Total Hotel | AO104: 1 | AP104: 1 | AQ104: 1 | AS104: Total Hotel | BJ104: 1 | BK104: 1 | BL104: 1
...

Sheet Operaciones Venta
A1: Fecha | B1: AÑO | C1: MES | D1: Ref # | E1: Unificador | F1: Publicación | G1: Estado | H1: Portal | I1: Precio Publicación | J1: Precio Cierre Total | K1: RANGO_TCMC | L1: Moneda Cierre | M1: Moneda Publicación | N1: Dirección | O1: Ubicación | P1: Tipo Propiedad | Q1: Lados | R1: Oficina | S1: Tipo Operación | T1: TIPO_OPERACION2 | U1: Operación | V1: Zona CB | W1: Localidad CB
A2: 46062 | B2: =YEAR($A2) -> 2026 | C2: =MONTH($A2) -> 2 | D2: CAP7557679 | E2: 1 | F2: Venta departamento de un dormitorio y balcón en 4 y 63 - LA PLATA | G2: Realizado | H2: AR ZonaProp | I2: 38000 | J2: 36000 | K2: =IF(J2<'Mapa Oficinas'!$I$21,0,IF(J2>'Mapa Oficinas'!$I$20,0,1)) -> 0 | L2: Dólares | M2: Dólares | N2: Venta departamento de un dormitorio y balcón en 4 y 63 - LA PLATA | O2: Argentina | G.B.A. Zona Sur | La Plata | La Plata | P2: Departamento | Q2: 1 | R2: Golden Team | S2: (Interior) Compartida Fuera de la Red Captación Propia | T2: =VLOOKUP(S2,'Mapa Oficinas'!$H$7:$I$16,2,FALSE) -> Otra Red Captación | U2: Venta | V2: =VLOOKUP($R2,'Mapa Oficinas'!$A$7:$C$46,2,FALSE) -> Zona Sur (GBA) | W2: =VLOOKUP($R2,'Mapa Oficinas'!$A$7:$C$46,3,FALSE) -> La Plata
A3: 45863 | B3: =YEAR($A3) -> 2025 | C3: =MONTH($A3) -> 7 | E3: 0 | F3: UF 13 Loteo A Quetrihue 387,55 | G3: Realizado | H3: Conocido | I3: 36000 | J3: 36000 | K3: =IF(J3<'Mapa Oficinas'!$I$21,0,IF(J3>'Mapa Oficinas'!$I$20,0,1)) -> 0 | L3: Dólares | M3: Dólares | N3: Bv, Quetrihue y Amancay | O3: Argentina | Neuquen | Villa La Angostura | Selva Triste | P3: Terreno | Q3: 2 | R3: Patagonia Lakes VLA | S3: Compartida en Oficina (Dos Asesores) | T3: =VLOOKUP(S3,'Mapa Oficinas'!$H$7:$I$16,2,FALSE) -> CB | U3: Venta | V3: =VLOOKUP($R3,'Mapa Oficinas'!$A$7:$C$46,2,FALSE) -> Interior - Neuquén | W3: =VLOOKUP($R3,'Mapa Oficinas'!$A$7:$C$46,3,FALSE) -> Villa La Angostura
A4: 45699 | B4: =YEAR($A4) -> 2025 | C4: =MONTH($A4) -> 2 | D4: CLA6351991 | E4: 1 | F4: VENTA Lote/terreno de 407,04 m2, UF 26 loteo Quetrihue B° Selva Triste Villa la Angostura | G4: Realizado | H4: Instagram | I4: 36000 | J4: 36000 | K4: =IF(J4<'Mapa Oficinas'!$I$21,0,IF(J4>'Mapa Oficinas'!$I$20,0,1)) -> 0 | L4: Dólares | M4: Dólares | N4: Quetrihue | O4: Argentina | Neuquen | Villa La Angostura | Puerto | P4: Terreno | Q4: 2 | R4: Patagonia Lakes VLA | S4: Compartida en Oficina (Dos Asesores) | T4: =VLOOKUP(S4,'Mapa Oficinas'!$H$7:$I$16,2,FALSE) -> CB | U4: Venta | V4: =VLOOKUP($R4,'Mapa Oficinas'!$A$7:$C$46,2,FALSE) -> Interior - Neuquén | W4: =VLOOKUP($R4,'Mapa Oficinas'!$A$7:$C$46,3,FALSE) -> Villa La Angostura
A5: 45796 | B5: =YEAR($A5) -> 2025 | C5: =MONTH($A5) -> 5 | D5: CHO6746075 | E5: 1 | F5: Casa - Las Paredes | G5: Realizado | H5: AR ZonaProp | I5: 36000 | J5: 36000 | K5: =IF(J5<'Mapa Oficinas'!$I$21,0,IF(J5>'Mapa Oficinas'!$I$20,0,1)) -> 0 | L5: Dólares | M5: Dólares | N5: LOS FILTROS al 8000 | O5: Argentina | Mendoza | San Rafael | Las Paredes | P5: Casa | Q5: 2 | R5: Andes | S5: Compartida en Oficina (Dos Asesores) | T5: =VLOOKUP(S5,'Mapa Oficinas'!$H$7:$I$16,2,FALSE) -> CB | U5: Venta | V5: =VLOOKUP($R5,'Mapa Oficinas'!$A$7:$C$46,2,FALSE) -> Interior - Mendoza | W5: =VLOOKUP($R5,'Mapa Oficinas'!$A$7:$C$46,3,FALSE) -> San Rafael
A6: 45862 | B6: =YEAR($A6) -> 2025 | C6: =MONTH($A6) -> 7 | D6: CAP6796724 | E6: 1 | F6: Departamento en almagro | G6: Realizado | H6: AR ZonaProp | I6: 37000 | J6: 36000 | K6: =IF(J6<'Mapa Oficinas'!$I$21,0,IF(J6>'Mapa Oficinas'!$I$20,0,1)) -> 0 | L6: Dólares | M6: Dólares | N6: Quintino Bocayuva al 400 | O6: Argentina | Capital Federal | Almagro | Almagro Sur | P6: Departamento | Q6: 2 | R6: Haka | S6: Compartida en Oficina (Dos Asesores) | T6: =VLOOKUP(S6,'Mapa Oficinas'!$H$7:$I$16,2,FALSE) -> CB | U6: Venta | V6: =VLOOKUP($R6,'Mapa Oficinas'!$A$7:$C$46,2,FALSE) -> CABA | W6: =VLOOKUP($R6,'Mapa Oficinas'!$A$7:$C$46,3,FALSE) -> Núñez
A7: 45863 | B7: =YEAR($A7) -> 2025 | C7: =MONTH($A7) -> 7 | E7: 1 | F7: UF 12 Loteo A Quetrihue | G7: Realizado | H7: Conocido | I7: 36000 | J7: 36000 | K7: =IF(J7<'Mapa Oficinas'!$I$21,0,IF(J7>'Mapa Oficinas'!$I$20,0,1)) -> 0 | L7: Dólares | M7: Dólares | N7: Bv, Quetrihue y Amancay | O7: Argentina | Neuquen | Villa La Angostura | Selva Triste | P7: Terreno | Q7: 2 | R7: Patagonia Lakes VLA | S7: Compartida en Oficina (Dos Asesores) | T7: =VLOOKUP(S7,'Mapa Oficinas'!$H$7:$I$16,2,FALSE) -> CB | U7: Venta | V7: =VLOOKUP($R7,'Mapa Oficinas'!$A$7:$C$46,2,FALSE) -> Interior - Neuquén | W7: =VLOOKUP($R7,'Mapa Oficinas'!$A$7:$C$46,3,FALSE) -> Villa La Angostura
A8: 45777 | B8: =YEAR($A8) -> 2025 | C8: =MONTH($A8) -> 4 | D8: CAP6917146 | E8: 1 | F8: Departamento | Venta | Juan Pablo II | 3 habitaciones | G8: Realizado | H8: Facebook | I8: 36000 | J8: 36000 | K8: =IF(J8<'Mapa Oficinas'!$I$21,0,IF(J8>'Mapa Oficinas'!$I$20,0,1)) -> 0 | L8: Dólares | M8: Dólares | N8: Juan Pablo II 7 | O8: Argentina | Salta | Capital | Salta | Zona Sur | P8: Departamento | Q8: 2 | R8: Realty Group | S8: Propia (Único Asesor) | T8: =VLOOKUP(S8,'Mapa Oficinas'!$H$7:$I$16,2,FALSE) -> CB | U8: Venta | V8: =VLOOKUP($R8,'Mapa Oficinas'!$A$7:$C$46,2,FALSE) -> Interior - Salta | W8: =VLOOKUP($R8,'Mapa Oficinas'!$A$7:$C$46,3,FALSE) -> San Lorenzo Chico
A9: 45827 | B9: =YEAR($A9) -> 2025 | C9: =MONTH($A9) -> 6 | D9: CAP6916550 | E9: 1 | F9: Departamento en Juan Pablo | G9: Realizado | H9: Referido | I9: 36000 | J9: 36000 | K9: =IF(J9<'Mapa Oficinas'!$I$21,0,IF(J9>'Mapa Oficinas'!$I$20,0,1)) -> 0 | L9: Dólares | M9: Dólares | N9: Juan Pablo | O9: Argentina | Salta | Capital | Salta | Zona Sur | P9: Departamento | Q9: 2 | R9: Realty Group | S9: Propia (Único Asesor) | T9: =VLOOKUP(S9,'Mapa Oficinas'!$H$7:$I$16,2,FALSE) -> CB | U9: Venta | V9: =VLOOKUP($R9,'Mapa Oficinas'!$A$7:$C$46,2,FALSE) -> Interior - Salta | W9: =VLOOKUP($R9,'Mapa Oficinas'!$A$7:$C$46,3,FALSE) -> San Lorenzo Chico
A10: 45882 | B10: =YEAR($A10) -> 2025 | C10: =MONTH($A10) -> 8 | D10: CAP7166417 | E10: 1 | F10: Departamento de 1 dormitorio en 45 e/ 19 y 20, La Plata | G10: Realizado | H10: AR ArgenProp | I10: 37000 | J10: 36000 | K10: =IF(J10<'Mapa Oficinas'!$I$21,0,IF(J10>'Mapa Oficinas'!$I$20,0,1)) -> 0 | L10: Dólares | M10: Dólares | N10: 45 e/ 19 y 20 | O10: Argentina | G.B.A. Zona Sur | La Plata | La Plata | P10: Departamento | Q10: 2 | R10: Golden Team | S10: Propia (Único Asesor) | T10: =VLOOKUP(S10,'Mapa Oficinas'!$H$7:$I$16,2,FALSE) -> CB | U10: Venta | V10: =VLOOKUP($R10,'Mapa Oficinas'!$A$7:$C$46,2,FALSE) -> Zona Sur (GBA) | W10: =VLOOKUP($R10,'Mapa Oficinas'!$A$7:$C$46,3,FALSE) -> La Plata
A11: 45889 | B11: =YEAR($A11) -> 2025 | C11: =MONTH($A11) -> 8 | D11: CAP7214043 | E11: 1 | F11: Departamento en Venta de 1 dormitorio en 46 entre 13 y 14 en La Plata | G11: Realizado | H11: AR ZonaProp | I11: 39900 | J11: 36000 | K11: =IF(J11<'Mapa Oficinas'!$I$21,0,IF(J11>'Mapa Oficinas'!$I$20,0,1)) -> 0 | L11: Dólares | M11: Dólares | N11: Departamento en Venta de 1 dormitorio en 46 entre 13 y 14 en La Plata | O11: Argentina | G.B.A. Zona Sur | La Plata | La Plata | P11: Departamento | Q11: 2 | R11: Golden Team | S11: Propia (Único Asesor) | T11: =VLOOKUP(S11,'Mapa Oficinas'!$H$7:$I$16,2,FALSE) -> CB | U11: Venta | V11: =VLOOKUP($R11,'Mapa Oficinas'!$A$7:$C$46,2,FALSE) -> Zona Sur (GBA) | W11: =VLOOKUP($R11,'Mapa Oficinas'!$A$7:$C$46,3,FALSE) -> La Plata
A12: 45889 | B12: =YEAR($A12) -> 2025 | C12: =MONTH($A12) -> 8 | D12: CLA7090806 | E12: 1 | F12: Terreno en venta ubicado en La Verbena - Salta | G12: Realizado | H12: Facebook | I12: 37500 | J12: 36000 | K12: =IF(J12<'Mapa Oficinas'!$I$21,0,IF(J12>'Mapa Oficinas'!$I$20,0,1)) -> 0 | L12: Dólares | M12: Dólares | N12: La Verbena Calle 8 | O12: Argentina | Salta | Capital | Salta | Zona Sur | P12: Terreno | Q12: 2 | R12: Realty Group | S12: Propia (Único Asesor) | T12: =VLOOKUP(S12,'Mapa Oficinas'!$H$7:$I$16,2,FALSE) -> CB | U12: Venta | V12: =VLOOKUP($R12,'Mapa Oficinas'!$A$7:$C$46,2,FALSE) -> Interior - Salta | W12: =VLOOKUP($R12,'Mapa Oficinas'!$A$7:$C$46,3,FALSE) -> San Lorenzo Chico
A13: 45911 | B13: =YEAR($A13) -> 2025 | C13: =MONTH($A13) -> 9 | D13: CLA6972631 | E13: 1 | F13: Terreno en Las Paredes, San Rafael | G13: Realizado | H13: AR ZonaProp | I13: 40000 | J13: 36000 | K13: =IF(J13<'Mapa Oficinas'!$I$21,0,IF(J13>'Mapa Oficinas'!$I$20,0,1)) -> 0 | L13: Dólares | M13: Dólares | N13: zamarvide al 600 | O13: Argentina | Mendoza | San Rafael | Las Paredes | P13: Terreno | Q13: 2 | R13: Andes | S13: Propia (Único Asesor) | T13: =VLOOKUP(S13,'Mapa Oficinas'!$H$7:$I$16,2,FALSE) -> CB | U13: Venta | V13: =VLOOKUP($R13,'Mapa Oficinas'!$A$7:$C$46,2,FALSE) -> Interior - Mendoza | W13: =VLOOKUP($R13,'Mapa Oficinas'!$A$7:$C$46,3,FALSE) -> San Rafael
A14: 45978 | B14: =YEAR($A14) -> 2025 | C14: =MONTH($A14) -> 11 | D14: CHO7388867 | E14: 1 | F14: Casa en venta a reciclar 158 entre 67 y 68 Los Hornos | G14: Realizado | H14: AR ZonaProp | I14: 35000 | J14: 36000 | K14: =IF(J14<'Mapa Oficinas'!$I$21,0,IF(J14>'Mapa Oficinas'!$I$20,0,1)) -> 0 | L14: Dólares | M14: Dólares | N14: 158 entre 67 y 68 | O14: Argentina | G.B.A. Zona Sur | La Plata | Los Hornos | P14: Casa | Q14: 2 | R14: Golden Team | S14: Propia (Único Asesor) | T14: =VLOOKUP(S14,'Mapa Oficinas'!$H$7:$I$16,2,FALSE) -> CB | U14: Venta | V14: =VLOOKUP($R14,'Mapa Oficinas'!$A$7:$C$46,2,FALSE) -> Zona Sur (GBA) | W14: =VLOOKUP($R14,'Mapa Oficinas'!$A$7:$C$46,3,FALSE) -> La Plata
A15: 45986 | B15: =YEAR($A15) -> 2025 | C15: =MONTH($A15) -> 11 | D15: CLA7046370 | E15: 1 | F15: VENTA Lote Villa Meliquina 1000m2 Oportunidad lote 4 MANZANA J | G15: Realizado | H15: Web Coldwell-Banker | I15: 38500 | J15: 36000 | K15: =IF(J15<'Mapa Oficinas'!$I$21,0,IF(J15>'Mapa Oficinas'!$I$20,0,1)) -> 0 | L15: Dólares | M15: Dólares | N15: meliquina | O15: Argentina | Neuquen | Lacar | San Martin De Los Andes | Villa Lago Meliquina | P15: Terreno | Q15: 2 | R15: Patagonia Lakes SMA | S15: Propia (Único Asesor) | T15: =VLOOKUP(S15,'Mapa Oficinas'!$H$7:$I$16,2,FALSE) -> CB | U15: Venta | V15: =VLOOKUP($R15,'Mapa Oficinas'!$A$7:$C$46,2,FALSE) -> Interior - Neuquén | W15: =VLOOKUP($R15,'Mapa Oficinas'!$A$7:$C$46,3,FALSE) -> San Martín de los Andes
A16: 45995 | B16: =YEAR($A16) -> 2025 | C16: =MONTH($A16) -> 12 | D16: CLA7597779 | E16: 1 | F16: Terreno en Zona Sur | G16: Realizado | H16: Facebook | I16: 37000 | J16: 36000 | K16: =IF(J16<'Mapa Oficinas'!$I$21,0,IF(J16>'Mapa Oficinas'!$I$20,0,1)) -> 0 | L16: Dólares | M16: Dólares | N16: La Verbena, calle 18 | O16: Argentina | Salta | Capital | Salta | Zona Sur | P16: Terreno | Q16: 2 | R16: Realty Group | S16: Propia (Único Asesor) | T16: =VLOOKUP(S16,'Mapa Oficinas'!$H$7:$I$16,2,FALSE) -> CB | U16: Venta | V16: =VLOOKUP($R16,'Mapa Oficinas'!$A$7:$C$46,2,FALSE) -> Interior - Salta | W16: =VLOOKUP($R16,'Mapa Oficinas'!$A$7:$C$46,3,FALSE) -> San Lorenzo Chico
A17: 45996 | B17: =YEAR($A17) -> 2025 | C17: =MONTH($A17) -> 12 | D17: san eliseo golf 414 | E17: 1 | F17: lote venta san elíseo golf 414 | G17: Realizado | H17: AR MercadoLibre | I17: 36000 | J17: 36000 | K17: =IF(J17<'Mapa Oficinas'!$I$21,0,IF(J17>'Mapa Oficinas'!$I$20,0,1)) -> 0 | L17: Dólares | M17: Dólares | O17: Argentina | G.B.A. Zona Sur | San Vicente | P17: Terreno | Q17: 2 | R17: Livello | S17: Propia (Único Asesor) | T17: =VLOOKUP(S17,'Mapa Oficinas'!$H$7:$I$16,2,FALSE) -> CB | U17: Venta | V17: =VLOOKUP($R17,'Mapa Oficinas'!$A$7:$C$46,2,FALSE) -> CABA | W17: =VLOOKUP($R17,'Mapa Oficinas'!$A$7:$C$46,3,FALSE) -> Palermo
A18: 46090 | B18: =YEAR($A18) -> 2026 | C18: =MONTH($A18) -> 3 | D18: CLA7470286 | E18: 1 | F18: Venta terreno en las heras | G18: Realizado | H18: AR ZonaProp | I18: 40000 | J18: 36000 | K18: =IF(J18<'Mapa Oficinas'!$I$21,0,IF(J18>'Mapa Oficinas'!$I$20,0,1)) -> 0 | L18: Dólares | M18: Dólares | N18: Belgrano al 700 | O18: Argentina | Mendoza | Las Heras | P18: Casa | Q18: 2 | R18: Cuyo Real | S18: Propia (Único Asesor) | T18: =VLOOKUP(S18,'Mapa Oficinas'!$H$7:$I$16,2,FALSE) -> CB | U18: Venta | V18: =VLOOKUP($R18,'Mapa Oficinas'!$A$7:$C$46,2,FALSE) -> Interior - Mendoza | W18: =VLOOKUP($R18,'Mapa Oficinas'!$A$7:$C$46,3,FALSE) -> Capital Mendoza
A19: 46092 | B19: =YEAR($A19) -> 2026 | C19: =MONTH($A19) -> 3 | D19: CLA7762823 | E19: 1 | F19: Excelente Terreno en Venta | G19: Realizado | H19: Conocido | I19: 36000 | J19: 36000 | K19: =IF(J19<'Mapa Oficinas'!$I$21,0,IF(J19>'Mapa Oficinas'!$I$20,0,1)) -> 0 | L19: Dólares | M19: Dólares | N19: Terreno en Colastine Norte sobre calle Los Algarrobos | O19: Argentina | Santa Fe | La Capital | Santa Fe | Colastine Norte | P19: Terreno | Q19: 2 | R19: De la Veracruz | S19: Propia (Único Asesor) | T19: =VLOOKUP(S19,'Mapa Oficinas'!$H$7:$I$16,2,FALSE) -> CB | U19: Venta | V19: =VLOOKUP($R19,'Mapa Oficinas'!$A$7:$C$46,2,FALSE) -> Interior - Santa Fe | W19: =VLOOKUP($R19,'Mapa Oficinas'!$A$7:$C$46,3,FALSE) -> Capital Santa Fe
A20: 46100 | B20: =YEAR($A20) -> 2026 | C20: =MONTH($A20) -> 3 | E20: 1 | F20: Lote, con superficie aproximada de 860 m2, ubicado en el Barrio El Remanso, de la ciudad de San Martin de Los andes Pcia. De Neuquén, nomenclaturas catastrales (lotes madres): 15 RR 023 5026 / 5028, identificado internamente como LOTE RE12 | G20: Realizado | H20: Conocido | I20: 36000 | J20: 36000 | K20: =IF(J20<'Mapa Oficinas'!$I$21,0,IF(J20>'Mapa Oficinas'!$I$20,0,1)) -> 0 | L20: Dólares | M20: Dólares | O20: Argentina | Neuquen | Lacar | San Martin De Los Andes | P20: Terreno | Q20: 2 | R20: Patagonia Lakes SMA | S20: Propia (Único Asesor) | T20: =VLOOKUP(S20,'Mapa Oficinas'!$H$7:$I$16,2,FALSE) -> CB | U20: Venta | V20: =VLOOKUP($R20,'Mapa Oficinas'!$A$7:$C$46,2,FALSE) -> Interior - Neuquén | W20: =VLOOKUP($R20,'Mapa Oficinas'!$A$7:$C$46,3,FALSE) -> San Martín de los Andes
A21: 45733 | B21: =YEAR($A21) -> 2025 | C21: =MONTH($A21) -> 3 | D21: CLA6351973 | E21: 1 | F21: VENTA Lote/terreno de 407,04 m2, UF 25 loteo Quetrihue B° Selva Triste Villa la Angostura | G21: Realizado | H21: Conocido | I21: 38000 | J21: 36500 | K21: =IF(J21<'Mapa Oficinas'!$I$21,0,IF(J21>'Mapa Oficinas'!$I$20,0,1)) -> 0 | L21: Dólares | M21: Dólares | N21: Quetrihue | O21: Argentina | Neuquen | Villa La Angostura | Selva Triste | P21: Terreno | Q21: 2 | R21: Patagonia Lakes VLA | S21: Compartida en Oficina (Dos Asesores) | T21: =VLOOKUP(S21,'Mapa Oficinas'!$H$7:$I$16,2,FALSE) -> CB | U21: Venta | V21: =VLOOKUP($R21,'Mapa Oficinas'!$A$7:$C$46,2,FALSE) -> Interior - Neuquén | W21: =VLOOKUP($R21,'Mapa Oficinas'!$A$7:$C$46,3,FALSE) -> Villa La Angostura
A22: 45741 | B22: =YEAR($A22) -> 2025 | C22: =MONTH($A22) -> 3 | D22: CLA6399702 | E22: 1 | F22: Terreno 300 m2 Confluencia Neuquén | G22: Realizado | H22: AR ZonaProp | I22: 37000 | J22: 36500 | K22: =IF(J22<'Mapa Oficinas'!$I$21,0,IF(J22>'Mapa Oficinas'!$I$20,0,1)) -> 0 | L22: Dólares | M22: Dólares | N22: Venta terreno 300 m2 Confluencia Neuquén | O22: Argentina | Neuquen | Confluencia | Neuquen | P22: Terreno | Q22: 2 | R22: Sensus | S22: Compartida en Oficina (Dos Asesores) | T22: =VLOOKUP(S22,'Mapa Oficinas'!$H$7:$I$16,2,FALSE) -> CB | U22: Venta | V22: =VLOOKUP($R22,'Mapa Oficinas'!$A$7:$C$46,2,FALSE) -> Interior - Neuquén | W22: =VLOOKUP($R22,'Mapa Oficinas'!$A$7:$C$46,3,FALSE) -> Capital Neuquén
A23: 45726 | B23: =YEAR($A23) -> 2025 | C23: =MONTH($A23) -> 3 | D23: Lote en carrodilla | E23: 1 | F23: Lote con obra gruesa en carrodilla | G23: Realizado | H23: Conocido | I23: 36500 | J23: 36500 | K23: =IF(J23<'Mapa Oficinas'!$I$21,0,IF(J23>'Mapa Oficinas'!$I$20,0,1)) -> 0 | L23: Dólares | M23: Dólares | O23: Argentina | Mendoza | Lujan De Cuyo | Lujan De Cuyo | Carrodilla | P23: Terreno | Q23: 1 | R23: Cuyo Real | S23: Compartida Fuera de la Red Búsqueda | T23: =VLOOKUP(S23,'Mapa Oficinas'!$H$7:$I$16,2,FALSE) -> Otra Red Búsqueda | U23: Venta | V23: =VLOOKUP($R23,'Mapa Oficinas'!$A$7:$C$46,2,FALSE) -> Interior - Mendoza | W23: =VLOOKUP($R23,'Mapa Oficinas'!$A$7:$C$46,3,FALSE) -> Capital Mendoza
A24: 45881 | B24: =YEAR($A24) -> 2025 | C24: =MONTH($A24) -> 8 | D24: CAP7303870 | E24: 0 | F24: Monoambiente en venta calle Constitución 1950 B San Cristóbal | G24: Realizado | H24: Referido | I24: 36500 | J24: 36500 | K24: =IF(J24<'Mapa Oficinas'!$I$21,0,IF(J24>'Mapa Oficinas'!$I$20,0,1)) -> 0 | L24: Dólares | M24: Dólares | N24: Monoambiente en venta calle Constitución 1950 B San Cristóbal | O24: Argentina | Capital Federal | San Cristobal | P24: Departamento | Q24: 2 | R24: Golden Team | S24: Profesional Referenciador (30%) | T24: =VLOOKUP(S24,'Mapa Oficinas'!$H$7:$I$16,2,FALSE) -> CB | U24: Venta | V24: =VLOOKUP($R24,'Mapa Oficinas'!$A$7:$C$46,2,FALSE) -> Zona Sur (GBA) | W24: =VLOOKUP($R24,'Mapa Oficinas'!$A$7:$C$46,3,FALSE) -> La Plata
A25: 45856 | B25: =YEAR($A25) -> 2025 | C25: =MONTH($A25) -> 7 | D25: CAP6894585 | E25: 1 | F25: VENTA MONOAMBIENTE SAN CRISTOBAL -APTO CREDITO- OPORTUNIDAD | G25: Realizado | H25: AR ZonaProp | I25: 38000 | J25: 36500 | K25: =IF(J25<'Mapa Oficinas'!$I$21,0,IF(J25>'Mapa Oficinas'!$I$20,0,1)) -> 0 | L25: Dólares | M25: Dólares | N25: Constitucion al 1900 | O25: Argentina | Capital Federal | San Cristobal | P25: Departamento | Q25: 2 | R25: Seniority | S25: Profesional Referido (70%) | T25: =VLOOKUP(S25,'Mapa Oficinas'!$H$7:$I$16,2,FALSE) -> CB | U25: Venta | V25: =VLOOKUP($R25,'Mapa Oficinas'!$A$7:$C$46,2,FALSE) -> CABA | W25: =VLOOKUP($R25,'Mapa Oficinas'!$A$7:$C$46,3,FALSE) -> Barrio Parque
A26: 45674 | B26: =YEAR($A26) -> 2025 | C26: =MONTH($A26) -> 1 | D26: Pola 2800 | E26: 1 | F26: POLA 2855 DPTO 3 | G26: Realizado | H26: AR ZonaProp | I26: 36500 | J26: 36500 | K26: =IF(J26<'Mapa Oficinas'!$I$21,0,IF(J26>'Mapa Oficinas'!$I$20,0,1)) -> 0 | L26: Dólares | M26: Dólares | N26: POLA 2855 DPTO 3 | O26: Argentina | Capital Federal | Villa Lugano | P26: PH | Q26: 2 | R26: Lion Team Norte | S26: Propia (Único Asesor) | T26: =VLOOKUP(S26,'Mapa Oficinas'!$H$7:$I$16,2,FALSE) -> CB | U26: Venta | V26: =VLOOKUP($R26,'Mapa Oficinas'!$A$7:$C$46,2,FALSE) -> Zona Norte (GBA) | W26: =VLOOKUP($R26,'Mapa Oficinas'!$A$7:$C$46,3,FALSE) -> Vicente López
A27: 45952 | B27: =YEAR($A27) -> 2025 | C27: =MONTH($A27) -> 10 | D27: Cuenca 4547 | E27: 1 | F27: Cuenca 4547 | G27: Realizado | H27: AR MercadoLibre | I27: 73000 | J27: 36500 | K27: =IF(J27<'Mapa Oficinas'!$I$21,0,IF(J27>'Mapa Oficinas'!$I$20,0,1)) -> 0 | L27: Dólares | M27: Dólares | N27: Cuenca 4547 | O27: Argentina | Capital Federal | Capital Federal | P27: Departamento | Q27: 2 | R27: Lion Team | S27: Propia (Único Asesor) | T27: =VLOOKUP(S27,'Mapa Oficinas'!$H$7:$I$16,2,FALSE) -> CB | U27: Venta | V27: =VLOOKUP($R27,'Mapa Oficinas'!$A$7:$C$46,2,FALSE) -> CABA | W27: =VLOOKUP($R27,'Mapa Oficinas'!$A$7:$C$46,3,FALSE) -> Villa Urquiza
A28: 45768 | B28: =YEAR($A28) -> 2025 | C28: =MONTH($A28) -> 4 | D28: CLA6351579 | E28: 1 | F28: VENTA Lote/Terreno 407m2 UF24 loteo Quetrihue B° Selva Triste Villa la Angostura | G28: Realizado | H28: Web Coldwell-Banker | I28: 36000 | J28: 37000 | K28: =IF(J28<'Mapa Oficinas'!$I$21,0,IF(J28>'Mapa Oficinas'!$I$20,0,1)) -> 0 | L28: Dólares | M28: Dólares | N28: Quetrihue | O28: Argentina | Neuquen | Villa La Angostura | Selva Triste | P28: Terreno | Q28: 2 | R28: Patagonia Lakes VLA | S28: Compartida en Oficina (Dos Asesores) | T28: =VLOOKUP(S28,'Mapa Oficinas'!$H$7:$I$16,2,FALSE) -> CB | U28: Venta | V28: =VLOOKUP($R28,'Mapa Oficinas'!$A$7:$C$46,2,FALSE) -> Interior - Neuquén | W28: =VLOOKUP($R28,'Mapa Oficinas'!$A$7:$C$46,3,FALSE) -> Villa La Angostura
A29: 45996 | B29: =YEAR($A29) -> 2025 | C29: =MONTH($A29) -> 12 | D29: Juan Manuel de Rosas 470 | E29: 1 | F29: Juan Manuel de Rosas 470 | G29: Realizado | H29: AR ZonaProp | I29: 37000 | J29: 37000 | K29: =IF(J29<'Mapa Oficinas'!$I$21,0,IF(J29>'Mapa Oficinas'!$I$20,0,1)) -> 0 | L29: Dólares | M29: Dólares | N29: Juan Manuel de Rosas 470 | O29: Argentina | G.B.A. Zona Oeste | La Matanza | Lomas Del Mirador | P29: Departamento | Q29: 2 | R29: Lion Team | S29: Compartida en Oficina (Dos Asesores) | T29: =VLOOKUP(S29,'Mapa Oficinas'!$H$7:$I$16,2,FALSE) -> CB | U29: Venta | V29: =VLOOKUP($R29,'Mapa Oficinas'!$A$7:$C$46,2,FALSE) -> CABA | W29: =VLOOKUP($R29,'Mapa Oficinas'!$A$7:$C$46,3,FALSE) -> Villa Urquiza
A30: 45694 | B30: =YEAR($A30) -> 2025 | C30: =MONTH($A30) -> 2 | E30: 3 | F30: UF N° 23 de 407,04 m2 Loteo B, Loteo Quetrihue | G30: Realizado | H30: AR MercadoLibre | I30: 37000 | J30: 37000 | K30: =IF(J30<'Mapa Oficinas'!$I$21,0,IF(J30>'Mapa Oficinas'!$I$20,0,1)) -> 0 | L30: Dólares | M30: Dólares | N30: Bv. Quetrihue y Bv. Amancay | O30: Argentina | Neuquen | Villa La Angostura | Selva Triste | P30: Terreno | Q30: 2 | R30: Patagonia Lakes VLA | S30: Master | T30: =VLOOKUP(S30,'Mapa Oficinas'!$H$7:$I$16,2,FALSE) -> CB | U30: Venta | V30: =VLOOKUP($R30,'Mapa Oficinas'!$A$7:$C$46,2,FALSE) -> Interior - Neuquén | W30: =VLOOKUP($R30,'Mapa Oficinas'!$A$7:$C$46,3,FALSE) -> Villa La Angostura
A31: 45726 | B31: =YEAR($A31) -> 2025 | C31: =MONTH($A31) -> 3 | D31: Santa Elisa Pilar del Este | E31: 3 | F31: Terreno en venta Barrio Santa Elisa Pilar del Este | G31: Realizado | H31: AR MercadoLibre | I31: 37000 | J31: 37000 | K31: =IF(J31<'Mapa Oficinas'!$I$21,0,IF(J31>'Mapa Oficinas'!$I$20,0,1)) -> 0 | L31: Dólares | M31: Dólares | O31: Argentina | G.B.A. Zona Norte | Pilar | Countries/B.Cerrado (Pilar) | Pilar Del Este | P31: Terreno | Q31: 2 | R31: North Team | S31: Master | T31: =VLOOKUP(S31,'Mapa Oficinas'!$H$7:$I$16,2,FALSE) -> CB | U31: Venta | V31: =VLOOKUP($R31,'Mapa Oficinas'!$A$7:$C$46,2,FALSE) -> Zona Norte (GBA) | W31: =VLOOKUP($R31,'Mapa Oficinas'!$A$7:$C$46,3,FALSE) -> Pilar
A32: 45834 | B32: =YEAR($A32) -> 2025 | C32: =MONTH($A32) -> 6 | D32: N/C - URUGUAY 847 | E32: 1 | F32: VENTA DPTO MONOAMBIENTE RECOLETA | G32: Realizado | H32: AR ZonaProp | I32: 37000 | J32: 37000 | K32: =IF(J32<'Mapa Oficinas'!$I$21,0,IF(J32>'Mapa Oficinas'!$I$20,0,1)) -> 0 | L32: Dólares | M32: Dólares | N32: URUGUAY 847 | O32: Argentina | Capital Federal | Recoleta | P32: Departamento | Q32: 1 | R32: Destino II | S32: Compartida Fuera de la Red Búsqueda | T32: =VLOOKUP(S32,'Mapa Oficinas'!$H$7:$I$16,2,FALSE) -> Otra Red Búsqueda | U32: Venta | V32: =VLOOKUP($R32,'Mapa Oficinas'!$A$7:$C$46,2,FALSE) -> CABA | W32: =VLOOKUP($R32,'Mapa Oficinas'!$A$7:$C$46,3,FALSE) -> Recoleta
A33: 45820 | B33: =YEAR($A33) -> 2025 | C33: =MONTH($A33) -> 6 | D33: CLO6758717 | E33: 1 | F33: Local en Venta | G33: Realizado | H33: AR ArgenProp | I33: 39000 | J33: 37000 | K33: =IF(J33<'Mapa Oficinas'!$I$21,0,IF(J33>'Mapa Oficinas'!$I$20,0,1)) -> 0 | L33: Dólares | M33: Dólares | N33: Montevideo al 700 | O33: Argentina | Capital Federal | Centro (Capital Federal) | Tribunales | P33: Local Comercial | Q33: 2 | R33: Ser | S33: Compartida Fuera de la Red Captación Propia | T33: =VLOOKUP(S33,'Mapa Oficinas'!$H$7:$I$16,2,FALSE) -> Otra Red Captación | U33: Venta | V33: =VLOOKUP($R33,'Mapa Oficinas'!$A$7:$C$46,2,FALSE) -> CABA | W33: =VLOOKUP($R33,'Mapa Oficinas'!$A$7:$C$46,3,FALSE) -> Belgrano
A34: 45992 | B34: =YEAR($A34) -> 2025 | C34: =MONTH($A34) -> 12 | D34: CAP7382562 | E34: 1 | F34: Monoambiente en venta en Palermo Soho. | G34: Realizado | H34: AR ZonaProp | I34: 40000 | J34: 37000 | K34: =IF(J34<'Mapa Oficinas'!$I$21,0,IF(J34>'Mapa Oficinas'!$I$20,0,1)) -> 0 | L34: Dólares | M34: Dólares | N34: Fray Justo Santa Maria de Oro al 2200, y Charcas | O34: Argentina | Capital Federal | Palermo | Palermo Soho | P34: Departamento | Q34: 2 | R34: Wings | S34: Compartida Fuera de la Red Captación Propia | T34: =VLOOKUP(S34,'Mapa Oficinas'!$H$7:$I$16,2,FALSE) -> Otra Red Captación | U34: Venta | V34: =VLOOKUP($R34,'Mapa Oficinas'!$A$7:$C$46,2,FALSE) -> CABA | W34: =VLOOKUP($R34,'Mapa Oficinas'!$A$7:$C$46,3,FALSE) -> Núñez
A35: 45726 | B35: =YEAR($A35) -> 2025 | C35: =MONTH($A35) -> 3 | D35: CHO6692253 | E35: 1 | F35: Casa en Venta en La Silleta | G35: Realizado | H35: Facebook | I35: 42000 | J35: 37000 | K35: =IF(J35<'Mapa Oficinas'!$I$21,0,IF(J35>'Mapa Oficinas'!$I$20,0,1)) -> 0 | L35: Dólares | M35: Dólares | N35: Barrio Justo Juez, calle Avelino Araoz esquina Gregorio Moreno | O35: Argentina | Salta | Rosario De Lerma | La Silleta | P35: Casa | Q35: 2 | R35: Realty Group | S35: Propia (Único Asesor) | T35: =VLOOKUP(S35,'Mapa Oficinas'!$H$7:$I$16,2,FALSE) -> CB | U35: Venta | V35: =VLOOKUP($R35,'Mapa Oficinas'!$A$7:$C$46,2,FALSE) -> Interior - Salta | W35: =VLOOKUP($R35,'Mapa Oficinas'!$A$7:$C$46,3,FALSE) -> San Lorenzo Chico
A36: 45776 | B36: =YEAR($A36) -> 2025 | C36: =MONTH($A36) -> 4 | D36: CHO6871958 | E36: 1 | F36: Departamento en Tres Cerritos | G36: Realizado | H36: Facebook | I36: 40000 | J36: 37000 | K36: =IF(J36<'Mapa Oficinas'!$I$21,0,IF(J36>'Mapa Oficinas'!$I$20,0,1)) -> 0 | L36: Dólares | M36: Dólares | N36: Los Parrales al 400 | O36: Argentina | Salta | Capital | Salta | Bo.Tres Cerritos | P36: Departamento | Q36: 2 | R36: Realty Group | S36: Propia (Único Asesor) | T36: =VLOOKUP(S36,'Mapa Oficinas'!$H$7:$I$16,2,FALSE) -> CB | U36: Venta | V36: =VLOOKUP($R36,'Mapa Oficinas'!$A$7:$C$46,2,FALSE) -> Interior - Salta | W36: =VLOOKUP($R36,'Mapa Oficinas'!$A$7:$C$46,3,FALSE) -> San Lorenzo Chico
A37: 45827 | B37: =YEAR($A37) -> 2025 | C37: =MONTH($A37) -> 6 | D37: CLA6367239 | E37: 1 | F37: BARRIO GARCIA BAYON - NEUQUEN CAPITAL | G37: Realizado | H37: AR ZonaProp | I37: 37000 | J37: 37000 | K37: =IF(J37<'Mapa Oficinas'!$I$21,0,IF(J37>'Mapa Oficinas'!$I$20,0,1)) -> 0 | L37: Dólares | M37: Dólares | N37: TERRENO GARCIA BAYON | O37: Argentina | Neuquen | Capital | P37: Terreno | Q37: 2 | R37: Sensus | S37: Propia (Único Asesor) | T37: =VLOOKUP(S37,'Mapa Oficinas'!$H$7:$I$16,2,FALSE) -> CB | U37: Venta | V37: =VLOOKUP($R37,'Mapa Oficinas'!$A$7:$C$46,2,FALSE) -> Interior - Neuquén | W37: =VLOOKUP($R37,'Mapa Oficinas'!$A$7:$C$46,3,FALSE) -> Capital Neuquén
A38: 46052 | B38: =YEAR($A38) -> 2026 | C38: =MONTH($A38) -> 1 | D38: CAP6526820 | E38: 1 | F38: Departamento Ideal para renta, Venta 3 dormitorios y cochera | G38: Realizado | H38: Conocido | I38: 40000 | J38: 37000 | K38: =IF(J38<'Mapa Oficinas'!$I$21,0,IF(J38>'Mapa Oficinas'!$I$20,0,1)) -> 0 | L38: Dólares | M38: Dólares | N38: Ideal para renta, Departamento 3 dormitorios y cochera | O38: Argentina | Santa Fe | La Capital | Santo Tome | Sargento Cabral | P38: Departamento | Q38: 2 | R38: De la Veracruz | S38: Propia (Único Asesor) | T38: =VLOOKUP(S38,'Mapa Oficinas'!$H$7:$I$16,2,FALSE) -> CB | U38: Venta | V38: =VLOOKUP($R38,'Mapa Oficinas'!$A$7:$C$46,2,FALSE) -> Interior - Santa Fe | W38: =VLOOKUP($R38,'Mapa Oficinas'!$A$7:$C$46,3,FALSE) -> Capital Santa Fe
A39: 46062 | B39: =YEAR($A39) -> 2026 | C39: =MONTH($A39) -> 2 | D39: CLA6306352 | E39: 1 | F39: Terreno de 436m2 en Dina Huapi con vista al Cerro Leones | G39: Realizado | H39: Teléfono | I39: 38500 | J39: 37000 | K39: =IF(J39<'Mapa Oficinas'!$I$21,0,IF(J39>'Mapa Oficinas'!$I$20,0,1)) -> 0 | L39: Dólares | M39: Dólares | N39: Dina Hue, Dina Huapi | O39: Argentina | Rio Negro | Pilcaniyeu | Dina Huapi | P39: Terreno | Q39: 2 | R39: Patagonia Lakes BRC | S39: Propia (Único Asesor) | T39: =VLOOKUP(S39,'Mapa Oficinas'!$H$7:$I$16,2,FALSE) -> CB | U39: Venta | V39: =VLOOKUP($R39,'Mapa Oficinas'!$A$7:$C$46,2,FALSE) -> Interior - Río Negro | W39: =VLOOKUP($R39,'Mapa Oficinas'!$A$7:$C$46,3,FALSE) -> Bariloche
A40: 45839 | B40: =YEAR($A40) -> 2025 | C40: =MONTH($A40) -> 7 | D40: CHO6782984 | E40: 3 | F40: Venta Casa San Martin de los Andes 72m2 Construidos a Terminar barrio Kaleuche alto | G40: Realizado | H40: Facebook | I40: 45000 | J40: 37500 | K40: =IF(J40<'Mapa Oficinas'!$I$21,0,IF(J40>'Mapa Oficinas'!$I$20,0,1)) -> 0 | L40: Dólares | M40: Dólares | N40: Paseo de los Músicos | O40: Argentina | Neuquen | Lacar | San Martin De Los Andes | Kaleuche | P40: Casa | Q40: 2 | R40: Patagonia Lakes SMA | S40: Master | T40: =VLOOKUP(S40,'Mapa Oficinas'!$H$7:$I$16,2,FALSE) -> CB | U40: Venta | V40: =VLOOKUP($R40,'Mapa Oficinas'!$A$7:$C$46,2,FALSE) -> Interior - Neuquén | W40: =VLOOKUP($R40,'Mapa Oficinas'!$A$7:$C$46,3,FALSE) -> San Martín de los Andes
A41: 45754 | B41: =YEAR($A41) -> 2025 | C41: =MONTH($A41) -> 4 | D41: CLO6045228 | E41: 1 | F41: BARRACAS LOCAL EN VENTA SIN EXPENSAS CON ALTILLO EN BARRACAS | G41: Realizado | H41: AR ZonaProp | I41: 40000 | J41: 37500 | K41: =IF(J41<'Mapa Oficinas'!$I$21,0,IF(J41>'Mapa Oficinas'!$I$20,0,1)) -> 0 | L41: Dólares | M41: Dólares | N41: LOS PATOS al 1800 | O41: Argentina | Capital Federal | Barracas | P41: Local Comercial | Q41: 2 | R41: Lion Team Norte | S41: Propia (Único Asesor) | T41: =VLOOKUP(S41,'Mapa Oficinas'!$H$7:$I$16,2,FALSE) -> CB | U41: Venta | V41: =VLOOKUP($R41,'Mapa Oficinas'!$A$7:$C$46,2,FALSE) -> Zona Norte (GBA) | W41: =VLOOKUP($R41,'Mapa Oficinas'!$A$7:$C$46,3,FALSE) -> Vicente López
A42: 45852 | B42: =YEAR($A42) -> 2025 | C42: =MONTH($A42) -> 7 | D42: CAP7125750 | E42: 1 | F42: DEPARTAMENTO 3 AMBIENTES EN VENTA EN PARQUE AVELLANEDA | G42: Realizado | H42: AR MercadoLibre | I42: 85000 | J42: 37500 | K42: =IF(J42<'Mapa Oficinas'!$I$21,0,IF(J42>'Mapa Oficinas'!$I$20,0,1)) -> 0 | L42: Dólares | M42: Dólares | N42: Juan B, Alberdi al 4800 | O42: Argentina | Capital Federal | Parque Avellaneda | P42: Departamento | Q42: 2 | R42: Lion Team | S42: Propia (Único Asesor) | T42: =VLOOKUP(S42,'Mapa Oficinas'!$H$7:$I$16,2,FALSE) -> CB | U42: Venta | V42: =VLOOKUP($R42,'Mapa Oficinas'!$A$7:$C$46,2,FALSE) -> CABA | W42: =VLOOKUP($R42,'Mapa Oficinas'!$A$7:$C$46,3,FALSE) -> Villa Urquiza
A43: 45853 | B43: =YEAR($A43) -> 2025 | C43: =MONTH($A43) -> 7 | D43: Ortega y Gasset 1898 | E43: 1 | F43: Ortega y Gasset 1898 | G43: Realizado | H43: AR MercadoLibre | I43: 37500 | J43: 37500 | K43: =IF(J43<'Mapa Oficinas'!$I$21,0,IF(J43>'Mapa Oficinas'!$I$20,0,1)) -> 0 | L43: Dólares | M43: Dólares | N43: Ortega y Gasset 1898 | O43: Argentina | G.B.A. Zona Norte | San Isidro | Martinez | P43: Departamento | Q43: 2 | R43: Lion Team | S43: Propia (Único Asesor) | T43: =VLOOKUP(S43,'Mapa Oficinas'!$H$7:$I$16,2,FALSE) -> CB | U43: Venta | V43: =VLOOKUP($R43,'Mapa Oficinas'!$A$7:$C$46,2,FALSE) -> CABA | W43: =VLOOKUP($R43,'Mapa Oficinas'!$A$7:$C$46,3,FALSE) -> Villa Urquiza
... A47: 45838 | B47: =YEAR($A47) -> 2025 | C47: =MONTH($A47) -> 6 | D47: CBA47695 LA6353622 | E47: 1 | F47: VENTA terreno de 337m2 en LOTEO "ANTIGUO CAMINO" Bariloche | G47: Realizado | H47: Teléfono | I47: 41760 | J47: 37753 | K47: =IF(J47<'Mapa Oficinas'!$I$21,0,IF(J47>'Mapa Oficinas'!$I$20,0,1)) -> 0 | L47: Dólares | M47: Dólares | N47: Antiguo Camino, San Carlos de Bariloche | O47: Argentina | Rio Negro | Bariloche | San Carlos De Bariloche | Lago Moreno | P47: Terreno | Q47: 2 | R47: Patagonia Lakes BRC | S47: Compartida en Oficina (Dos Asesores) | T47: =VLOOKUP(S47,'Mapa Oficinas'!$H$7:$I$16,2,FALSE) -> CB | U47: Venta | V47: =VLOOKUP($R47,'Mapa Oficinas'!$A$7:$C$46,2,FALSE) -> Interior - Río Negro | W47: =VLOOKUP($R47,'Mapa Oficinas'!$A$7:$C$46,3,FALSE) -> Bariloche
A48: 45940 | B48: =YEAR($A48) -> 2025 | C48: =MONTH($A48) -> 10 | E48: 1 | F48: Lote 12 MZ E Barrio Piedras de San Francisco,NC 1525 051 7962 0000, 1000 m2, 20m x 50, SMA | G48: Realizado | H48: Web Coldwell-Banker | I48: 38000 | J48: 38000 | K48: =IF(J48<'Mapa Oficinas'!$I$21,0,IF(J48>'Mapa Oficinas'!$I$20,0,1)) -> 0 | L48: Dólares | M48: Dólares | N48: Piedra San Francisco | O48: Argentina | Neuquen | Lacar | San Martin De Los Andes | P48: Terreno | Q48: 1 | R48: Patagonia Lakes SMA | S48: (Interior) Compartida Fuera de la Red Búsqueda | T48: =VLOOKUP(S48,'Mapa Oficinas'!$H$7:$I$16,2,FALSE) -> Otra Red Búsqueda | U48: Venta | V48: =VLOOKUP($R48,'Mapa Oficinas'!$A$7:$C$46,2,FALSE) -> Interior - Neuquén | W48: =VLOOKUP($R48,'Mapa Oficinas'!$A$7:$C$46,3,FALSE) -> San Martín de los Andes
A49: 45705 | B49: =YEAR($A49) -> 2025 | C49: =MONTH($A49) -> 2 | D49: CLA6351579 | E49: 1 | F49: VENTA Lote/Terreno 407m2 UF24 loteo Quetrihue B° Selva Triste Villa la Angostura | G49: Realizado | H49: Web Coldwell-Banker | I49: 36000 | J49: 38000 | K49: =IF(J49<'Mapa Oficinas'!$I$21,0,IF(J49>'Mapa Oficinas'!$I$20,0,1)) -> 0 | L49: Dólares | M49: Dólares | N49: Quetrihue | O49: Argentina | Neuquen | Villa La Angostura | Selva Triste | P49: Terreno | Q49: 2 | R49: Patagonia Lakes VLA | S49: Compartida en Oficina (Dos Asesores) | T49: =VLOOKUP(S49,'Mapa Oficinas'!$H$7:$I$16,2,FALSE) -> CB | U49: Venta | V49: =VLOOKUP($R49,'Mapa Oficinas'!$A$7:$C$46,2,FALSE) -> Interior - Neuquén | W49: =VLOOKUP($R49,'Mapa Oficinas'!$A$7:$C$46,3,FALSE) -> Villa La Angostura
A50: 45770 | B50: =YEAR($A50) -> 2025 | C50: =MONTH($A50) -> 4 | D50: CHO6089217 | E50: 1 | F50: Casa en venta en Villa Mitre | G50: Realizado | H50: Facebook | I50: 40000 | J50: 38000 | K50: =IF(J50<'Mapa Oficinas'!$I$21,0,IF(J50>'Mapa Oficinas'!$I$20,0,1)) -> 0 | L50: Dólares | M50: Dólares | N50: Villa Mitre | O50: Argentina | Salta | Capital | Salta | Va.Mitre | P50: Casa | Q50: 2 | R50: Realty Group | S50: Compartida en Oficina (Dos Asesores) | T50: =VLOOKUP(S50,'Mapa Oficinas'!$H$7:$I$16,2,FALSE) -> CB | U50: Venta | V50: =VLOOKUP($R50,'Mapa Oficinas'!$A$7:$C$46,2,FALSE) -> Interior - Salta | W50: =VLOOKUP($R50,'Mapa Oficinas'!$A$7:$C$46,3,FALSE) -> San Lorenzo Chico
A51: 46038 | B51: =YEAR($A51) -> 2026 | C51: =MONTH($A51) -> 1 | E51: 1 | F51: UF 5 Loteo B Quetrihue | G51: Realizado | H51: AR ZonaProp | I51: 38000 | J51: 38000 | K51: =IF(J51<'Mapa Oficinas'!$I$21,0,IF(J51>'Mapa Oficinas'!$I$20,0,1)) -> 0 | L51: Dólares | M51: Dólares | N51: Bv, quetrihue y amancay | O51: Argentina | Neuquen | Villa La Angostura | Selva Triste | P51: Terreno | Q51: 2 | R51: Patagonia Lakes VLA | S51: Compartida en Oficina (Dos Asesores) | T51: =VLOOKUP(S51,'Mapa Oficinas'!$H$7:$I$16,2,FALSE) -> CB | U51: Venta | V51: =VLOOKUP($R51,'Mapa Oficinas'!$A$7:$C$46,2,FALSE) -> Interior - Neuquén | W51: =VLOOKUP($R51,'Mapa Oficinas'!$A$7:$C$46,3,FALSE) -> Villa La Angostura
A52: 46074 | B52: =YEAR($A52) -> 2026 | C52: =MONTH($A52) -> 2 | E52: 1 | F52: UF 4 Loteo C Quetrihue | G52: Realizado | H52: Conocido | I52: 38000 | J52: 38000 | K52: =IF(J52<'Mapa Oficinas'!$I$21,0,IF(J52>'Mapa Oficinas'!$I$20,0,1)) -> 0 | L52: Dólares | M52: Dólares | N52: Bv. Quetrihue y Amancay | O52: Argentina | Neuquen | Villa La Angostura | Selva Triste | P52: Terreno | Q52: 2 | R52: Patagonia Lakes VLA | S52: Compartida en Oficina (Dos Asesores) | T52: =VLOOKUP(S52,'Mapa Oficinas'!$H$7:$I$16,2,FALSE) -> CB | U52: Venta | V52: =VLOOKUP($R52,'Mapa Oficinas'!$A$7:$C$46,2,FALSE) -> Interior - Neuquén | W52: =VLOOKUP($R52,'Mapa Oficinas'!$A$7:$C$46,3,FALSE) -> Villa La Angostura
A53: 46087 | B53: =YEAR($A53) -> 2026 | C53: =MONTH($A53) -> 3 | D53: CBA59141 LA7277567 | E53: 1 | F53: VENTA Lote/terreno Villa La Angostura 374 m2, Loteo Quetrihue, Vista a las montañas, Selvana Triste. | G53: Realizado | H53: Conocido | I53: 40700 | J53: 38000 | K53: =IF(J53<'Mapa Oficinas'!$I$21,0,IF(J53>'Mapa Oficinas'!$I$20,0,1)) -> 0 | L53: Dólares | M53: Dólares | N53: Blvd Quetrihue y Blvd Amancay | O53: Argentina | Neuquen | Villa La Angostura | Selva Triste | P53: Terreno | Q53: 2 | R53: Patagonia Lakes VLA | S53: Compartida en Oficina (Dos Asesores) | T53: =VLOOKUP(S53,'Mapa Oficinas'!$H$7:$I$16,2,FALSE) -> CB | U53: Venta | V53: =VLOOKUP($R53,'Mapa Oficinas'!$A$7:$C$46,2,FALSE) -> Interior - Neuquén | W53: =VLOOKUP($R53,'Mapa Oficinas'!$A$7:$C$46,3,FALSE) -> Villa La Angostura
A54: 45817 | B54: =YEAR($A54) -> 2025 | C54: =MONTH($A54) -> 6 | E54: 1 | F54: UF 8 Loteo Quetrihue Loteo A | G54: Realizado | H54: AR ZonaProp | I54: 38000 | J54: 38000 | K54: =IF(J54<'Mapa Oficinas'!$I$21,0,IF(J54>'Mapa Oficinas'!$I$20,0,1)) -> 0 | L54: Dólares | M54: Dólares | N54: Bv. Quetrihue y Amancay | O54: Argentina | Neuquen | Villa La Angostura | Selva Triste | P54: Terreno | Q54: 2 | R54: Patagonia Lakes VLA | S54: Compartida en Oficina (Dos Asesores) | T54: =VLOOKUP(S54,'Mapa Oficinas'!$H$7:$I$16,2,FALSE) -> CB | U54: Venta | V54: =VLOOKUP($R54,'Mapa Oficinas'!$A$7:$C$46,2,FALSE) -> Interior - Neuquén | W54: =VLOOKUP($R54,'Mapa Oficinas'!$A$7:$C$46,3,FALSE) -> Villa La Angostura
A55: 45827 | B55: =YEAR($A55) -> 2025 | C55: =MONTH($A55) -> 6 | D55: CLA6630574 | E55: 3 | F55: VENTA terreno/lote, 600 m2, San Carlos de Bariloche | G55: Realizado | H55: Referido | I55: 48000 | J55: 38000 | K55: =IF(J55<'Mapa Oficinas'!$I$21,0,IF(J55>'Mapa Oficinas'!$I$20,0,1)) -> 0 | L55: Dólares | M55: Dólares | N55: Venta Lote de 600 m2 en barrio privado Solares del este, San Carlos de Bariloche | O55: Argentina | Rio Negro | Bariloche | Solares del este | P55: Terreno | Q55: 2 | R55: Patagonia Lakes BRC | S55: Master | T55: =VLOOKUP(S55,'Mapa Oficinas'!$H$7:$I$16,2,FALSE) -> CB | U55: Venta | V55: =VLOOKUP($R55,'Mapa Oficinas'!$A$7:$C$46,2,FALSE) -> Interior - Río Negro | W55: =VLOOKUP($R55,'Mapa Oficinas'!$A$7:$C$46,3,FALSE) -> Bariloche
A56: 45791 | B56: =YEAR($A56) -> 2025 | C56: =MONTH($A56) -> 5 | D56: CAP6411494 | E56: 1 | F56: VENTA depto monoambiente divisible apto profesional en San Nicolás | G56: Realizado | H56: AR ZonaProp | I56: 39000 | J56: 38000 | K56: =IF(J56<'Mapa Oficinas'!$I$21,0,IF(J56>'Mapa Oficinas'!$I$20,0,1)) -> 0 | L56: Dólares | M56: Dólares | N56: Libertad al 300 | O56: Argentina | Capital Federal | San Nicolás | P56: Departamento | Q56: 2 | R56: Seniority | S56: Propia (Único Asesor) | T56: =VLOOKUP(S56,'Mapa Oficinas'!$H$7:$I$16,2,FALSE) -> CB | U56: Venta | V56: =VLOOKUP($R56,'Mapa Oficinas'!$A$7:$C$46,2,FALSE) -> CABA | W56: =VLOOKUP($R56,'Mapa Oficinas'!$A$7:$C$46,3,FALSE) -> Barrio Parque
A57: 45803 | B57: =YEAR($A57) -> 2025 | C57: =MONTH($A57) -> 5 | D57: CLA6243456 | E57: 1 | F57: VENTA Lote/Terreno 600 m2 Barrio Los Manzanos - San Martin de los Andes | G57: Realizado | H57: Instagram | I57: 38000 | J57: 38000 | K57: =IF(J57<'Mapa Oficinas'!$I$21,0,IF(J57>'Mapa Oficinas'!$I$20,0,1)) -> 0 | L57: Dólares | M57: Dólares | N57: cascada rio bonito al 300 | O57: Argentina | Neuquen | Lacar | San Martin De Los Andes | Chacra 28 | P57: Terreno | Q57: 2 | R57: Patagonia Lakes SMA | S57: Propia (Único Asesor) | T57: =VLOOKUP(S57,'Mapa Oficinas'!$H$7:$I$16,2,FALSE) -> CB | U57: Venta | V57: =VLOOKUP($R57,'Mapa Oficinas'!$A$7:$C$46,2,FALSE) -> Interior - Neuquén | W57: =VLOOKUP($R57,'Mapa Oficinas'!$A$7:$C$46,3,FALSE) -> San Martín de los Andes
A58: 45869 | B58: =YEAR($A58) -> 2025 | C58: =MONTH($A58) -> 7 | D58: CAP6859449 | E58: 1 | F58: VENTA departamento dos ambientes apto crédito | G58: Realizado | H58: AR ArgenProp | I58: 40000 | J58: 38000 | K58: =IF(J58<'Mapa Oficinas'!$I$21,0,IF(J58>'Mapa Oficinas'!$I$20,0,1)) -> 0 | L58: Dólares | M58: Dólares | N58: Gambaro al 200 | O58: Argentina | G.B.A. Zona Oeste | Hurlingham | Villa Santos Tesei | P58: Departamento | Q58: 2 | R58: Lion Team | S58: Propia (Único Asesor) | T58: =VLOOKUP(S58,'Mapa Oficinas'!$H$7:$I$16,2,FALSE) -> CB | U58: Venta | V58: =VLOOKUP($R58,'Mapa Oficinas'!$A$7:$C$46,2,FALSE) -> CABA | W58: =VLOOKUP($R58,'Mapa Oficinas'!$A$7:$C$46,3,FALSE) -> Villa Urquiza
A59: 45896 | B59: =YEAR($A59) -> 2025 | C59: =MONTH($A59) -> 8 | D59: CHO7006377 | E59: 1 | F59: VENTA CASA EN VOLCAN | G59: Realizado | H59: Conocido | I59: 40000 | J59: 38000 | K59: =IF(J59<'Mapa Oficinas'!$I$21,0,IF(J59>'Mapa Oficinas'!$I$20,0,1)) -> 0 | L59: Dólares | M59: Dólares | N59: Mariano Moreno al 100 | O59: Argentina | Jujuy | Tumbaya | P59: Casa | Q59: 2 | R59: Plaza | S59: Propia (Único Asesor) | T59: =VLOOKUP(S59,'Mapa Oficinas'!$H$7:$I$16,2,FALSE) -> CB | U59: Venta | V59: =VLOOKUP($R59,'Mapa Oficinas'!$A$7:$C$46,2,FALSE) -> Interior - Jujuy | W59: =VLOOKUP($R59,'Mapa Oficinas'!$A$7:$C$46,3,FALSE) -> Capital Jujuy
A60: 45947 | B60: =YEAR($A60) -> 2025 | C60: =MONTH($A60) -> 10 | D60: Boticelli 4719 | E60: 1 | F60: Boticelli 4719 | G60: Realizado | H60: AR ArgenProp | I60: 38000 | J60: 38000 | K60: =IF(J60<'Mapa Oficinas'!$I$21,0,IF(J60>'Mapa Oficinas'!$I$20,0,1)) -> 0 | L60: Dólares | M60: Dólares | N60: Boticelli 4719 | O60: Argentina | G.B.A. Zona Norte | Pilar | P60: Departamento | Q60: 2 | R60: Lion Team | S60: Propia (Único Asesor) | T60: =VLOOKUP(S60,'Mapa Oficinas'!$H$7:$I$16,2,FALSE) -> CB | U60: Venta | V60: =VLOOKUP($R60,'Mapa Oficinas'!$A$7:$C$46,2,FALSE) -> CABA | W60: =VLOOKUP($R60,'Mapa Oficinas'!$A$7:$C$46,3,FALSE) -> Villa Urquiza
A61: 45954 | B61: =YEAR($A61) -> 2025 | C61: =MONTH($A61) -> 10 | D61: Rosas Castillo 2800 | E61: 1 | F61: Rosas Castillo 2800 | G61: Realizado | H61: AR MercadoLibre | I61: 38000 | J61: 38000 | K61: =IF(J61<'Mapa Oficinas'!$I$21,0,IF(J61>'Mapa Oficinas'!$I$20,0,1)) -> 0 | L61: Dólares | M61: Dólares | N61: Rosas Castillo 2800 | O61: Argentina | Interior Buenos Aires | Balcarce | P61: Departamento | Q61: 2 | R61: Lion Team | S61: Propia (Único Asesor) | T61: =VLOOKUP(S61,'Mapa Oficinas'!$H$7:$I$16,2,FALSE) -> CB | U61: Venta | V61: =VLOOKUP($R61,'Mapa Oficinas'!$A$7:$C$46,2,FALSE) -> CABA | W61: =VLOOKUP($R61,'Mapa Oficinas'!$A$7:$C$46,3,FALSE) -> Villa Urquiza
A62: 46029 | B62: =YEAR($A62) -> 2026 | C62: =MONTH($A62) -> 1 | D62: CAP7474209 | E62: 1 | F62: Departamento en Ciudadela | G62: Realizado | H62: AR ZonaProp | I62: 40500 | J62: 38000 | K62: =IF(J62<'Mapa Oficinas'!$I$21,0,IF(J62>'Mapa Oficinas'!$I$20,0,1)) -> 0 | L62: Dólares | M62: Dólares | N62: Avenida Republica al 400 | O62: Argentina | G.B.A. Zona Oeste | Tres De Febrero | Ciudadela | P62: Departamento | Q62: 2 | R62: Destino | S62: Propia (Único Asesor) | T62: =VLOOKUP(S62,'Mapa Oficinas'!$H$7:$I$16,2,FALSE) -> CB | U62: Venta | V62: =VLOOKUP($R62,'Mapa Oficinas'!$A$7:$C$46,2,FALSE) -> CABA | W62: =VLOOKUP($R62,'Mapa Oficinas'!$A$7:$C$46,3,FALSE) -> Recoleta
A63: 46045 | B63: =YEAR($A63) -> 2026 | C63: =MONTH($A63) -> 1 | D63: CBA59141 LA7272080 | E63: 1 | F63: VENTA Lote/terreno Villa La Angostura 374 m2, Loteo Quetrihue, Vista a las montañas, Selvana Triste. | G63: Realizado | H63: Referido | I63: 42735 | J63: 38000 | K63: =IF(J63<'Mapa Oficinas'!$I$21,0,IF(J63>'Mapa Oficinas'!$I$20,0,1)) -> 0 | L63: Dólares | M63: Dólares | N63: Blvd Quetrihue y Blvd Amancay | O63: Argentina | Neuquen | Villa La Angostura | Selva Triste | P63: Terreno | Q63: 2 | R63: Patagonia Lakes VLA | S63: Propia (Único Asesor) | T63: =VLOOKUP(S63,'Mapa Oficinas'!$H$7:$I$16,2,FALSE) -> CB | U63: Venta | V63: =VLOOKUP($R63,'Mapa Oficinas'!$A$7:$C$46,2,FALSE) -> Interior - Neuquén | W63: =VLOOKUP($R63,'Mapa Oficinas'!$A$7:$C$46,3,FALSE) -> Villa La Angostura
A64: 46049 | B64: =YEAR($A64) -> 2026 | C64: =MONTH($A64) -> 1 | D64: CBA59141 LA7272078 | E64: 1 | F64: VENTA Lote/terreno Villa La Angostura 374 m2, Loteo Quetrihue, Vista a las montañas, Selvana Triste. | G64: Realizado | H64: Teléfono | I64: 40700 | J64: 38000 | K64: =IF(J64<'Mapa Oficinas'!$I$21,0,IF(J64>'Mapa Oficinas'!$I$20,0,1)) -> 0 | L64: Dólares | M64: Dólares | N64: Blvd Quetrihue y Blvd Amancay | O64: Argentina | Neuquen | Villa La Angostura | Selva Triste | P64: Terreno | Q64: 2 | R64: Patagonia Lakes VLA | S64: Propia (Único Asesor) | T64: =VLOOKUP(S64,'Mapa Oficinas'!$H$7:$I$16,2,FALSE) -> CB | U64: Venta | V64: =VLOOKUP($R64,'Mapa Oficinas'!$A$7:$C$46,2,FALSE) -> Interior - Neuquén | W64: =VLOOKUP($R64,'Mapa Oficinas'!$A$7:$C$46,3,FALSE) -> Villa La Angostura
A65: 45792 | B65: =YEAR($A65) -> 2025 | C65: =MONTH($A65) -> 5 | E65: 1 | F65: Lavalle 1131 - Remax Express - Leo Maroni | G65: Realizado | H65: AR ZonaProp | I65: 38500 | J65: 38500 | K65: =IF(J65<'Mapa Oficinas'!$I$21,0,IF(J65>'Mapa Oficinas'!$I$20,0,1)) -> 0 | L65: Dólares | M65: Dólares | N65: Lavalle 1131 | O65: Argentina | Capital Federal | Palermo | P65: Departamento | Q65: 1 | R65: Destino | S65: Compartida Fuera de la Red Búsqueda | T65: =VLOOKUP(S65,'Mapa Oficinas'!$H$7:$I$16,2,FALSE) -> Otra Red Búsqueda | U65: Venta | V65: =VLOOKUP($R65,'Mapa Oficinas'!$A$7:$C$46,2,FALSE) -> CABA | W65: =VLOOKUP($R65,'Mapa Oficinas'!$A$7:$C$46,3,FALSE) -> Recoleta
A66: 45821 | B66: =YEAR($A66) -> 2025 | C66: =MONTH($A66) -> 6 | E66: 0 | F66: UF 19 Loteo Quetrihue Loteo A | G66: Realizado | H66: Salón | I66: 38735 | J66: 38735 | K66: =IF(J66<'Mapa Oficinas'!$I$21,0,IF(J66>'Mapa Oficinas'!$I$20,0,1)) -> 0 | L66: Dólares | M66: Dólares | N66: Bv. Quetrihue y Amancay | O66: Argentina | Neuquen | Villa La Angostura | Selva Triste | P66: Terreno | Q66: 2 | R66: Patagonia Lakes VLA | S66: Master | T66: =VLOOKUP(S66,'Mapa Oficinas'!$H$7:$I$16,2,FALSE) -> CB | U66: Venta | V66: =VLOOKUP($R66,'Mapa Oficinas'!$A$7:$C$46,2,FALSE) -> Interior - Neuquén | W66: =VLOOKUP($R66,'Mapa Oficinas'!$A$7:$C$46,3,FALSE) -> Villa La Angostura
A67: 46020 | B67: =YEAR($A67) -> 2025 | C67: =MONTH($A67) -> 12 | D67: CAP7270855 | E67: 1 | F67: Departamento en Esperanza | G67: Realizado | H67: Referido | I67: 45000 | J67: 39000 | K67: =IF(J67<'Mapa Oficinas'!$I$21,0,IF(J67>'Mapa Oficinas'!$I$20,0,1)) -> 0 | L67: Dólares | M67: Dólares | N67: Deoartamento en planta alta, en ciudad de Esperanza | O67: Argentina | Santa Fe | Las Colonias | Esperanza | P67: Departamento | Q67: 1 | R67: De la Veracruz | S67: (Interior) Compartida Fuera de la Red Captación Propia | T67: =VLOOKUP(S67,'Mapa Oficinas'!$H$7:$I$16,2,FALSE) -> Otra Red Captación | U67: Venta | V67: =VLOOKUP($R67,'Mapa Oficinas'!$A$7:$C$46,2,FALSE) -> Interior - Santa Fe | W67: =VLOOKUP($R67,'Mapa Oficinas'!$A$7:$C$46,3,FALSE) -> Capital Santa Fe
A68: 45776 | B68: =YEAR($A68) -> 2025 | C68: =MONTH($A68) -> 4 | E68: 0 | F68: UF 9 Loteo Quetrihue Loteo A | G68: Realizado | H68: Conocido | I68: 39000 | J68: 39000 | K68: =IF(J68<'Mapa Oficinas'!$I$21,0,IF(J68>'Mapa Oficinas'!$I$20,0,1)) -> 0 | L68: Dólares | M68: Dólares | N68: Bv. Quetrihue y Amancay | O68: Argentina | Neuquen | Villa La Angostura | Puerto | P68: Terreno | Q68: 2 | R68: Patagonia Lakes VLA | S68: Compartida en Oficina (Dos Asesores) | T68: =VLOOKUP(S68,'Mapa Oficinas'!$H$7:$I$16,2,FALSE) -> CB | U68: Venta | V68: =VLOOKUP($R68,'Mapa Oficinas'!$A$7:$C$46,2,FALSE) -> Interior - Neuquén | W68: =VLOOKUP($R68,'Mapa Oficinas'!$A$7:$C$46,3,FALSE) -> Villa La Angostura
A69: 45734 | B69: =YEAR($A69) -> 2025 | C69: =MONTH($A69) -> 3 | D69: AAP6667782 | E69: 1 | F69: Departamento monoambiente en San Nicolás | G69: Realizado | H69: AR ArgenProp | I69: 39500 | J69: 39000 | K69: =IF(J69<'Mapa Oficinas'!$I$21,0,IF(J69>'Mapa Oficinas'!$I$20,0,1)) -> 0 | L69: Dólares | M69: Dólares | N69: Viamonte 800 | O69: Argentina | Capital Federal | San Nicolás | P69: Departamento | Q69: 2 | R69: Desiderio | S69: Compartida Fuera de la Red Captación Propia | T69: =VLOOKUP(S69,'Mapa Oficinas'!$H$7:$I$16,2,FALSE) -> Otra Red Captación | U69: Venta | V69: =VLOOKUP($R69,'Mapa Oficinas'!$A$7:$C$46,2,FALSE) -> CABA | W69: =VLOOKUP($R69,'Mapa Oficinas'!$A$7:$C$46,3,FALSE) -> Caballito
A70: 45785 | B70: =YEAR($A70) -> 2025 | C70: =MONTH($A70) -> 5 | D70: CAP4510385 | E70: 1 | F70: Oportunidad Venta Departamento 4 amb 82M2 | G70: Realizado | H70: Referido | I70: 45000 | J70: 39000 | K70: =IF(J70<'Mapa Oficinas'!$I$21,0,IF(J70>'Mapa Oficinas'!$I$20,0,1)) -> 0 | L70: Dólares | M70: Dólares | N70: MANGE 822 | O70: Argentina | Rio Negro | Bariloche | P70: Departamento | Q70: 2 | R70: Patagonia Lakes BRC | S70: Propia (Único Asesor) | T70: =VLOOKUP(S70,'Mapa Oficinas'!$H$7:$I$16,2,FALSE) -> CB | U70: Venta | V70: =VLOOKUP($R70,'Mapa Oficinas'!$A$7:$C$46,2,FALSE) -> Interior - Río Negro | W70: =VLOOKUP($R70,'Mapa Oficinas'!$A$7:$C$46,3,FALSE) -> Bariloche
A71: 45868 | B71: =YEAR($A71) -> 2025 | C71: =MONTH($A71) -> 7 | D71: CAP6400410 | E71: 1 | F71: Departamento en venta ubicado en Barrio El Bosque | G71: Realizado | H71: Facebook | I71: 40000 | J71: 39000 | K71: =IF(J71<'Mapa Oficinas'!$I$21,0,IF(J71>'Mapa Oficinas'!$I$20,0,1)) -> 0 | L71: Dólares | M71: Dólares | N71: El Bosque | O71: Argentina | Salta | Capital | Salta | P71: Departamento | Q71: 2 | R71: Realty Group | S71: Propia (Único Asesor) | T71: =VLOOKUP(S71,'Mapa Oficinas'!$H$7:$I$16,2,FALSE) -> CB | U71: Venta | V71: =VLOOKUP($R71,'Mapa Oficinas'!$A$7:$C$46,2,FALSE) -> Interior - Salta | W71: =VLOOKUP($R71,'Mapa Oficinas'!$A$7:$C$46,3,FALSE) -> San Lorenzo Chico
A72: 45953 | B72: =YEAR($A72) -> 2025 | C72: =MONTH($A72) -> 10 | D72: CPH7050534 | E72: 1 | F72: VENTA PH 2 AMBIENTES Y ENTREPISO, BALCON, LUMINOSO, APTO CREDITO | G72: Realizado | H72: AR ZonaProp | I72: 44000 | J72: 39000 | K72: =IF(J72<'Mapa Oficinas'!$I$21,0,IF(J72>'Mapa Oficinas'!$I$20,0,1)) -> 0 | L72: Dólares | M72: Dólares | N72: PORTELA al 1700 | O72: Argentina | Capital Federal | Flores | P72: PH | Q72: 2 | R72: Seniority | S72: Propia (Único Asesor) | T72: =VLOOKUP(S72,'Mapa Oficinas'!$H$7:$I$16,2,FALSE) -> CB | U72: Venta | V72: =VLOOKUP($R72,'Mapa Oficinas'!$A$7:$C$46,2,FALSE) -> CABA | W72: =VLOOKUP($R72,'Mapa Oficinas'!$A$7:$C$46,3,FALSE) -> Barrio Parque
A73: 46078 | B73: =YEAR($A73) -> 2026 | C73: =MONTH($A73) -> 2 | D73: Boticelli 4719 | E73: 1 | F73: Boticelli 4719 | G73: Realizado | H73: AR MercadoLibre | I73: 38000 | J73: 39000 | K73: =IF(J73<'Mapa Oficinas'!$I$21,0,IF(J73>'Mapa Oficinas'!$I$20,0,1)) -> 0 | L73: Dólares | M73: Dólares | N73: Boticelli 4719 | O73: Argentina | G.B.A. Zona Norte | Pilar | P73: Departamento | Q73: 2 | R73: Lion Team | S73: Propia (Único Asesor) | T73: =VLOOKUP(S73,'Mapa Oficinas'!$H$7:$I$16,2,FALSE) -> CB | U73: Venta | V73: =VLOOKUP($R73,'Mapa Oficinas'!$A$7:$C$46,2,FALSE) -> CABA | W73: =VLOOKUP($R73,'Mapa Oficinas'!$A$7:$C$46,3,FALSE) -> Villa Urquiza
A74: 45996 | B74: =YEAR($A74) -> 2025 | C74: =MONTH($A74) -> 12 | D74: INCLAN 4278 | E74: 1 | F74: INCLAN 4278 | G74: Realizado | H74: AR ZonaProp | I74: 39500 | J74: 39500 | K74: =IF(J74<'Mapa Oficinas'!$I$21,0,IF(J74>'Mapa Oficinas'!$I$20,0,1)) -> 0 | L74: Dólares | M74: Dólares | N74: INCLAN 4278 | O74: Argentina | Capital Federal | Boedo | P74: Departamento | Q74: 1 | R74: Lion Team Norte | S74: (Interior) Compartida Fuera de la Red Búsqueda | T74: =VLOOKUP(S74,'Mapa Oficinas'!$H$7:$I$16,2,FALSE) -> Otra Red Búsqueda | U74: Venta | V74: =VLOOKUP($R74,'Mapa Oficinas'!$A$7:$C$46,2,FALSE) -> Zona Norte (GBA) | W74: =VLOOKUP($R74,'Mapa Oficinas'!$A$7:$C$46,3,FALSE) -> Vicente López
A75: 46003 | B75: =YEAR($A75) -> 2025 | C75: =MONTH($A75) -> 12 | D75: CAP6834181 | E75: 1 | F75: Departamento - San Salvador De Jujuy | G75: Realizado | H75: Conocido | I75: 42500 | J75: 39500 | K75: =IF(J75<'Mapa Oficinas'!$I$21,0,IF(J75>'Mapa Oficinas'!$I$20,0,1)) -> 0 | L75: Dólares | M75: Dólares | N75: Av. Illia al 600 | O75: Argentina | Jujuy | Dr Manuel Belgrano | San Salvador De Jujuy | P75: Departamento | Q75: 2 | R75: Plaza | S75: Compartida en Oficina (Dos Asesores) | T75: =VLOOKUP(S75,'Mapa Oficinas'!$H$7:$I$16,2,FALSE) -> CB | U75: Venta | V75: =VLOOKUP($R75,'Mapa Oficinas'!$A$7:$C$46,2,FALSE) -> Interior - Jujuy | W75: =VLOOKUP($R75,'Mapa Oficinas'!$A$7:$C$46,3,FALSE) -> Capital Jujuy
A76: 45777 | B76: =YEAR($A76) -> 2025 | C76: =MONTH($A76) -> 4 | E76: 1 | F76: LOTE EN VENTA , MASCHWITZ | G76: Realizado | H76: AR ZonaProp | I76: 39500 | J76: 39500 | K76: =IF(J76<'Mapa Oficinas'!$I$21,0,IF(J76>'Mapa Oficinas'!$I$20,0,1)) -> 0 | L76: Dólares | M76: Dólares | N76: LAMBARE 448 | O76: Argentina | G.B.A. Zona Norte | Escobar | Ingeniero Maschwitz | Zelaya | P76: Terreno | Q76: 2 | R76: Puerto Norte | S76: Propia (Único Asesor) | T76: =VLOOKUP(S76,'Mapa Oficinas'!$H$7:$I$16,2,FALSE) -> CB | U76: Venta | V76: =VLOOKUP($R76,'Mapa Oficinas'!$A$7:$C$46,2,FALSE) -> Zona Norte (GBA) | W76: =VLOOKUP($R76,'Mapa Oficinas'!$A$7:$C$46,3,FALSE) -> Nordelta
A77: 45741 | B77: =YEAR($A77) -> 2025 | C77: =MONTH($A77) -> 3 | D77: CLA6284234 | E77: 1 | F77: Terreno en calpa | G77: Realizado | H77: AR ZonaProp | I77: 52000 | J77: 39800 | K77: =IF(J77<'Mapa Oficinas'!$I$21,0,IF(J77>'Mapa Oficinas'!$I$20,0,1)) -> 0 | L77: Dólares | M77: Dólares | N77: TERRENO EN CALPA NEUQUEN (CERCA DE LA CONFLUENCIA DE LOS RIOS) | O77: Argentina | Neuquen | Confluencia | Neuquen | P77: Terreno | Q77: 2 | R77: Sensus | S77: Propia (Único Asesor) | T77: =VLOOKUP(S77,'Mapa Oficinas'!$H$7:$I$16,2,FALSE) -> CB | U77: Venta | V77: =VLOOKUP($R77,'Mapa Oficinas'!$A$7:$C$46,2,FALSE) -> Interior - Neuquén | W77: =VLOOKUP($R77,'Mapa Oficinas'!$A$7:$C$46,3,FALSE) -> Capital Neuquén
A78: 45770 | B78: =YEAR($A78) -> 2025 | C78: =MONTH($A78) -> 4 | D78: CAP6880903 | E78: 1 | F78: Departamento en venta bajo la viña | G78: Realizado | H78: Conocido | I78: 39900 | J78: 39900 | K78: =IF(J78<'Mapa Oficinas'!$I$21,0,IF(J78>'Mapa Oficinas'!$I$20,0,1)) -> 0 | L78: Dólares | M78: Dólares | N78: bajo la viña calle raul noceti | O78: Argentina | Jujuy | Dr Manuel Belgrano | San Salvador De Jujuy | Bajo La Viña | P78: Departamento | Q78: 2 | R78: Plaza | S78: Propia (Único Asesor) | T78: =VLOOKUP(S78,'Mapa Oficinas'!$H$7:$I$16,2,FALSE) -> CB | U78: Venta | V78: =VLOOKUP($R78,'Mapa Oficinas'!$A$7:$C$46,2,FALSE) -> Interior - Jujuy | W78: =VLOOKUP($R78,'Mapa Oficinas'!$A$7:$C$46,3,FALSE) -> Capital Jujuy
A79: 45772 | B79: =YEAR($A79) -> 2025 | C79: =MONTH($A79) -> 4 | E79: 1 | F79: Op. con Finca Sur. Lote en Piedra San Francisco | G79: Realizado | H79: Conocido | I79: 40000 | J79: 40000 | K79: =IF(J79<'Mapa Oficinas'!$I$21,0,IF(J79>'Mapa Oficinas'!$I$20,0,1)) -> 0 | L79: Dólares | M79: Dólares | O79: Argentina | Neuquen | Lacar | San Martin De Los Andes | P79: Terreno | Q79: 1 | R79: Patagonia Lakes SMA | S79: (Interior) Compartida Fuera de la Red Búsqueda | T79: =VLOOKUP(S79,'Mapa Oficinas'!$H$7:$I$16,2,FALSE) -> Otra Red Búsqueda | U79: Venta | V79: =VLOOKUP($R79,'Mapa Oficinas'!$A$7:$C$46,2,FALSE) -> Interior - Neuquén | W79: =VLOOKUP($R79,'Mapa Oficinas'!$A$7:$C$46,3,FALSE) -> San Martín de los Andes
A80: 45867 | B80: =YEAR($A80) -> 2025 | C80: =MONTH($A80) -> 7 | D80: CHO4565523 | E80: 1 | F80: Casa - Guadalupe oeste | G80: Realizado | H80: AR ZonaProp | I80: 41000 | J80: 40000 | K80: =IF(J80<'Mapa Oficinas'!$I$21,0,IF(J80>'Mapa Oficinas'!$I$20,0,1)) -> 0 | L80: Dólares | M80: Dólares | N80: OPORTUNIDAD !! CASA CON PATIO SECO Y COCHERA!! GUADALUPE "O" | O80: Argentina | Santa Fe | La Capital | Santa Fe | Guadalupe | P80: Casa | Q80: 1 | R80: De la Veracruz | S80: (Interior) Compartida Fuera de la Red Captación Propia | T80: =VLOOKUP(S80,'Mapa Oficinas'!$H$7:$I$16,2,FALSE) -> Otra Red Captación | U80: Venta | V80: =VLOOKUP($R80,'Mapa Oficinas'!$A$7:$C$46,2,FALSE) -> Interior - Santa Fe | W80: =VLOOKUP($R80,'Mapa Oficinas'!$A$7:$C$46,3,FALSE) -> Capital Santa Fe
A81: 45946 | B81: =YEAR($A81) -> 2025 | C81: =MONTH($A81) -> 10 | D81: CHO7112738 | E81: 1 | F81: Metan | Casa | 4 habitaciones | terreno 566 m2 | G81: Realizado | H81: Facebook | I81: 52000 | J81: 40000 | K81: =IF(J81<'Mapa Oficinas'!$I$21,0,IF(J81>'Mapa Oficinas'!$I$20,0,1)) -> 0 | L81: Dólares | M81: Dólares | N81: Calle Salta (este) al 100 - Metan | O81: Argentina | Salta | Metan | Metan | P81: Casa | Q81: 1 | R81: Realty Group | S81: (Interior) Compartida Fuera de la Red Captación Propia | T81: =VLOOKUP(S81,'Mapa Oficinas'!$H$7:$I$16,2,FALSE) -> Otra Red Captación | U81: Venta | V81: =VLOOKUP($R81,'Mapa Oficinas'!$A$7:$C$46,2,FALSE) -> Interior - Salta | W81: =VLOOKUP($R81,'Mapa Oficinas'!$A$7:$C$46,3,FALSE) -> San Lorenzo Chico
A82: 45771 | B82: =YEAR($A82) -> 2025 | C82: =MONTH($A82) -> 4 | D82: CAP6678664 | E82: 1 | F82: Departamento en venta en gran lote a 100 mts de Avda A del Valle | G82: Realizado | H82: Conocido | I82: 40000 | J82: 40000 | K82: =IF(J82<'Mapa Oficinas'!$I$21,0,IF(J82>'Mapa Oficinas'!$I$20,0,1)) -> 0 | L82: Dólares | M82: Dólares | N82: Esmeralda al 2500 OPORTUNIDAD lote con departamento al fondo | O82: Argentina | Santa Fe | La Capital | P82: Departamento | Q82: 2 | R82: De la Veracruz | S82: Compartida en Oficina (Dos Asesores) | T82: =VLOOKUP(S82,'Mapa Oficinas'!$H$7:$I$16,2,FALSE) -> CB | U82: Venta | V82: =VLOOKUP($R82,'Mapa Oficinas'!$A$7:$C$46,2,FALSE) -> Interior - Santa Fe | W82: =VLOOKUP($R82,'Mapa Oficinas'!$A$7:$C$46,3,FALSE) -> Capital Santa Fe
A83: 45814 | B83: =YEAR($A83) -> 2025 | C83: =MONTH($A83) -> 6 | D83: CAP6974906 | E83: 1 | F83: Departamento en Chijra | G83: Realizado | H83: Conocido | I83: 43000 | J83: 40000 | K83: =IF(J83<'Mapa Oficinas'!$I$21,0,IF(J83>'Mapa Oficinas'!$I$20,0,1)) -> 0 | L83: Dólares | M83: Dólares | N83: Calle El Pensamiento al 700 | O83: Argentina | Jujuy | Dr Manuel Belgrano | San Salvador De Jujuy | Chijra | P83: Departamento | Q83: 2 | R83: Plaza | S83: Compartida en Oficina (Dos Asesores) | T83: =VLOOKUP(S83,'Mapa Oficinas'!$H$7:$I$16,2,FALSE) -> CB | U83: Venta | V83: =VLOOKUP($R83,'Mapa Oficinas'!$A$7:$C$46,2,FALSE) -> Interior - Jujuy | W83: =VLOOKUP($R83,'Mapa Oficinas'!$A$7:$C$46,3,FALSE) -> Capital Jujuy
A84: 45826 | B84: =YEAR($A84) -> 2025 | C84: =MONTH($A84) -> 6 | E84: 1 | F84: UF 11 Loteo A Loteo Quetrihue | G84: Realizado | H84: Referido | I84: 40000 | J84: 40000 | K84: =IF(J84<'Mapa Oficinas'!$I$21,0,IF(J84>'Mapa Oficinas'!$I$20,0,1)) -> 0 | L84: Dólares | M84: Dólares | N84: Bv. Quetrihue y Amancay | O84: Argentina | Neuquen | Villa La Angostura | Selva Triste | P84: Terreno | Q84: 2 | R84: Patagonia Lakes VLA | S84: Compartida en Oficina (Dos Asesores) | T84: =VLOOKUP(S84,'Mapa Oficinas'!$H$7:$I$16,2,FALSE) -> CB | U84: Venta | V84: =VLOOKUP($R84,'Mapa Oficinas'!$A$7:$C$46,2,FALSE) -> Interior - Neuquén | W84: =VLOOKUP($R84,'Mapa Oficinas'!$A$7:$C$46,3,FALSE) -> Villa La Angostura
A85: 45898 | B85: =YEAR($A85) -> 2025 | C85: =MONTH($A85) -> 8 | D85: CLA6528978 | E85: 1 | F85: VENTA Lote/Terreno 295,6 m2 Lomas del Correntoso, Villa La Angostura | G85: Realizado | H85: Conocido | I85: 40000 | J85: 40000 | K85: =IF(J85<'Mapa Oficinas'!$I$21,0,IF(J85>'Mapa Oficinas'!$I$20,0,1)) -> 0 | L85: Dólares | M85: Dólares | N85: Del Radal al 600 | O85: Argentina | Neuquen | Villa La Angostura | Lomas De Correntoso | P85: Terreno | Q85: 2 | R85: Patagonia Lakes VLA | S85: Compartida en Oficina (Dos Asesores) | T85: =VLOOKUP(S85,'Mapa Oficinas'!$H$7:$I$16,2,FALSE) -> CB | U85: Venta | V85: =VLOOKUP($R85,'Mapa Oficinas'!$A$7:$C$46,2,FALSE) -> Interior - Neuquén | W85: =VLOOKUP($R85,'Mapa Oficinas'!$A$7:$C$46,3,FALSE) -> Villa La Angostura
A86: 45898 | B86: =YEAR($A86) -> 2025 | C86: =MONTH($A86) -> 8 | D86: CLO6651445 | E86: 1 | F86: VENTA Local Comercial 27.5m² UF1 Cordones de Chapelco San Martin de Los Andes | G86: Realizado | H86: Referido | I86: 40000 | J86: 40000 | K86: =IF(J86<'Mapa Oficinas'!$I$21,0,IF(J86>'Mapa Oficinas'!$I$20,0,1)) -> 0 | L86: Dólares | M86: Dólares | N86: Cerro La Virgen - Cordones de Chapelco | O86: Argentina | Neuquen | Lacar | San Martin De Los Andes | P86: Local Comercial | Q86: 2 | R86: Patagonia Lakes SMA | S86: Compartida en Oficina (Dos Asesores) | T86: =VLOOKUP(S86,'Mapa Oficinas'!$H$7:$I$16,2,FALSE) -> CB | U86: Venta | V86: =VLOOKUP($R86,'Mapa Oficinas'!$A$7:$C$46,2,FALSE) -> Interior - Neuquén | W86: =VLOOKUP($R86,'Mapa Oficinas'!$A$7:$C$46,3,FALSE) -> San Martín de los Andes
A87: 45994 | B87: =YEAR($A87) -> 2025 | C87: =MONTH($A87) -> 12 | D87: Tizado | E87: 1 | F87: Antiguo Camino Manzana 595 UF 2 Parcela 6 | G87: Realizado | H87: Teléfono | I87: 36881 | J87: 40000 | K87: =IF(J87<'Mapa Oficinas'!$I$21,0,IF(J87>'Mapa Oficinas'!$I$20,0,1)) -> 0 | L87: Dólares | M87: Dólares | O87: Argentina | Rio Negro | Bariloche | P87: Terreno | Q87: 2 | R87: Patagonia Lakes BRC | S87: Compartida en Oficina (Dos Asesores) | T87: =VLOOKUP(S87,'Mapa Oficinas'!$H$7:$I$16,2,FALSE) -> CB | U87: Venta | V87: =VLOOKUP($R87,'Mapa Oficinas'!$A$7:$C$46,2,FALSE) -> Interior - Río Negro | W87: =VLOOKUP($R87,'Mapa Oficinas'!$A$7:$C$46,3,FALSE) -> Bariloche
A88: 46034 | B88: =YEAR($A88) -> 2026 | C88: =MONTH($A88) -> 1 | D88: CBA59141 LA7558630 | E88: 1 | F88: VENTA Lote/terreno 407,04 m2, Loteo Quetrihue, Selvana Triste, Villa la Angostura | G88: Realizado | H88: Web Coldwell-Banker | I88: 35000 | J88: 40000 | K88: =IF(J88<'Mapa Oficinas'!$I$21,0,IF(J88>'Mapa Oficinas'!$I$20,0,1)) -> 0 | L88: Dólares | M88: Dólares | N88: Blvd Quetrihue y Blvd Amancay | O88: Argentina | Neuquen | Villa La Angostura | Selva Triste | P88: Terreno | Q88: 2 | R88: Patagonia Lakes VLA | S88: Compartida en Oficina (Dos Asesores) | T88: =VLOOKUP(S88,'Mapa Oficinas'!$H$7:$I$16,2,FALSE) -> CB | U88: Venta | V88: =VLOOKUP($R88,'Mapa Oficinas'!$A$7:$C$46,2,FALSE) -> Interior - Neuquén | W88: =VLOOKUP($R88,'Mapa Oficinas'!$A$7:$C$46,3,FALSE) -> Villa La Angostura
A89: 45776 | B89: =YEAR($A89) -> 2025 | C89: =MONTH($A89) -> 4 | E89: 0 | F89: UF 14 Loteo B Quetrihue | G89: Realizado | H89: Salón | I89: 40000 | J89: 40000 | K89: =IF(J89<'Mapa Oficinas'!$I$21,0,IF(J89>'Mapa Oficinas'!$I$20,0,1)) -> 0 | L89: Dólares | M89: Dólares | N89: Bv. Quetrihue y Amancay | O89: Argentina | Neuquen | Villa La Angostura | P89: Terreno | Q89: 2 | R89: Patagonia Lakes VLA | S89: Compartida en Oficina (Dos Asesores) | T89: =VLOOKUP(S89,'Mapa Oficinas'!$H$7:$I$16,2,FALSE) -> CB | U89: Venta | V89: =VLOOKUP($R89,'Mapa Oficinas'!$A$7:$C$46,2,FALSE) -> Interior - Neuquén | W89: =VLOOKUP($R89,'Mapa Oficinas'!$A$7:$C$46,3,FALSE) -> Villa La Angostura
A90: 45819 | B90: =YEAR($A90) -> 2025 | C90: =MONTH($A90) -> 6 | E90: 0 | F90: UF 10 Loteo A Loteo Quetrihue | G90: Realizado | H90: Conocido | I90: 40000 | J90: 40000 | K90: =IF(J90<'Mapa Oficinas'!$I$21,0,IF(J90>'Mapa Oficinas'!$I$20,0,1)) -> 0 | L90: Dólares | M90: Dólares | N90: Bv. Quetrihue y Amancay | O90: Argentina | Neuquen | Villa La Angostura | Selva Triste | P90: Terreno | Q90: 2 | R90: Patagonia Lakes VLA | S90: Compartida en Oficina (Dos Asesores) | T90: =VLOOKUP(S90,'Mapa Oficinas'!$H$7:$I$16,2,FALSE) -> CB | U90: Venta | V90: =VLOOKUP($R90,'Mapa Oficinas'!$A$7:$C$46,2,FALSE) -> Interior - Neuquén | W90: =VLOOKUP($R90,'Mapa Oficinas'!$A$7:$C$46,3,FALSE) -> Villa La Angostura
A91: 45835 | B91: =YEAR($A91) -> 2025 | C91: =MONTH($A91) -> 6 | D91: CAP7097865 | E91: 1 | F91: Departamento en Alquiler 2 ambientes calle 9 e/ 47 y diagonal 74 N° 731 3 C | La Plata | G91: Realizado | H91: Conocido | I91: 42700 | J91: 40000 | K91: =IF(J91<'Mapa Oficinas'!$I$21,0,IF(J91>'Mapa Oficinas'!$I$20,0,1)) -> 0 | L91: Dólares | M91: Dólares | N91: Alquiler Dpto 2 ambientes calle 9 e/ 47 y diagonal 74 N° 731 Piso 3 C | La Plata | O91: Argentina | G.B.A. Zona Sur | La Plata | La Plata | P91: Departamento | Q91: 1 | R91: Golden Team | S91: Compartida Fuera de la Red Búsqueda | T91: =VLOOKUP(S91,'Mapa Oficinas'!$H$7:$I$16,2,FALSE) -> Otra Red Búsqueda | U91: Venta | V91: =VLOOKUP($R91,'Mapa Oficinas'!$A$7:$C$46,2,FALSE) -> Zona Sur (GBA) | W91: =VLOOKUP($R91,'Mapa Oficinas'!$A$7:$C$46,3,FALSE) -> La Plata
A92: 45777 | B92: =YEAR($A92) -> 2025 | C92: =MONTH($A92) -> 4 | D92: CAP6253711 | E92: 1 | F92: Departamento en venta | G92: Realizado | H92: AR ZonaProp | I92: 41400 | J92: 40000 | K92: =IF(J92<'Mapa Oficinas'!$I$21,0,IF(J92>'Mapa Oficinas'!$I$20,0,1)) -> 0 | L92: Dólares | M92: Dólares | N92: Av luro al 2500 | O92: Argentina | Costa Atlantica | Mar Del Plata | P92: Departamento | Q92: 2 | R92: Horizon Group | S92: Compartida Fuera de la Red Captación Propia | T92: =VLOOKUP(S92,'Mapa Oficinas'!$H$7:$I$16,2,FALSE) -> Otra Red Captación | U92: Venta | V92: =VLOOKUP($R92,'Mapa Oficinas'!$A$7:$C$46,2,FALSE) -> CABA | W92: =VLOOKUP($R92,'Mapa Oficinas'!$A$7:$C$46,3,FALSE) -> Núñez
A93: 45667 | B93: =YEAR($A93) -> 2025 | C93: =MONTH($A93) -> 1 | D93: CAP6403040 | E93: 1 | F93: DEPARTAMENTO en 1 y 57 LA PLATA | G93: Realizado | H93: Referido | I93: 45000 | J93: 40000 | K93: =IF(J93<'Mapa Oficinas'!$I$21,0,IF(J93>'Mapa Oficinas'!$I$20,0,1)) -> 0 | L93: Dólares | M93: Dólares | N93: DEPARTAMENTO 1 dormitorio en 1 y 57 | O93: Argentina | G.B.A. Zona Sur | La Plata | La Plata | P93: Departamento | Q93: 2 | R93: Golden Team | S93: Propia (Único Asesor) | T93: =VLOOKUP(S93,'Mapa Oficinas'!$H$7:$I$16,2,FALSE) -> CB | U93: Venta | V93: =VLOOKUP($R93,'Mapa Oficinas'!$A$7:$C$46,2,FALSE) -> Zona Sur (GBA) | W93: =VLOOKUP($R93,'Mapa Oficinas'!$A$7:$C$46,3,FALSE) -> La Plata
A94: 45674 | B94: =YEAR($A94) -> 2025 | C94: =MONTH($A94) -> 1 | D94: CLA6695688 | E94: 1 | F94: VENTA Lote/Terreno 1.651,30m2 Las Marías del Valle, Club de campo, San Martín de los Andes | G94: Realizado | H94: Teléfono | I94: 50000 | J94: 40000 | K94: =IF(J94<'Mapa Oficinas'!$I$21,0,IF(J94>'Mapa Oficinas'!$I$20,0,1)) -> 0 | L94: Dólares | M94: Dólares | N94: RN 40 al 2200 | O94: Argentina | Neuquen | Lacar | San Martin De Los Andes | Las Marias Del Valle | P94: Terreno | Q94: 2 | R94: Patagonia Lakes SMA | S94: Propia (Único Asesor) | T94: =VLOOKUP(S94,'Mapa Oficinas'!$H$7:$I$16,2,FALSE) -> CB | U94: Venta | V94: =VLOOKUP($R94,'Mapa Oficinas'!$A$7:$C$46,2,FALSE) -> Interior - Neuquén | W94: =VLOOKUP($R94,'Mapa Oficinas'!$A$7:$C$46,3,FALSE) -> San Martín de los Andes
A95: 45869 | B95: =YEAR($A95) -> 2025 | C95: =MONTH($A95) -> 7 | D95: CAP6898647 | E95: 1 | F95: Departamento en REMEDIOS DE ESCALADA- LANUS | G95: Realizado | H95: AR ZonaProp | I95: 45000 | J95: 40000 | K95: =IF(J95<'Mapa Oficinas'!$I$21,0,IF(J95>'Mapa Oficinas'!$I$20,0,1)) -> 0 | L95: Dólares | M95: Dólares | N95: Doctor Melo al 5000 | O95: Argentina | G.B.A. Zona Sur | Lanús | Remedios De Escalada | P95: Departamento | Q95: 2 | R95: Destino | S95: Propia (Único Asesor) | T95: =VLOOKUP(S95,'Mapa Oficinas'!$H$7:$I$16,2,FALSE) -> CB | U95: Venta | V95: =VLOOKUP($R95,'Mapa Oficinas'!$A$7:$C$46,2,FALSE) -> CABA | W95: =VLOOKUP($R95,'Mapa Oficinas'!$A$7:$C$46,3,FALSE) -> Recoleta
A96: 45882 | B96: =YEAR($A96) -> 2025 | C96: =MONTH($A96) -> 8 | D96: bouchard 3273 | E96: 1 | F96: bouchard 3273 vte lopez | G96: Realizado | H96: AR ZonaProp | I96: 45000 | J96: 40000 | K96: =IF(J96<'Mapa Oficinas'!$I$21,0,IF(J96>'Mapa Oficinas'!$I$20,0,1)) -> 0 | L96: Dólares | M96: Dólares | N96: bouchard 3273 olivos | O96: Argentina | G.B.A. Zona Norte | Vicente López | Olivos | P96: Local Comercial | Q96: 2 | R96: Concept | S96: Propia (Único Asesor) | T96: =VLOOKUP(S96,'Mapa Oficinas'!$H$7:$I$16,2,FALSE) -> CB | U96: Venta | V96: =VLOOKUP($R96,'Mapa Oficinas'!$A$7:$C$46,2,FALSE) -> Zona Norte (GBA) | W96: =VLOOKUP($R96,'Mapa Oficinas'!$A$7:$C$46,3,FALSE) -> Tigre
A97: 45933 | B97: =YEAR($A97) -> 2025 | C97: =MONTH($A97) -> 10 | D97: CPH7293621 | E97: 1 | F97: Venta permuta PH Barracas apto credito dos ambientes sin expensas con patio | G97: Realizado | H97: AR ZonaProp | I97: 45000 | J97: 40000 | K97: =IF(J97<'Mapa Oficinas'!$I$21,0,IF(J97>'Mapa Oficinas'!$I$20,0,1)) -> 0 | L97: Dólares | M97: Dólares | N97: Santa Magdalena al 783 | O97: Argentina | Capital Federal | Barracas | P97: PH | Q97: 2 | R97: Lion Team | S97: Propia (Único Asesor) | T97: =VLOOKUP(S97,'Mapa Oficinas'!$H$7:$I$16,2,FALSE) -> CB | U97: Venta | V97: =VLOOKUP($R97,'Mapa Oficinas'!$A$7:$C$46,2,FALSE) -> CABA | W97: =VLOOKUP($R97,'Mapa Oficinas'!$A$7:$C$46,3,FALSE) -> Villa Urquiza
A98: 45946 | B98: =YEAR($A98) -> 2025 | C98: =MONTH($A98) -> 10 | D98: CWE6870466 | E98: 1 | F98: Quinta en San Patricio del Chañar | G98: Realizado | H98: AR ZonaProp | I98: 48000 | J98: 40000 | K98: =IF(J98<'Mapa Oficinas'!$I$21,0,IF(J98>'Mapa Oficinas'!$I$20,0,1)) -> 0 | L98: Dólares | M98: Dólares | N98: Casa Quinta, 4.800 m2, ruta 7, S.P. Chañar- Añelo- Neuquén | O98: Argentina | Neuquen | Añelo | San Patricio Del Chañar | P98: CASA | Q98: 2 | R98: Sensus | S98: Propia (Único Asesor) | T98: =VLOOKUP(S98,'Mapa Oficinas'!$H$7:$I$16,2,FALSE) -> CB | U98: Venta | V98: =VLOOKUP($R98,'Mapa Oficinas'!$A$7:$C$46,2,FALSE) -> Interior - Neuquén | W98: =VLOOKUP($R98,'Mapa Oficinas'!$A$7:$C$46,3,FALSE) -> Capital Neuquén
A99: 45954 | B99: =YEAR($A99) -> 2025 | C99: =MONTH($A99) -> 10 | D99: CFA6928177 | E99: 1 | F99: Finca de 8 has, con casa y galpón, a 18 minutos de San Rafael! | G99: Realizado | H99: Teléfono | I99: 45000 | J99: 40000 | K99: =IF(J99<'Mapa Oficinas'!$I$21,0,IF(J99>'Mapa Oficinas'!$I$20,0,1)) -> 0 | L99: Dólares | M99: Dólares | N99: Sardini y calle 4 0 | O99: Argentina | Mendoza | San Rafael | San Rafael | P99: Granja | Q99: 2 | R99: Andes | S99: Propia (Único Asesor) | T99: =VLOOKUP(S99,'Mapa Oficinas'!$H$7:$I$16,2,FALSE) -> CB | U99: Venta | V99: =VLOOKUP($R99,'Mapa Oficinas'!$A$7:$C$46,2,FALSE) -> Interior - Mendoza | W99: =VLOOKUP($R99,'Mapa Oficinas'!$A$7:$C$46,3,FALSE) -> San Rafael
A100: 46042 | B100: =YEAR($A100) -> 2026 | C100: =MONTH($A100) -> 1 | D100: CPH7360399 | E100: 1 | F100: PH 3 Ambientes en Venta en San Martin | G100: Realizado | H100: AR ZonaProp | I100: 42000 | J100: 40000 | K100: =IF(J100<'Mapa Oficinas'!$I$21,0,IF(J100>'Mapa Oficinas'!$I$20,0,1)) -> 0 | L100: Dólares | M100: Dólares | N100: Lincoln al 4300 | O100: Argentina | G.B.A. Zona Norte | General San Martin | San Martin | P100: PH | Q100: 2 | R100: Audacity | S100: Propia (Único Asesor) | T100: =VLOOKUP(S100,'Mapa Oficinas'!$H$7:$I$16,2,FALSE) -> CB | U100: Venta | V100: =VLOOKUP($R100,'Mapa Oficinas'!$A$7:$C$46,2,FALSE) -> Zona Oeste (GBA) | W100: =VLOOKUP($R100,'Mapa Oficinas'!$A$7:$C$46,3,FALSE) -> Parque Leloir
A101: 46058 | B101: =YEAR($A101) -> 2026 | C101: =MONTH($A101) -> 2 | D101: 110Beti | E101: 1 | F101: Terreno Los Duendes | G101: Realizado | H101: Cartel | I101: 55000 | J101: 40000 | K101: =IF(J101<'Mapa Oficinas'!$I$21,0,IF(J101>'Mapa Oficinas'!$I$20,0,1)) -> 0 | L101: Dólares | M101: Dólares | N101: Los duendes 2763 | O101: Argentina | Santa Fe | La Capital | San Jose Del Rincon | Villa California | P101: Terreno | Q101: 2 | R101: De la Veracruz | S101: Propia (Único Asesor) | T101: =VLOOKUP(S101,'Mapa Oficinas'!$H$7:$I$16,2,FALSE) -> CB | U101: Venta | V101: =VLOOKUP($R101,'Mapa Oficinas'!$A$7:$C$46,2,FALSE) -> Interior - Santa Fe | W101: =VLOOKUP($R101,'Mapa Oficinas'!$A$7:$C$46,3,FALSE) -> Capital Santa Fe
A102: 46076 | B102: =YEAR($A102) -> 2026 | C102: =MONTH($A102) -> 2 | D102: CLA7241558 | E102: 1 | F102: Terreno en El Cerrito | G102: Realizado | H102: UY MercadoLibre | I102: 45000 | J102: 40000 | K102: =IF(J102<'Mapa Oficinas'!$I$21,0,IF(J102>'Mapa Oficinas'!$I$20,0,1)) -> 0 | L102: Dólares | M102: Dólares | N102: ADOLFO CALLE al 5100 | O102: Argentina | Mendoza | San Rafael | El Cerrito | P102: Terreno | Q102: 2 | R102: Andes | S102: Propia (Único Asesor) | T102: =VLOOKUP(S102,'Mapa Oficinas'!$H$7:$I$16,2,FALSE) -> CB | U102: Venta | V102: =VLOOKUP($R102,'Mapa Oficinas'!$A$7:$C$46,2,FALSE) -> Interior - Mendoza | W102: =VLOOKUP($R102,'Mapa Oficinas'!$A$7:$C$46,3,FALSE) -> San Rafael
... A122: 45824 | B122: =YEAR($A122) -> 2025 | C122: =MONTH($A122) -> 6 | D122: CHO6429916 | E122: 1 | F122: VENTA Casa 2habitaciones 72m2 Lote 180m2 PH Valle Chapelco a terminar Chacra 26 San Martín de los Andes | G122: Realizado | H122: Conocido | I122: 52000 | J122: 42000 | K122: =IF(J122<'Mapa Oficinas'!$I$21,0,IF(J122>'Mapa Oficinas'!$I$20,0,1)) -> 0 | L122: Dólares | M122: Dólares | N122: Lote 3 A, Mza 18, | O122: Argentina | Neuquen | Lacar | San Martin De Los Andes | Chacra 28 | P122: Casa | Q122: 2 | R122: Patagonia Lakes SMA | S122: Propia (Único Asesor) | T122: =VLOOKUP(S122,'Mapa Oficinas'!$H$7:$I$16,2,FALSE) -> CB | U122: Venta | V122: =VLOOKUP($R122,'Mapa Oficinas'!$A$7:$C$46,2,FALSE) -> Interior - Neuquén | W122: =VLOOKUP($R122,'Mapa Oficinas'!$A$7:$C$46,3,FALSE) -> San Martín de los Andes
...

Sheet Mapa Oficinas
A1: Mapeo Oficinas CB → Zona → Localidad
A4: Referencia del PDF oficial Oficinas-CB-ARG-UY-PY.pdf
A6: Oficina | B6: Zona CB | C6: Localidad CB | D6: Operaciones en dataset
A7: Seniority | B7: CABA | C7: Barrio Parque | H7: (Interior) Compartida Fuera de la Red Búsqueda | I7: Otra Red Búsqueda
A8: Ser | B8: CABA | C8: Belgrano | H8: (Interior) Compartida Fuera de la Red Captación Propia | I8: Otra Red Captación
A9: Space BA | B9: CABA | C9: Belgrano | H9: Compartida en Oficina (Dos Asesores) | I9: CB
A10: Desiderio | B10: CABA | C10: Caballito | H10: Compartida en Red (50%) | I10: CB
A11: Goyena | B11: CABA | C11: Caballito | H11: Compartida Fuera de la Red Búsqueda | I11: Otra Red Búsqueda
A12: Database | B12: CABA | C12: Núñez | H12: Compartida Fuera de la Red Captación Propia | I12: Otra Red Captación
A13: Haka | B13: CABA | C13: Núñez | H13: Master | I13: CB
A14: Horizon Group | B14: CABA | C14: Núñez | H14: Profesional Referenciador (30%) | I14: CB
A15: Wings | B15: CABA | C15: Núñez | H15: Profesional Referido (70%) | I15: CB
A16: Livello | B16: CABA | C16: Palermo | H16: Propia (Único Asesor) | I16: CB
A17: Niceto | B17: CABA | C17: Palermo
A18: Notable | B18: CABA | C18: Palermo
A19: Seniority Plus | B19: CABA | C19: Palermo | J19: 0.3
A20: Grupo Elite | B20: CABA | C20: Puerto Madero | H20: RANGO SUPERIOR | I20: 1000000 | J20: =I20*J19 -> 300000
A21: Destino | B21: CABA | C21: Recoleta | H21: RANGO INFERIOR | I21: 69999 | J21: =I21*J19 -> 20999.7
A22: Destino II | B22: CABA | C22: Recoleta
A23: Beyker | B23: CABA | C23: Retiro
A24: Lion Team | B24: CABA | C24: Villa Urquiza
A25: Plaza | B25: Interior - Jujuy | C25: Capital Jujuy
A26: Cuyo Real | B26: Interior - Mendoza | C26: Capital Mendoza
A27: Impacto Pro | B27: Interior - Mendoza | C27: Godoy Cruz
A28: Andes | B28: Interior - Mendoza | C28: San Rafael
A29: Sensus | B29: Interior - Neuquén | C29: Capital Neuquén
A30: Patagonia Lakes SMA | B30: Interior - Neuquén | C30: San Martín de los Andes
A31: Patagonia Lakes VLA | B31: Interior - Neuquén | C31: Villa La Angostura
A32: Patagonia Lakes BRC | B32: Interior - Río Negro | C32: Bariloche
A33: Realty Group | B33: Interior - Salta | C33: San Lorenzo Chico
... A46: Golden Team | B46: Zona Sur (GBA) | C46: La Plata

Sheet DESCARTADO
A2: 45943 | B2: 9102025 | D2: Reserva Venta Flor Lote Dos Valles A25 | E2: Realizado | F2: Teléfono | G2: 43000 | H2: 750 | I2: Dólares | J2: Dólares | L2: Argentina | Rio Negro | Bariloche | San Carlos De Bariloche | M2: Terreno | N2: 1 | O2: Patagonia Lakes BRC | P2: Master | Q2: Venta
A3: 45798 | B3: VCO59064 AP6619653 | D3: Departamento en Altos de Maschwitz - 2 AMB con Jardín | E3: Realizado | F3: AR ZonaProp | G3: 102194 | H3: 1000 | I3: Dólares | J3: Dólares | K3: Departamento en Altos de Maschwitz - 2 AMB con Jardín | L3: Argentina | G.B.A. Zona Norte | Escobar | Ingeniero Maschwitz | Altos de Maschwitz | M3: Departamento | N3: 2 | O3: Puerto Norte | P3: Compartida en Oficina (Dos Asesores) | Q3: Venta
A4: 45992 | B4: CAP7356426 | D4: Departamento en Las Heras | E4: Realizado | F4: AR ZonaProp | G4: 31900 | H4: 2000 | I4: Dólares | J4: Local | K4: Adolfo Calle y Bombal | L4: Argentina | Mendoza | Las Heras | M4: Departamento | N4: 2 | O4: Cuyo Real | P4: Propia (Único Asesor) | Q4: Venta
A5: 45706 | B5: VAP6607532 | D5: Departamento 3 AMB en Alquiler en Infinity Nordelta | E5: Realizado | F5: AR ZonaProp | G5: 800 | H5: 3000 | I5: Dólares | J5: Dólares | K5: Departamento 3 AMB en Alquiler en Infinity Nordelta | L5: Argentina | G.B.A. Zona Norte | Tigre | Countries/B.Cerrado (Tigre) | Nordelta | El Palmar | Infinity Residences | M5: Departamento | N5: 2 | O5: Puerto Norte | P5: Propia (Único Asesor) | Q5: Venta
A6: 45758 | B6: CLA6354054 | D6: LOTES en Barrio Estancia Kingsbroock - 122 y 612 | E6: Realizado | F6: AR ZonaProp | G6: 5200 | H6: 4500 | I6: Dólares | J6: Dólares | K6: LOTES en Barrio Estancia Kingsbroock - 122 y 612 | L6: Argentina | G.B.A. Zona Sur | La Plata | Villa Elvira | M6: Terreno | N6: 2 | O6: Golden Team | P6: Propia (Único Asesor) | Q6: Venta
A7: 45721 | B7: CLA6354054 | D7: LOTES en Barrio Estancia Kingsbroock - 122 y 612 | E7: Realizado | F7: Referido | G7: 5300 | H7: 4774 | I7: Dólares | J7: Dólares | K7: LOTES en Barrio Estancia Kingsbroock - 122 y 612 | L7: Argentina | G.B.A. Zona Sur | La Plata | Villa Elvira | M7: Terreno | N7: 2 | O7: Golden Team | P7: Propia (Único Asesor) | Q7: Venta
A8: 45992 | B8: CHO7100411 | D8: Casa en Las Heras | E8: Realizado | F8: AR ZonaProp | G8: 48000 | H8: 4840 | I8: Dólares | J8: Dólares | K8: 3 de febrero al 500 | L8: Argentina | Mendoza | Las Heras | M8: Casa | N8: 2 | O8: Cuyo Real | P8: Propia (Único Asesor) | Q8: Venta
A9: 45952 | B9: CGA7289163 | D9: Cochera en Mendoza | E9: Realizado | F9: Facebook | G9: 4900 | H9: 4900 | I9: Dólares | J9: Dólares | K9: Garibaldi al 100 | L9: Argentina | Mendoza | Capital | Mendoza | M9: Garage | N9: 2 | O9: Cuyo Real | P9: Propia (Único Asesor) | Q9: Venta
A10: 45992 | B10: CHO6734839 | D10: CASA EN VENTA VISTALBA LOTEO DON CARLOS | E10: Realizado | F10: AR ZonaProp | G10: 140000 | H10: 5000 | I10: Dólares | J10: Dólares | K10: LOTEO DON CARLOS LOS TILOS LOTE K | L10: Argentina | Mendoza | Lujan De Cuyo | Vistalba | M10: Casa | N10: 1 | O10: Cuyo Real | P10: (Interior) Compartida Fuera de la Red Búsqueda | Q10: Venta
A11: 45777 | B11: CGA6673233 | D11: Venta Cochera en Almagro | E11: Realizado | F11: AR ZonaProp | G11: 7000 | H11: 5000 | I11: Dólares | J11: Dólares | K11: Corrientes al 3800 | L11: Argentina | Capital Federal | Almagro | M11: Garage | N11: 2 | O11: Seniority | P11: Propia (Único Asesor) | Q11: Venta
A12: 45951 | B12: CAP7331334 | D12: Departamento 2 AMB en Alquiler - Marinas del Portezuelo | E12: Realizado | F12: AR MercadoLibre | G12: 650 | H12: 5200 | I12: Dólares | J12: Dólares | K12: Departamento 2 AMB en Alquiler - Marinas del Portezuelo | L12: Argentina | G.B.A. Zona Norte | Tigre | Countries/B.Cerrado (Tigre) | Nordelta | Portezuelo | Marinas del Portezuelo | M12: Departamento | N12: 2 | O12: Puerto Norte | P12: Propia (Único Asesor) | Q12: Venta
A13: 45842 | B13: CLA6354054 | D13: LOTES en Barrio Estancia Kingsbroock - 122 y 612 | E13: Realizado | F13: AR ZonaProp | G13: 5200 | H13: 5200 | I13: Dólares | J13: Dólares | K13: LOTES en Barrio Estancia Kingsbroock - 122 y 612 | L13: Argentina | G.B.A. Zona Sur | La Plata | Villa Elvira | M13: Terreno | N13: 2 | O13: Golden Team | P13: Propia (Único Asesor) | Q13: Venta
A14: 45954 | B14: CHO7300194 | D14: Casa en alquiler permanente en Bariloche | E14: Realizado | F14: Teléfono | G14: 2800 | H14: 5600 | I14: Dólares | J14: Dólares | K14: Centro, San Carlos de Bariloche | L14: Argentina | Rio Negro | Bariloche | M14: Casa | N14: 2 | O14: Patagonia Lakes BRC | P14: Master | Q14: Venta
... A27: 45929 | B27: CHO5031458 | D27: ALQUILER TURÍSTICO - Casa categoria impresionante vista al lago en barrio cerrado Villa la Angostura | E27: Realizado | F27: Referido | G27: 700 | H27: 8400 | I27: Dólares | J27: Dólares | K27: Barrio cerrado Dos Lagos, Villa La Angostura | L27: Argentina | Neuquen | Villa La Angostura | Countries/ B. Cerrado (V. La Angostura) | M27: Casa | N27: 2 | O27: Patagonia Lakes VLA | P27: Propia (Único Asesor) | Q27: Venta
A28: 45992 | B28: Casa C/ Remax Follow | D28: Casa c/ remax follow | E28: Realizado | F28: AR ZonaProp | G28: 34000 | H28: 8450 | I28: Dólares | J28: Dólares | L28: Argentina | Mendoza | Guaymallen | M28: Casa | N28: 1 | O28: Cuyo Real | P28: (Interior) Compartida Fuera de la Red Búsqueda | Q28: Venta
A29: 46077 | B29: CLA7827009 | D29: Terreno en Lujan | E29: Realizado | F29: Repetido | G29: 8500 | H29: 8500 | I29: Dólares | J29: Dólares | K29: BARRIO SANTA IRENE RUTA 6 KM 155.5 LUJAN 30 | L29: Argentina | G.B.A. Zona Oeste | Lujan | M29: Terreno | N29: 2 | O29: Audacity | P29: Propia (Único Asesor) | Q29: Venta
A30: 46066 | B30: CLA6250455 | D30: Terreno en Venta, Santo Tome, Santa Fe | E30: Realizado | F30: Conocido | G30: 10000 | H30: 8500 | I30: Dólares | J30: Dólares | K30: Terreno en Venta, Santo Tome, Santa Fe | L30: Argentina | Santa Fe | La Capital | Santo Tome | M30: Terreno | N30: 2 | O30: De la Veracruz | P30: Compartida en Oficina (Dos Asesores) | Q30: Venta
A31: 46066 | B31: CLA6250311 | D31: Terreno en Venta, Santo Tome, Santa Fe | E31: Realizado | F31: Conocido | G31: 10000 | H31: 8500 | I31: Dólares | J31: Dólares | K31: Terreno en Venta, Santo Tome, Santa Fe | L31: Argentina | Santa Fe | La Capital | Santo Tome | M31: Terreno | N31: 2 | O31: De la Veracruz | P31: Compartida en Oficina (Dos Asesores) | Q31: Venta
A32: 46066 | B32: CLA6250352 | D32: Terreno en Venta, Santo Tome, Santa Fe | E32: Realizado | F32: Conocido | G32: 10000 | H32: 8500 | I32: Dólares | J32: Dólares | K32: Terreno en Venta, Santo Tome, Santa Fe | L32: Argentina | Santa Fe | La Capital | Santo Tome | M32: Terreno | N32: 2 | O32: De la Veracruz | P32: Compartida en Oficina (Dos Asesores) | Q32: Venta
A33: 46059 | B33: CLA6250391 | D33: Terreno en Venta, Santo Tome, Santa Fe | E33: Realizado | F33: Conocido | G33: 10000 | H33: 8500 | I33: Dólares | J33: Dólares | K33: Terreno en Venta, Santo Tome, Santa Fe | L33: Argentina | Santa Fe | La Capital | Santo Tome | M33: Terreno | N33: 2 | O33: De la Veracruz | P33: Compartida en Oficina (Dos Asesores) | Q33: Venta
A34: 46059 | B34: CLA6250401 | D34: Terreno en Venta, Santo Tome, Santa Fe | E34: Realizado | F34: Conocido | G34: 10000 | H34: 8500 | I34: Dólares | J34: Dólares | K34: Terreno en Venta, Santo Tome, Santa Fe | L34: Argentina | Santa Fe | La Capital | Santo Tome | M34: Terreno | N34: 2 | O34: De la Veracruz | P34: Compartida en Oficina (Dos Asesores) | Q34: Venta
A35: 45816 | B35: CLA6687636 | D35: Terreno en venta Pucara | E35: Realizado | F35: Facebook | G35: 8600 | H35: 8600 | I35: Dólares | J35: Dólares | K35: PUCARA | L35: Argentina | Salta | Capital | Salta | Zona Oeste | M35: Terreno | N35: 2 | O35: Realty Group | P35: Compartida en Oficina (Dos Asesores) | Q35: Venta
A36: 45973 | B36: CLA6250455 | D36: Terreno en Venta, Santo Tome, Santa Fe | E36: Realizado | F36: Facebook | G36: 10000 | H36: 9000 | I36: Dólares | J36: Dólares | K36: Terreno en Venta, Santo Tome, Santa Fe | L36: Argentina | Santa Fe | La Capital | Santo Tome | M36: Terreno | N36: 2 | O36: De la Veracruz | P36: Compartida en Oficina (Dos Asesores) | Q36: Venta
A37: 45926 | B37: CAP7128288 | D37: Departamento en alquiler 2amb con balcón | E37: Realizado | F37: AR MercadoLibre | G37: 450000 | H37: 9000 | I37: Dólares | J37: Local | K37: Bonifacini al 3800 | L37: Argentina | G.B.A. Zona Oeste | Tres De Febrero | Santos Lugares | M37: Departamento | N37: 2 | O37: Lion Team | P37: Propia (Único Asesor) | Q37: Venta
A38: 45897 | B38: CLA7070818 | D38: Terreno en Jardines del valle (Cerrillos) | E38: Realizado | F38: Facebook | G38: 11000 | H38: 9000 | I38: Dólares | J38: Dólares | K38: RUTA 68 cerrillos | L38: Argentina | Salta | Cerrillos | M38: Terreno | N38: 2 | O38: Realty Group | P38: Propia (Único Asesor) | Q38: Venta
A39: 45780 | B39: CPN57379 LA6447276 | D39: Terreno - Los Hornos | E39: Realizado | F39: Teléfono | G39: 9000 | H39: 9000 | I39: Dólares | J39: Dólares | K39: Terreno en VENTA, Barrio PRIVADO, Solares, Calle 83 y 139 | L39: Argentina | G.B.A. Zona Sur | La Plata | Los Hornos | M39: Terreno | N39: 2 | O39: Golden Team | P39: Propia (Único Asesor) | Q39: Venta
A40: 45780 | B40: CPN57379 LA6447276 | D40: Terreno - Los Hornos | E40: Realizado | F40: Conocido | G40: 9000 | H40: 9000 | I40: Dólares | J40: Dólares | K40: Terreno en VENTA, Barrio PRIVADO, Solares, Calle 83 y 139 | L40: Argentina | G.B.A. Zona Sur | La Plata | Los Hornos | M40: Terreno | N40: 2 | O40: Golden Team | P40: Propia (Único Asesor) | Q40: Venta
A41: 46094 | B41: Corralitos terreno | D41: Terreno en venta en corralitos | E41: Realizado | F41: AR ZonaProp | G41: 0 | H41: 9500 | I41: Dólares | J41: Dólares | L41: Argentina | Mendoza | Guaymallen | Los Corralitos | M41: Terreno | N41: 1 | O41: Cuyo Real | P41: (Interior) Compartida Fuera de la Red Búsqueda | Q41: Venta
A42: 45841 | B42: CGA6814291 | D42: Venta Cochera céntrica Bariloche OPORTUNIDAD Permuta | E42: Realizado | F42: Teléfono | G42: 10000 | H42: 9500 | I42: Dólares | J42: Dólares | K42: Centro, San Carlos de Bariloche | L42: Argentina | Rio Negro | Bariloche | San Carlos De Bariloche | Centro | M42: Garage | N42: 2 | O42: Patagonia Lakes BRC | P42: Propia (Único Asesor) | Q42: Venta
A43: 45761 | B43: CLA6730114 | D43: Terreno en venta nuevo alisos | E43: Realizado | F43: Conocido | G43: 10500 | H43: 9551 | I43: Dólares | J43: Dólares | K43: nuevo alisos manzana 8 lote 1 | L43: Argentina | Jujuy | San Antonio | Los Alisos | M43: Terreno | N43: 2 | O43: Plaza | P43: Compartida en Oficina (Dos Asesores) | Q43: Venta
A44: 45854 | B44: CLA6758657 | D44: Terreno en venta en Valle Alegre | E44: Realizado | F44: Referido | G44: 9600 | H44: 9600 | I44: Dólares | J44: Dólares | K44: VALLE ALEGRE | L44: Argentina | Salta | La Caldera | M44: Terreno | N44: 2 | O44: Realty Group | P44: Compartida en Oficina (Dos Asesores) | Q44: Venta
A45: 46065 | B45: CLA7690260 | D45: Terreno en venta Loteo Pucara | E45: Realizado | F45: Facebook | G45: 10500 | H45: 9965 | I45: Dólares | J45: Dólares | K45: LOTEO PUCARA | L45: Argentina | Salta | Capital | Salta | Zona Oeste | M45: Terreno | N45: 2 | O45: Realty Group | P45: Propia (Único Asesor) | Q45: Venta
A46: 46063 | B46: CLA7484087 | D46: Terreno en venta ubicado en Potreros de Quijano - Salta | E46: Realizado | F46: AR ZonaProp | G46: 10000 | H46: 10000 | I46: Dólares | J46: Dólares | K46: Potreros de Quijano | L46: Argentina | Salta | Rosario De Lerma | Campo Quijano | M46: Terreno | N46: 2 | O46: Realty Group | P46: Propia (Único Asesor) | Q46: Venta
A47: 46056 | B47: CLA7320742 | D47: Terreno en venta ubicado en Loteo Pucara - Salta | E47: Realizado | F47: Facebook | G47: 10500 | H47: 10000 | I47: Dólares | J47: Dólares | K47: Loteo Pucara | L47: Argentina | Salta | Capital | Salta | Zona Sur | M47: Terreno | N47: 2 | O47: Realty Group | P47: Propia (Único Asesor) | Q47: Venta
A48: 46036 | B48: CPN57379 LA6447276 | D48: Terreno - Los Hornos | E48: Realizado | F48: AR ZonaProp | G48: 10000 | H48: 10000 | I48: Dólares | J48: Dólares | K48: Terreno en VENTA, Barrio PRIVADO, Solares, Calle 83 y 139 | L48: Argentina | G.B.A. Zona Sur | La Plata | Los Hornos | M48: Terreno | N48: 2 | O48: Golden Team | P48: Propia (Único Asesor) | Q48: Venta
A49: 46028 | B49: CLA6752890 | D49: Terreno en Barrio Santa Rita | E49: Realizado | F49: Facebook | G49: 12000 | H49: 10000 | I49: Dólares | J49: Dólares | K49: TERRENO BARRIO SANTA RITA | L49: Argentina | Santa Fe | La Capital | Santa Fe | M49: Terreno | N49: 2 | O49: De la Veracruz | P49: Propia (Único Asesor) | Q49: Venta
A50: 45992 | B50: CHO6728128 | D50: Venta casa 3 habitaciones barrio privado maipu | E50: Realizado | F50: AR ZonaProp | G50: 115000 | H50: 10000 | I50: Dólares | J50: Dólares | K50: Videla Castillo | L50: Argentina | Mendoza | Maipu | M50: Casa | N50: 1 | O50: Cuyo Real | P50: (Interior) Compartida Fuera de la Red Búsqueda | Q50: Venta
A51: 45981 | B51: CLA6948853 | D51: VENTA TERRENO DE 1132 M2 EN AREA 60, LA VICTORIA POLO COUNTRY ¡OFERTA INCREIBLE! | E51: Realizado | F51: AR ZonaProp | G51: 13000 | H51: 10000 | I51: Dólares | J51: Dólares | K51: Club de campo La Victoria, Area 60, Lote 160 | L51: Argentina | Interior Buenos Aires | Coronel Brandsen | Area 60 | M51: Terreno | N51: 2 | O51: Destino II | P51: Propia (Único Asesor) | Q51: Venta
A52: 45965 | B52: CLA7384505 | D52: CB VENDE - TERRENO - BOSQUE DEL CEIBAL I | E52: Realizado | F52: Conocido | G52: 10500 | H52: 10000 | I52: Dólares | J52: Dólares | K52: Calle Lapacho al 800 | L52: Argentina | Jujuy | San Antonio | M52: Terreno | N52: 2 | O52: Plaza | P52: Propia (Único Asesor) | Q52: Venta
A53: 45938 | B53: CLA7263283 | D53: Terreno en los Domingos sauce viejo | E53: Realizado | F53: Conocido | G53: 13000 | H53: 10000 | I53: Dólares | J53: Dólares | K53: Lote en los Domingos, sauce Viejo | L53: Argentina | Santa Fe | La Capital | Sauce Viejo | M53: Terreno | N53: 2 | O53: De la Veracruz | P53: Propia (Único Asesor) | Q53: Venta
... A59: 45775 | B59: CLA6949078 | D59: Terrenos en Rio Blanco | E59: Realizado | F59: Referido | G59: 10000 | H59: 10000 | I59: Dólares | J59: Dólares | K59: LOTEO PAYPAYA | L59: Argentina | Jujuy | Dr Manuel Belgrano | Rio Blanco | M59: Terreno | N59: 2 | O59: Plaza | P59: Compartida en Oficina (Dos Asesores) | Q59: Venta
A60: 45760 | D60: Op. con inmo colega LOTE PH UF 4 VALLE CHAPELCO 312,05m2 NC 152106681480004 | E60: Realizado | F60: Repetido | G60: 10000 | H60: 10000 | I60: Dólares | J60: Dólares | L60: Argentina | Neuquen | Lacar | San Martin De Los Andes | Valle Chapelco | M60: Terreno | N60: 1 | O60: Patagonia Lakes SMA | P60: (Interior) Compartida Fuera de la Red Búsqueda | Q60: Venta
A61: 45713 | D61: Op. con inmo colega LOTE PH UF 3 VALLE CHAPELCO 312,05m2 NC 152106681480003 | E61: Realizado | F61: Conocido | G61: 10000 | H61: 10000 | I61: Dólares | J61: Dólares | L61: Argentina | Neuquen | Lacar | San Martin De Los Andes | Valle Chapelco | M61: Terreno | N61: 1 | O61: Patagonia Lakes SMA | P61: (Interior) Compartida Fuera de la Red Búsqueda | Q61: Venta
A62: 45700 | B62: CGA6497473 | D62: Cochera en venta calle 45 e/ 5 y 6 | E62: Realizado | F62: AR ArgenProp | G62: 10500 | H62: 10000 | I62: Dólares | J62: Dólares | K62: Cochera en venta calle 45 e/ 5 y 6 | L62: Argentina | G.B.A. Zona Sur | La Plata | La Plata | Microcentro | M62: Garage | N62: 2 | O62: Golden Team | P62: Propia (Único Asesor) | Q62: Venta
A63: 46108 | B63: CGA7476226 | D63: Venta Cochera Av. Cabildo 100 Palermo Caba | E63: Realizado | F63: AR ZonaProp | G63: 15000 | H63: 10500 | I63: Dólares | J63: Dólares | K63: Av. Cabildo al 100 Palermo Caba | L63: Argentina | Capital Federal | Palermo | M63: Garage | N63: 2 | O63: Lion Team | P63: Propia (Único Asesor) | Q63: Venta
A64: 46087 | B64: CLA7568177 | D64: Terreno Pucara | E64: Realizado | F64: Facebook | G64: 10500 | H64: 10500 | I64: Dólares | J64: Dólares | K64: LOTEO PUCARA | L64: Argentina | Salta | Capital | Salta | Zona Oeste | M64: Terreno | N64: 2 | O64: Realty Group | P64: Propia (Único Asesor) | Q64: Venta
A65: 45912 | B65: CLA6972931 | D65: Terreno en La Viña | E65: Realizado | F65: Facebook | G65: 12000 | H65: 10500 | I65: Dólares | J65: Dólares | K65: Coronel Moldes | L65: Argentina | Salta | La Viña | M65: Terreno | N65: 2 | O65: Realty Group | P65: Propia (Único Asesor) | Q65: Venta
A66: 45777 | B66: CLA6673168 | D66: Terreno en Venta La Celestina Mza I | E66: Realizado | F66: Facebook | G66: 10000 | H66: 10500 | I66: Dólares | J66: Dólares | K66: Terreno La Celestina Mza I | L66: Argentina | Salta | Cerrillos | Cerrillos | M66: Terreno | N66: 2 | O66: Realty Group | P66: Propia (Único Asesor) | Q66: Venta
A67: 45687 | B67: CLA6236629 | D67: Terreno en venta en barrio abierto SENDAS UR | E67: Realizado | F67: Facebook | G67: 10500 | H67: 10500 | I67: Dólares | J67: Dólares | K67: SENDAS UR | L67: Argentina | Salta | Capital | Salta | Zona Oeste | M67: Terreno | N67: 2 | O67: Realty Group | P67: Propia (Único Asesor) | Q67: Venta
A68: 46111 | B68: CGA7342048 | D68: Cochera en Colegiales | E68: Realizado | F68: AR ZonaProp | G68: 12000 | H68: 10600 | I68: Dólares | J68: Dólares | K68: Aguilar al 2500 | L68: Argentina | Capital Federal | Colegiales | M68: Garage | N68: 2 | O68: Niceto | P68: Propia (Único Asesor) | Q68: Venta
A69: 46049 | B69: CLA7387500 | D69: Terreno en venta ubicado en Cielos del Valle - Ruta 68 - Salta | E69: Realizado | F69: Facebook | G69: 12500 | H69: 11000 | I69: Dólares | J69: Dólares | K69: Cielos del Valle | L69: Argentina | Salta | Capital | Salta | Zona Sur | M69: Terreno | N69: 2 | O69: Realty Group | P69: Propia (Único Asesor) | Q69: Venta
A70: 45658 | B70: CGA6322619 | D70: Cochera fija en venta! Ubicación estratégica! | E70: Realizado | F70: AR ZonaProp | G70: 13000 | H70: 11000 | I70: Dólares | J70: Dólares | K70: Marcelo t de Alvear al 1300 | L70: Argentina | Capital Federal | Recoleta | M70: Garage | N70: 2 | O70: Destino | P70: Propia (Único Asesor) | Q70: Venta
A71: 45973 | B71: CGA7248532 | D71: COCHERA CUBIERTA EN RECOLETA | E71: Realizado | F71: AR ZonaProp | G71: 13000 | H71: 11500 | I71: Dólares | J71: Dólares | K71: Billinghurst al 2000 | L71: Argentina | Capital Federal | Recoleta | M71: Garage | N71: 2 | O71: Destino II | P71: Compartida en Oficina (Dos Asesores) | Q71: Venta
A72: 45946 | B72: CLA7341975 | D72: Terreno en venta en La Celestina, Cerrillos | E72: Realizado | F72: Facebook | G72: 12000 | H72: 11500 | I72: Dólares | J72: Dólares | K72: La Celestina | L72: Argentina | Salta | Cerrillos | Cerrillos | M72: Terreno | N72: 2 | O72: Realty Group | P72: Compartida en Oficina (Dos Asesores) | Q72: Venta
A73: 45827 | B73: CLA6925280 | D73: Terreno en Santa María de los Cerrillos | E73: Realizado | F73: Facebook | G73: 12000 | H73: 11500 | I73: Dólares | J73: Dólares | K73: Terreno Santa María de los Cerrillos | L73: Argentina | Salta | Cerrillos | Cerrillos | M73: Terreno | N73: 2 | O73: Realty Group | P73: Propia (Único Asesor) | Q73: Venta
... A100: 46108 | B100: CAP7734188 | D100: depto en alquiler en temperley, 3 ambientes en alquiler, a estrenar, amenities, zona sur | E100: Realizado | F100: AR MercadoLibre | G100: 750000 | H100: 15000 | I100: Dólares | J100: Local | K100: CANGALLO al 400 | L100: Argentina | G.B.A. Zona Sur | Lomas De Zamora (Partido) | Temperley | Temperley Este | M100: Departamento | N100: 2 | O100: Lion Team | P100: Propia (Único Asesor) | Q100: Venta
A101: 46105 | B101: COCHERA EL FARO | D101: COCHERA EN VENTA EN EL EDIFICIO EL FARO | E101: Realizado | F101: AR ZonaProp | G101: 15000 | H101: 15000 | I101: Dólares | J101: Dólares | L101: Argentina | G.B.A. Zona Norte | Tigre | Countries/B.Cerrado (Tigre) | Nordelta | Portezuelo | El Faro | M101: Garage | N101: 2 | O101: Puerto Norte | P101: Propia (Único Asesor) | Q101: Venta
A102: 46101 | B102: CLA7261069 | D102: VENTA Lote/Terreno 800m² Kaleuche Alto San Martín de los Andes | E102: Realizado | F102: AR ZonaProp | G102: 16000 | H102: 15000 | I102: Dólares | J102: Dólares | K102: B° Kaleuche Alto | L102: Argentina | Neuquen | Lacar | San Martin De Los Andes | M102: Terreno | N102: 2 | O102: Patagonia Lakes SMA | P102: Propia (Único Asesor) | Q102: Venta
A103: 46058 | B103: CLA7240665 | D103: Terreno en Arroyo Leyes | E103: Realizado | F103: Referido | G103: 16000 | H103: 15000 | I103: Dólares | J103: Dólares | K103: Terreno con financiación en Arroyo Leyes | L103: Argentina | Santa Fe | La Capital | Arroyo Leyes | M103: Terreno | N103: 2 | O103: De la Veracruz | P103: Propia (Único Asesor) | Q103: Venta
A104: 46048 | B104: CLA4698257 | D104: Lote en venta zona norte Santa Fe | E104: Realizado | F104: Facebook | G104: 15000 | H104: 15000 | I104: Dólares | J104: Dólares | K104: Lote en venta zona Norte Santa Fe | L104: Argentina | Santa Fe | La Capital | Santa Fe | M104: Terreno | N104: 2 | O104: De la Veracruz | P104: Propia (Único Asesor) | Q104: Venta
A105: 45959 | B105: Nuñez 2120 | D105: Nuñez 2120 | E105: Realizado | F105: AR MercadoLibre | G105: 15000 | H105: 15000 | I105: Dólares | J105: Dólares | K105: Nuñez 2120 | L105: Argentina | Capital Federal | Capital Federal | M105: Departamento | N105: 2 | O105: Lion Team | P105: Compartida en Oficina (Dos Asesores) | Q105: Venta
A106: 45958 | B106: CLA4698181 | D106: Terreno - Santa Fe | E106: Realizado | F106: Conocido | G106: 15000 | H106: 15000 | I106: Dólares | J106: Dólares | K106: Diagonal aguado 8800 | L106: Argentina | Santa Fe | La Capital | Santa Fe | M106: Terreno | N106: 2 | O106: De la Veracruz | P106: Propia (Único Asesor) | Q106: Venta
A107: 45906 | B107: CLA7056731 | D107: VENTA DE LOTE BARRIO FRONTERAS SAN VICENTE | E107: Realizado | F107: AR ZonaProp | G107: 15000 | H107: 15000 | I107: Dólares | J107: Dólares | K107: CALLE IBAÑEZ | L107: Argentina | G.B.A. Zona Sur | San Vicente | M107: Terreno | N107: 2 | O107: Boutique | P107: Propia (Único Asesor) | Q107: Venta
A108: 45836 | B108: CLA5742225 | D108: Terreno en General Fernandez Oro | E108: Realizado | F108: AR ZonaProp | G108: 14000 | H108: 15000 | I108: Dólares | J108: Dólares | K108: loteo el sol | L108: Argentina | Rio Negro | General Fernandez Oro | M108: Terreno | N108: 2 | O108: Sensus | P108: Compartida Fuera de la Red Captación Propia | Q108: Venta
A109: 45821 | B109: OP 143 | D109: Libertador 1080 cochera | E109: Realizado | F109: AR ZonaProp | G109: 15000 | H109: 15000 | I109: Dólares | J109: Dólares | K109: Libertador 1080 | L109: Argentina | Capital Federal | Recoleta | M109: Garage | N109: 2 | O109: Seniority Plus | P109: Propia (Único Asesor) | Q109: Venta
A110: 45803 | B110: Cinco Saltos | D110: Terreno Cinco Saltos | E110: Realizado | F110: AR ZonaProp | G110: 15000 | H110: 15000 | I110: Dólares | J110: Dólares | L110: Argentina | Rio Negro | General Roca | Cinco Saltos | M110: Terreno | N110: 2 | O110: Sensus | P110: Propia (Único Asesor) | Q110: Venta
A111: 45685 | B111: CLA6564185 | D111: Terreno en venta villa Casa del Sol San luis | E111: Realizado | F111: Facebook | G111: 15000 | H111: 15000 | I111: Dólares | J111: Dólares | K111: casa del sol | L111: Argentina | Salta | Capital | Salta | Zona Sur | M111: Terreno | N111: 2 | O111: Realty Group | P111: Propia (Único Asesor) | Q111: Venta
A112: 45665 | B112: CLO6520624 | D112: Venta de Local en Manzanares Paseo Dino | E112: Realizado | F112: Cartel | G112: 15000 | H112: 15000 | I112: Dólares | J112: Dólares | K112: Paseo Dino, Manzanares | L112: Argentina | G.B.A. Zona Norte | Pilar | Manzanares | M112: Local Comercial | N112: 2 | O112: Acqua | P112: Propia (Único Asesor) | Q112: Venta
A113: 46083 | B113: CLA7469441 | D113: VENTA Lote | Terreno 308 m2, Valle Chapelco, San Martín de los Andes | E113: Realizado | F113: Conocido | G113: 17900 | H113: 15500 | I113: Dólares | J113: Dólares | K113: PH UF N1 Lote PH | L113: Argentina | Neuquen | Lacar | San Martin De Los Andes | Valle Chapelco | M113: Terreno | N113: 2 | O113: Patagonia Lakes SMA | P113: Propia (Único Asesor) | Q113: Venta
A114: 45877 | B114: CAP6660554 | D114: ALQUILER depto 3 amb REMODELADO A NUEVO balcón hermosa vista Recoleta | E114: Realizado | F114: AR ZonaProp | G114: 1300 | H114: 15600 | I114: Dólares | J114: Dólares | K114: Quintana al 500 | L114: Argentina | Capital Federal | Recoleta | M114: Departamento | N114: 2 | O114: Seniority | P114: Propia (Único Asesor) | Q114: Venta
A115: 45974 | B115: CST7123830 | D115: Depósito en Esandi Bariloche a la VENTA | E115: Realizado | F115: Salón | G115: 17500 | H115: 16000 | I115: Dólares | J115: Dólares | K115: Esandi | L115: Argentina | Rio Negro | Bariloche | San Carlos De Bariloche | Ñireco | M115: Storage | N115: 2 | O115: Patagonia Lakes BRC | P115: Compartida en Oficina (Dos Asesores) | Q115: Venta
A116: 45797 | D116: Op. con inmo colega María Belén Nuñez Gerstmayer UF 1 Valle Chapelco | E116: Realizado | F116: Conocido | G116: 16000 | H116: 16000 | I116: Dólares | J116: Dólares | L116: Argentina | Neuquen | Lacar | San Martin De Los Andes | Valle Chapelco | M116: Terreno | N116: 1 | O116: Patagonia Lakes SMA | P116: (Interior) Compartida Fuera de la Red Búsqueda | Q116: Venta
A117: 45995 | B117: Manuel Artigas 5106 | D117: Manuel Artigas 5106 | E117: Realizado | F117: AR ZonaProp | G117: 65000 | H117: 16250 | I117: Dólares | J117: Dólares | K117: Manuel Artigas 5106 | L117: Argentina | Capital Federal | Capital Federal | M117: Departamento | N117: 2 | O117: Lion Team | P117: Propia (Único Asesor) | Q117: Venta
A118: 45680 | B118: CLA6353157 | D118: LOTES en Barrio DON CARMELO - 22 y 652 | E118: Realizado | F118: Teléfono | G118: 16284 | H118: 16274 | I118: Dólares | J118: Dólares | K118: LOTES en Barrio DON CARMELO - 22 y 652 | L118: Argentina | G.B.A. Zona Sur | La Plata | Villa Parque Sicardi | M118: Terreno | N118: 2 | O118: Golden Team | P118: Propia (Único Asesor) | Q118: Venta
A119: 45831 | B119: CBA47695 LA6263100 | D119: VENTA terreno de 146,30 m2 en LOTEO "ANTIGUO CAMINO" Bariloche | E119: Realizado | F119: Teléfono | G119: 17600 | H119: 16417 | I119: Dólares | J119: Dólares | K119: Antiguo Camino, San Carlos de Bariloche | L119: Argentina | Rio Negro | Bariloche | San Carlos De Bariloche | Lago Moreno | M119: Terreno | N119: 2 | O119: Patagonia Lakes BRC | P119: Compartida en Oficina (Dos Asesores) | Q119: Venta
A120: 45861 | B120: 76edu | D120: Oficina Hermes | E120: Realizado | F120: AR ZonaProp | G120: 18000 | H120: 16500 | I120: Dólares | J120: Dólares | K120: Primera Junta 2507 | L120: Argentina | Santa Fe | La Capital | Santa Fe | M120: Oficina | N120: 1 | O120: De la Veracruz | P120: (Interior) Compartida Fuera de la Red Búsqueda | Q120: Venta
A121: 45874 | B121: CLA6942928 | D121: TERRENO EN LA MESETA CENTENARIO | E121: Realizado | F121: AR ZonaProp | G121: 10000 | H121: 16660 | I121: Dólares | J121: Dólares | K121: ALBERDI Y SANTA FE-LA MESETA CENTENARIO | L121: Argentina | Neuquen | Confluencia | Centenario | M121: Terreno | N121: 2 | O121: Sensus | P121: Propia (Único Asesor) | Q121: Venta
A122: 45749 | B122: CLA6606201 | D122: Terreno en BARRIO LA MESETA 2 CENTENARIO | E122: Realizado | F122: AR ZonaProp | G122: 10000 | H122: 16660 | I122: Dólares | J122: Dólares | K122: S,N | L122: Argentina | Neuquen | Confluencia | Centenario | Sarmiento II | M122: Terreno | N122: 2 | O122: Sensus | P122: Propia (Único Asesor) | Q122: Venta
A123: 45747 | B123: CLA6374066 | D123: Terreno en Lote 5 Mz 773 SEJUN Centenario | E123: Realizado | F123: AR ZonaProp | G123: 4500 | H123: 16660 | I123: Dólares | J123: Dólares | K123: VENTA LOTE 300 M2 SEJUN CENTENARIO | L123: Argentina | Neuquen | Confluencia | Centenario | M123: Terreno | N123: 2 | O123: Sensus | P123: Compartida en Oficina (Dos Asesores) | Q123: Venta
A124: 46031 | B124: CLA6969938 | D124: Terreno en La Meseta Centenario | E124: Realizado | F124: Cartel | G124: 11000000 | H124: 17000 | I124: Dólares | J124: Local | K124: Calle S/N | L124: Argentina | Neuquen | Confluencia | Centenario | M124: Terreno | N124: 2 | O124: Sensus | P124: Compartida en Oficina (Dos Asesores) | Q124: Venta
A125: 46008 | B125: COF7502573 | D125: Venta Oficina en Microcentro a metros del Obelico / No apta vivienda | E125: Realizado | F125: AR MercadoLibre | G125: 19000 | H125: 17000 | I125: Dólares | J125: Dólares | K125: Cerrito esquina Avenida Presidente Roque Sáenz Peña | L125: Argentina | Capital Federal | Centro (Capital Federal) | Microcentro | M125: Oficina | N125: 2 | O125: Concept | P125: Propia (Único Asesor) | Q125: Venta
A126: 45972 | B126: CAP7419403 | D126: Departamento en alquiler dos ambientes con balcon y amenities. | E126: Realizado | F126: AR MercadoLibre | G126: 900000 | H126: 17000 | I126: Dólares | J126: Local | K126: Rio de Janeiro al 200 | L126: Argentina | Capital Federal | Caballito | M126: Departamento | N126: 2 | O126: Lion Team | P126: Propia (Único Asesor) | Q126: Venta
A127: 45857 | B127: CLA6939233 | D127: Lotes en Venta - Jardines de La Falda | E127: Realizado | F127: AR ZonaProp | G127: 18200 | H127: 17000 | I127: Dólares | J127: Dólares | K127: Venezuela y Quilmebai | L127: Argentina | Rio Negro | General Roca | Cipolletti | Distrito Noreste | M127: Terreno | N127: 2 | O127: Sensus | P127: Compartida Fuera de la Red Captación Propia | Q127: Venta
A128: 45968 | B128: CLA4698164 | D128: Lote en venta zona norte Santa Fe | E128: Realizado | F128: Referido | G128: 15000 | H128: 17100 | I128: Dólares | J128: Dólares | K128: Lote en venta zona norte Santa Fe | L128: Argentina | Santa Fe | La Capital | Santa Fe | M128: Terreno | N128: 2 | O128: De la Veracruz | P128: Propia (Único Asesor) | Q128: Venta
... A133: 46097 | B133: CLA7689447 | D133: Terreno en venta ubicado en el Mollar II - Cerrillos - Salta | E133: Realizado | F133: Facebook | G133: 18000 | H133: 18000 | I133: Dólares | J133: Dólares | K133: El Mollar II | L133: Argentina | Salta | Capital | Salta | Zona Sur | M133: Terreno | N133: 2 | O133: Realty Group | P133: Compartida en Oficina (Dos Asesores) | Q133: Venta
A134: 46078 | B134: Santa Clara 855 | D134: Santa Clara al sur 855 | E134: Realizado | F134: AR MercadoLibre | G134: 18000 | H134: 18000 | I134: Dólares | J134: Dólares | L134: Argentina | G.B.A. Zona Sur | San Vicente | M134: Terreno | N134: 2 | O134: Livello | P134: Propia (Único Asesor) | Q134: Venta
A135: 46065 | B135: CLA6980928 | D135: Terreno en venta en barrio Los Sauces | E135: Realizado | F135: AR MercadoLibre | G135: 20000 | H135: 18000 | I135: Dólares | J135: Dólares | K135: Ruta 52 | L135: Argentina | G.B.A. Zona Sur | Ezeiza | Canning (Ezeiza) | M135: Terreno | N135: 2 | O135: Boutique | P135: Propia (Único Asesor) | Q135: Venta
A136: 46044 | B136: CHO7678463 | D136: Casa en San Rafael | E136: Realizado | F136: Facebook | G136: 18000 | H136: 18000 | I136: Dólares | J136: Dólares | K136: comodoro Pí al 200 | L136: Argentina | Mendoza | San Rafael | San Rafael | M136: Casa | N136: 2 | O136: Andes | P136: Propia (Único Asesor) | Q136: Venta
A137: 46029 | B137: CGA7659656 | D137: COCHERA EN VENTA VILLA URQUIZA | E137: Realizado | F137: AR ZonaProp | G137: 18000 | H137: 18000 | I137: Dólares | J137: Dólares | K137: Av. Congreso al 4300 | L137: Argentina | Capital Federal | Villa Urquiza | M137: Garage | N137: 2 | O137: Destino II | P137: Propia (Único Asesor) | Q137: Venta
A138: 46027 | B138: CLA7467331 | D138: TERRENO EN VENTA MAIPU CON TOUR VIRTUAL | E138: Realizado | F138: AR ZonaProp | G138: 19000 | H138: 18000 | I138: Dólares | J138: Dólares | K138: La Florida Lunlunta | L138: Argentina | Mendoza | Maipu | M138: Terreno | N138: 2 | O138: Impacto Pro | P138: Propia (Único Asesor) | Q138: Venta
A139: 46022 | D139: UC 8 | E139: Realizado | F139: Repetido | G139: 20000 | H139: 18000 | I139: Dólares | J139: Dólares | K139: Retamas 200 | L139: Argentina | Neuquen | Villa La Angostura | Centro | M139: Garage | N139: 2 | O139: Patagonia Lakes VLA | P139: Compartida en Oficina (Dos Asesores) | Q139: Venta
A140: 46022 | D140: UC 7 | E140: Realizado | F140: Repetido | G140: 20000 | H140: 18000 | I140: Dólares | J140: Dólares | K140: Retamas 200 | L140: Argentina | Neuquen | Villa La Angostura | Centro | M140: Garage | N140: 2 | O140: Patagonia Lakes VLA | P140: Compartida en Oficina (Dos Asesores) | Q140: Venta
A141: 46008 | B141: CGA7621543 | D141: COCHERA EN VENTA VILLA URQUIZA | E141: Realizado | F141: AR ZonaProp | G141: 18000 | H141: 18000 | I141: Dólares | J141: Dólares | K141: Av. Congreso al 4300 | L141: Argentina | Capital Federal | Villa Urquiza | M141: Garage | N141: 2 | O141: Destino II | P141: Propia (Único Asesor) | Q141: Venta
A142: 45876 | B142: CLA6950692 | D142: Terreno en Barrio Norte | E142: Realizado | F142: Cartel | G142: 20000 | H142: 18000 | I142: Dólares | J142: Dólares | K142: BARRIO NORTE | L142: Argentina | Jujuy | Dr Manuel Belgrano | San Salvador De Jujuy | M142: Terreno | N142: 2 | O142: Plaza | P142: Propia (Único Asesor) | Q142: Venta
A143: 45875 | B143: CCH7037710 | D143: Chacra en Cinco Saltos | E143: Realizado | F143: AR ZonaProp | G143: 35000 | H143: 18000 | I143: Dólares | J143: Dólares | K143: Calle S/N | L143: Argentina | Rio Negro | General Roca | Cinco Saltos | M143: Rancho | N143: 2 | O143: Sensus | P143: Propia (Único Asesor) | Q143: Venta
A144: 45737 | B144: La Elina | D144: Lote en Venta Barrio Cerrado La Elina, Comarcas de Lujan | E144: Realizado | F144: Conocido | G144: 18000 | H144: 18000 | I144: Dólares | J144: Dólares | L144: Argentina | G.B.A. Zona Oeste | Lujan | M144: Terreno | N144: 1 | O144: Audacity | P144: (Interior) Compartida Fuera de la Red Búsqueda | Q144: Venta
A145: 45694 | B145: CLA6618292 | D145: Terreno en VENTA VALLE AZUL Bariloche | E145: Realizado | F145: Teléfono | G145: 18000 | H145: 18000 | I145: Dólares | J145: Dólares | K145: VALLE AZUL -CASCADA CHACHIN | L145: Argentina | Rio Negro | Bariloche | San Carlos De Bariloche | Valle Azul | M145: Terreno | N145: 2 | O145: Patagonia Lakes BRC | P145: Propia (Único Asesor) | Q145: Venta
A146: 45659 | B146: CLA5798692 | D146: Terreno en Venta Sauce Viejo Santa Fe | E146: Realizado | F146: AR ZonaProp | G146: 21000 | H146: 18000 | I146: Dólares | J146: Dólares | K146: Terreno en Venta, Guatemala entre Antartida Argentina y Malvinas, Sauce Viejo | L146: Argentina | Santa Fe | La Capital | Sauce Viejo | M146: Terreno | N146: 2 | O146: De la Veracruz | P146: Propia (Único Asesor) | Q146: Venta
A147: 45735 | B147: CLA4152962 | D147: Terreno Estacion Alvarado Zona Sur Salta - Capital | E147: Realizado | F147: Referido | G147: 18500 | H147: 18500 | I147: Dólares | J147: Dólares | K147: estacion alvarado | L147: Argentina | Salta | Capital | Salta | Zona Sur | M147: Terreno | N147: 2 | O147: Realty Group | P147: Compartida en Oficina (Dos Asesores) | Q147: Venta
A148: 45930 | B148: CLA6367472 | D148: VENTA LOTE en PH de 98 mts, Las Victorias San Carlos de Bariloche | E148: Realizado | F148: Teléfono | G148: 21000 | H148: 18600 | I148: Dólares | J148: Dólares | K148: Las Victorias, San Carlos de Bariloche | L148: Argentina | Rio Negro | Bariloche | San Carlos De Bariloche | Las Victorias | M148: Terreno | N148: 1 | O148: Patagonia Lakes BRC | P148: (Interior) Compartida Fuera de la Red Búsqueda | Q148: Venta
...
