Workbook

Sheet TCA
A1: RESPUESTAS PROVISORIAS A CUESTIONARIO TCA — FCIC CRÉDITOS HIPOTECARIOS
A2: Fuente: Propuesta Cono Sur Investments (Marzo 2026) + definiciones Capital Token Group. Sujeto a revisión y confirmación.
A3: # | B3: Pregunta TCA | C3: Respuesta Provisoria | D3: Status / Notas
A4: SECCIÓN I — PAUTAS DE INVERSIÓN Y ESTRUCTURA DEL FCIC
A5: 1 | B5: Nombre del FCIC (debe constar desde el inicio para actas de creación de órganos) | C5: A definir. Propuesta: "TCMC Créditos Hipotecarios I" o "Tu Casa +Cerca I — FCIC de Créditos" | D5: PENDIENTE — Definir con CTG
A6: 2 | B6: Participantes: depositaria / asesor de inversiones / comité de inversiones (integración y pautas generales de funcionamiento) | C6: Sociedad Gerente: Cono Sur S.G.F.C.I.S.A. Sociedad Depositaria: Banco Comafi S.A. (a confirmar) Asesor de Inversión: Capital Token Group S.A. (en formación) Organizador/Asesor Financiero/Hacedor de Mercado: Cono Sur Inversiones S.A. Comité de Inversiones: integración y pautas a definir en reglamento de gestión | D6: CONFIRMADO por Cono Sur Depo. a confirmar CTG en formación
A7: 3 | B7: Monto del FCIC y cantidad de cuotapartes / posibilidad de aumento de monto y emisión de nuevas cuotapartes | C7: Primer tramo: mínimo USD 3.000.000. Máximo a definir según colocación. Meta de crecimiento a USD 30M (2026-2030). Cuotapartes: a definir VN unitario. Posibilidad de emitir nuevos tramos sujeto a asamblea y CNV. | D7: CORREGIDO 06/04 — Mínimo USD 3M, máximo según colocación (no fijo)
A8: 4 | B8: Plazo del FCIC | C8: Base: 5 años, ampliable a 11 años. Si se amplía, REVISAR con SL (asesor fiscal in-house) si se mantienen los beneficios impositivos (reducción/exención IG bajo Art. 206 Ley 27.440). Modelo financiero corre ambos escenarios. | D8: CORREGIDO 06/04 — 5Y base ampliable a 11Y. Validar fiscal con SL
A9: 5 | B9: Objetivo de inversión del FCIC | C9: Invertir en originación y/o adquisición de créditos hipotecarios a personas humanas destinados a vivienda en Argentina. Ticket promedio estimado USD 30.000. Plazos de crédito: 1 a 5 años. LTV máx 30%. El mix por duration se medirá contra mercado (no se predetermina la distribución por plazo). | D9: CORREGIDO 06/04 — Eliminado mix fijo por duration. Se mide contra mercado
A10: 6 | B10: Principales activos elegibles | C10: Activos específicos: créditos hipotecarios originados o adquiridos por el fondo, garantizados con hipoteca en primer grado sobre inmuebles residenciales en Argentina (min. 75% del patrimonio del fondo). Activos transitorios: FCI money market, depósitos bancarios, títulos públicos, ONs, VDF, cauciones y otros instrumentos líquidos (hasta 25% del patrimonio). | D10: CONFIRMADO por Cono Sur
A11: 7 | B11: Tipos de inversión en los activos elegibles | C11: Originación directa de créditos hipotecarios a personas humanas a través del canal Coldwell Banker (red inmobiliaria exclusiva). Sistema francés de amortización. Tasa fija en USD. | D11: PARCIAL — Confirmar si también adquisición de cartera de terceros
A12: 8 | B12: Pautas de diversificación y condiciones de elegibilidad de los activos | C12: Diversificación: ningún crédito individual puede exceder el 5% del patrimonio del fondo. Elegibilidad: (i) hipoteca en 1er grado, (ii) destino vivienda única o primera vivienda, (iii) LTV max 30%, (iv) inmueble en Argentina, (v) deudor persona humana con capacidad de repago verificada, (vi) seguro de vida del deudor, (vii) tasación por valuador independiente registrado. | D12: PROVISORIO — Sujeto a definición final de scoring y criterios de originación
A13: 9 | B13: Formas de valuación de activos | C13: Créditos performing: costo amortizado (valor presente de flujos futuros descontados a tasa de originación). Créditos en mora >90 días: valor recuperable neto (valor de garantía menos costos de ejecución). Activos transitorios: valor de mercado o cotización. | D13: PROVISORIO — Sujeto a validación con auditor y CNV
A14: 10 | B14: Tipo y Clases de cuotapartes | C14: Propuesta inicial: clase única de cuotapartes (cuotapartes de condominio). Alternativa a evaluar: Clase A (senior, renta fija) + Clase B (subordinada, equity). Cuotapartes escriturales, nominativas, no endosables. | D14: PENDIENTE — Definir si una o dos clases
A15: 11 | B15: Moneda del FCIC y bimonetariedad (suscripción y rescate en otras monedas para alguna clase) | C15: Moneda del fondo: dólares estadounidenses (USD). Suscripción: en USD. Evaluar posibilidad de suscripción en ARS al tipo de cambio MEP/CCL del día. Rescate: en USD. | D15: PARCIAL — Confirmar mecanismo de suscripción en ARS
A16: 12 | B16: Forma de integración (posibilidad de integración en especie) | C16: Integración en efectivo (USD). No se prevé integración en especie en la etapa inicial. Podría evaluarse para futuras ampliaciones la cesión de carteras de créditos hipotecarios como aporte en especie. | D16: PROVISORIO
... A19: 15 | B19: Forma de liquidación del FCIC | C19: Al vencimiento del plazo, por decisión de asamblea extraordinaria de cuotapartistas (mayoría calificada), o por eventos regulatorios previstos en Ley 24.083. Liquidación: realización ordenada de activos, pago de pasivos y distribución del remanente a prorrata. | D19: CONFIRMADO por Cono Sur
A21: SECCIÓN II — INFORMACIÓN DEL ASESOR DE INVERSIÓN (para Prospecto)
A22: 1 | B22: Denominación social | C22: Capital Token Group S.A. (en proceso de constitución) | D22: PENDIENTE — CTG en formación
A23: 2 | B23: CUIT | C23: A obtener con inscripción societaria | D23: PENDIENTE
A24: 3 | B24: Sede Social | C24: A definir (Buenos Aires, Argentina) | D24: PENDIENTE
A25: 4 | B25: Estatuto Social | C25: En redacción. Objeto social incluirá asesoramiento de inversión en FCI. | D25: PENDIENTE
A26: 5 | B26: Dirección de email | C26: A definir (ej. info@capitaltokengroup.com) | D26: PENDIENTE
A27: 6 | B27: Página web | C27: A definir. Landing actual del producto: developfb.github.io/TuCasaMasCerca/ | D27: PARCIAL
A28: 7 | B28: Datos registrales ante Registro Público de Comercio | C28: Pendiente de constitución e inscripción | D28: PENDIENTE
A29: 8 | B29: Nómina de miembros del Órgano de Administración y Fiscalización (fecha designación y vencimiento mandato) | C29: A completar una vez constituida la sociedad | D29: PENDIENTE — CTG
A30: 9 | B30: Nómina de Accionistas y/o Socios | C30: A completar una vez constituida la sociedad | D30: PENDIENTE — CTG
A31: 10 | B31: 0.015 | C31: 1.5% por crédito originado (one-time), cobrado al FCIC. El fondo recibe el 5% del tomador y paga 1.5% al asesor por la originación. | D31: CORREGIDO 06/04 — 1.5% (no 1%). El asesor cobra al fondo, no al tomador.
A32: 11 | B32: Reseña histórica de la empresa (info comercial/promocional) | C32: Capital Token Group nace como vehículo de inversión y asesoramiento enfocado en créditos hipotecarios de bajo monto (micro-mortgages) para el segmento de primera vivienda en Argentina, en alianza con la red inmobiliaria Coldwell Banker. | D32: PROVISORIO — Expandir
A33: 12 | B33: EECC anuales últimos 3 ejercicios | C33: No disponibles (sociedad en formación, sin ejercicios previos) | D33: N/A — Sociedad nueva
A34: 13 | B34: Información sobre política ambiental (si existe) | C34: En desarrollo. El fondo se orientará a financiar vivienda accesible, alineado con ODS 11 (Ciudades y Comunidades Sostenibles). | D34: PROVISORIO
B35: A DEFINIR | C35: NO replicar el tope fijo de 5.4% de Lendar. En su lugar: definir rendimiento objetivo en el plazo propuesto, sin comprometer un ratio transaccional fijo. Fundamento: el FCIC es un fondo a riesgo, no a renta fija. Un tope rígido obliga al sponsor a cubrir desfasajes financieros momentáneos, lo cual es inconsistente con la naturaleza del vehículo. Lendar (Cl. 10.5) fija 5.4% como referencia. | D35: CORREGIDO 06/04 — Sin tope fijo. Rendimiento objetivo, no transaccional. Fondo a riesgo.
A36: SECCIÓN III — ESTRUCTURA DE HONORARIOS (Ref. Propuesta Cono Sur)
A37: # | B37: Concepto | C37: Honorario / Comisión | D37: Responsable
A38: 1 | B38: 0.05 | C38: 5% + IVA cobrado al tomador del crédito. El 100% ingresa al FCIC como ingreso del fondo. No hay extracción pre-fondo. | D38: CORREGIDO 06/04 — Todo el 5% va al fondo. No hay split pre-fondo.
A39: 2 | B39: Sociedad Depositaria | C39: 0.20% anual del PN (en propuesta Cono Sur; modelo usa 0.15%) | D39: Banco Comafi S.A.
A40: 3 | B40: Asesor de Inversión (Mgmt Fee) | C40: Opción A (ACTIVA EN MODELO): SIN mgmt fee % PN → cobra 1% por crédito originado (one-time). Opción B (propuesta ConoSur): 1% PN + 10% carry >6% hurdle. SUPUESTOS fila 30: B30 = 0% (sin fee anual sobre PN). | D40: CORREGIDO — Modelo usa Opción A (0% PN). TCA anterior decía 1.25% → INCORRECTO
A41: 4 | B41: Carried Interest | C41: 10% sobre exceso de hurdle 6% — Consistente con Propuesta ConoSur Mar-2026. SUPUESTOS fila 33: B33 = 10%, fila 34: B34 = 6%. | D41: CONFIRMADO 06/04 — 10% carry sobre exceso hurdle 6%
A42: 5 | B42: Colocadores | C42: 1.50% del monto suscripto (one-time) — Propuesta ConoSur Mar-2026. SUPUESTOS fila 36: B36 = 1.5%. | D42: Cono Sur Inversiones + otros ACyDIs
A43: 6 | B43: Organizador | C43: 0.25% del monto suscripto (one-time) | D43: Cono Sur Inversiones S.A.
A44: 7 | B44: Hacedor de Mercado | C44: 1.20% anual (all-in cost) sobre activos de cada cuenta de proveedor de liquidez — SUPUESTOS fila 61: B61 = 1.2%. Costo FUERA del fondo. | D44: Cono Sur Inversiones S.A.
A45: 8 | B45: Límite gastos totales | C45: 5.40% anual del PN del fondo | D45: Per reglamento de gestión
A47: NOTA (actualizada 06/04/2026): Correcciones aplicadas según revisión de Pancho: (1) Monto: mín 3M, máx según colocación, (2) Plazo: 5Y base ampliable a 11Y + validar fiscal, (3) Mix sin distribución fija por duration, (4) Upfront 5% todo al fondo, (5) Fee asesor originación 1.5%, (6) Carry 10%/6% confirmado, (7) Apalancamiento como alternativa en reglamento, (8) Nuevas cláusulas: ejecución extrajudicial + compra/venta créditos, (9) Sin tope fijo de gastos (rendimiento objetivo, fondo a riesgo).
A49: SECCIÓN IV — APALANCAMIENTO Y ESTRUCTURA DE CAPITAL
A50: 1 | B50: Posibilidad de endeudamiento del FCIC | C50: Alternativa a incluir en reglamento de gestión. Cláusula habilitante para que el FCIC pueda tomar endeudamiento garantizado con los créditos de su cartera, hasta 1x PN, previa autorización CNV. Referencia: Lendar Cl. 16.1.5. Parámetros de modelo: leverage efectivo 0.2x, inicio año 3, costo deuda senior 9% USD. Activación sujeta a track record y condiciones de mercado. | D50: CORREGIDO 06/04 — Es alternativa habilitada en reglamento, no obligatoria
A51: 2 | B51: Estructura Senior / Subordinada | C51: Evaluar emisión de cuotapartes Clase A (senior, renta fija, prioridad de cobro) y Clase B (subordinada, equity, con carry). Alternativa: línea de crédito bancaria con colateral de cartera hipotecaria. El leverage permite incrementar TIR equity de ~8.2% a ~10% con 1x y deuda al 6.5%. | D51: PENDIENTE — Definir timing y estructura
A52: 3 | B52: Timing del apalancamiento | C52: Se recomienda introducir leverage a partir de Serie 2 o 3 del fondo, una vez establecido track record de originación y cobranza (12-18 meses mínimo). Esto es consistente con la práctica de mercado y facilita pricing de la deuda senior. | D52: PROVISORIO — Sujeto a track record
A53: 4 | B53: Covenants y protecciones | C53: Covenants típicos para deuda senior hipotecaria: (i) LTV estructura ≤60%, (ii) DSCR mínimo 1.3x, (iii) subordinación mínima 40%, (iv) mora >90 días <5% de cartera, (v) ratio cobertura de intereses. Ver pestaña LEVERAGE ANALYSIS para sensibilidad. | D53: PROVISORIO — Negociar con proveedor de deuda
A54: 5 | B54: Impacto en reglamento de gestión | C54: La cláusula de endeudamiento debe figurar expresamente en el reglamento de gestión aprobado por CNV. Debe especificar: (a) límite máximo de endeudamiento, (b) tipos de deuda permitidos, (c) requisito de autorización previa CNV, (d) información a cuotapartistas. Lendar (Cl. 16.1.5) es modelo a seguir. | D54: ACCIÓN REQUERIDA — Incluir en borrador de reglamento
A55: 6 | B55: Cláusula de ejecución extrajudicial | C55: Incluir en reglamento cláusula que habilite ejecución extrajudicial de hipotecas bajo Ley 24.441, Título V (Arts. 52-67). Cada contrato de mutuo hipotecario deberá contener cláusula expresa de sometimiento. Ventaja: plazos de 3-6 meses vs 6-24 meses judicial. | D55: ACCIÓN — Incluir en borrador de reglamento y modelo de contrato
A56: 7
A57: 8 | B57: Cláusula de venta/securitización de créditos | C57: Habilitar en reglamento que el FCIC pueda: (a) vender créditos individuales de su cartera a terceros, y (b) securitizar paquetes de créditos (emitir VDF u otros instrumentos respaldados por la cartera). Permite gestión activa de cartera y generación de liquidez. | D57: ACCIÓN — Incluir en reglamento. Clave para way-out y liquidez.
A60: SECCIÓN V — RÉGIMEN DE COBRANZA Y EJECUCIÓN HIPOTECARIA
A61: 1 | B61: Régimen de ejecución hipotecaria | C61: Ejecución extrajudicial bajo Ley 24.441, Título V, Arts. 52-67. Permite ejecutar hipotecas sin intervención judicial cuando el contrato incluye cláusula expresa. Plazo estimado: 3-6 meses (vs 6-24 meses vía judicial). | D61: RECOMENDADO — Ventaja operativa clave
A62: 2 | B62: Legitimación activa para ejecutar | C62: La Sociedad Depositaria (Banco Comafi) es la legitimada activa como titular fiduciario de los créditos del FCIC. El Asesor de Inversión (CTG/TCMC) coordina operativamente vía mandato otorgado por la Depositaria. | D62: CONFIRMAR con Banco Comafi
A63: 3
A64: 4 | B64: Costo máximo de ejecución | C64: Ley 24.441 establece tope de 3% del monto del crédito para costos de ejecución extrajudicial (honorarios, tasación, publicación). | D64: CONFIRMADO — Ley 24.441
A65: 5 | B65: Mora y procedimiento pre-ejecución | C65: Previo a ejecución: (i) intimación fehaciente al deudor (30 días), (ii) intervención de escribano para acta de constatación de mora, (iii) tasación del inmueble, (iv) publicación de edictos por 3 días. | D65: PROVISORIO — Definir política de gestión de mora
A67: SECCIÓN VI — OBJETO SOCIAL CAPITAL TOKEN GROUP
A68: 1 | B68: Borrador recomendado | C68: Se recomienda el borrador ajustado (v2) que incluye incisos d) y e) excluyendo expresamente actividades reguladas por Ley 21.526 (entidades financieras) y normativa BCRA. Esto evita que CTG sea considerada intermediaria financiera. | D68: RECOMENDADO — Usar borrador v2 (ajustado)
A69: 2 | B69: Incisos clave del objeto social | C69: a) Asesoramiento en inversiones y FCI. b) Originación y administración de créditos hipotecarios como mandatario. c) Desarrollo tecnológico para plataformas fintech. d) Exclusión Ley 21.526. e) Exclusión captación de ahorro público. | D69: PROVISORIO — Validar con abogado societario
A70: 3 | B70: Riesgo regulatorio | C70: Sin los incisos d) y e), CTG podría ser interpretada como entidad financiera no autorizada (Art. 7, Ley 21.526). La exclusión expresa protege ante BCRA y UIF. | D70: CRÍTICO — No omitir exclusiones

Sheet TODO LIST
A1: TODO LIST — TCMC FCIC
A2: Última reunión: 31 marzo 2026 | Próximo follow-up: semana 7-11 abril 2026
A4: A. ACCIONES POST-REUNIÓN 31/03/2026
A5: # | B5: Prioridad | C5: Tarea / Descripción | D5: Responsable | E5: Consultar con | F5: Deadline | G5: Estado / Notas
A6: 1 | B6: ALTA | C6: Elaborar Term Sheet (TS) del FCIC — resumen de términos y condiciones | D6: Gonzalo Ortiz / Pancho | E6: TCA (asesores legales) | F6: 10/04/2026 | G6: PENDIENTE — Usar datos Tanoira (Sección C) como base
A7: 2 | B7: ALTA | C7: Validar comisión up-front 5% que abona tomador a favor del FCIC | D7: Pancho | E7: TCA / SL (asesor fiscal) | F7: 10/04/2026 | G7: PENDIENTE — Definir si es IVA gravado
A8: 3 | B8: ALTA | C8: Confirmar si extensión de plazo FCIC (~5 a ~11 años) mantiene reducción/exención de IG | D8: CONO SUR | E8: SL (asesor fiscal in-house) | F8: 10/04/2026 | G8: PENDIENTE — Clave para definición de plazo
A9: 4 | B9: ALTA | C9: Definir mecanismo de liquidación (way out) del FCIC | D9: CONO SUR | E9: TCA (asesores legales) | F9: Reunión follow-up | G9: PENDIENTE
A10: 5 | B10: ALTA | C10: Definir mecanismo para ampliar monto o emitir nueva serie | D10: Gonzalo Ortiz / Pancho | E10: TCA (asesores legales) | F10: Reunión follow-up | G10: PENDIENTE
A11: 6 | B11: MEDIA | C11: Programa de liquidez para cuotapartes del FCIC | D11: CONO SUR | E11: A3 / BYMA (mercados) | F11: Reunión follow-up | G11: PENDIENTE — Evaluar market maker
A12: 7 | B12: MEDIA | C12: Mecanismo de recompra de cuotapartes por parte del FCIC | D12: Gonzalo Ortiz / Pancho | E12: TCA (asesores legales) | F12: Reunión follow-up | G12: PENDIENTE
A13: 8 | B13: MEDIA | C13: Apalancamiento mediante financiamiento garantizado con créditos del FCIC | D13: Gonzalo Ortiz / Pancho | E13: TCA / potenciales inversores | F13: Reunión follow-up | G13: PENDIENTE — Evaluar viabilidad regulatoria
A14: 9 | B14: MEDIA | C14: Mecanismo de venta de créditos por parte del FCIC | D14: CONO SUR | E14: TCA (asesores legales) | F14: Reunión follow-up | G14: PENDIENTE
A15: 10 | B15: ALTA | C15: Compartir TS con TCA, FAs de ConoSur y potenciales colocadores/distribuidores | D15: Gonzalo Ortiz / Pancho | E15: — | F15: Post 10/04 | G15: PENDIENTE — Depende de #1
A16: 11 | B16: ALTA | C16: Agendar reunión de follow-up | D16: Pancho | E16: Todos | F16: Semana 7-11/04 | G16: PENDIENTE
A18: B. FACTURACIÓN TCA (TANOIRA CASSAGNE) — USD 6.000 (30% gestión)
A19: # | B19: Prioridad | C19: Tarea / Descripción | D19: Responsable | E19: Consultar con | F19: Deadline | G19: Estado / Notas
A20: 12 | B20: ALTA | C20: Proveer datos de facturación a TCA para emisión factura USD 6K (30% valor gestión) | D20: Pancho | E20: TCA | F20: URGENTE | G20: Me contacto desde la administración de TCA Tanoira Cassagne. Nos encontramos en condiciones de avanzar con la facturación de USD 6.000 + impuestos, en concepto de FCI Cerrado - Cuota 1 - 30% emitida de manera anticipada al inicio de los trabajos Agradeceremos que nos brinden su conformidad y nos proporcionen los datos de facturación correspondientes para proceder con la emisión.
A21: 13 | B21: MEDIA | C21: Confirmar forma de pago y moneda de facturación | D21: Pancho | E21: TCA | F21: ASAP | G21: PENDIENTE
A23: C. INFORMACIÓN REQUERIDA POR TCA (TANOIRA CASSAGNE) — Para Reglamento y Prospecto
A25: C.1. DEFINICIONES ESTRUCTURALES DEL FCIC (15 puntos — para borrador de Reglamento de Gestión)
A26: # | C26: Pregunta / Requerimiento TCA | D26: Responsable | E26: Respuesta / Definición | F26: Estado | G26: Notas para TS
A27: C1.1 | C27: Nombre del FCIC | D27: Pancho / Gonzalo | F27: PENDIENTE | G27: Debe constar desde el inicio para actas de creación
A28: C1.2 | C28: Participantes: Depositaria / Asesor de Inversión / Comité de Inversiones (integración y pautas) | D28: Pancho / Gonzalo | F28: PENDIENTE | G28: Definir roles y funcionamiento
A29: C1.3 | C29: Monto del FCIC y cantidad de cuotapartes / posibilidad de aumento y nueva emisión | D29: Pancho / Gonzalo | F29: PENDIENTE | G29: Relacionado con tarea #5
A30: C1.4 | C30: Plazo del FCIC | D30: Pancho / SL | F30: PENDIENTE | G30: Relacionado con tarea #3 (5Y vs 11Y)
A31: C1.5 | C31: Objetivo de inversión del FCIC | D31: Pancho | F31: PENDIENTE | G31: Micro-hipotecas residenciales
A32: C1.6 | C32: Principales activos elegibles | D32: Pancho | F32: PENDIENTE | G32: Créditos hipotecarios
A33: C1.7 | C33: Tipos de inversión en los activos elegibles | D33: Pancho | F33: PENDIENTE
A34: C1.8 | C34: Pautas de diversificación y condiciones de elegibilidad de activos | D34: Pancho | F34: PENDIENTE | G34: LTV, cuota/ingreso, scoring
A35: C1.9 | C35: Formas de valuación de activos | D35: Pancho / Gonzalo | F35: PENDIENTE
A36: C1.10 | C36: Tipo y Clases de cuotapartes | D36: Pancho / TCA | F36: PENDIENTE
A37: C1.11 | C37: Moneda del FCIC y bimonetariedad (suscripción/rescate en otras monedas) | D37: Pancho | F37: PENDIENTE | G37: USD base
A38: C1.12 | C38: Forma de integración (posibilidad de integración en especie) | D38: Pancho / TCA | F38: PENDIENTE
A39: C1.13 | C39: Distribución de utilidades / posibilidad de capitalización | D39: Pancho / Gonzalo | F39: PENDIENTE | G39: Ver waterfall del modelo
A40: C1.14 | C40: Supuesto de rescate parcial anticipado | D40: Pancho / TCA | F40: PENDIENTE | G40: Relacionado con tarea #7
A41: C1.15 | C41: Forma de liquidación del FCIC | D41: Pancho / TCA | F41: PENDIENTE | G41: Relacionado con tarea #4
A43: C.2. DATOS DEL ASESOR DE INVERSIÓN — Para Prospecto (13 puntos)
A44: # | C44: Dato Requerido por TCA | D44: Responsable | E44: Dato / Documento | F44: Estado | G44: Notas
A45: C2.1 | C45: Denominación social | D45: Pancho | F45: PENDIENTE | G45: Nombre legal de +Cerca
A46: C2.2 | C46: CUIT | D46: Pancho | F46: PENDIENTE
A47: C2.3 | C47: Sede Social | D47: Pancho | F47: PENDIENTE | G47: Dirección legal
A48: C2.4 | C48: Estatuto Social | D48: Pancho | F48: PENDIENTE | G48: Adjuntar copia certificada
A49: C2.5 | C49: Dirección de email | D49: Pancho | F49: PENDIENTE | G49: Email corporativo
A50: C2.6 | C50: Página web | D50: Pancho | F50: PENDIENTE | G50: tucasamascerca.com.ar o similar
A51: C2.7 | C51: Datos registrales ante Registro Público de Comercio | D51: Pancho | F51: PENDIENTE
A52: C2.8 | C52: Nómina de miembros del Órgano de Administración y Fiscalización (fecha designación y vto. mandato) | D52: Pancho | F52: PENDIENTE | G52: Incluir directores y síndicos
A53: C2.9 | C53: Nómina de Accionistas y/o Socios | D53: Pancho | F53: PENDIENTE
A54: C2.10 | C54: Antecedentes personales, técnicos y empresariales de administradores (educación, experiencia) | D54: Pancho | F54: PENDIENTE | G54: CVs de cada administrador
A55: C2.11 | C55: Reseña histórica de la empresa (información comercial/promocional) | D55: Pancho | F55: PENDIENTE | G55: Para sección del Prospecto
A56: C2.12 | C56: EECC anuales últimos 3 ejercicios (si existen) | D56: Pancho | F56: PENDIENTE | G56: Si la empresa es nueva, indicarlo
A57: C2.13 | C57: Información sobre política ambiental (si existe) | D57: Pancho | F57: PENDIENTE | G57: Opcional pero recomendable
A59: D. CLÁUSULAS CLAVE PARA REGLAMENTO DE GESTIÓN (Definidas 06/04/2026)
A60: # | B60: Prioridad | C60: Cláusula / Tema | D60: Responsable | E60: Consultar con | F60: Deadline | G60: Estado / Notas
A61: 14 | B61: ALTA | C61: Incluir cláusula de ejecución extrajudicial (Ley 24.441 Título V) en reglamento y modelo de contrato de mutuo hipotecario | D61: Pancho / Gonzalo | E61: TCA (asesores legales) | F61: Para TS 10/04 | G61: PENDIENTE — Ventaja operativa: 3-6 meses vs 6-24 judicial
A62: 15 | B62: ALTA | C62: Habilitar en reglamento adquisición de créditos hipotecarios de terceros (bancos, fintech, otros fondos) | D62: Pancho / Gonzalo | E62: TCA (asesores legales) | F62: Para TS 10/04 | G62: PENDIENTE — Flexibiliza crecimiento y diversificación
A63: 16 | B63: ALTA | C63: Habilitar en reglamento venta de créditos individuales a terceros + securitización de paquetes de cartera (VDF u otros) | D63: Pancho / Gonzalo | E63: TCA (asesores legales) | F63: Para TS 10/04 | G63: PENDIENTE — Clave para way-out y gestión activa de cartera
A64: 17 | B64: ALTA | C64: Replantear tope de gastos: NO fijar 5.4% fijo (como Lendar). Definir rendimiento objetivo en plazo propuesto. Fondo a riesgo, no renta fija. | D64: Pancho / Gonzalo | E64: TCA / ConoSur | F64: Para TS 10/04 | G64: PENDIENTE — Evitar que sponsor cubra desfasajes momentáneos
A65: 18 | B65: ALTA | C65: Incluir cláusula habilitante de apalancamiento (hasta 1x PN, previa CNV). Es alternativa, no obligatoria. | D65: Pancho / Gonzalo | E65: TCA (asesores legales) | F65: Para TS 10/04 | G65: PENDIENTE — Ref: Lendar Cl. 16.1.5
A66: 19 | B66: ALTA | C66: Confirmar fee asesor originación en 1.5% (cobrado al fondo, no al tomador). Upfront 5% íntegro al fondo. | D66: Pancho | E66: ConoSur / TCA | F66: Para TS 10/04 | G66: DEFINIDO 06/04 — Actualizar modelo
A67: 20 | B67: MEDIA | C67: Validar con SL si extensión de 5Y a 11Y mantiene beneficios IG (Art. 206 Ley 27.440) | D67: Pancho | E67: SL (asesor fiscal) | F67: Antes de TS | G67: PENDIENTE — Crítico para definición de plazo
A71: NOTA: Los datos de la Sección C.2 son los que TCA necesita para facturar USD 6K (30% gestión). La Sección D agrupa las cláusulas clave que deben incluirse en el borrador de reglamento de gestión y en el Term Sheet (TS) del 10/04.

Sheet SUPUESTOS
A1: MODELO TCMC — FCIC HIPOTECARIO (Cono Sur Investments)
A2: Basado en Propuesta ConoSur a Capital Token Group S.A., Marzo 2026. Capital: USD 5M Tramo I. Plazo base: 5yr / Alt: 11yr.
B3: TCMC (TBD) | C3: Detalle / Fuente | D3: LENDAR (Allaria) | E3: Detalle / CI (Cláusula Informativa)
A5: I. PARÁMETROS DEL FONDO
A6: Capital Inicial (USD) | B6: 3000000 | C6: Tramo 1 — Propuesta ConoSur Mar-2026: ≈USD 5M (ampliable). Mín emisión: USD 2.5M, Máx: USD 100M | D6: 3000000 | E6: No publicado. Usamos 3M como referencia. | F6: 2.4 Mínimo de emisión: 2.500.000 Máximo 100.000.000
A7: Plazo del Fondo (años) | B7: 11 | C7: Base: 5yr (ConoSur) / Alt: 11yr. ≈5 años con opción de extensión | D7: 11 | E7: Plazos crédito hasta 11 años. Cl. 16.3.5 | F7: 2.3.3 El vencimiento de los diversos créditos hipotecarios originados y/o adquiridos por el Fondo podrá operar con posterioridad al vencimiento del Plazo del Fondo.
A8: Ticket Promedio Crédito (USD) | B8: 40000 | C8: ≈USD 30,000 por crédito. Plazos 1-3 años. Aforos ≈30% | D8: N/D | E8: No publicado
A9: LTV Máximo | B9: 0.35 | C9: 30% — Propuesta ConoSur Mar-2026 | D9: 0.35 | E9: Presentación prensa Lendar | F9: 3.2.5 | G9: LTV máximo 35% según Cl. 3.2.5 Reglamento
A10: Moneda | B10: USD | C10: Dólares estadounidenses — Propuesta ConoSur Mar-2026 | D10: USD | E10: Cl. 2.5: "La moneda del Fondo será el Dólar Estadounidense"
A12: II. MIX DE CRÉDITOS
A13: Plazo (años) | B13: Tasa TNA | C13: Distribución % | D13: Lendar Tasa TNA | E13: Fuente CI
A14: 1 | B14: 0.105 | C14: 0.1 | D14: 0.095 | E14: Cl. 16.3.5 — piso de rango | G14: =-PMT((B14/12),(12*A14),(C14*B$6)) -> 26444.581
A15: 2 | B15: 0.115 | C15: 0.25 | D15: 0.105 | E15: 2.7 | G15: =-PMT((B15/12),(12*A15),(C15*B$6)) -> 35130.236
A16: 3 | B16: 0.125 | C16: 0.4 | D16: 0.115 | E16: 2.7 | G16: =-PMT((B16/12),(12*A16),(C16*B$6)) -> 40144.351
A17: 4 | B17: 0.135 | C17: 0.15 | D17: 0.125 | E17: 2.7 | G17: =-PMT((B17/12),(12*A17),(C17*B$6)) -> 12184.345
A18: 5 | B18: 0.145 | C18: 0.1 | D18: 0.135 | E18: Cl. 16.3.5 — techo de rango | G18: =-PMT((B18/12),(12*A18),(C18*B$6)) -> 7058.4843
G19: =SUM(G14:G18) -> 120962
A20: WAL (años) | B20: =A14*C14+A15*C15+A16*C16+A17*C17+A18*C18 -> 2.9 | G20: =G19*12 -> 1451544
A21: Tasa Media Ponderada | B21: =B14*C14+B15*C15+B16*C16+B17*C17+B18*C18 -> 0.124
A22: Rotación Anual (1/WAL) | B22: =1/B20 -> 0.34482759
A23: Rotación Imperfecta | B23: 1
A24: Tasa Media Ajustada | B24: =B21*B23 -> 0.124 | C24: =B24*0.7 -> 0.0868
A26: III. COSTOS DEL FONDO (% sobre PN)
A27: Concepto | B27: TCMC | C27: Detalle | D27: LENDAR | E27: CI Lendar
A28: Honorarios Soc. Gerente (anual) | B28: 0.012 | C28: 1.20% anual PN — Cono Sur S.G.F.C.I.S.A. (Propuesta ConoSur Mar-2026) | D28: 0.0125 | E28: Cl. 16.5.1: 1.25% anual del PN | F28: 10.1 | G28: Cl. 10.1: máx 1.20% anual del PN. Liquidación trimestral + IVA.
A29: Honorarios Soc. Depositaria (anual) | B29: 0.002 | C29: 0.20% anual PN neto — Banco Comafi S.A. (a confirmar). Mín USD 21,600+IVA/año (Propuesta ConoSur) | D29: 0.002 | E29: Cl. 16.5.2: 0.20% anual del PN. NOTA: parece caro vs mercado | F29: 10.3 | G29: Mínimo de 21600 USD + IVA anual. Fee inicial de 10000 USD + IVA (one-time). Si 0.2%*PN < 21600, aplica el mínimo.
A30: Honorarios Asesor Inversión (anual % PN) | B30: 0 | C30: Opción A (activa): SIN mgmt fee % PN, cobra por crédito. Alt B: 1% PN + 10% carry >6% hurdle (Propuesta ConoSur) | D30: 0 | E30: NO cobra % anual PN. Cobra one-time por crédito (ver abajo) | F30: 16.5 | G30: Lendar Cl. 16.5: NO prevé mgmt fee % PN para asesor. Solo fee por crédito (1%/0.7%)
A31: Fee Asesor por crédito originado (one-time) | B31: 0.0125 | C31: 1% por crédito originado — Propuesta ConoSur Mar-2026 (antes 1.5%) | D31: 0.01 | E31: Cl. 16.5.5: 1% por crédito originado directamente | F31: 16.5.5 | G31: Cl. 16.5.5: ≤1% anual del valor de cada crédito originado + IVA
A32: Fee Asesor por crédito adquirido (one-time) | B32: 0.01 | C32: 1% por crédito adquirido — Propuesta ConoSur Mar-2026 | D32: 0.007 | E32: Cl. 16.5.5: 0.7% por crédito adquirido a terceros | F32: 16.5.5 | G32: Cl. 16.5.5: ≤0.7% anual del valor de cada crédito adquirido + IVA
A33: Carried Interest | B33: 0.1 | C33: 10% sobre exceso hurdle — Opción B de Propuesta ConoSur Mar-2026. EDITABLE. | D33: 0 | E33: Cl. 16.4: No previsto. "No se garantiza rendimiento"
A34: Hurdle Rate | B34: 0.06 | C34: 6% hurdle rate — Propuesta ConoSur Mar-2026 (antes 10%). EDITABLE. | D34: 0 | E34: N/A — sin carry, sin hurdle
A35: Tope Máximo Gastos (Reglamento) | B35: 0.054 | C35: 5.4% anual PN — Propuesta ConoSur Mar-2026 | D35: 0.054 | E35: Cl. 16.5: Tope 5.4% anual PN | F35: 10.5 | G35: Cl. 10.5: tope gastos ordinarios + hon. Adm + Cust = 5.4% + IVA
A36: Comisión Colocadores (one-time) | B36: 0.015 | C36: 1.5% del monto suscripto — Propuesta ConoSur Mar-2026 | D36: 0.015 | E36: Cl. 16.5.4: 0.5% del monto suscripto | F36: 10.4
A37: Comisión Organizador (one-time) | B37: 0.0025 | C37: 0.25% del monto suscripto — Cono Sur Inversiones S.A. (Propuesta ConoSur Mar-2026) | D37: 0.0025 | E37: Incluida en Soc. Gerente según reglamento | F37: 10.4
A38: Upfront Fee al Fondo | B38: 0.05 | C38: 5% del monto otorgado (4% al fondo + 1% extracción asesor) — Propuesta ConoSur Mar-2026 | D38: 0.05 | E38: Cl. 16.3.5: 5% + IVA cobrado al tomador. Ingresa al fondo. | F38: 2.7 | G38: Cl. 2.7: CFT = tasa + amort + 5% fee + IVA. Cobrado al tomador.
A39: IVA | B39: 0.21 | D39: 0.21
A40: Mín. Anual Soc. Depositaria (USD sin IVA) | B40: 21600 | C40: Cl. 10.3: aplica si 0.2%*PN < este mínimo | D40: 21600 | E40: Cl. 10.3
A41: IV. COSTOS FIJOS ANUALES (USD)
A42: Auditoría externa | B42: 10000 | C42: Anual
A43: Asesoría legal | B43: 10000 | C43: Anual
A44: Set Up: Abogados + Fee Inicial Depositaria (solo Año 1) | B44: 12100 | C44: One-time. Fee Depositaria: USD 10,000+IVA (Cl. 10.3)
A45: Asesoría contable / impositiva | B45: 12000 | C45: Anual
A46: Valuadores independientes | B46: 12000 | C46: Anual | D46: NAv | E46: =B46/3000000 -> 0.004
A47: Gastos bancarios operativos | B47: 6000 | C47: Anual
A48: Custodia documental | B48: 6000 | C48: Anual
A50: V. PARÁMETROS DE APALANCAMIENTO
A51: Leverage máximo autorizado (x PN) | B51: 1 | C51: Ratio deuda/equity | D51: 1 | E51: Cl. 16.1.5: hasta 1x PN, previa autorización CNV | F51: 16.1 | G51: Cl. 16.1: endeudamiento no podrá superar PN del último EECC
A52: Leverage efectivo usado (x PN) | B52: 0.5 | C52: Supuesto: 0.5x inicialmente, creciente
A53: Año inicio apalancamiento | B53: 3 | C53: Desde año 3 (track record necesario)
A54: Costo deuda senior (USD, base) | B54: 0.08 | C54: Tasa USD para línea senior con colateral hipotecario
A56: VI. RESCATES / RETIROS PARCIALES (2 CASOS)
A57: Caso 1: Fondo de Liquidez — Monto editable por año en FLUJO fila 72 | B57: 50000 | C57: Propuesta ConoSur: ≈20% PN por evento, a partir mes 24. Proveedores de Liquidez ≈25% PN | D57: 3 | E57: Cl. 16.8: después de 2 años mínimos | F57: 6.11 | G57: Cl. 6.11: rescate parcial desde año 3, máx 20% PN, periodicidad anual
A58: Caso 2: Año inicio retiro variable | B58: 0.2 | C58: Rescate parcial: ≈20% PN por evento (Si > prorrateo), desde mes 24 — Propuesta ConoSur | D58: 0.2 | E58: Cl. 16.8: penalidad hasta 5% del monto rescatado | F58: 6.11 | G58: Cl. 6.11: máximo 20% del patrimonio por evento de rescate
A59: Fee sobre retiros (% del monto retirado) | B59: 0 | C59: EDITABLE — Propuesta ConoSur no define penalidad explícita. 0% default. | D59: 0.05 | E59: Cl. 16.8: hasta 5% penalidad | F59: 6.11 | G59: Lendar Cl. 6.11: no prevé penalidad explícita, pero TCMC podría definirla
A60: Penalidad rescate anticipado (adicional, si aplica) | B60: 0 | C60: Sin penalidad adicional (a definir en reglamento). EDITABLE.
A61: Honorarios Hacedor de Mercado (fuera del fondo) | B61: 0.012 | C61: 1.2% anual (all in cost) sobre valor de mercado activos Proveedores de Liquidez — Propuesta ConoSur
A62: VII. IMPACTO FISCAL RESCATES
A63: Alícuota Ganancias PF Residente (renta financiera) | B63: 0.15 | C63: Dto. 382/2019, Art.90 Ley 20.628 | F63: Prospecto p.8 | G63: Art.90 Ley 20.628, Dto.382/2019. 15% cedular USD si >5 años de vida del fondo.
A64: Alícuota Ganancias PJ Residente | B64: 0.15 | C64: Cedular moneda extranjera
A65: Base imponible rescate | C65: Solo la GANANCIA: (Valor Cuotaparte Rescate - Valor Cuotaparte Suscripción)
A66: Retención en la fuente | C66: Soc. Gerente retiene al momento del rescate (Art.90 bis Ley 20.628)
A68: VIII. CIERRE / WIND-DOWN
A69: Tasa Securitización (cierre) | B69: 0.09 | F69: Supuesto | G69: Discount rate para securitizar cartera remanente al cierre. No regulatorio.
A70: Año cierre / wind-down | B70: 11 | C70: Año 11 = 2036 (último año)
A72: IX. UPFRONT FEE EXTRACTION (Análisis Asesor)
A73: Upfront total al tomador | B73: 0.05 | C73: 5% + IVA cobrado al deudor hipotecario — Propuesta ConoSur Mar-2026
A74: Porción que ingresa al fondo | B74: =B38 -> 0.05 | C74: 4% ingresa al fondo como ingreso — Propuesta ConoSur
A75: Extracción pre-fondo (asesor) | B75: =B73-B74 -> 0 | C75: 1% se cobra antes de que entre al fondo (asesor). Sujeto a aprobación — Propuesta ConoSur
A76: IVA sobre extracción | B76: 0.21 | C76: IVA facturado por asesor
A77: Tasa Media | B77: Row 21
A78: Rot Anual | B78: Row 22
A79: Rot Imperfecta | B79: Row 23
A80: Tasa Ajust | B80: Row 24
A81: Gerente | B81: Row 28
A82: Depo | B82: Row 29
A83: Asesor %PN | B83: Row 30
A84: Asesor Orig | B84: Row 31
A85: Asesor Adq | B85: Row 32
A86: Carry | B86: Row 33
A87: Hurdle | B87: Row 34
A88: Tope | B88: Row 35
... A103: Tasa Sec | B103: Row 69
A105: X. PARTICIPANTES DEL FONDO (Propuesta ConoSur Mar-2026)
A106: Nombre del Fondo | B106: TCMC Tramo I o "Tu Casa Más Cerca" Tramo I (a confirmar)
A107: Tipo de Fondo | B107: Fondo Común de Inversión Cerrado de Créditos (FCIC)
A108: Sociedad Gerente | B108: Cono Sur S.G.F.C.I.S.A.
A109: Sociedad Depositaria | B109: Banco Comafi S.A. (a confirmar)
A110: Asesor de Inversión | B110: Capital Token Group S.A. (en formación)
A111: Organizador, Asesor Financiero y Hacedor de Mercado | B111: Cono Sur Inversiones S.A.
A112: Proveedores de Liquidez | B112: A ser designados (≈25% del patrimonio neto del fondo)
A113: Porcentaje mínimo en activos específicos | B113: ≈75% del patrimonio del fondo
A114: Activos transitorios | B114: FCI money market, depósitos bancarios, títulos públicos, ONs, VDF, cauciones
A115: Objetivo de inversión | B115: Créditos hipotecarios a personas humanas, ≈USD 30K, plazos 1-3 años, aforos ≈30%
A116: Liquidación del FCIC | B116: Al vencimiento del plazo, por decisión de asamblea o eventos regulatorios
A117: Anticipo Organizador (no reembolsable) | B117: 6250 | C117: USD 6,250 — a cuenta Comisión Organizador. 15 días corridos.

Sheet FLUJO 5 AÑOS (5Y)
A1: FLUJO DEL FONDO — MODELO TCMC 5 AÑOS (Cono Sur / Capital Token Group, USD 5M)
A3: AÑO | B3: 2026 | C3: 2027 | D3: 2028 | E3: 2029 | F3: 2030 | G3: TOTAL
A4: A. CAPITAL Y ORIGINACIÓN | B4: 0.9 | C4: 1 | D4: 1 | E4: 1 | F4: 1
A5: Cartera Total Desplegada Inicio | B5: =B47*(1-SUPUESTOS!$B$36-SUPUESTOS!$B$37)+B14 -> 2947500 | C5: =B9+B42+C14-B14 -> 3187809.9 | D5: =C9+C42+D14-C14 -> 4985016.5 | E5: =D9+D42+E14-D14 -> 5237747 | F5: =E9+E42+F14-E14 -> 5467012.8
A6: Capital Liberado (Amortización) | B6: =B5*SUPUESTOS!$B$22 -> 1016379.3 | C6: =C5*SUPUESTOS!$B$22 -> 1099244.8 | D6: =D5*SUPUESTOS!$B$22 -> 1718971.2 | E6: =E5*SUPUESTOS!$B$22 -> 1806119.7 | F6: =F5*SUPUESTOS!$B$22 -> 1885176.8
A7: ¿Año de Originación Activa? | B7: 1 | C7: 1 | D7: 1 | E7: 1 | F7: 0
A8: Nuevos Créditos (re-originación) | B8: =IF(B7=1,B6*SUPUESTOS!$B$23,0) -> 1016379.3 | C8: =IF(C7=1,C6*SUPUESTOS!$B$23,0) -> 1099244.8 | D8: =IF(D7=1,D6*SUPUESTOS!$B$23,0) -> 1718971.2 | E8: =IF(E7=1,E6*SUPUESTOS!$B$23,0) -> 1806119.7 | F8: =IF(F7=1,F6*SUPUESTOS!$B$23,0) -> 0
A9: Stock de Capital Fin Año | B9: =B5-B6+B8 -> 2947500 | C9: =C5-C6+C8 -> 3187809.9 | D9: =D5-D6+D8 -> 4985016.5 | E9: =E5-E6+E8 -> 5237747 | F9: =F5-F6+F8 -> 3581836
A10: Volumen Total Originado | B10: =B5+B8 -> 3963879.3 | C10: =C8+MAX(0,C5-B9) -> 1339554.7 | D10: =D8+MAX(0,D5-C9) -> 3516177.8 | E10: =E8+MAX(0,E5-D9) -> 2058850.2 | F10: =F8+MAX(0,F5-E9) -> 229265.82 | G10: =SUM(B10:F10) -> 11107728
A12: B. APALANCAMIENTO (editar fila 13: 1=ajustar deuda al 50% PN, 0=mantener nivel anterior)
A13: ¿Ajustar deuda? (1=reset a 0.5x PN, 0=mantener) — editable por año | B13: 0 | C13: 0 | D13: 1 | E13: 0 | F13: 0 | G13: 0
A14: Deuda Senior (monto) | B14: =IF(B13=1, B47*SUPUESTOS!$B$52, 0) -> 0 | C14: =IF(C13=1, C47*SUPUESTOS!$B$52, B14) -> 0 | D14: =IF(D13=1, D47*SUPUESTOS!$B$52, C14) -> 1679172.2 | E14: =IF(E13=1, E47*SUPUESTOS!$B$52, D14) -> 1679172.2 | F14: =IF(F13=1, F47*SUPUESTOS!$B$52, E14) -> 1679172.2
A15: Capital Total Desplegado (Equity + Deuda) | B15: =B5 -> 2947500 | C15: =C5 -> 3187809.9 | D15: =D5 -> 4985016.5 | E15: =E5 -> 5237747 | F15: =F5 -> 5467012.8
A16: Leverage Ratio (Deuda / PN Inicio) | B16: =IF(B5>0,B14/B5,0) -> 0 | C16: =IF(C5>0,C14/C5,0) -> 0 | D16: =IF(D5>0,D14/D5,0) -> 0.33684385 | E16: =IF(E5>0,E14/E5,0) -> 0.32059054 | F16: =IF(F5>0,F14/F5,0) -> 0.30714619
A18: C. INGRESOS
A19: Interés Ganado (sobre capital total desplegado) | B19: =((B5+B9)/2)*SUPUESTOS!$B$24*B4 -> 328941 | C19: =((C5+C9)/2)*SUPUESTOS!$B$24*C4 -> 395288.42 | D19: =((D5+D9)/2)*SUPUESTOS!$B$24*D4 -> 618142.04 | E19: =((E5+E9)/2)*SUPUESTOS!$B$24*E4 -> 649480.63 | F19: =((F5+F9)/2)*SUPUESTOS!$B$24*F4 -> 561028.63 | G19: =SUM(B19:F19) -> 2552880.7
A20: Upfront Fee (4% al Fondo) | B20: =(B10/(1+SUPUESTOS!$B$38))*SUPUESTOS!$B$38 -> 188756.16 | C20: =(C10/(1+SUPUESTOS!$B$38))*SUPUESTOS!$B$38 -> 63788.317 | D20: =(D10/(1+SUPUESTOS!$B$38))*SUPUESTOS!$B$38 -> 167437.04 | E20: =(E10/(1+SUPUESTOS!$B$38))*SUPUESTOS!$B$38 -> 98040.484 | F20: =(F10/(1+SUPUESTOS!$B$38))*SUPUESTOS!$B$38 -> 10917.42 | G20: =SUM(B20:F20) -> 528939.42
A21: TOTAL INGRESOS FONDO | B21: =B19+B20 -> 517697.16 | C21: =C19+C20 -> 459076.74 | D21: =D19+D20 -> 785579.08 | E21: =E19+E20 -> 747521.11 | F21: =F19+F20 -> 571946.05 | G21: =SUM(B21:F21) -> 3081820.1
A23: D. COSTOS DEL FONDO
A24: Honorarios Soc. Gerente (1.2%) | B24: =B47*SUPUESTOS!$B$28 -> 36000 | C24: =C47*SUPUESTOS!$B$28 -> 38883.718 | D24: =D47*SUPUESTOS!$B$28 -> 40300.132 | E24: =E47*SUPUESTOS!$B$28 -> 43332.898 | F24: =F47*SUPUESTOS!$B$28 -> 46084.088 | G24: =SUM(B24:F24) -> 204600.84
A25: Honorarios Soc. Depositaria (0.2%, mín $21,600/yr + $10K inicial Y1) | B25: =MAX(B47*SUPUESTOS!$B$29,SUPUESTOS!$B$40)+10000 -> 31600 | C25: =MAX(C47*SUPUESTOS!$B$29,SUPUESTOS!$B$40) -> 21600 | D25: =MAX(D47*SUPUESTOS!$B$29,SUPUESTOS!$B$40) -> 21600 | E25: =MAX(E47*SUPUESTOS!$B$29,SUPUESTOS!$B$40) -> 21600 | F25: =MAX(F47*SUPUESTOS!$B$29,SUPUESTOS!$B$40) -> 21600 | G25: =SUM(B25:F25) -> 118000
A26: Honorarios Asesor Inversión (0% PN — eliminado) | B26: =B47*SUPUESTOS!$B$30 -> 0 | C26: =C47*SUPUESTOS!$B$30 -> 0 | D26: =D47*SUPUESTOS!$B$30 -> 0 | E26: =E47*SUPUESTOS!$B$30 -> 0 | F26: =F47*SUPUESTOS!$B$30 -> 0 | G26: =SUM(B26:F26) -> 0
A27: Fee Asesor (Originación + Adquisición) | B27: =B10*(SUPUESTOS!$B$31) -> 49548.491 | C27: =C10*(SUPUESTOS!$B$31) -> 16744.433 | D27: =D10*(SUPUESTOS!$B$31) -> 43952.223 | E27: =E10*(SUPUESTOS!$B$31) -> 25735.627 | F27: =F10*(SUPUESTOS!$B$31) -> 2865.8228 | G27: =SUM(B27:F27) -> 138846.6
A28: Costos Fijos Operativos | B28: =SUPUESTOS!$B$42+SUPUESTOS!$B$43+SUPUESTOS!$B$44+SUPUESTOS!$B$45+SUPUESTOS!$B$46+SUPUESTOS!$B$47+SUPUESTOS!$B$48 -> 68100 | C28: =SUPUESTOS!$B$42+SUPUESTOS!$B$43+SUPUESTOS!$B$45+SUPUESTOS!$B$46+SUPUESTOS!$B$47+SUPUESTOS!$B$48 -> 56000 | D28: =SUPUESTOS!$B$42+SUPUESTOS!$B$43+SUPUESTOS!$B$45+SUPUESTOS!$B$46+SUPUESTOS!$B$47+SUPUESTOS!$B$48 -> 56000 | E28: =SUPUESTOS!$B$42+SUPUESTOS!$B$43+SUPUESTOS!$B$45+SUPUESTOS!$B$46+SUPUESTOS!$B$47+SUPUESTOS!$B$48 -> 56000 | F28: =SUPUESTOS!$B$42+SUPUESTOS!$B$43+SUPUESTOS!$B$45+SUPUESTOS!$B$46+SUPUESTOS!$B$47+SUPUESTOS!$B$48 -> 56000 | G28: =SUM(B28:F28) -> 292100
A29: Comisiones (Colocador+Org) sobre capital | B29: =(SUPUESTOS!$B$6+B45)*(SUPUESTOS!$B$36+SUPUESTOS!$B$37) -> 52500 | C29: =C45*(SUPUESTOS!$B$36+SUPUESTOS!$B$37) -> 0 | D29: =D45*(SUPUESTOS!$B$36+SUPUESTOS!$B$37) -> 0 | E29: =E45*(SUPUESTOS!$B$36+SUPUESTOS!$B$37) -> 0 | F29: =F45*(SUPUESTOS!$B$36+SUPUESTOS!$B$37) -> 0 | G29: =SUM(B29:F29) -> 52500
A30: IVA sobre Upfront Fee (REVISAR: ¿lo paga el fondo o el tomador?) | B30: =B20*SUPUESTOS!$B$39 -> 39638.793 | C30: =C20*SUPUESTOS!$B$39 -> 13395.547 | D30: =D20*SUPUESTOS!$B$39 -> 35161.778 | E30: =E20*SUPUESTOS!$B$39 -> 20588.502 | F30: =F20*SUPUESTOS!$B$39 -> 2292.6582 | G30: =SUM(B30:F30) -> 111077.28
A31: Intereses Deuda Senior | B31: =B14*SUPUESTOS!$B$54 -> 0 | C31: =C14*SUPUESTOS!$B$54 -> 0 | D31: =D14*SUPUESTOS!$B$54 -> 134333.77 | E31: =E14*SUPUESTOS!$B$54 -> 134333.77 | F31: =F14*SUPUESTOS!$B$54 -> 134333.77 | G31: =SUM(B31:F31) -> 403001.32
A32: TOTAL COSTOS | B32: =B24+B25+B26+B27+B28+B29+B30+B31+B34 -> 277387.28 | C32: =C24+C25+C26+C27+C28+C29+C30+C31+C34 -> 146623.7 | D32: =D24+D25+D26+D27+D28+D29+D30+D31+D34 -> 331347.91 | E32: =E24+E25+E26+E27+E28+E29+E30+E31+E34 -> 301590.8 | F32: =F24+F25+F26+F27+F28+F29+F30+F31+F34 -> 337045.33 | G32: =SUM(B32:F32) -> 1393995
A33: Carry devengado del período | B33: ='RESULTADOS ASESOR TCMC (5Y)'!B14 -> 6030.9873 | C33: ='RESULTADOS ASESOR TCMC (5Y)'!C14 -> 11803.445 | D33: ='RESULTADOS ASESOR TCMC (5Y)'!D14 -> 25273.052 | E33: ='RESULTADOS ASESOR TCMC (5Y)'!E14 -> 22926.582 | F33: ='RESULTADOS ASESOR TCMC (5Y)'!F14 -> 7834.9265 | G33: ='RESULTADOS ASESOR TCMC (5Y)'!G14 -> 73868.993
A34: Carry COBRADO (Success Fee: sólo al cierre Y6, tope 5% Cl.10.5) | B34: ='RESULTADOS ASESOR TCMC (5Y)'!B18 -> 0 | C34: ='RESULTADOS ASESOR TCMC (5Y)'!C18 -> 0 | D34: ='RESULTADOS ASESOR TCMC (5Y)'!D18 -> 0 | E34: ='RESULTADOS ASESOR TCMC (5Y)'!E18 -> 0 | F34: ='RESULTADOS ASESOR TCMC (5Y)'!F18 -> 73868.993 | G34: ='RESULTADOS ASESOR TCMC (5Y)'!G18 -> 73868.993
B35: =(B32-B31)/B48 -> 0.085605172 | C35: =(C32-C31)/C48 -> 0.04127033 | D35: =(D32-D31)/D48 -> 0.051674815 | E35: =(E32-E31)/E48 -> 0.041226723 | F35: =(F32-F31)/F48 -> 0.049742222
A36: =CONCATENATE("SPONSOR SI > ",SUPUESTOS!B35*100,"%") -> SPONSOR SI > 5.4% | B36: =IF(B35>SUPUESTOS!$B$35,(B48*SUPUESTOS!$B$35)-B32,0) -> -102410.55 | C36: =IF(C35>SUPUESTOS!$B$35,(C48*SUPUESTOS!$B$35)-C32,0) -> 0 | D36: =IF(D35>SUPUESTOS!$B$35,(D48*SUPUESTOS!$B$35)-D32,0) -> 0 | E36: =IF(E35>SUPUESTOS!$B$35,(E48*SUPUESTOS!$B$35)-E32,0) -> 0 | F36: =IF(F35>SUPUESTOS!$B$35,(F48*SUPUESTOS!$B$35)-F32,0) -> 0
A38: E. RESULTADO
A39: EBITDA Fondo (neto de carry) | B39: =B21-B32 -> 240309.87 | C39: =C21-C32 -> 312453.04 | D39: =D21-D32 -> 454231.18 | E39: =E21-E32 -> 445930.31 | F39: =F21-F32 -> 234900.71 | G39: =SUM(B39:F39) -> 1687825.1
A40: EBITDA / Equity (%) | B40: =IF(B47>0,B39/B47,0) -> 0.080103291 | C40: =IF(C47>0,C39/C47,0) -> 0.096426902 | D40: =IF(D47>0,D39/D47,0) -> 0.1352545 | E40: =IF(E47>0,E39/E47,0) -> 0.12348963 | F40: =IF(F47>0,F39/F47,0) -> 0.061166634
A41: Retiros Parciales Inversores (detalle filas 69-80) | B41: =B79 -> 0 | C41: =C79 -> 194418.59 | D41: =D79 -> 201500.66 | E41: =E79 -> 216664.49 | F41: =F79 -> 0 | G41: =SUM(B41:F41) -> 612583.74
A42: Neto Reinvertido / Acumulado | B42: =B39-B41 -> 240309.87 | C42: =C39-C41 -> 118034.45 | D42: =D39-D41 -> 252730.52 | E42: =E39-E41 -> 229265.82 | F42: =F39-F41 -> 234900.71 | G42: =SUM(B42:F42) -> 1075241.4
A44: F. PATRIMONIO NETO
A45: Captaciones Nuevas (ingreso capital por año) | B45: 0 | C45: 0 | D45: 0 | E45: 0 | F45: 0 | G45: =SUM(B45:F45) -> 0
A46: Nota: Captaciones editable por año. Comisiones se cobran sobre capital nuevo.
A47: PN Inicio | B47: =SUPUESTOS!$B$6+B45 -> 3000000 | C47: =B48-B41+C45 -> 3240309.9 | D47: =C48-C41+D45 -> 3358344.3 | E47: =D48-D41+E45 -> 3611074.8 | F47: =E48-E41+F45 -> 3840340.7
A48: PN Fin (antes retiros) | B48: =B47+B39 -> 3240309.9 | C48: =C47+C39 -> 3552762.9 | D48: =D47+D39 -> 3812575.5 | E48: =E47+E39 -> 4057005.2 | F48: =F47+F39 -> 4075241.4
A50: G. CIERRE DEL FONDO — WIND-DOWN AÑO 5 (2030)
A51: Revolving Año Cierre (devuelto como cash) | F51: =IF(F7=0,F6,0) -> 1885176.8
A52: Cartera Remanente (Stock Fin) | F52: =F9 -> 3581836
A53: Valor Securitización | F53: =F52/(1+SUPUESTOS!$B$69) -> 3286088.1
A54: Repago Deuda Senior (si aplica) | F54: =F14 -> 1679172.2
A55: CASH NETO CIERRE (revolving + securit - deuda) | F55: =F51+F53-F54 -> 3492092.7
A57: H. CASH FLOW INVERSOR (EQUITY)
A58: Retiros Parciales Recibidos (neto de fee) | B58: =B82 -> 0 | C58: =C82 -> 194418.59 | D58: =D82 -> 201500.66 | E58: =E82 -> 216664.49 | F58: =F82 -> 0 | G58: =SUM(B58:F58) -> 612583.74
A59: Cash Cierre Fondo | B59: 0 | C59: 0 | D59: 0 | E59: 0 | F59: =F55 -> 3492092.7 | G59: =SUM(B59:F59) -> 3492092.7
A60: Cash Flow Inversor TOTAL | B60: =B58+B59 -> 0 | C60: =C58+C59 -> 194418.59 | D60: =D58+D59 -> 201500.66 | E60: =E58+E59 -> 216664.49 | F60: =F58+F59 -> 3492092.7 | G60: =G58+G59 -> 4104676.5
A61: Retorno Acumulado | B61: =B60 -> 0 | C61: =B61+C60 -> 194418.59 | D61: =C61+D60 -> 395919.25 | E61: =D61+E60 -> 612583.74 | F61: =E61+F60 -> 4104676.5
A63: I. METRICAS DE RETORNO
A64: CF para TIR (t=0 a t=5) | B64: =-SUPUESTOS!$B$6-B45+B60 -> -3000000 | C64: =C60-C45 -> 194418.59 | D64: =D60-D45 -> 201500.66 | E64: =E60-E45 -> 216664.49 | F64: =-F45+F60 -> 3492092.7 | I64: IMPOSITIVAMENTE CÓMO IMPACTA?
A65: TIR Inversor | B65: =IFERROR(IRR(B64:G64),"-") -> 0.088919693
A66: MOIC (Total Distributions / Total Capital Invested) | B66: =IF((SUPUESTOS!$B$6+G45)>0,G60/(SUPUESTOS!$B$6+G45),0) -> 1.3682255
A68: Nota: TIR asume liquidación de cartera remanente dentro del último año del fondo.
A69: Success fee del carry se cobra en Y5 al cierre. Ver SENSIBILIDAD 5Y para análisis con apalancamiento.
A72: J. RETIROS POR LIQUIDEZ — DETALLE 2 CASOS
A73: Concepto | B73: 2026 | C73: 2027 | D73: 2028 | E73: 2029 | F73: 2030 | G73: TOTAL
A74: CASO 1: Fondo de Liquidez | B74: =MIN(B75, B47) -> 0 | C74: =MIN(C75, C47) -> 0 | D74: =MIN(D75, D47) -> 0 | E74: =MIN(E75, E47) -> 0 | F74: =MIN(F75, F47) -> 0 | G74: =SUM(B74:F74) -> 0
A75: Monto Fondo Liquidez por año (EDITABLE →) | B75: 0 | C75: 0 | D75: 0 | E75: 0 | F75: 0
A76: % Retiro Caso 2 (EDITABLE por año →) | B76: 0 | C76: 0.06 | D76: 0.06 | E76: 0.06
A77: CASO 2: Retiro Variable (% × PN) | B77: =IF(1>=SUPUESTOS!$B$58, B47*B76, 0) -> 0 | C77: =IF(2>=SUPUESTOS!$B$58, C47*C76, 0) -> 194418.59 | D77: =IF(3>=SUPUESTOS!$B$58, D47*D76, 0) -> 201500.66 | E77: =IF(4>=SUPUESTOS!$B$58, E47*E76, 0) -> 216664.49 | F77: =IF(5>=SUPUESTOS!$B$58, F47*F76, 0) -> 0 | G77: =SUM(B77:F77) -> 612583.74
A79: TOTAL RETIRO BRUTO (Caso 1 + Caso 2) | B79: =B74+B77 -> 0 | C79: =C74+C77 -> 194418.59 | D79: =D74+D77 -> 201500.66 | E79: =E74+E77 -> 216664.49 | F79: =F74+F77 -> 0 | G79: =SUM(B79:F79) -> 612583.74
A80: Fee sobre Retiro (%) | B80: =SUPUESTOS!$B$59 -> 0 | C80: =SUPUESTOS!$B$59 -> 0 | D80: =SUPUESTOS!$B$59 -> 0 | E80: =SUPUESTOS!$B$59 -> 0 | F80: =SUPUESTOS!$B$59 -> 0
A81: Fee Retiro (USD) — ingreso TCMC | B81: =B79*B80 -> 0 | C81: =C79*C80 -> 0 | D81: =D79*D80 -> 0 | E81: =E79*E80 -> 0 | F81: =F79*F80 -> 0 | G81: =SUM(B81:F81) -> 0
A82: Retiro Neto al Inversor (Bruto − Fee) | B82: =B79-B81 -> 0 | C82: =C79-C81 -> 194418.59 | D82: =D79-D81 -> 201500.66 | E82: =E79-E81 -> 216664.49 | F82: =F79-F81 -> 0 | G82: =SUM(B82:F82) -> 612583.74
A83: Impacto en NAV del Fondo (= Bruto sale, Fee a TCMC) | B83: =B79 -> 0 | C83: =C79 -> 194418.59 | D83: =D79 -> 201500.66 | E83: =E79 -> 216664.49 | F83: =F79 -> 0
A84: Nota: El retiro BRUTO sale del fondo (reduce NAV). El fee es ingreso TCMC fuera del fondo.

Sheet Copia de FLUJO 5 AÑOS (5Y)
A1: FLUJO DEL FONDO — MODELO TCMC 5 AÑOS (Cono Sur / Capital Token Group, USD 5M)
B2: 0.96
A3: AÑO | B3: 2026 | C3: 2027 | D3: 2028 | E3: 2029 | F3: 2030 | G3: TOTAL
A4: A. CAPITAL Y ORIGINACIÓN
A5: Cartera Total Desplegada Inicio | B5: =(B44*(1-SUPUESTOS!$B$36-SUPUESTOS!$B$37)+B14)*B2 -> 2829600 | C5: =(C44+C14) -> 3258256.5 | D5: =(D44+D14) -> 5081919.9 | E5: =(E44+E14) -> 5343094.2 | F5: =(F44+F14) -> 5580773
A6: Capital Liberado (Amortización) | B6: =B5*SUPUESTOS!$B$22 -> 975724.14 | C6: =(C5*SUPUESTOS!$B$22)*($B2) -> 1078595.3 | D6: =(D5*SUPUESTOS!$B$22)*($B2) -> 1682290.7 | E6: =(E5*SUPUESTOS!$B$22)*($B2) -> 1768748.4 | F6: =(F5*SUPUESTOS!$B$22)*($B2) -> 1847428.3
A7: ¿Año de Originación Activa? | B7: 1 | C7: 1 | D7: 1 | E7: 1 | F7: 0
A8: Nuevos Créditos (re-originación) | B8: =IF(B7=1,B6*SUPUESTOS!$B$23,0) -> 975724.14 | C8: =IF(C7=1,C6*SUPUESTOS!$B$23,0) -> 1078595.3 | D8: =IF(D7=1,D6*SUPUESTOS!$B$23,0) -> 1682290.7 | E8: =IF(E7=1,E6*SUPUESTOS!$B$23,0) -> 1768748.4 | F8: =IF(F7=1,F6*SUPUESTOS!$B$23,0) -> 0
A9: Stock de Capital Fin Año | B9: =B5-B6+B8 -> 2829600 | C9: =C5-C6+C8 -> 3258256.5 | D9: =D5-D6+D8 -> 5081919.9 | E9: =E5-E6+E8 -> 5343094.2 | F9: =F5-F6+F8 -> 3733344.7
A10: Volumen Total Originado | B10: =B5+B8 -> 3805324.1 | C10: =C8+MAX(0,C5-B9) -> 1507251.8 | D10: =D8+MAX(0,D5-C9) -> 3505954.1 | E10: =E8+MAX(0,E5-D9) -> 2029922.7 | F10: =F8+MAX(0,F5-E9) -> 237678.83 | G10: =SUM(B10:F10) -> 11086132
A12: B. APALANCAMIENTO (editar fila 13: 1=ajustar deuda al 50% PN, 0=mantener nivel anterior)
A13: ¿Ajustar deuda? (1=reset a 0.5x PN, 0=mantener) — editable por año | B13: 0 | C13: 0 | D13: 1 | E13: 0 | F13: 0 | G13: 0
A14: Deuda Senior (monto) | B14: =IF(B13=1, B44*SUPUESTOS!$B$52, 0) -> 0 | C14: =IF(C13=1, C44*SUPUESTOS!$B$52, B14) -> 0 | D14: =IF(D13=1, D44*SUPUESTOS!$B$52, C14) -> 1693973.3 | E14: =IF(E13=1, E44*SUPUESTOS!$B$52, D14) -> 1693973.3 | F14: =IF(F13=1, F44*SUPUESTOS!$B$52, E14) -> 1693973.3
A15: Capital Total Desplegado (Equity + Deuda) | B15: =B5 -> 2829600 | C15: =C5 -> 3258256.5 | D15: =D5 -> 5081919.9 | E15: =E5 -> 5343094.2 | F15: =F5 -> 5580773
A16: Leverage Ratio (Deuda / PN Inicio) | B16: =IF(B5>0,B14/B5,0) -> 0 | C16: =IF(C5>0,C14/C5,0) -> 0 | D16: =IF(D5>0,D14/D5,0) -> 0.33333333 | E16: =IF(E5>0,E14/E5,0) -> 0.31703976 | F16: =IF(F5>0,F14/F5,0) -> 0.30353739
A18: C. INGRESOS
A19: Interés Ganado (sobre capital total desplegado) | B19: =IF(B7=1,B5*SUPUESTOS!$B$24,B5*SUPUESTOS!$B$24/2) -> 350870.4 | C19: =IF(C7=1,C5*SUPUESTOS!$B$24,C5*SUPUESTOS!$B$24/2) -> 404023.81 | D19: =IF(D7=1,D5*SUPUESTOS!$B$24,D5*SUPUESTOS!$B$24/2) -> 630158.07 | E19: =IF(E7=1,E5*SUPUESTOS!$B$24,E5*SUPUESTOS!$B$24/2) -> 662543.68 | F19: =IF(F7=1,F5*SUPUESTOS!$B$24,F5*SUPUESTOS!$B$24/2) -> 346007.93 | G19: =SUM(B19:F19) -> 2393603.9
A20: Upfront Fee (4% al Fondo) | B20: =(B10/(1+SUPUESTOS!$B$38))*SUPUESTOS!$B$38 -> 181205.91 | C20: =(C10/(1+SUPUESTOS!$B$38))*SUPUESTOS!$B$38 -> 71773.894 | D20: =(D10/(1+SUPUESTOS!$B$38))*SUPUESTOS!$B$38 -> 166950.19 | E20: =(E10/(1+SUPUESTOS!$B$38))*SUPUESTOS!$B$38 -> 96662.985 | F20: =(F10/(1+SUPUESTOS!$B$38))*SUPUESTOS!$B$38 -> 11318.04 | G20: =SUM(B20:F20) -> 527911.02
A21: TOTAL INGRESOS FONDO | B21: =B19+B20 -> 532076.31 | C21: =C19+C20 -> 475797.7 | D21: =D19+D20 -> 797108.26 | E21: =E19+E20 -> 759206.66 | F21: =F19+F20 -> 357325.97 | G21: =SUM(B21:F21) -> 2921514.9
A23: D. COSTOS DEL FONDO
A24: Honorarios Soc. Gerente (1.2%) | B24: =B44*SUPUESTOS!$B$28 -> 36000 | C24: =C44*SUPUESTOS!$B$28 -> 39099.078 | D24: =D44*SUPUESTOS!$B$28 -> 40655.359 | E24: =E44*SUPUESTOS!$B$28 -> 43789.45 | F24: =F44*SUPUESTOS!$B$28 -> 46641.596 | G24: =SUM(B24:F24) -> 206185.48
A25: Honorarios Soc. Depositaria (0.2%, mín $21,600/yr + $10K inicial Y1) | B25: =MAX(B44*SUPUESTOS!$B$29,SUPUESTOS!$B$40)+10000 -> 31600 | C25: =MAX(C44*SUPUESTOS!$B$29,SUPUESTOS!$B$40) -> 21600 | D25: =MAX(D44*SUPUESTOS!$B$29,SUPUESTOS!$B$40) -> 21600 | E25: =MAX(E44*SUPUESTOS!$B$29,SUPUESTOS!$B$40) -> 21600 | F25: =MAX(F44*SUPUESTOS!$B$29,SUPUESTOS!$B$40) -> 21600 | G25: =SUM(B25:F25) -> 118000
A26: Honorarios Asesor Inversión (0% PN — eliminado) | B26: =B44*SUPUESTOS!$B$30 -> 0 | C26: =C44*SUPUESTOS!$B$30 -> 0 | D26: =D44*SUPUESTOS!$B$30 -> 0 | E26: =E44*SUPUESTOS!$B$30 -> 0 | F26: =F44*SUPUESTOS!$B$30 -> 0 | G26: =SUM(B26:F26) -> 0
A27: Fee Asesor (Originación + Adquisición) | B27: =B10*(SUPUESTOS!$B$31) -> 47566.552 | C27: =C10*(SUPUESTOS!$B$31) -> 18840.647 | D27: =D10*(SUPUESTOS!$B$31) -> 43824.426 | E27: =E10*(SUPUESTOS!$B$31) -> 25374.034 | F27: =F10*(SUPUESTOS!$B$31) -> 2970.9854 | G27: =SUM(B27:F27) -> 138576.64
A28: Costos Fijos Operativos | B28: =SUPUESTOS!$B$42+SUPUESTOS!$B$43+SUPUESTOS!$B$44+SUPUESTOS!$B$45+SUPUESTOS!$B$46+SUPUESTOS!$B$47+SUPUESTOS!$B$48 -> 68100 | C28: =SUPUESTOS!$B$42+SUPUESTOS!$B$43+SUPUESTOS!$B$45+SUPUESTOS!$B$46+SUPUESTOS!$B$47+SUPUESTOS!$B$48 -> 56000 | D28: =SUPUESTOS!$B$42+SUPUESTOS!$B$43+SUPUESTOS!$B$45+SUPUESTOS!$B$46+SUPUESTOS!$B$47+SUPUESTOS!$B$48 -> 56000 | E28: =SUPUESTOS!$B$42+SUPUESTOS!$B$43+SUPUESTOS!$B$45+SUPUESTOS!$B$46+SUPUESTOS!$B$47+SUPUESTOS!$B$48 -> 56000 | F28: =SUPUESTOS!$B$42+SUPUESTOS!$B$43+SUPUESTOS!$B$45+SUPUESTOS!$B$46+SUPUESTOS!$B$47+SUPUESTOS!$B$48 -> 56000 | G28: =SUM(B28:F28) -> 292100
A29: Comisiones (Colocador+Org) sobre capital | B29: =(SUPUESTOS!$B$6+B42)*(SUPUESTOS!$B$36+SUPUESTOS!$B$37) -> 52500 | C29: =C42*(SUPUESTOS!$B$36+SUPUESTOS!$B$37) -> 0 | D29: =D42*(SUPUESTOS!$B$36+SUPUESTOS!$B$37) -> 0 | E29: =E42*(SUPUESTOS!$B$36+SUPUESTOS!$B$37) -> 0 | F29: =F42*(SUPUESTOS!$B$36+SUPUESTOS!$B$37) -> 0 | G29: =SUM(B29:F29) -> 52500
A30: IVA sobre Upfront Fee (REVISAR: ¿lo paga el fondo o el tomador?) | B30: =B20*SUPUESTOS!$B$39 -> 38053.241 | C30: =C20*SUPUESTOS!$B$39 -> 15072.518 | D30: =D20*SUPUESTOS!$B$39 -> 35059.541 | E30: =E20*SUPUESTOS!$B$39 -> 20299.227 | F30: =F20*SUPUESTOS!$B$39 -> 2376.7883 | G30: =SUM(B30:F30) -> 110861.32
A31: Intereses Deuda Senior | B31: =B14*SUPUESTOS!$B$54 -> 0 | C31: =C14*SUPUESTOS!$B$54 -> 0 | D31: =D14*SUPUESTOS!$B$54 -> 135517.86 | E31: =E14*SUPUESTOS!$B$54 -> 135517.86 | F31: =F14*SUPUESTOS!$B$54 -> 135517.86 | G31: =SUM(B31:F31) -> 406553.59
A32: TOTAL COSTOS | B32: =B24+B25+B26+B27+B28+B29+B30+B31+B34 -> 273819.79 | C32: =C24+C25+C26+C27+C28+C29+C30+C31+C34 -> 150612.24 | D32: =D24+D25+D26+D27+D28+D29+D30+D31+D34 -> 332657.19 | E32: =E24+E25+E26+E27+E28+E29+E30+E31+E34 -> 302580.57 | F32: =F24+F25+F26+F27+F28+F29+F30+F31+F34 -> 338976.23 | G32: =SUM(B32:F32) -> 1398646
A33: Carry devengado del período | B33: ='RESULTADOS ASESOR TCMC (5Y)'!B14 -> 6030.9873 | C33: ='RESULTADOS ASESOR TCMC (5Y)'!C14 -> 11803.445 | D33: ='RESULTADOS ASESOR TCMC (5Y)'!D14 -> 25273.052 | E33: ='RESULTADOS ASESOR TCMC (5Y)'!E14 -> 22926.582 | F33: ='RESULTADOS ASESOR TCMC (5Y)'!F14 -> 7834.9265 | G33: ='RESULTADOS ASESOR TCMC (5Y)'!G14 -> 73868.993
A34: Carry COBRADO (Success Fee: sólo al cierre Y6, tope 5% Cl.10.5) | B34: ='RESULTADOS ASESOR TCMC (5Y)'!B18 -> 0 | C34: ='RESULTADOS ASESOR TCMC (5Y)'!C18 -> 0 | D34: ='RESULTADOS ASESOR TCMC (5Y)'!D18 -> 0 | E34: ='RESULTADOS ASESOR TCMC (5Y)'!E18 -> 0 | F34: ='RESULTADOS ASESOR TCMC (5Y)'!F18 -> 73868.993 | G34: ='RESULTADOS ASESOR TCMC (5Y)'!G18 -> 73868.993
A35: E. RESULTADO
A36: EBITDA Fondo (neto de carry) | B36: =B21-B32 -> 258256.52 | C36: =C21-C32 -> 325185.46 | D36: =D21-D32 -> 464451.07 | E36: =E21-E32 -> 456626.09 | F36: =F21-F32 -> 18349.739 | G36: =SUM(B36:F36) -> 1522868.9
A37: EBITDA / Equity (%) | B37: =IF(B44>0,B36/B44,0) -> 0.086085506 | C37: =IF(C44>0,C36/C44,0) -> 0.099803517 | D37: =IF(D44>0,D36/D44,0) -> 0.13708925 | E37: =IF(E44>0,E36/E44,0) -> 0.12513318 | F37: =IF(F44>0,F36/F44,0) -> 0.0047210404
A38: Retiros Parciales Inversores (detalle filas 69-80) | B38: =B76 -> 0 | C38: =C76 -> 195495.39 | D38: =D76 -> 203276.8 | E38: =E76 -> 218947.25 | F38: =F76 -> 0 | G38: =SUM(B38:F38) -> 617719.44
A39: Neto Reinvertido / Acumulado | B39: =B36-B38 -> 258256.52 | C39: =C36-C38 -> 129690.07 | D39: =D36-D38 -> 261174.27 | E39: =E36-E38 -> 237678.83 | F39: =F36-F38 -> 18349.739 | G39: =SUM(B39:F39) -> 905149.43
A41: F. PATRIMONIO NETO
A42: Captaciones Nuevas (ingreso capital por año) | B42: 0 | C42: 0 | D42: 0 | E42: 0 | F42: 0 | G42: =SUM(B42:F42) -> 0
A43: Nota: Captaciones editable por año. Comisiones se cobran sobre capital nuevo.
A44: PN Inicio | B44: =SUPUESTOS!$B$6+B42 -> 3000000 | C44: =B45-B38+C42 -> 3258256.5 | D44: =C45-C38+D42 -> 3387946.6 | E44: =D45-D38+E42 -> 3649120.9 | F44: =E45-E38+F42 -> 3886799.7
A45: PN Fin (antes retiros) | B45: =B44+B36 -> 3258256.5 | C45: =C44+C36 -> 3583442 | D45: =D44+D36 -> 3852397.7 | E45: =E44+E36 -> 4105746.9 | F45: =F44+F36 -> 3905149.4
A47: G. CIERRE DEL FONDO — WIND-DOWN AÑO 5 (2030)
A48: Revolving Año Cierre (devuelto como cash) | F48: =IF(F7=0,F6,0) -> 1847428.3
A49: Cartera Remanente (Stock Fin) | F49: =F9 -> 3733344.7
A50: Valor Securitización | F50: =F49/(1+SUPUESTOS!$B$69) -> 3425086.9
A51: Repago Deuda Senior (si aplica) | F51: =F14 -> 1693973.3
A52: CASH NETO CIERRE (revolving + securit - deuda) | F52: =F48+F50-F51 -> 3578541.9
A54: H. CASH FLOW INVERSOR (EQUITY)
A55: Retiros Parciales Recibidos (neto de fee) | B55: =B79 -> 0 | C55: =C79 -> 195495.39 | D55: =D79 -> 203276.8 | E55: =E79 -> 218947.25 | F55: =F79 -> 0 | G55: =SUM(B55:F55) -> 617719.44
A56: Cash Cierre Fondo | B56: 0 | C56: 0 | D56: 0 | E56: 0 | F56: =F52 -> 3578541.9 | G56: =SUM(B56:F56) -> 3578541.9
A57: Cash Flow Inversor TOTAL | B57: =B55+B56 -> 0 | C57: =C55+C56 -> 195495.39 | D57: =D55+D56 -> 203276.8 | E57: =E55+E56 -> 218947.25 | F57: =F55+F56 -> 3578541.9 | G57: =G55+G56 -> 4196261.3
A58: Retorno Acumulado | B58: =B57 -> 0 | C58: =B58+C57 -> 195495.39 | D58: =C58+D57 -> 398772.19 | E58: =D58+E57 -> 617719.44 | F58: =E58+F57 -> 4196261.3
A60: I. METRICAS DE RETORNO
A61: CF para TIR (t=0 a t=5) | B61: =-SUPUESTOS!$B$6-B42+B57 -> -3000000 | C61: =C57-C42 -> 195495.39 | D61: =D57-D42 -> 203276.8 | E61: =E57-E42 -> 218947.25 | F61: =-F42+F57 -> 3578541.9 | I61: IMPOSITIVAMENTE CÓMO IMPACTA?
A62: TIR Inversor | B62: =IFERROR(IRR(B61:G61),"-") -> 0.095396806
A63: MOIC (Total Distributions / Total Capital Invested) | B63: =IF((SUPUESTOS!$B$6+G42)>0,G57/(SUPUESTOS!$B$6+G42),0) -> 1.3987538
A65: Nota: TIR asume liquidación de cartera remanente dentro del último año del fondo.
A66: Success fee del carry se cobra en Y5 al cierre. Ver SENSIBILIDAD 5Y para análisis con apalancamiento.
A69: J. RETIROS POR LIQUIDEZ — DETALLE 2 CASOS
A70: Concepto | B70: 2026 | C70: 2027 | D70: 2028 | E70: 2029 | F70: 2030 | G70: TOTAL
A71: CASO 1: Fondo de Liquidez | B71: =MIN(B72, B44) -> 0 | C71: =MIN(C72, C44) -> 0 | D71: =MIN(D72, D44) -> 0 | E71: =MIN(E72, E44) -> 0 | F71: =MIN(F72, F44) -> 0 | G71: =SUM(B71:F71) -> 0
A72: Monto Fondo Liquidez por año (EDITABLE →) | B72: 0 | C72: 0 | D72: 0 | E72: 0 | F72: 0
A73: % Retiro Caso 2 (EDITABLE por año →) | B73: 0 | C73: 0.06 | D73: 0.06 | E73: 0.06
A74: CASO 2: Retiro Variable (% × PN) | B74: =IF(1>=SUPUESTOS!$B$58, B44*B73, 0) -> 0 | C74: =IF(2>=SUPUESTOS!$B$58, C44*C73, 0) -> 195495.39 | D74: =IF(3>=SUPUESTOS!$B$58, D44*D73, 0) -> 203276.8 | E74: =IF(4>=SUPUESTOS!$B$58, E44*E73, 0) -> 218947.25 | F74: =IF(5>=SUPUESTOS!$B$58, F44*F73, 0) -> 0 | G74: =SUM(B74:F74) -> 617719.44
A76: TOTAL RETIRO BRUTO (Caso 1 + Caso 2) | B76: =B71+B74 -> 0 | C76: =C71+C74 -> 195495.39 | D76: =D71+D74 -> 203276.8 | E76: =E71+E74 -> 218947.25 | F76: =F71+F74 -> 0 | G76: =SUM(B76:F76) -> 617719.44
A77: Fee sobre Retiro (%) | B77: =SUPUESTOS!$B$59 -> 0 | C77: =SUPUESTOS!$B$59 -> 0 | D77: =SUPUESTOS!$B$59 -> 0 | E77: =SUPUESTOS!$B$59 -> 0 | F77: =SUPUESTOS!$B$59 -> 0
A78: Fee Retiro (USD) — ingreso TCMC | B78: =B76*B77 -> 0 | C78: =C76*C77 -> 0 | D78: =D76*D77 -> 0 | E78: =E76*E77 -> 0 | F78: =F76*F77 -> 0 | G78: =SUM(B78:F78) -> 0
A79: Retiro Neto al Inversor (Bruto − Fee) | B79: =B76-B78 -> 0 | C79: =C76-C78 -> 195495.39 | D79: =D76-D78 -> 203276.8 | E79: =E76-E78 -> 218947.25 | F79: =F76-F78 -> 0 | G79: =SUM(B79:F79) -> 617719.44
A80: Impacto en NAV del Fondo (= Bruto sale, Fee a TCMC) | B80: =B76 -> 0 | C80: =C76 -> 195495.39 | D80: =D76 -> 203276.8 | E80: =E76 -> 218947.25 | F80: =F76 -> 0
A81: Nota: El retiro BRUTO sale del fondo (reduce NAV). El fee es ingreso TCMC fuera del fondo.

Sheet RESULTADOS ASESOR TCMC (5Y)
A1: RESULTADOS ASESOR — MODELO TCMC 5 AÑOS (Propuesta ConoSur Mar-2026)
A2: Escenario ácido: USD 5M, sin captaciones. Fee 1% originación, hurdle 6%, carry 10%.
A4: I. MANAGEMENT FEE (Honorarios Asesor)
A5: Concepto | B5: 2026 | C5: 2027 | D5: 2028 | E5: 2029 | F5: 2030 | G5: TOTAL
A6: PN Inicio | B6: ='FLUJO 5 AÑOS (5Y)'!B47 -> 3000000 | C6: ='FLUJO 5 AÑOS (5Y)'!C47 -> 3240309.9 | D6: ='FLUJO 5 AÑOS (5Y)'!D47 -> 3358344.3 | E6: ='FLUJO 5 AÑOS (5Y)'!E47 -> 3611074.8 | F6: ='FLUJO 5 AÑOS (5Y)'!F47 -> 3840340.7 | G6: =SUM(B6:F6) -> 17050070
A7: Management Fee (0% — eliminado, modelo Lendar) | B7: ='FLUJO 5 AÑOS (5Y)'!B26 -> 0 | C7: ='FLUJO 5 AÑOS (5Y)'!C26 -> 0 | D7: ='FLUJO 5 AÑOS (5Y)'!D26 -> 0 | E7: ='FLUJO 5 AÑOS (5Y)'!E26 -> 0 | F7: ='FLUJO 5 AÑOS (5Y)'!F26 -> 0 | G7: =SUM(B7:F7) -> 0
A8: Fee por Crédito: 1% Orig + 1% Adq (ver SUPUESTOS B31/B32) | B8: ='FLUJO 5 AÑOS (5Y)'!B27 -> 49548.491 | C8: ='FLUJO 5 AÑOS (5Y)'!C27 -> 16744.433 | D8: ='FLUJO 5 AÑOS (5Y)'!D27 -> 43952.223 | E8: ='FLUJO 5 AÑOS (5Y)'!E27 -> 25735.627 | F8: ='FLUJO 5 AÑOS (5Y)'!F27 -> 2865.8228 | G8: =SUM(B8:F8) -> 138846.6
A9: TOTAL FEES ASESOR (dentro del fondo) | B9: =B7+B8 -> 49548.491 | C9: =C7+C8 -> 16744.433 | D9: =D7+D8 -> 43952.223 | E9: =E7+E8 -> 25735.627 | F9: =F7+F8 -> 2865.8228 | G9: =G7+G8 -> 138846.6
A11: II. CARRY WATERFALL (con tope 5.4% — Cl. 10.5)
A12: Concepto | B12: 2026 | C12: 2027 | D12: 2028 | E12: 2029 | F12: 2030 | G12: TOTAL
A13: EBITDA pre-carry | B13: ='FLUJO 5 AÑOS (5Y)'!B21-'FLUJO 5 AÑOS (5Y)'!B24-'FLUJO 5 AÑOS (5Y)'!B25-'FLUJO 5 AÑOS (5Y)'!B26-'FLUJO 5 AÑOS (5Y)'!B27-'FLUJO 5 AÑOS (5Y)'!B28-'FLUJO 5 AÑOS (5Y)'!B29-'FLUJO 5 AÑOS (5Y)'!B30-'FLUJO 5 AÑOS (5Y)'!B31 -> 240309.87 | C13: ='FLUJO 5 AÑOS (5Y)'!C21-'FLUJO 5 AÑOS (5Y)'!C24-'FLUJO 5 AÑOS (5Y)'!C25-'FLUJO 5 AÑOS (5Y)'!C26-'FLUJO 5 AÑOS (5Y)'!C27-'FLUJO 5 AÑOS (5Y)'!C28-'FLUJO 5 AÑOS (5Y)'!C29-'FLUJO 5 AÑOS (5Y)'!C30-'FLUJO 5 AÑOS (5Y)'!C31 -> 312453.04 | D13: ='FLUJO 5 AÑOS (5Y)'!D21-'FLUJO 5 AÑOS (5Y)'!D24-'FLUJO 5 AÑOS (5Y)'!D25-'FLUJO 5 AÑOS (5Y)'!D26-'FLUJO 5 AÑOS (5Y)'!D27-'FLUJO 5 AÑOS (5Y)'!D28-'FLUJO 5 AÑOS (5Y)'!D29-'FLUJO 5 AÑOS (5Y)'!D30-'FLUJO 5 AÑOS (5Y)'!D31 -> 454231.18 | E13: ='FLUJO 5 AÑOS (5Y)'!E21-'FLUJO 5 AÑOS (5Y)'!E24-'FLUJO 5 AÑOS (5Y)'!E25-'FLUJO 5 AÑOS (5Y)'!E26-'FLUJO 5 AÑOS (5Y)'!E27-'FLUJO 5 AÑOS (5Y)'!E28-'FLUJO 5 AÑOS (5Y)'!E29-'FLUJO 5 AÑOS (5Y)'!E30-'FLUJO 5 AÑOS (5Y)'!E31 -> 445930.31 | F13: ='FLUJO 5 AÑOS (5Y)'!F21-'FLUJO 5 AÑOS (5Y)'!F24-'FLUJO 5 AÑOS (5Y)'!F25-'FLUJO 5 AÑOS (5Y)'!F26-'FLUJO 5 AÑOS (5Y)'!F27-'FLUJO 5 AÑOS (5Y)'!F28-'FLUJO 5 AÑOS (5Y)'!F29-'FLUJO 5 AÑOS (5Y)'!F30-'FLUJO 5 AÑOS (5Y)'!F31 -> 308769.7 | G13: =SUM(B13:F13) -> 1761694.1
A14: Carry Devengado del Período | B14: =MAX(0,B13-'FLUJO 5 AÑOS (5Y)'!B47*SUPUESTOS!$B$34)*SUPUESTOS!$B$33 -> 6030.9873 | C14: =MAX(0,C13-'FLUJO 5 AÑOS (5Y)'!C47*SUPUESTOS!$B$34)*SUPUESTOS!$B$33 -> 11803.445 | D14: =MAX(0,D13-'FLUJO 5 AÑOS (5Y)'!D47*SUPUESTOS!$B$34)*SUPUESTOS!$B$33 -> 25273.052 | E14: =MAX(0,E13-'FLUJO 5 AÑOS (5Y)'!E47*SUPUESTOS!$B$34)*SUPUESTOS!$B$33 -> 22926.582 | F14: =MAX(0,F13-'FLUJO 5 AÑOS (5Y)'!F47*SUPUESTOS!$B$34)*SUPUESTOS!$B$33 -> 7834.9265 | G14: =SUM(B14:F14) -> 73868.993
A15: Carry Diferido Acum. (entrada) | B15: 0 | C15: =B19 -> 6030.9873 | D15: =C19 -> 17834.432 | E15: =D19 -> 43107.484 | F15: =E19 -> 66034.066
A16: Total Carry Pendiente (devengado + diferido) | B16: =B14+B15 -> 6030.9873 | C16: =C14+C15 -> 17834.432 | D16: =D14+D15 -> 43107.484 | E16: =E14+E15 -> 66034.066 | F16: =F14+F15 -> 73868.993 | G16: =SUM(B14:F14)+B15 -> 73868.993
A17: Espacio Disponible (5.4%*PN − costos cubiertos por tope) | B17: =MAX(0, SUPUESTOS!$B$35*'FLUJO 5 AÑOS (5Y)'!B47-('FLUJO 5 AÑOS (5Y)'!B24+'FLUJO 5 AÑOS (5Y)'!B25+'FLUJO 5 AÑOS (5Y)'!B26+'FLUJO 5 AÑOS (5Y)'!B27+'FLUJO 5 AÑOS (5Y)'!B28)) -> 0 | C17: =MAX(0, SUPUESTOS!$B$35*'FLUJO 5 AÑOS (5Y)'!C47-('FLUJO 5 AÑOS (5Y)'!C24+'FLUJO 5 AÑOS (5Y)'!C25+'FLUJO 5 AÑOS (5Y)'!C26+'FLUJO 5 AÑOS (5Y)'!C27+'FLUJO 5 AÑOS (5Y)'!C28)) -> 41748.581 | D17: =MAX(0, SUPUESTOS!$B$35*'FLUJO 5 AÑOS (5Y)'!D47-('FLUJO 5 AÑOS (5Y)'!D24+'FLUJO 5 AÑOS (5Y)'!D25+'FLUJO 5 AÑOS (5Y)'!D26+'FLUJO 5 AÑOS (5Y)'!D27+'FLUJO 5 AÑOS (5Y)'!D28)) -> 19498.239 | E17: =MAX(0, SUPUESTOS!$B$35*'FLUJO 5 AÑOS (5Y)'!E47-('FLUJO 5 AÑOS (5Y)'!E24+'FLUJO 5 AÑOS (5Y)'!E25+'FLUJO 5 AÑOS (5Y)'!E26+'FLUJO 5 AÑOS (5Y)'!E27+'FLUJO 5 AÑOS (5Y)'!E28)) -> 48329.516 | F17: =MAX(0, SUPUESTOS!$B$35*'FLUJO 5 AÑOS (5Y)'!F47-('FLUJO 5 AÑOS (5Y)'!F24+'FLUJO 5 AÑOS (5Y)'!F25+'FLUJO 5 AÑOS (5Y)'!F26+'FLUJO 5 AÑOS (5Y)'!F27+'FLUJO 5 AÑOS (5Y)'!F28)) -> 80828.485 | G17: =SUM(B17:F17) -> 190404.82
A18: Carry COBRADO (limitado por tope) | B18: 0 | C18: 0 | D18: 0 | E18: 0 | F18: =MIN(F16,F17) -> 73868.993 | G18: =SUM(B18:F18) -> 73868.993
A19: Carry Diferido Acum. (salida → pasa al año sig.) | B19: =B16-B18 -> 6030.9873 | C19: =C16-C18 -> 17834.432 | D19: =D16-D18 -> 43107.484 | E19: =E16-E18 -> 66034.066 | F19: =F16-F18 -> 0 | G19: =G16-G18 -> 0
A20: Nota: excluidos del tope 5.4%: comisiones colocador (row29), IVA upfront (row30), intereses deuda (row31)
A21: III. UPFRONT FEE EXTRACTION (pre-fondo)
A22: Concepto | B22: 2026 | C22: 2027 | D22: 2028 | E22: 2029 | F22: 2030 | G22: TOTAL
A23: Volumen Total Originado | B23: ='FLUJO 5 AÑOS (5Y)'!B10 -> 3963879.3 | C23: ='FLUJO 5 AÑOS (5Y)'!C10 -> 1339554.7 | D23: ='FLUJO 5 AÑOS (5Y)'!D10 -> 3516177.8 | E23: ='FLUJO 5 AÑOS (5Y)'!E10 -> 2058850.2 | F23: ='FLUJO 5 AÑOS (5Y)'!F10 -> 229265.82 | G23: =SUM(B23:F23) -> 11107728
A24: Upfront Total (5% del otorgado neto) | B24: =(B23/(1+SUPUESTOS!$B$73))*SUPUESTOS!$B$73 -> 188756.16 | C24: =(C23/(1+SUPUESTOS!$B$73))*SUPUESTOS!$B$73 -> 63788.317 | D24: =(D23/(1+SUPUESTOS!$B$73))*SUPUESTOS!$B$73 -> 167437.04 | E24: =(E23/(1+SUPUESTOS!$B$73))*SUPUESTOS!$B$73 -> 98040.484 | F24: =(F23/(1+SUPUESTOS!$B$73))*SUPUESTOS!$B$73 -> 10917.42 | G24: =SUM(B24:F24) -> 528939.42
A25: Porción al Fondo (4%) | B25: =(B23/(1+SUPUESTOS!$B$73))*SUPUESTOS!$B$74 -> 188756.16 | C25: =(C23/(1+SUPUESTOS!$B$73))*SUPUESTOS!$B$74 -> 63788.317 | D25: =(D23/(1+SUPUESTOS!$B$73))*SUPUESTOS!$B$74 -> 167437.04 | E25: =(E23/(1+SUPUESTOS!$B$73))*SUPUESTOS!$B$74 -> 98040.484 | F25: =(F23/(1+SUPUESTOS!$B$73))*SUPUESTOS!$B$74 -> 10917.42 | G25: =SUM(B25:F25) -> 528939.42
A26: Extracción Asesor Pre-Fondo (1%) | B26: =(B23/(1+SUPUESTOS!$B$73))*SUPUESTOS!$B$75 -> 0 | C26: =(C23/(1+SUPUESTOS!$B$73))*SUPUESTOS!$B$75 -> 0 | D26: =(D23/(1+SUPUESTOS!$B$73))*SUPUESTOS!$B$75 -> 0 | E26: =(E23/(1+SUPUESTOS!$B$73))*SUPUESTOS!$B$75 -> 0 | F26: =(F23/(1+SUPUESTOS!$B$73))*SUPUESTOS!$B$75 -> 0 | G26: =SUM(B26:F26) -> 0
A27: IVA sobre Extracción (21%) | B27: =B26*SUPUESTOS!$B$76 -> 0 | C27: =C26*SUPUESTOS!$B$76 -> 0 | D27: =D26*SUPUESTOS!$B$76 -> 0 | E27: =E26*SUPUESTOS!$B$76 -> 0 | F27: =F26*SUPUESTOS!$B$76 -> 0 | G27: =SUM(B27:F27) -> 0
A28: Neto Extracción (sin IVA) | B28: =B26 -> 0 | C28: =C26 -> 0 | D28: =D26 -> 0 | E28: =E26 -> 0 | F28: =F26 -> 0 | G28: =G26 -> 0
A29: Fee por Retiros de Liquidez (5% default) | B29: ='FLUJO 5 AÑOS (5Y)'!B81 -> 0 | C29: ='FLUJO 5 AÑOS (5Y)'!C81 -> 0 | D29: ='FLUJO 5 AÑOS (5Y)'!D81 -> 0 | E29: ='FLUJO 5 AÑOS (5Y)'!E81 -> 0 | F29: ='FLUJO 5 AÑOS (5Y)'!F81 -> 0 | G29: =SUM(B29:F29) -> 0
A30: TOTAL A COBRAR ASESOR TCMC (año por año) | B30: =B9+B18+B28+B29 -> 49548.491 | C30: =C9+C18+C28+C29+B32 -> 39992.925 | D30: =D9+D18+D28+D29+C32 -> 43952.223 | E30: =E9+E18+E28+E29+D32 -> 25735.627 | F30: =F9+F18+F28+F29+E32 -> 76734.816 | G30: =SUM(B30:F30) -> 235964.08
A31: TOTAL ACUMULADO (sumador) | B31: =B30 -> 49548.491 | C31: =B31+C30 -> 89541.416 | D31: =C31+D30 -> 133493.64 | E31: =D31+E30 -> 159229.27 | F31: =E31+F30 -> 235964.08
A32: SPONSOR (exceso >5.4% PN → pago fuera del fondo) | B32: =MAX(0, ('FLUJO 5 AÑOS (5Y)'!B24+'FLUJO 5 AÑOS (5Y)'!B25+'FLUJO 5 AÑOS (5Y)'!B26+'FLUJO 5 AÑOS (5Y)'!B27+'FLUJO 5 AÑOS (5Y)'!B28) - SUPUESTOS!$B$35*'FLUJO 5 AÑOS (5Y)'!B47) -> 23248.491 | C32: =MAX(0, ('FLUJO 5 AÑOS (5Y)'!C24+'FLUJO 5 AÑOS (5Y)'!C25+'FLUJO 5 AÑOS (5Y)'!C26+'FLUJO 5 AÑOS (5Y)'!C27+'FLUJO 5 AÑOS (5Y)'!C28) - SUPUESTOS!$B$35*'FLUJO 5 AÑOS (5Y)'!C47) -> 0 | D32: =MAX(0, ('FLUJO 5 AÑOS (5Y)'!D24+'FLUJO 5 AÑOS (5Y)'!D25+'FLUJO 5 AÑOS (5Y)'!D26+'FLUJO 5 AÑOS (5Y)'!D27+'FLUJO 5 AÑOS (5Y)'!D28) - SUPUESTOS!$B$35*'FLUJO 5 AÑOS (5Y)'!D47) -> 0 | E32: =MAX(0, ('FLUJO 5 AÑOS (5Y)'!E24+'FLUJO 5 AÑOS (5Y)'!E25+'FLUJO 5 AÑOS (5Y)'!E26+'FLUJO 5 AÑOS (5Y)'!E27+'FLUJO 5 AÑOS (5Y)'!E28) - SUPUESTOS!$B$35*'FLUJO 5 AÑOS (5Y)'!E47) -> 0 | F32: =MAX(0, ('FLUJO 5 AÑOS (5Y)'!F24+'FLUJO 5 AÑOS (5Y)'!F25+'FLUJO 5 AÑOS (5Y)'!F26+'FLUJO 5 AÑOS (5Y)'!F27+'FLUJO 5 AÑOS (5Y)'!F28) - SUPUESTOS!$B$35*'FLUJO 5 AÑOS (5Y)'!F47) -> 0 | G32: =SUM(B32:F32) -> 23248.491 | I32: Se cobra el año siguiente si hay lugar
A33: IV. RESUMEN TOTAL ASESOR — ESCENARIOS
A35: Escenario | B35: Total 5Y (USD) | C35: Promedio Anual
A36: A. Solo Fee por Crédito (1%/0.7%) | B36: =G8 -> 138846.6 | C36: =B36/5 -> 27769.319
A37: B. Fee Crédito + Carry | B37: =G8+G18 -> 212715.59 | C37: =B37/5 -> 42543.118
A38: C. Full (Fee Crédito + Carry + Extracción 1%) | B38: =G8+G18+G26 -> 212715.59 | C38: =B38/5 -> 42543.118
A39: D. Full + Fee Retiros Liquidez | B39: =G8+G18+G26+G29 -> 212715.59 | C39: =B39/5 -> 42543.118
A41: V. MÉTRICAS CLAVE
A42: TIR Inversor (post all fees) | B42: ='FLUJO 5 AÑOS (5Y)'!B65 -> 0.088919693
A43: MOIC | B43: ='FLUJO 5 AÑOS (5Y)'!B66 -> 1.3682255
A44: Total EBITDA Acumulado (6Y) | B44: =G13 -> 1761694.1
A45: Total Carry Devengado (6Y) | B45: =G14 -> 73868.993
A46: Total Carry Cobrado (6Y) | B46: =G18 -> 73868.993
A47: Carry Diferido Final (no cobrado) | B47: =F32 -> 0
A48: Mgmt Fee como % del PN promedio | B48: =SUPUESTOS!B30 -> 0
A50: NOTAS
A51: 1. El carry se calcula año a año: 20% sobre exceso de EBITDA vs hurdle (8% * PN). Se cobra como Success Fee al cierre (Y6).
A52: 2. La extracción pre-fondo (1% del upfront) está sujeta a aprobación regulatoria y del reglamento FCIC.
A53: 3. Si se completa B32 en SUPUESTOS (fee adquirido), se suma automáticamente como costo del fondo.
A54: 4. Las captaciones por año (fila 42 en FLUJO) afectan el PN, comisiones, portfolio y TIR.
A55: 5. Fee por originación+adquisición: actualmente 1%+1% (total 2% por crédito). Verificar con TBD si el 1.5% se refiere al fee total.

Sheet FLUJO 11 AÑOS
A1: FLUJO DEL FONDO — MODELO TCMC 11 AÑOS (Cono Sur / Capital Token Group, con captaciones)
A3: AÑO | B3: 2026 | C3: 2027 | D3: 2028 | E3: 2029 | F3: 2030 | G3: 2031 | H3: 2032 | I3: 2033 | J3: 2034 | K3: 2035 | L3: 2036 | M3: TOTAL
A4: A. CAPITAL Y ORIGINACIÓN
A5: Cartera Total Desplegada Inicio | B5: =B44*(1-SUPUESTOS!$B$36-SUPUESTOS!$B$37)+B14 -> 2947500 | C5: =C44+C14 -> 8276858.9 | D5: =D44+D14 -> 13582179 | E5: =E44+E14 -> 19097054 | F5: =F44+F14 -> 27830408 | G5: =G44+G14 -> 36929753 | H5: =H44+H14 -> 46390089 | I5: =I44+I14 -> 56225245 | J5: =J44+J14 -> 58450061 | ... L5: =L44+L14 -> 63057631
A6: Capital Liberado (Amortización) | B6: =B5*SUPUESTOS!$B$22 -> 1016379.3 | C6: =C5*SUPUESTOS!$B$22 -> 2854089.3 | D6: =D5*SUPUESTOS!$B$22 -> 4683509.9 | E6: =E5*SUPUESTOS!$B$22 -> 6585191 | F6: =F5*SUPUESTOS!$B$22 -> 9596692.3 | G6: =G5*SUPUESTOS!$B$22 -> 12734398 | H6: =H5*SUPUESTOS!$B$22 -> 15996582 | I6: =I5*SUPUESTOS!$B$22 -> 19388016 | ... L6: =L5*SUPUESTOS!$B$22 -> 21744011
A7: ¿Año de Originación Activa? | B7: 1 | C7: 1 | D7: 1 | E7: 1 | F7: 1 | G7: 1 | H7: 1 | I7: 1 | J7: 1 | K7: 1 | L7: 0
A8: Nuevos Créditos (re-originación) | B8: =IF(B7=1,B6*SUPUESTOS!$B$23,0) -> 1016379.3 | C8: =IF(C7=1,C6*SUPUESTOS!$B$23,0) -> 2854089.3 | D8: =IF(D7=1,D6*SUPUESTOS!$B$23,0) -> 4683509.9 | E8: =IF(E7=1,E6*SUPUESTOS!$B$23,0) -> 6585191 | F8: =IF(F7=1,F6*SUPUESTOS!$B$23,0) -> 9596692.3 | G8: =IF(G7=1,G6*SUPUESTOS!$B$23,0) -> 12734398 | H8: =IF(H7=1,H6*SUPUESTOS!$B$23,0) -> 15996582 | I8: =IF(I7=1,I6*SUPUESTOS!$B$23,0) -> 19388016 | ... L8: =IF(L7=1,L6*SUPUESTOS!$B$23,0) -> 0
A9: Stock de Capital Fin Año | B9: =B5-B6+B8 -> 2947500 | C9: =C5-C6+C8 -> 8276858.9 | D9: =D5-D6+D8 -> 13582179 | E9: =E5-E6+E8 -> 19097054 | F9: =F5-F6+F8 -> 27830408 | G9: =G5-G6+G8 -> 36929753 | H9: =H5-H6+H8 -> 46390089 | I9: =I5-I6+I8 -> 56225245 | ... L9: =L5-L6+L8 -> 41313620
A10: Volumen Total Originado | B10: =B5+B8 -> 3963879.3 | C10: =C8+MAX(0,C5-B9) -> 8183448.1 | D10: =D8+MAX(0,D5-C9) -> 9988829.8 | E10: =E8+MAX(0,E5-D9) -> 12100066 | F10: =F8+MAX(0,F5-E9) -> 18330046 | G10: =G8+MAX(0,G5-F9) -> 21833743 | H10: =H8+MAX(0,H5-G9) -> 25456918 | I10: =I8+MAX(0,I5-H9) -> 29223172 | J10: =J8+MAX(0,J5-I9) -> 22380009 | ... L10: =L8+MAX(0,L5-K9) -> 2347904.4 | M10: =SUM(B10:L10) -> 1.7700207e+08
B11: =ROUND(B10/SUPUESTOS!$B$8,0) -> 99 | C11: =ROUND(C10/SUPUESTOS!$B$8,0) -> 205 | D11: =ROUND(D10/SUPUESTOS!$B$8,0) -> 250 | E11: =ROUND(E10/SUPUESTOS!$B$8,0) -> 303 | F11: =ROUND(F10/SUPUESTOS!$B$8,0) -> 458 | G11: =ROUND(G10/SUPUESTOS!$B$8,0) -> 546 | H11: =ROUND(H10/SUPUESTOS!$B$8,0) -> 636 | I11: =ROUND(I10/SUPUESTOS!$B$8,0) -> 731 | ... L11: =ROUND(L10/SUPUESTOS!$B$8,0) -> 59
A12: B. APALANCAMIENTO (editar fila 13: 1=ajustar deuda al 50% PN, 0=mantener nivel anterior)
A13: ¿Ajustar deuda? (1=reset a 0.5x PN, 0=mantener) | B13: 0 | C13: 0 | D13: 0 | E13: 0 | F13: 0 | G13: 0 | H13: 0 | I13: 0 | J13: 0 | K13: 0 | L13: 0
A14: Deuda Senior (monto) | B14: =IF(B13=1, B44*SUPUESTOS!$B$52, 0) -> 0 | C14: =IF(C13=1, C44*SUPUESTOS!$B$52, B14) -> 0 | D14: =IF(D13=1, D44*SUPUESTOS!$B$52, C14) -> 0 | E14: =IF(E13=1, E44*SUPUESTOS!$B$52, D14) -> 0 | F14: =IF(F13=1, F44*SUPUESTOS!$B$52, E14) -> 0 | G14: =IF(G13=1, G44*SUPUESTOS!$B$52, F14) -> 0 | H14: =IF(H13=1, H44*SUPUESTOS!$B$52, G14) -> 0 | I14: =IF(I13=1, I44*SUPUESTOS!$B$52, H14) -> 0 | J14: =IF(J13=1, J44*SUPUESTOS!$B$52, I14) -> 0 | ... L14: =IF(L13=1, L44*SUPUESTOS!$B$52, K14) -> 0
A15: Capital Total Desplegado (Equity + Deuda) | B15: =B5 -> 2947500 | C15: =C5 -> 8276858.9 | D15: =D5 -> 13582179 | E15: =E5 -> 19097054 | F15: =F5 -> 27830408 | G15: =G5 -> 36929753 | H15: =H5 -> 46390089 | I15: =I5 -> 56225245 | ... L15: =L5 -> 63057631
A16: Leverage Ratio (Deuda / PN Inicio) | B16: =IF(B5>0,B14/B5,0) -> 0 | C16: =IF(C5>0,C14/C5,0) -> 0 | D16: =IF(D5>0,D14/D5,0) -> 0 | E16: =IF(E5>0,E14/E5,0) -> 0 | F16: =IF(F5>0,F14/F5,0) -> 0 | G16: =IF(G5>0,G14/G5,0) -> 0 | H16: =IF(H5>0,H14/H5,0) -> 0 | I16: =IF(I5>0,I14/I5,0) -> 0 | ... L16: =IF(L5>0,L14/L5,0) -> 0
A18: C. INGRESOS
A19: Interés Ganado (sobre capital total desplegado) | B19: =IF(B7=1,B5*SUPUESTOS!$B$24,B5*SUPUESTOS!$B$24/2) -> 365490 | C19: =IF(C7=1,C5*SUPUESTOS!$B$24,C5*SUPUESTOS!$B$24/2) -> 1026330.5 | D19: =IF(D7=1,D5*SUPUESTOS!$B$24,D5*SUPUESTOS!$B$24/2) -> 1684190.2 | E19: =IF(E7=1,E5*SUPUESTOS!$B$24,E5*SUPUESTOS!$B$24/2) -> 2368034.7 | F19: =IF(F7=1,F5*SUPUESTOS!$B$24,F5*SUPUESTOS!$B$24/2) -> 3450970.6 | G19: =IF(G7=1,G5*SUPUESTOS!$B$24,G5*SUPUESTOS!$B$24/2) -> 4579289.4 | H19: =IF(H7=1,H5*SUPUESTOS!$B$24,H5*SUPUESTOS!$B$24/2) -> 5752371 | I19: =IF(I7=1,I5*SUPUESTOS!$B$24,I5*SUPUESTOS!$B$24/2) -> 6971930.4 | ... L19: =IF(L7=1,L5*SUPUESTOS!$B$24,L5*SUPUESTOS!$B$24/2) -> 3909573.1 | M19: =SUM(B19:L19) -> 44883994
A20: Upfront Fee (% al Fondo) | B20: =(B10/(1+SUPUESTOS!$B$38))*SUPUESTOS!$B$38 -> 188756.16 | C20: =(C10/(1+SUPUESTOS!$B$38))*SUPUESTOS!$B$38 -> 389688.01 | D20: =(D10/(1+SUPUESTOS!$B$38))*SUPUESTOS!$B$38 -> 475658.56 | E20: =(E10/(1+SUPUESTOS!$B$38))*SUPUESTOS!$B$38 -> 576193.63 | F20: =(F10/(1+SUPUESTOS!$B$38))*SUPUESTOS!$B$38 -> 872859.34 | G20: =(G10/(1+SUPUESTOS!$B$38))*SUPUESTOS!$B$38 -> 1039702.1 | H20: =(H10/(1+SUPUESTOS!$B$38))*SUPUESTOS!$B$38 -> 1212234.2 | I20: =(I10/(1+SUPUESTOS!$B$38))*SUPUESTOS!$B$38 -> 1391579.6 | ... L20: =(L10/(1+SUPUESTOS!$B$38))*SUPUESTOS!$B$38 -> 111804.97 | M20: =SUM(B20:L20) -> 8428670
A21: TOTAL INGRESOS FONDO | B21: =B19+B20 -> 554246.16 | C21: =C19+C20 -> 1416018.5 | D21: =D19+D20 -> 2159848.7 | E21: =E19+E20 -> 2944228.3 | F21: =F19+F20 -> 4323829.9 | G21: =G19+G20 -> 5618991.5 | H21: =H19+H20 -> 6964605.2 | I21: =I19+I20 -> 8363510 | ... L21: =L19+L20 -> 4021378.1 | M21: =SUM(B21:L21) -> 53312664
A23: D. COSTOS DEL FONDO
A24: Honorarios Soc. Gerente (1.2%) | B24: =B44*SUPUESTOS!$B$28 -> 36000 | C24: =C44*SUPUESTOS!$B$28 -> 99322.306 | D24: =D44*SUPUESTOS!$B$28 -> 162986.15 | E24: =E44*SUPUESTOS!$B$28 -> 229164.65 | F24: =F44*SUPUESTOS!$B$28 -> 333964.89 | G24: =G44*SUPUESTOS!$B$28 -> 443157.04 | H24: =H44*SUPUESTOS!$B$28 -> 556681.07 | I24: =I44*SUPUESTOS!$B$28 -> 674702.94 | ... L24: =L44*SUPUESTOS!$B$28 -> 756691.58 | M24: =SUM(B24:L24) -> 4722588.1
A25: Honorarios Soc. Depositaria (0.2%, mín $21,600/yr + $10K inicial Y1) | B25: =MAX(B44*SUPUESTOS!$B$29,SUPUESTOS!$B$40)+10000 -> 31600 | C25: =MAX(C44*SUPUESTOS!$B$29,SUPUESTOS!$B$40) -> 21600 | D25: =MAX(D44*SUPUESTOS!$B$29,SUPUESTOS!$B$40) -> 27164.358 | E25: =MAX(E44*SUPUESTOS!$B$29,SUPUESTOS!$B$40) -> 38194.108 | F25: =MAX(F44*SUPUESTOS!$B$29,SUPUESTOS!$B$40) -> 55660.816 | G25: =MAX(G44*SUPUESTOS!$B$29,SUPUESTOS!$B$40) -> 73859.507 | H25: =MAX(H44*SUPUESTOS!$B$29,SUPUESTOS!$B$40) -> 92780.178 | I25: =MAX(I44*SUPUESTOS!$B$29,SUPUESTOS!$B$40) -> 112450.49 | J25: =MAX(J44*SUPUESTOS!$B$29,SUPUESTOS!$B$40) -> 116900.12 | ... L25: =MAX(L44*SUPUESTOS!$B$29,SUPUESTOS!$B$40) -> 126115.26 | M25: =SUM(B25:L25) -> 817744.29
A26: Honorarios Asesor Inversión (0% PN — eliminado) | B26: =B44*SUPUESTOS!$B$30 -> 0 | C26: =C44*SUPUESTOS!$B$30 -> 0 | D26: =D44*SUPUESTOS!$B$30 -> 0 | E26: =E44*SUPUESTOS!$B$30 -> 0 | F26: =F44*SUPUESTOS!$B$30 -> 0 | G26: =G44*SUPUESTOS!$B$30 -> 0 | H26: =H44*SUPUESTOS!$B$30 -> 0 | I26: =I44*SUPUESTOS!$B$30 -> 0 | ... L26: =L44*SUPUESTOS!$B$30 -> 0 | M26: =SUM(B26:L26) -> 0
A27: Fee Asesor (Originación + Adquisición) | B27: =B10*(SUPUESTOS!$B$31) -> 49548.491 | C27: =C10*(SUPUESTOS!$B$31) -> 102293.1 | D27: =D10*(SUPUESTOS!$B$31) -> 124860.37 | E27: =E10*(SUPUESTOS!$B$31) -> 151250.83 | F27: =F10*(SUPUESTOS!$B$31) -> 229125.58 | G27: =G10*(SUPUESTOS!$B$31) -> 272921.79 | H27: =H10*(SUPUESTOS!$B$31) -> 318211.47 | I27: =I10*(SUPUESTOS!$B$31) -> 365289.65 | ... L27: =L10*(SUPUESTOS!$B$31) -> 29348.805 | M27: =SUM(B27:L27) -> 2212525.9
A28: Costos Fijos Operativos | B28: =SUPUESTOS!$B$42+SUPUESTOS!$B$43+SUPUESTOS!$B$44+SUPUESTOS!$B$45+SUPUESTOS!$B$46+SUPUESTOS!$B$47+SUPUESTOS!$B$48 -> 68100 | C28: =SUPUESTOS!$B$42+SUPUESTOS!$B$43+SUPUESTOS!$B$45+SUPUESTOS!$B$46+SUPUESTOS!$B$47+SUPUESTOS!$B$48 -> 56000 | D28: =SUPUESTOS!$B$42+SUPUESTOS!$B$43+SUPUESTOS!$B$45+SUPUESTOS!$B$46+SUPUESTOS!$B$47+SUPUESTOS!$B$48 -> 56000 | E28: =SUPUESTOS!$B$42+SUPUESTOS!$B$43+SUPUESTOS!$B$45+SUPUESTOS!$B$46+SUPUESTOS!$B$47+SUPUESTOS!$B$48 -> 56000 | F28: =SUPUESTOS!$B$42+SUPUESTOS!$B$43+SUPUESTOS!$B$45+SUPUESTOS!$B$46+SUPUESTOS!$B$47+SUPUESTOS!$B$48 -> 56000 | G28: =SUPUESTOS!$B$42+SUPUESTOS!$B$43+SUPUESTOS!$B$45+SUPUESTOS!$B$46+SUPUESTOS!$B$47+SUPUESTOS!$B$48 -> 56000 | H28: =SUPUESTOS!$B$42+SUPUESTOS!$B$43+SUPUESTOS!$B$45+SUPUESTOS!$B$46+SUPUESTOS!$B$47+SUPUESTOS!$B$48 -> 56000 | I28: =SUPUESTOS!$B$42+SUPUESTOS!$B$43+SUPUESTOS!$B$45+SUPUESTOS!$B$46+SUPUESTOS!$B$47+SUPUESTOS!$B$48 -> 56000 | J28: =SUPUESTOS!$B$42+SUPUESTOS!$B$43+SUPUESTOS!$B$45+SUPUESTOS!$B$46+SUPUESTOS!$B$47+SUPUESTOS!$B$48 -> 56000 | ... L28: =SUPUESTOS!$B$42+SUPUESTOS!$B$43+SUPUESTOS!$B$45+SUPUESTOS!$B$46+SUPUESTOS!$B$47+SUPUESTOS!$B$48 -> 56000 | M28: =SUM(B28:L28) -> 628100
A29: Comisiones (Colocador+Org) sobre capital | B29: =(SUPUESTOS!$B$6+B42)*(SUPUESTOS!$B$36+SUPUESTOS!$B$37) -> 52500 | C29: =C42*(SUPUESTOS!$B$36+SUPUESTOS!$B$37) -> 87500 | D29: =D42*(SUPUESTOS!$B$36+SUPUESTOS!$B$37) -> 87500 | E29: =E42*(SUPUESTOS!$B$36+SUPUESTOS!$B$37) -> 87500 | F29: =F42*(SUPUESTOS!$B$36+SUPUESTOS!$B$37) -> 140000 | G29: =G42*(SUPUESTOS!$B$36+SUPUESTOS!$B$37) -> 140000 | H29: =H42*(SUPUESTOS!$B$36+SUPUESTOS!$B$37) -> 140000 | I29: =I42*(SUPUESTOS!$B$36+SUPUESTOS!$B$37) -> 140000 | J29: =J42*(SUPUESTOS!$B$36+SUPUESTOS!$B$37) -> 0 | ... L29: =L42*(SUPUESTOS!$B$36+SUPUESTOS!$B$37) -> 0 | M29: =SUM(B29:L29) -> 875000
A30: IVA sobre Upfront Fee (REVISAR: ¿lo paga el fondo o el tomador?) | B30: =B20*SUPUESTOS!$B$39 -> 39638.793 | C30: =C20*SUPUESTOS!$B$39 -> 81834.481 | D30: =D20*SUPUESTOS!$B$39 -> 99888.298 | E30: =E20*SUPUESTOS!$B$39 -> 121000.66 | F30: =F20*SUPUESTOS!$B$39 -> 183300.46 | G30: =G20*SUPUESTOS!$B$39 -> 218337.43 | H30: =H20*SUPUESTOS!$B$39 -> 254569.18 | I30: =I20*SUPUESTOS!$B$39 -> 292231.72 | ... L30: =L20*SUPUESTOS!$B$39 -> 23479.044 | M30: =SUM(B30:L30) -> 1770020.7
A31: Intereses Deuda Senior | B31: =B14*SUPUESTOS!$B$54 -> 0 | C31: =C14*SUPUESTOS!$B$54 -> 0 | D31: =D14*SUPUESTOS!$B$54 -> 0 | E31: =E14*SUPUESTOS!$B$54 -> 0 | F31: =F14*SUPUESTOS!$B$54 -> 0 | G31: =G14*SUPUESTOS!$B$54 -> 0 | H31: =H14*SUPUESTOS!$B$54 -> 0 | I31: =I14*SUPUESTOS!$B$54 -> 0 | ... L31: =L14*SUPUESTOS!$B$54 -> 0 | M31: =SUM(B31:L31) -> 0
A32: TOTAL COSTOS | B32: =B24+B25+B26+B27+B28+B29+B30+B31+B34 -> 277387.28 | C32: =C24+C25+C26+C27+C28+C29+C30+C31+C34 -> 448549.89 | D32: =D24+D25+D26+D27+D28+D29+D30+D31+D34 -> 558399.17 | E32: =E24+E25+E26+E27+E28+E29+E30+E31+E34 -> 683110.25 | F32: =F24+F25+F26+F27+F28+F29+F30+F31+F34 -> 998051.75 | G32: =G24+G25+G26+G27+G28+G29+G30+G31+G34 -> 1204275.8 | H32: =H24+H25+H26+H27+H28+H29+H30+H31+H34 -> 1418241.9 | I32: =I24+I25+I26+I27+I28+I29+I30+I31+I34 -> 1640674.8 | ... L32: =L24+L25+L26+L27+L28+L29+L30+L31+L34 -> 2934380.6 | M32: =SUM(B32:L32) -> 12968725
A33: Carry devengado del período | B33: ='RESULTADOS ASESOR TCMC'!B14 -> 9685.8873 | C33: ='RESULTADOS ASESOR TCMC'!C14 -> 47085.708 | D33: ='RESULTADOS ASESOR TCMC'!D14 -> 78651.883 | E33: ='RESULTADOS ASESOR TCMC'!E14 -> 111529.48 | F33: ='RESULTADOS ASESOR TCMC'!F14 -> 165595.37 | G33: ='RESULTADOS ASESOR TCMC'!G14 -> 219893.05 | H33: ='RESULTADOS ASESOR TCMC'!H14 -> 276295.8 | I33: ='RESULTADOS ASESOR TCMC'!I14 -> 334932.05 | ... M33: ='RESULTADOS ASESOR TCMC'!M14 -> 1942745.9
A34: Carry COBRADO (tope 5.4% Cl.10.5) | B34: ='RESULTADOS ASESOR TCMC'!B18 -> 0 | C34: ='RESULTADOS ASESOR TCMC'!C18 -> 0 | D34: 0 | E34: 0 | F34: 0 | G34: 0 | H34: 0 | I34: 0 | J34: 0 | K34: 0 | L34: ='RESULTADOS ASESOR TCMC'!L18 -> 1942745.9 | M34: ='RESULTADOS ASESOR TCMC'!M18 -> 1942745.9
A35: E. RESULTADO
A36: EBITDA Fondo (neto de carry) | B36: =B21-B32 -> 276858.87 | C36: =C21-C32 -> 967468.62 | D36: =D21-D32 -> 1601449.6 | E36: =E21-E32 -> 2261118.1 | F36: =F21-F32 -> 3325778.2 | G36: =G21-G32 -> 4414715.7 | H36: =H21-H32 -> 5546363.3 | I36: =I21-I32 -> 6722835.2 | ... L36: =L21-L32 -> 1086997.5 | M36: =SUM(B36:L36) -> 40343939
A37: EBITDA / Equity (%) | B37: =IF(B44>0,B36/B44,0) -> 0.092286291 | C37: =IF(C44>0,C36/C44,0) -> 0.11688838 | D37: =IF(D44>0,D36/D44,0) -> 0.11790815 | E37: =IF(E44>0,E36/E44,0) -> 0.11840141 | F37: =IF(F44>0,F36/F44,0) -> 0.1195016 | G37: =IF(G44>0,G36/G44,0) -> 0.1195436 | H37: =IF(H44>0,H36/H44,0) -> 0.11955923 | I37: =IF(I44>0,I36/I44,0) -> 0.11956969 | ... L37: =IF(L44>0,L36/L44,0) -> 0.01723816
A38: Retiros Parciales Inversores (detalle filas 69-80) | B38: =B76 -> 0 | C38: =C76 -> 662148.71 | D38: =D76 -> 1086574.3 | E38: =E76 -> 1527764.3 | F38: =F76 -> 2226432.6 | G38: =G76 -> 2954380.3 | H38: =H76 -> 3711207.1 | I38: =I76 -> 4498019.6 | ... L38: =L76 -> 0 | M38: =SUM(B38:L38) -> 26199310
A39: Neto Reinvertido / Acumulado | B39: =B36-B38 -> 276858.87 | C39: =C36-C38 -> 305319.91 | D39: =D36-D38 -> 514875.26 | E39: =E36-E38 -> 733353.76 | F39: =F36-F38 -> 1099345.5 | G39: =G36-G38 -> 1460335.4 | H39: =H36-H38 -> 1835156.2 | I39: =I36-I38 -> 2224815.6 | ... L39: =L36-L38 -> 1086997.5 | M39: =SUM(B39:L39) -> 14144629
A41: F. PATRIMONIO NETO
A42: Captaciones Nuevas (ingreso capital por año) | B42: 0 | C42: 5000000 | D42: 5000000 | E42: 5000000 | F42: 8000000 | G42: 8000000 | H42: 8000000 | I42: 8000000 | J42: 0 | K42: 0 | L42: 0 | M42: =SUM(B42:L42) -> 47000000
A43: Nota: Captaciones editable por año. Comisiones se cobran sobre capital nuevo.
A44: PN Inicio | B44: =SUPUESTOS!$B$6+B42 -> 3000000 | C44: =B45-B38+C42 -> 8276858.9 | D44: =C45-C38+D42 -> 13582179 | E44: =D45-D38+E42 -> 19097054 | F44: =E45-E38+F42 -> 27830408 | G44: =F45-F38+G42 -> 36929753 | H44: =G45-G38+H42 -> 46390089 | I44: =H45-H38+I42 -> 56225245 | J44: =I45-I38+J42 -> 58450061 | ... L44: =K45-K38+L42 -> 63057631
A45: PN Fin (antes retiros) | B45: =B44+B36 -> 3276858.9 | C45: =C44+C36 -> 9244327.5 | D45: =D44+D36 -> 15183628 | E45: =E44+E36 -> 21358172 | F45: =F44+F36 -> 31156186 | G45: =G44+G36 -> 41344469 | H45: =H44+H36 -> 51936452 | I45: =I44+I36 -> 62948080 | ... L45: =L44+L36 -> 64144629
A47: G. CIERRE DEL FONDO — WIND-DOWN AÑO 11 (2036)
A48: Revolving Año Cierre (devuelto como cash) | L48: =IF(L7=0,L6,0) -> 21744011
A49: Cartera Remanente (Stock Fin) | L49: =L9 -> 41313620
A50: Valor Securitización | L50: =L49/(1+SUPUESTOS!$B$69) -> 37902404
A51: Repago Deuda Senior (si aplica) | L51: =L14 -> 0
A52: CASH NETO CIERRE (revolving + securit - deuda) | L52: =L48+L50-L51 -> 59646415
A54: H. CASH FLOW INVERSOR (EQUITY)
A55: Retiros Parciales Recibidos (neto de fee) | B55: =B79 -> 0 | C55: =C79 -> 662148.71 | D55: =D79 -> 1086574.3 | E55: =E79 -> 1527764.3 | F55: =F79 -> 2226432.6 | G55: =G79 -> 2954380.3 | H55: =H79 -> 3711207.1 | I55: =I79 -> 4498019.6 | ... L55: =L79 -> 0 | M55: =SUM(B55:L55) -> 26199310
A56: Cash Cierre Fondo | B56: 0 | C56: 0 | D56: 0 | E56: 0 | F56: 0 | G56: 0 | H56: 0 | I56: 0 | J56: 0 | K56: 0 | L56: =L52 -> 59646415 | M56: =SUM(B56:L56) -> 59646415
A57: Cash Flow Inversor TOTAL | B57: =B55+B56 -> 0 | C57: =C55+C56 -> 662148.71 | D57: =D55+D56 -> 1086574.3 | E57: =E55+E56 -> 1527764.3 | F57: =F55+F56 -> 2226432.6 | G57: =G55+G56 -> 2954380.3 | H57: =H55+H56 -> 3711207.1 | I57: =I55+I56 -> 4498019.6 | ... M57: =M55+M56 -> 85845725
A58: Retorno Acumulado | B58: =B57 -> 0 | C58: =B58+C57 -> 662148.71 | D58: =C58+D57 -> 1748723 | E58: =D58+E57 -> 3276487.3 | F58: =E58+F57 -> 5502920 | G58: =F58+G57 -> 8457300.2 | H58: =G58+H57 -> 12168507 | I58: =H58+I57 -> 16666527 | J58: =I58+J57 -> 21342532 | ... L58: =K58+L57 -> 85845725
A60: I. METRICAS DE RETORNO
A61: CF para TIR (t=0 a t=11) | B61: =-SUPUESTOS!$B$6-B42-B57 -> -3000000 | C61: =C57-C42 -> -4337851.3 | D61: =D57-D42 -> -3913425.7 | E61: =E57-E42 -> -3472235.7 | F61: =F57-F42 -> -5773567.4 | G61: =G57-G42 -> -5045619.7 | H61: =H57-H42 -> -4288792.9 | I61: =I57-I42 -> -3501980.4 | J61: =J57-J42 -> 4676004.8 | K61: =K57-K42 -> 4856778.2 | L61: =K57-L42+L57 -> 64503193
A62: TIR Inversor | B62: =IFERROR(IRR(B61:M61),"-") -> 0.1318127
A63: MOIC (Total Distributions / Total Capital Invested) | B63: =IF((SUPUESTOS!$B$6+M42)>0,M57/(SUPUESTOS!$B$6+M42),0) -> 1.7169145
A65: Nota: TIR asume liquidación de cartera remanente dentro del último año del fondo.
A66: Ver tab SENSIBILIDAD para analisis completo.
A69: J. RETIROS POR LIQUIDEZ — DETALLE 2 CASOS
A70: Concepto | B70: 2026 | C70: 2027 | D70: 2028 | E70: 2029 | F70: 2030 | G70: 2031 | H70: 2032 | I70: 2033 | J70: 2034 | K70: 2035 | L70: 2036 | M70: TOTAL
A71: CASO 1: Fondo de Liquidez | B71: =MIN(B72, B44) -> 0 | C71: =MIN(C72, C44) -> 0 | D71: =MIN(D72, D44) -> 0 | E71: =MIN(E72, E44) -> 0 | F71: =MIN(F72, F44) -> 0 | G71: =MIN(G72, G44) -> 0 | H71: =MIN(H72, H44) -> 0 | I71: =MIN(I72, I44) -> 0 | ... K71: =MIN(K72, K44) -> 0 | M71: =SUM(B71:L71) -> 0
A72: Monto Fondo Liquidez por año (EDITABLE →) | B72: 0 | C72: 0 | D72: 0 | E72: 0 | F72: 0 | G72: 0 | H72: 0 | I72: 0 | J72: 0 | K72: 0
A73: % Retiro Caso 2 (EDITABLE por año →) | B73: 0 | C73: 0.08 | D73: 0.08 | E73: 0.08 | F73: 0.08 | G73: 0.08 | H73: 0.08 | I73: 0.08 | J73: 0.08 | K73: 0.08
A74: CASO 2: Retiro Variable (% × PN) | B74: =IF(1>=SUPUESTOS!$B$58, B44*B73, 0) -> 0 | C74: =IF(2>=SUPUESTOS!$B$58, C44*C73, 0) -> 662148.71 | D74: =IF(3>=SUPUESTOS!$B$58, D44*D73, 0) -> 1086574.3 | E74: =IF(4>=SUPUESTOS!$B$58, E44*E73, 0) -> 1527764.3 | F74: =IF(5>=SUPUESTOS!$B$58, F44*F73, 0) -> 2226432.6 | G74: =IF(6>=SUPUESTOS!$B$58, G44*G73, 0) -> 2954380.3 | H74: =IF(7>=SUPUESTOS!$B$58, H44*H73, 0) -> 3711207.1 | I74: =IF(8>=SUPUESTOS!$B$58, I44*I73, 0) -> 4498019.6 | J74: =IF(9>=SUPUESTOS!$B$58, J44*J73, 0) -> 4676004.8 | K74: =IF(10>=SUPUESTOS!$B$58, K44*K73, 0) -> 4856778.2 | M74: =SUM(B74:L74) -> 26199310
A76: TOTAL RETIRO BRUTO (Caso 1 + Caso 2) | B76: =B71+B74 -> 0 | C76: =C71+C74 -> 662148.71 | D76: =D71+D74 -> 1086574.3 | E76: =E71+E74 -> 1527764.3 | F76: =F71+F74 -> 2226432.6 | G76: =G71+G74 -> 2954380.3 | H76: =H71+H74 -> 3711207.1 | I76: =I71+I74 -> 4498019.6 | ... K76: =K71+K74 -> 4856778.2 | M76: =SUM(B76:L76) -> 26199310
A77: Fee sobre Retiro (%) | B77: =SUPUESTOS!$B$59 -> 0 | C77: =SUPUESTOS!$B$59 -> 0 | D77: =SUPUESTOS!$B$59 -> 0 | E77: =SUPUESTOS!$B$59 -> 0 | F77: =SUPUESTOS!$B$59 -> 0 | G77: =SUPUESTOS!$B$59 -> 0 | H77: =SUPUESTOS!$B$59 -> 0 | I77: =SUPUESTOS!$B$59 -> 0 | ... K77: =SUPUESTOS!$B$59 -> 0
A78: Fee Retiro (USD) — ingreso TCMC | B78: =B76*B77 -> 0 | C78: =C76*C77 -> 0 | D78: =D76*D77 -> 0 | E78: =E76*E77 -> 0 | F78: =F76*F77 -> 0 | G78: =G76*G77 -> 0 | H78: =H76*H77 -> 0 | I78: =I76*I77 -> 0 | ... K78: =K76*K77 -> 0 | M78: =SUM(B78:L78) -> 0
A79: Retiro Neto al Inversor (Bruto − Fee) | B79: =B76-B78 -> 0 | C79: =C76-C78 -> 662148.71 | D79: =D76-D78 -> 1086574.3 | E79: =E76-E78 -> 1527764.3 | F79: =F76-F78 -> 2226432.6 | G79: =G76-G78 -> 2954380.3 | H79: =H76-H78 -> 3711207.1 | I79: =I76-I78 -> 4498019.6 | ... K79: =K76-K78 -> 4856778.2 | M79: =SUM(B79:L79) -> 26199310
A80: Impacto en NAV del Fondo (= Bruto sale, Fee a TCMC) | B80: =B76 -> 0 | C80: =C76 -> 662148.71 | D80: =D76 -> 1086574.3 | E80: =E76 -> 1527764.3 | F80: =F76 -> 2226432.6 | G80: =G76 -> 2954380.3 | H80: =H76 -> 3711207.1 | I80: =I76 -> 4498019.6 | ... K80: =K76 -> 4856778.2
A81: Nota: El retiro BRUTO sale del fondo (reduce NAV). El fee es ingreso TCMC fuera del fondo.

Sheet CUOTAS TOMADOR
A1: TU CASA +CERCA | CUOTAS POR TOMADOR — Amortización Francesa
B2: 12 | C2: 12 MESES — PLAZO | K2: Lendar | L2: Lendar: | N2: Período | O2: Saldo Inicial | P2: Interés | Q2: Capital | R2: Cuota | S2: Saldo Final | T2: Saldo Final
C3: Tomador | L3: 12 | M3: 0.095 | O3: 1 | P3: =H4 -> 294750 | Q3: =P3*(H$5/H$6) -> 2579.0625 | R3: =S3-Q3 -> 23402.738 | S3: =$H$7 -> 25981.801 | T3: =P3-R3 -> 271347.26 | V3: 1 | W3: =H7 -> 25981.801 | X3: =D5 -> 294750
C4: Pide | D4: =('FLUJO 5 AÑOS (5Y)'!$B$5)/(1+(E8*(1+E7)))*SUPUESTOS!$C$14 -> 277934.94 | E4: Estos va a pagar el depto | G4: Capital | H4: =D5 -> 294750 | L4: 24 | M4: 0.105 | O4: 2 | P4: =T3 -> 271347.26 | Q4: =P4*(H$5/H$6) -> 2374.2885 | R4: =S4-Q4 -> 23607.512 | S4: =$H$7 -> 25981.801 | T4: =P4-R4 -> 247739.75 | V4: 2 | W4: =H18 -> 34515.457 | X4: =D16 -> 736875
C5: Toma | D5: =D4*(1+(E8*(1+E7))) -> 294750 | G5: Interés | H5: =SUPUESTOS!$B$14 -> 0.105 | L5: 36 | M5: 0.115 | O5: 3 | P5: =T4 -> 247739.75 | Q5: =P5*(H$5/H$6) -> 2167.7228 | R5: =S5-Q5 -> 23814.078 | S5: =$H$7 -> 25981.801 | T5: =P5-R5 -> 223925.67 | V5: 3 | W5: =H29 -> 39441.825 | X5: =D27 -> 1179000
C6: Upfront | D6: =D5-D4 -> 16815.064 | G6: Plazo | H6: =B2 -> 12 | L6: 48 | M6: 0.125 | O6: 4 | P6: =T5 -> 223925.67 | Q6: =P6*(H$5/H$6) -> 1959.3496 | R6: =S6-Q6 -> 24022.451 | S6: =$H$7 -> 25981.801 | T6: =P6-R6 -> 199903.22 | V6: 4 | W6: =H40 -> 11971.119 | X6: =D38 -> 442125
C7: IVA | D7: =D6-D8 -> 2918.3168 | E7: 0.21 | G7: Cuota Neta | H7: =-PMT((H5/12),H6,H4) -> 25981.801 | L7: 60 | M7: 0.135 | O7: 5 | P7: =T6 -> 199903.22 | Q7: =P7*(H$5/H$6) -> 1749.1532 | R7: =S7-Q7 -> 24232.648 | S7: =$H$7 -> 25981.801 | T7: =P7-R7 -> 175670.57 | V7: 5 | W7: =H51 -> 6934.9608 | X7: =D49 -> 294750
C8: NETO | D8: =D6/(1+E7) -> 13896.747 | E8: 0.05 | O8: 6 | P8: =T7 -> 175670.57 | Q8: =P8*(H$5/H$6) -> 1537.1175 | R8: =S8-Q8 -> 24444.683 | S8: =$H$7 -> 25981.801 | T8: =P8-R8 -> 151225.89 | V8: Total | W8: =SUM(W3:W7) -> 118845.16 | X8: =SUM(X3:X7) -> 2947500
G9: TOTAL | H9: =H7*B2 -> 311781.61 | O9: 7 | P9: =T8 -> 151225.89 | Q9: =P9*(H$5/H$6) -> 1323.2265 | R9: =S9-Q9 -> 24658.574 | S9: =$H$7 -> 25981.801 | T9: =P9-R9 -> 126567.32 | V9: Anual | W9: =W8*12 -> 1426142
G10: TDirecta | H10: =H9/D4-1 -> 0.12177912 | O10: 8 | P10: =T9 -> 126567.32 | Q10: =P10*(H$5/H$6) -> 1107.464 | R10: =S10-Q10 -> 24874.337 | S10: =$H$7 -> 25981.801 | T10: =P10-R10 -> 101692.98 | W10: ='FLUJO 5 AÑOS (5Y)'!B6 -> 1016379.3
G11: CFT Anualizado | H11: =((1+H10)^(12/B2))-1 -> 0.12177912 | O11: 9 | P11: =T10 -> 101692.98 | Q11: =P11*(H$5/H$6) -> 889.81357 | R11: =S11-Q11 -> 25091.987 | S11: =$H$7 -> 25981.801 | T11: =P11-R11 -> 76600.992
O12: 10 | P12: =T11 -> 76600.992 | Q12: =P12*(H$5/H$6) -> 670.25868 | R12: =S12-Q12 -> 25311.542 | S12: =$H$7 -> 25981.801 | T12: =P12-R12 -> 51289.45
B13: 24 | C13: 24 MESES — PLAZO | O13: 11 | P13: =T12 -> 51289.45 | Q13: =P13*(H$5/H$6) -> 448.78269 | R13: =S13-Q13 -> 25533.018 | S13: =$H$7 -> 25981.801 | T13: =P13-R13 -> 25756.432
C14: Tomador | O14: 12 | P14: =T13 -> 25756.432 | Q14: =P14*(H$5/H$6) -> 225.36878 | R14: =S14-Q14 -> 25756.432 | S14: =$H$7 -> 25981.801 | T14: =P14-R14 -> 0
C15: Pide | D15: =('FLUJO 5 AÑOS (5Y)'!$B$5)/(1+(E19*(1+E18)))*SUPUESTOS!$C$15 -> 694837.34 | E15: Estos va a pagar el depto | G15: Capital | H15: =D16 -> 736875 | O15: TOTALES | Q15: =SUM(Q3:Q14) -> 17031.608 | R15: =SUM(R3:R14) -> 294750 | S15: =SUM(S3:S14) -> 311781.61
C16: Toma | D16: =D15*(1+(E19*(1+E18))) -> 736875 | G16: Interés | H16: =SUPUESTOS!$B$15 -> 0.115
C17: Upfront | D17: =D16-D15 -> 42037.659 | G17: Plazo | H17: =B13 -> 24 | P17: Total Int Nom/30k | Q17: =Q15/D4 -> 0.06127912
C18: IVA | D18: =D17-D19 -> 7295.7921 | E18: 0.21 | G18: Cuota Neta | H18: =-PMT((H16/12),H17,H15) -> 34515.457 | P18: Upfront Fee + IVA | Q18: =E8*1.21 -> 0.0605
C19: NETO | D19: =D17/(1+E18) -> 34741.867 | E19: 0.05 | P19: Tasa Directa | Q19: =Q18+Q17 -> 0.12177912
G20: TOTAL | H20: =H18*B13 -> 828370.98
G21: TDirecta | H21: =H20/D15-1 -> 0.1921797
G22: CFT Anualizado | H22: =((1+H21)^(12/B13))-1 -> 0.091869821
B24: 36 | C24: 36 MESES — PLAZO
C25: Tomador
C26: Pide | D26: =('FLUJO 5 AÑOS (5Y)'!$B$5)/(1+(E30*(1+E29)))*SUPUESTOS!$C$16 -> 1111739.7 | E26: Estos va a pagar el depto | G26: Capital | H26: =D27 -> 1179000
C27: Toma | D27: =D26*(1+(E30*(1+E29))) -> 1179000 | G27: Interés | H27: =SUPUESTOS!$B$16 -> 0.125
C28: Upfront | D28: =D27-D26 -> 67260.255 | G28: Plazo | H28: =B24 -> 36
C29: IVA | D29: =D28-D30 -> 11673.267 | E29: 0.21 | G29: Cuota Neta | H29: =-PMT((H27/12),H28,H26) -> 39441.825
C30: NETO | D30: =D28/(1+E29) -> 55586.987 | E30: 0.05
G31: TOTAL | H31: =H29*B24 -> 1419905.7
G32: TDirecta | H32: =H31/D26-1 -> 0.27719252
G33: CFT Anualizado | H33: =((1+H32)^(12/B24))-1 -> 0.084972645
B35: 48 | C35: 48 MESES — PLAZO
C36: Tomador
C37: Pide | D37: =('FLUJO 5 AÑOS (5Y)'!$B$5)/(1+(E41*(1+E40)))*SUPUESTOS!$C$17 -> 416902.4 | E37: Estos va a pagar el depto | G37: Capital | H37: =D38 -> 442125
C38: Toma | D38: =D37*(1+(E41*(1+E40))) -> 442125 | G38: Interés | H38: =SUPUESTOS!$B$17 -> 0.135
C39: Upfront | D39: =D38-D37 -> 25222.595 | G39: Plazo | H39: =B35 -> 48
C40: IVA | D40: =D39-D41 -> 4377.4752 | E40: 0.21 | G40: Cuota Neta | H40: =-PMT((H38/12),H39,H37) -> 11971.119
C41: NETO | D41: =D39/(1+E40) -> 20845.12 | E41: 0.05
G42: TOTAL | H42: =H40*B35 -> 574613.73
G43: CFT | H43: =H42/D37-1 -> 0.37829314
G44: CFT Anualizado | H44: =((1+H43)^(12/B35))-1 -> 0.083516175
B46: 60 | C46: 60 MESES — PLAZO
C47: Tomador
C48: Pide | D48: =('FLUJO 5 AÑOS (5Y)'!$B$5)/(1+(E52*(1+E51)))*SUPUESTOS!$C$18 -> 277934.94 | E48: Estos va a pagar el depto | G48: Capital | H48: =D49 -> 294750
C49: Toma | D49: =D48*(1+(E52*(1+E51))) -> 294750 | G49: Interés | H49: =SUPUESTOS!$B$18 -> 0.145
C50: Upfront | D50: =D49-D48 -> 16815.064 | G50: Plazo | H50: =B46 -> 60
C51: IVA | D51: =D50-D52 -> 2918.3168 | E51: 0.21 | G51: Cuota Neta | H51: =-PMT((H49/12),H50,H48) -> 6934.9608
C52: NETO | D52: =D50/(1+E51) -> 13896.747 | E52: 0.05
G53: TOTAL | H53: =H51*B46 -> 416097.65
G54: CFT | H54: =H53/D48-1 -> 0.49710453
G55: CFT Anualizado | H55: =((1+H54)^(12/B46))-1 -> 0.084052773

Sheet RESULTADOS ASESOR TCMC
A1: RESULTADOS ASESOR — MODELO TCMC 11 AÑOS (Propuesta ConoSur Mar-2026)
A2: Análisis de comisiones, carry (hurdle 6%), y extracción upfront. Propuesta ConoSur Marzo 2026.
A4: I. MANAGEMENT FEE (Honorarios Asesor)
A5: Concepto | B5: 2026 | C5: 2027 | D5: 2028 | E5: 2029 | F5: 2030 | G5: 2031 | H5: 2032 | I5: 2033 | J5: 2034 | K5: 2035 | L5: 2036 | M5: TOTAL
A6: PN Inicio | B6: ='FLUJO 11 AÑOS'!B44 -> 3000000 | C6: ='FLUJO 11 AÑOS'!C44 -> 8276858.9 | D6: ='FLUJO 11 AÑOS'!D44 -> 13582179 | E6: ='FLUJO 11 AÑOS'!E44 -> 19097054 | F6: ='FLUJO 11 AÑOS'!F44 -> 27830408 | G6: ='FLUJO 11 AÑOS'!G44 -> 36929753 | H6: ='FLUJO 11 AÑOS'!H44 -> 46390089 | I6: ='FLUJO 11 AÑOS'!I44 -> 56225245 | ... L6: ='FLUJO 11 AÑOS'!L44 -> 63057631 | M6: =SUM(B6:L6) -> 3.9354901e+08
A7: Management Fee (0% — eliminado, modelo Lendar) | B7: ='FLUJO 11 AÑOS'!B26 -> 0 | C7: ='FLUJO 11 AÑOS'!C26 -> 0 | D7: ='FLUJO 11 AÑOS'!D26 -> 0 | E7: ='FLUJO 11 AÑOS'!E26 -> 0 | F7: ='FLUJO 11 AÑOS'!F26 -> 0 | G7: ='FLUJO 11 AÑOS'!G26 -> 0 | H7: ='FLUJO 11 AÑOS'!H26 -> 0 | I7: ='FLUJO 11 AÑOS'!I26 -> 0 | ... L7: ='FLUJO 11 AÑOS'!L26 -> 0 | M7: =SUM(B7:L7) -> 0
A8: Fee por Crédito: % Originado + % Adquirido | B8: ='FLUJO 11 AÑOS'!B27 -> 49548.491 | C8: ='FLUJO 11 AÑOS'!C27 -> 102293.1 | D8: ='FLUJO 11 AÑOS'!D27 -> 124860.37 | E8: ='FLUJO 11 AÑOS'!E27 -> 151250.83 | F8: ='FLUJO 11 AÑOS'!F27 -> 229125.58 | G8: ='FLUJO 11 AÑOS'!G27 -> 272921.79 | H8: ='FLUJO 11 AÑOS'!H27 -> 318211.47 | I8: ='FLUJO 11 AÑOS'!I27 -> 365289.65 | ... L8: ='FLUJO 11 AÑOS'!L27 -> 29348.805 | M8: =SUM(B8:L8) -> 2212525.9
A9: TOTAL FEES ASESOR (dentro del fondo) | B9: =B7+B8 -> 49548.491 | C9: =C7+C8 -> 102293.1 | D9: =D7+D8 -> 124860.37 | E9: =E7+E8 -> 151250.83 | F9: =F7+F8 -> 229125.58 | G9: =G7+G8 -> 272921.79 | H9: =H7+H8 -> 318211.47 | I9: =I7+I8 -> 365289.65 | ... M9: =M7+M8 -> 2212525.9
B10: =B8/B6 -> 0.016516164 | C10: =C8/C6 -> 0.012358928 | D10: =D8/D6 -> 0.0091929561 | E10: =E8/E6 -> 0.0079201131 | F10: =F8/F6 -> 0.008232922 | G10: =G8/G6 -> 0.0073902955 | H10: =H8/H6 -> 0.0068594711 | I10: =I8/I6 -> 0.0064968974
A11: II. CARRY WATERFALL (con tope 5.4% — Cl. 10.5)
A12: Concepto | B12: 2026 | C12: 2027 | D12: 2028 | E12: 2029 | F12: 2030 | G12: 2031 | H12: 2032 | I12: 2033 | J12: 2034 | K12: 2035 | L12: 2036 | M12: TOTAL
A13: EBITDA pre-carry | B13: ='FLUJO 11 AÑOS'!B21-'FLUJO 11 AÑOS'!B24-'FLUJO 11 AÑOS'!B25-'FLUJO 11 AÑOS'!B26-'FLUJO 11 AÑOS'!B27-'FLUJO 11 AÑOS'!B28-'FLUJO 11 AÑOS'!B29-'FLUJO 11 AÑOS'!B30-'FLUJO 11 AÑOS'!B31 -> 276858.87 | C13: ='FLUJO 11 AÑOS'!C21-'FLUJO 11 AÑOS'!C24-'FLUJO 11 AÑOS'!C25-'FLUJO 11 AÑOS'!C26-'FLUJO 11 AÑOS'!C27-'FLUJO 11 AÑOS'!C28-'FLUJO 11 AÑOS'!C29-'FLUJO 11 AÑOS'!C30-'FLUJO 11 AÑOS'!C31 -> 967468.62 | D13: ='FLUJO 11 AÑOS'!D21-'FLUJO 11 AÑOS'!D24-'FLUJO 11 AÑOS'!D25-'FLUJO 11 AÑOS'!D26-'FLUJO 11 AÑOS'!D27-'FLUJO 11 AÑOS'!D28-'FLUJO 11 AÑOS'!D29-'FLUJO 11 AÑOS'!D30-'FLUJO 11 AÑOS'!D31 -> 1601449.6 | E13: ='FLUJO 11 AÑOS'!E21-'FLUJO 11 AÑOS'!E24-'FLUJO 11 AÑOS'!E25-'FLUJO 11 AÑOS'!E26-'FLUJO 11 AÑOS'!E27-'FLUJO 11 AÑOS'!E28-'FLUJO 11 AÑOS'!E29-'FLUJO 11 AÑOS'!E30-'FLUJO 11 AÑOS'!E31 -> 2261118.1 | F13: ='FLUJO 11 AÑOS'!F21-'FLUJO 11 AÑOS'!F24-'FLUJO 11 AÑOS'!F25-'FLUJO 11 AÑOS'!F26-'FLUJO 11 AÑOS'!F27-'FLUJO 11 AÑOS'!F28-'FLUJO 11 AÑOS'!F29-'FLUJO 11 AÑOS'!F30-'FLUJO 11 AÑOS'!F31 -> 3325778.2 | G13: ='FLUJO 11 AÑOS'!G21-'FLUJO 11 AÑOS'!G24-'FLUJO 11 AÑOS'!G25-'FLUJO 11 AÑOS'!G26-'FLUJO 11 AÑOS'!G27-'FLUJO 11 AÑOS'!G28-'FLUJO 11 AÑOS'!G29-'FLUJO 11 AÑOS'!G30-'FLUJO 11 AÑOS'!G31 -> 4414715.7 | H13: ='FLUJO 11 AÑOS'!H21-'FLUJO 11 AÑOS'!H24-'FLUJO 11 AÑOS'!H25-'FLUJO 11 AÑOS'!H26-'FLUJO 11 AÑOS'!H27-'FLUJO 11 AÑOS'!H28-'FLUJO 11 AÑOS'!H29-'FLUJO 11 AÑOS'!H30-'FLUJO 11 AÑOS'!H31 -> 5546363.3 | I13: ='FLUJO 11 AÑOS'!I21-'FLUJO 11 AÑOS'!I24-'FLUJO 11 AÑOS'!I25-'FLUJO 11 AÑOS'!I26-'FLUJO 11 AÑOS'!I27-'FLUJO 11 AÑOS'!I28-'FLUJO 11 AÑOS'!I29-'FLUJO 11 AÑOS'!I30-'FLUJO 11 AÑOS'!I31 -> 6722835.2 | ... L13: ='FLUJO 11 AÑOS'!L21-'FLUJO 11 AÑOS'!L24-'FLUJO 11 AÑOS'!L25-'FLUJO 11 AÑOS'!L26-'FLUJO 11 AÑOS'!L27-'FLUJO 11 AÑOS'!L28-'FLUJO 11 AÑOS'!L29-'FLUJO 11 AÑOS'!L30-'FLUJO 11 AÑOS'!L31 -> 3029743.4 | M13: =SUM(B13:L13) -> 42286685
A14: Carry Devengado del Período | B14: =MAX(0,B13-'FLUJO 11 AÑOS'!B44*SUPUESTOS!$B$34)*SUPUESTOS!$B$33 -> 9685.8873 | C14: =MAX(0,C13-'FLUJO 11 AÑOS'!C44*SUPUESTOS!$B$34)*SUPUESTOS!$B$33 -> 47085.708 | D14: =MAX(0,D13-'FLUJO 11 AÑOS'!D44*SUPUESTOS!$B$34)*SUPUESTOS!$B$33 -> 78651.883 | E14: =MAX(0,E13-'FLUJO 11 AÑOS'!E44*SUPUESTOS!$B$34)*SUPUESTOS!$B$33 -> 111529.48 | F14: =MAX(0,F13-'FLUJO 11 AÑOS'!F44*SUPUESTOS!$B$34)*SUPUESTOS!$B$33 -> 165595.37 | G14: =MAX(0,G13-'FLUJO 11 AÑOS'!G44*SUPUESTOS!$B$34)*SUPUESTOS!$B$33 -> 219893.05 | H14: =MAX(0,H13-'FLUJO 11 AÑOS'!H44*SUPUESTOS!$B$34)*SUPUESTOS!$B$33 -> 276295.8 | I14: =MAX(0,I13-'FLUJO 11 AÑOS'!I44*SUPUESTOS!$B$34)*SUPUESTOS!$B$33 -> 334932.05 | ... L14: =MAX(0,L13-'FLUJO 11 AÑOS'!L44*SUPUESTOS!$B$34)*SUPUESTOS!$B$33 -> 0 | M14: =SUM(B14:L14) -> 1942745.9
A15: Carry Diferido Acum. (entrada) | B15: 0 | C15: =B19 -> 9685.8873 | D15: =C19 -> 56771.596 | E15: =D19 -> 135423.48 | F15: =E19 -> 246952.96 | G15: =F19 -> 412548.33 | H15: =G19 -> 632441.38 | I15: =H19 -> 908737.18 | J15: =I19 -> 1243669.2 | ... L15: =K19 -> 1942745.9
A16: Total Carry Pendiente (devengado + diferido) | B16: =B14+B15 -> 9685.8873 | C16: =C14+C15 -> 56771.596 | D16: =D14+D15 -> 135423.48 | E16: =E14+E15 -> 246952.96 | F16: =F14+F15 -> 412548.33 | G16: =G14+G15 -> 632441.38 | H16: =H14+H15 -> 908737.18 | I16: =I14+I15 -> 1243669.2 | ... L16: =L14+L15 -> 1942745.9 | M16: =SUM(B14:L14)+B15 -> 1942745.9
A17: Espacio Disponible (5.4%*PN − costos cubiertos por tope) | B17: =MAX(0, SUPUESTOS!$B$35*'FLUJO 11 AÑOS'!B44-('FLUJO 11 AÑOS'!B24+'FLUJO 11 AÑOS'!B25+'FLUJO 11 AÑOS'!B26+'FLUJO 11 AÑOS'!B27+'FLUJO 11 AÑOS'!B28)) -> 0 | C17: =MAX(0, SUPUESTOS!$B$35*'FLUJO 11 AÑOS'!C44-('FLUJO 11 AÑOS'!C24+'FLUJO 11 AÑOS'!C25+'FLUJO 11 AÑOS'!C26+'FLUJO 11 AÑOS'!C27+'FLUJO 11 AÑOS'!C28)) -> 167734.97 | D17: =MAX(0, SUPUESTOS!$B$35*'FLUJO 11 AÑOS'!D44-('FLUJO 11 AÑOS'!D24+'FLUJO 11 AÑOS'!D25+'FLUJO 11 AÑOS'!D26+'FLUJO 11 AÑOS'!D27+'FLUJO 11 AÑOS'!D28)) -> 362426.78 | E17: =MAX(0, SUPUESTOS!$B$35*'FLUJO 11 AÑOS'!E44-('FLUJO 11 AÑOS'!E24+'FLUJO 11 AÑOS'!E25+'FLUJO 11 AÑOS'!E26+'FLUJO 11 AÑOS'!E27+'FLUJO 11 AÑOS'!E28)) -> 556631.33 | F17: =MAX(0, SUPUESTOS!$B$35*'FLUJO 11 AÑOS'!F44-('FLUJO 11 AÑOS'!F24+'FLUJO 11 AÑOS'!F25+'FLUJO 11 AÑOS'!F26+'FLUJO 11 AÑOS'!F27+'FLUJO 11 AÑOS'!F28)) -> 828090.74 | G17: =MAX(0, SUPUESTOS!$B$35*'FLUJO 11 AÑOS'!G44-('FLUJO 11 AÑOS'!G24+'FLUJO 11 AÑOS'!G25+'FLUJO 11 AÑOS'!G26+'FLUJO 11 AÑOS'!G27+'FLUJO 11 AÑOS'!G28)) -> 1148268.3 | H17: =MAX(0, SUPUESTOS!$B$35*'FLUJO 11 AÑOS'!H44-('FLUJO 11 AÑOS'!H24+'FLUJO 11 AÑOS'!H25+'FLUJO 11 AÑOS'!H26+'FLUJO 11 AÑOS'!H27+'FLUJO 11 AÑOS'!H28)) -> 1481392.1 | I17: =MAX(0, SUPUESTOS!$B$35*'FLUJO 11 AÑOS'!I44-('FLUJO 11 AÑOS'!I24+'FLUJO 11 AÑOS'!I25+'FLUJO 11 AÑOS'!I26+'FLUJO 11 AÑOS'!I27+'FLUJO 11 AÑOS'!I28)) -> 1827720.2 | ... L17: =MAX(0, SUPUESTOS!$B$35*'FLUJO 11 AÑOS'!L44-('FLUJO 11 AÑOS'!L24+'FLUJO 11 AÑOS'!L25+'FLUJO 11 AÑOS'!L26+'FLUJO 11 AÑOS'!L27+'FLUJO 11 AÑOS'!L28)) -> 2436956.4 | M17: =SUM(B17:L17) -> 12893937
A18: Carry COBRADO (limitado por tope) | B18: 0 | C18: 0 | D18: 0 | E18: 0 | F18: 0 | G18: 0 | H18: 0 | I18: 0 | J18: 0 | K18: 0 | L18: =MIN(L16,L17) -> 1942745.9 | M18: =SUM(B18:L18) -> 1942745.9
A19: Carry Diferido Acum. (salida → pasa al año sig.) | B19: =B16-B18 -> 9685.8873 | C19: =C16-C18 -> 56771.596 | D19: =D16-D18 -> 135423.48 | E19: =E16-E18 -> 246952.96 | F19: =F16-F18 -> 412548.33 | G19: =G16-G18 -> 632441.38 | H19: =H16-H18 -> 908737.18 | I19: =I16-I18 -> 1243669.2 | ... L19: =L16-L18 -> 0 | M19: =L19 -> 0
A20: Nota: excluidos del tope 5.4%: comisiones colocador (row29), IVA upfront (row30), intereses deuda (row31)
A21: III. UPFRONT FEE EXTRACTION (pre-fondo)
A22: Concepto | B22: 2026 | C22: 2027 | D22: 2028 | E22: 2029 | F22: 2030 | G22: 2031 | H22: 2032 | I22: 2033 | J22: 2034 | K22: 2035 | L22: 2036 | M22: TOTAL
A23: Volumen Total Originado | B23: ='FLUJO 11 AÑOS'!B10 -> 3963879.3 | C23: ='FLUJO 11 AÑOS'!C10 -> 8183448.1 | D23: ='FLUJO 11 AÑOS'!D10 -> 9988829.8 | E23: ='FLUJO 11 AÑOS'!E10 -> 12100066 | F23: ='FLUJO 11 AÑOS'!F10 -> 18330046 | G23: ='FLUJO 11 AÑOS'!G10 -> 21833743 | H23: ='FLUJO 11 AÑOS'!H10 -> 25456918 | I23: ='FLUJO 11 AÑOS'!I10 -> 29223172 | ... L23: ='FLUJO 11 AÑOS'!L10 -> 2347904.4 | M23: =SUM(B23:L23) -> 1.7700207e+08
A24: Upfront Total (5% del otorgado neto) | B24: =(B23/(1+SUPUESTOS!$B$73))*SUPUESTOS!$B$73 -> 188756.16 | C24: =(C23/(1+SUPUESTOS!$B$73))*SUPUESTOS!$B$73 -> 389688.01 | D24: =(D23/(1+SUPUESTOS!$B$73))*SUPUESTOS!$B$73 -> 475658.56 | E24: =(E23/(1+SUPUESTOS!$B$73))*SUPUESTOS!$B$73 -> 576193.63 | F24: =(F23/(1+SUPUESTOS!$B$73))*SUPUESTOS!$B$73 -> 872859.34 | G24: =(G23/(1+SUPUESTOS!$B$73))*SUPUESTOS!$B$73 -> 1039702.1 | H24: =(H23/(1+SUPUESTOS!$B$73))*SUPUESTOS!$B$73 -> 1212234.2 | I24: =(I23/(1+SUPUESTOS!$B$73))*SUPUESTOS!$B$73 -> 1391579.6 | ... L24: =(L23/(1+SUPUESTOS!$B$73))*SUPUESTOS!$B$73 -> 111804.97 | M24: =SUM(B24:L24) -> 8428670
A25: Porción al Fondo (4%) | B25: =(B23/(1+SUPUESTOS!$B$73))*SUPUESTOS!$B$74 -> 188756.16 | C25: =(C23/(1+SUPUESTOS!$B$73))*SUPUESTOS!$B$74 -> 389688.01 | D25: =(D23/(1+SUPUESTOS!$B$73))*SUPUESTOS!$B$74 -> 475658.56 | E25: =(E23/(1+SUPUESTOS!$B$73))*SUPUESTOS!$B$74 -> 576193.63 | F25: =(F23/(1+SUPUESTOS!$B$73))*SUPUESTOS!$B$74 -> 872859.34 | G25: =(G23/(1+SUPUESTOS!$B$73))*SUPUESTOS!$B$74 -> 1039702.1 | H25: =(H23/(1+SUPUESTOS!$B$73))*SUPUESTOS!$B$74 -> 1212234.2 | I25: =(I23/(1+SUPUESTOS!$B$73))*SUPUESTOS!$B$74 -> 1391579.6 | ... L25: =(L23/(1+SUPUESTOS!$B$73))*SUPUESTOS!$B$74 -> 111804.97 | M25: =SUM(B25:L25) -> 8428670
A26: Extracción Asesor Pre-Fondo (1%) | B26: =(B23/(1+SUPUESTOS!$B$73))*SUPUESTOS!$B$75 -> 0 | C26: =(C23/(1+SUPUESTOS!$B$73))*SUPUESTOS!$B$75 -> 0 | D26: =(D23/(1+SUPUESTOS!$B$73))*SUPUESTOS!$B$75 -> 0 | E26: =(E23/(1+SUPUESTOS!$B$73))*SUPUESTOS!$B$75 -> 0 | F26: =(F23/(1+SUPUESTOS!$B$73))*SUPUESTOS!$B$75 -> 0 | G26: =(G23/(1+SUPUESTOS!$B$73))*SUPUESTOS!$B$75 -> 0 | H26: =(H23/(1+SUPUESTOS!$B$73))*SUPUESTOS!$B$75 -> 0 | I26: =(I23/(1+SUPUESTOS!$B$73))*SUPUESTOS!$B$75 -> 0 | ... L26: =(L23/(1+SUPUESTOS!$B$73))*SUPUESTOS!$B$75 -> 0 | M26: =SUM(B26:L26) -> 0
A27: IVA sobre Extracción (21%) | B27: =B26*SUPUESTOS!$B$76 -> 0 | C27: =C26*SUPUESTOS!$B$76 -> 0 | D27: =D26*SUPUESTOS!$B$76 -> 0 | E27: =E26*SUPUESTOS!$B$76 -> 0 | F27: =F26*SUPUESTOS!$B$76 -> 0 | G27: =G26*SUPUESTOS!$B$76 -> 0 | H27: =H26*SUPUESTOS!$B$76 -> 0 | I27: =I26*SUPUESTOS!$B$76 -> 0 | ... L27: =L26*SUPUESTOS!$B$76 -> 0 | M27: =SUM(B27:L27) -> 0
A28: Neto Extracción (sin IVA) | B28: =B26 -> 0 | C28: =C26 -> 0 | D28: =D26 -> 0 | E28: =E26 -> 0 | F28: =F26 -> 0 | G28: =G26 -> 0 | H28: =H26 -> 0 | I28: =I26 -> 0 | ... M28: =M26 -> 0
A29: Fee por Retiros de Liquidez (5% default) | B29: ='FLUJO 11 AÑOS'!B78 -> 0 | C29: ='FLUJO 11 AÑOS'!C78 -> 0 | D29: ='FLUJO 11 AÑOS'!D78 -> 0 | E29: ='FLUJO 11 AÑOS'!E78 -> 0 | F29: ='FLUJO 11 AÑOS'!F78 -> 0 | G29: ='FLUJO 11 AÑOS'!G78 -> 0 | H29: ='FLUJO 11 AÑOS'!H78 -> 0 | I29: ='FLUJO 11 AÑOS'!I78 -> 0 | ... L29: ='FLUJO 11 AÑOS'!L78 -> 0 | M29: =SUM(B29:L29) -> 0
A30: TOTAL A COBRAR ASESOR TCMC (año por año) | B30: =B9+B18+B28+B29 -> 49548.491 | C30: =C9+C18+C28+C29 -> 102293.1 | D30: =D9+D18+D28+D29 -> 124860.37 | E30: =E9+E18+E28+E29 -> 151250.83 | F30: =F9+F18+F28+F29 -> 229125.58 | G30: =G9+G18+G28+G29 -> 272921.79 | H30: =H9+H18+H28+H29 -> 318211.47 | I30: =I9+I18+I28+I29 -> 365289.65 | ... L30: =L9+L18+L28+L29 -> 1972094.7 | M30: =SUM(B30:L30) -> 4155271.8
A31: TOTAL ACUMULADO (sumador) | B31: =B30 -> 49548.491 | C31: =B31+C30 -> 151841.59 | D31: =C31+D30 -> 276701.97 | E31: =D31+E30 -> 427952.79 | F31: =E31+F30 -> 657078.37 | G31: =F31+G30 -> 930000.16 | H31: =G31+H30 -> 1248211.6 | I31: =H31+I30 -> 1613501.3 | J31: =I31+J30 -> 1893251.4 | ... L31: =K31+L30 -> 4155271.8
A32: SPONSOR (exceso >5.4% PN → pago fuera del fondo) | B32: =MAX(0, ('FLUJO 11 AÑOS'!B24+'FLUJO 11 AÑOS'!B25+'FLUJO 11 AÑOS'!B26+'FLUJO 11 AÑOS'!B27+'FLUJO 11 AÑOS'!B28) - SUPUESTOS!$B$35*'FLUJO 11 AÑOS'!B44) -> 23248.491 | C32: =MAX(0, ('FLUJO 11 AÑOS'!C24+'FLUJO 11 AÑOS'!C25+'FLUJO 11 AÑOS'!C26+'FLUJO 11 AÑOS'!C27+'FLUJO 11 AÑOS'!C28) - SUPUESTOS!$B$35*'FLUJO 11 AÑOS'!C44) -> 0 | D32: =MAX(0, ('FLUJO 11 AÑOS'!D24+'FLUJO 11 AÑOS'!D25+'FLUJO 11 AÑOS'!D26+'FLUJO 11 AÑOS'!D27+'FLUJO 11 AÑOS'!D28) - SUPUESTOS!$B$35*'FLUJO 11 AÑOS'!D44) -> 0 | E32: =MAX(0, ('FLUJO 11 AÑOS'!E24+'FLUJO 11 AÑOS'!E25+'FLUJO 11 AÑOS'!E26+'FLUJO 11 AÑOS'!E27+'FLUJO 11 AÑOS'!E28) - SUPUESTOS!$B$35*'FLUJO 11 AÑOS'!E44) -> 0 | F32: =MAX(0, ('FLUJO 11 AÑOS'!F24+'FLUJO 11 AÑOS'!F25+'FLUJO 11 AÑOS'!F26+'FLUJO 11 AÑOS'!F27+'FLUJO 11 AÑOS'!F28) - SUPUESTOS!$B$35*'FLUJO 11 AÑOS'!F44) -> 0 | G32: =MAX(0, ('FLUJO 11 AÑOS'!G24+'FLUJO 11 AÑOS'!G25+'FLUJO 11 AÑOS'!G26+'FLUJO 11 AÑOS'!G27+'FLUJO 11 AÑOS'!G28) - SUPUESTOS!$B$35*'FLUJO 11 AÑOS'!G44) -> 0 | H32: =MAX(0, ('FLUJO 11 AÑOS'!H24+'FLUJO 11 AÑOS'!H25+'FLUJO 11 AÑOS'!H26+'FLUJO 11 AÑOS'!H27+'FLUJO 11 AÑOS'!H28) - SUPUESTOS!$B$35*'FLUJO 11 AÑOS'!H44) -> 0 | I32: =MAX(0, ('FLUJO 11 AÑOS'!I24+'FLUJO 11 AÑOS'!I25+'FLUJO 11 AÑOS'!I26+'FLUJO 11 AÑOS'!I27+'FLUJO 11 AÑOS'!I28) - SUPUESTOS!$B$35*'FLUJO 11 AÑOS'!I44) -> 0 | ... L32: =MAX(0, ('FLUJO 11 AÑOS'!L24+'FLUJO 11 AÑOS'!L25+'FLUJO 11 AÑOS'!L26+'FLUJO 11 AÑOS'!L27+'FLUJO 11 AÑOS'!L28) - SUPUESTOS!$B$35*'FLUJO 11 AÑOS'!L44) -> 0 | M32: =SUM(B32:L32) -> 23248.491
A33: IV. RESUMEN TOTAL ASESOR — ESCENARIOS
A35: Escenario | B35: Total 11Y (USD) | C35: Promedio Anual
A36: A. Solo Fee por Crédito (1%/0.7%) | B36: =M8 -> 2212525.9 | C36: =B36/11 -> 201138.72
A37: B. Fee Crédito + Carry | B37: =M8+M18 -> 4155271.8 | C37: =B37/11 -> 377751.98
A38: C. Full (Fee Crédito + Carry + Extracción 1%) | B38: =M8+M18+M26 -> 4155271.8 | C38: =B38/11 -> 377751.98
A39: D. Full + Fee Retiros Liquidez | B39: =M8+M18+M26+M29 -> 4155271.8 | C39: =B39/11 -> 377751.98
A41: V. MÉTRICAS CLAVE
A42: TIR Inversor (post all fees) | B42: ='FLUJO 11 AÑOS'!B62 -> 0.1318127
A43: MOIC | B43: ='FLUJO 11 AÑOS'!B63 -> 1.7169145
A44: Total EBITDA Acumulado (11Y) | B44: =M13 -> 42286685
A45: Total Carry Devengado (11Y) | B45: =M14 -> 1942745.9
A46: Total Carry Cobrado (11Y) | B46: =M18 -> 1942745.9
A47: Carry Diferido Final (no cobrado) | B47: =L19 -> 0
A48: Mgmt Fee como % del PN promedio | B48: =SUPUESTOS!B30 -> 0
A50: NOTAS
A51: 1. El carry se calcula año a año: 20% sobre el exceso de EBITDA respecto al hurdle (6% * PN Inicio).
A52: 2. La extracción pre-fondo (1% del upfront) está sujeta a aprobación regulatoria y del reglamento FCIC.
A53: 3. Si se completa B32 en SUPUESTOS (fee adquirido), se suma automáticamente como costo del fondo.
A54: 4. Las captaciones por año (fila 42 en FLUJO) afectan el PN, comisiones, portfolio y TIR.
A55: 5. Escenario D incluye fee por originación/adquisición, actualmente en 0% (ver SUPUESTOS B31/B32).

Sheet Datos extras
B5: A los fines de evaluar la elegibilidad de los potenciales Deudores para el otorgamiento
B6: de créditos hipotecarios, se aplicarán, como mínimo, los siguientes criterios de
B7: análisis de solvencia:
B8:  Verificación de antecedentes crediticios: Se analizará la situación crediticia del
B9: solicitante mediante informes provenientes de bases de datos públicas y
B10: privadas, tales como la Central de Deudores del Sistema Financiero del BCRA,
B11: informes comerciales (e.g., Veraz, Nosis), y registros de cheques rechazados;
B12:  Evaluación de cumplimiento: Será requisito excluyente que al momento del
B13: otorgamiento del crédito el solicitante no registre obligaciones financieras
B14: impagas ni situaciones de morosidad vigentes; y
B15:  Acreditación de ingresos: Se exigirá la presentación de documentación
B16: respaldatoria de los ingresos del solicitante, conforme su condición tributaria,
... B45: superen el noventa y cinco por ciento (95%) del Patrimonio del Fondo.
